Workbook

Sheet Introduction et instructions
B6: 45805
B8: Introduction et présentation du deck
B9: INTRODUCTION AU DOCUMENT
B10: Suite au rachat de Boardriders, le groupe Beaumanoir a mandaté une étude pour le choix d'un nouvel ERP "opérations achat et vente" commun à l’ensemble des entités du Groupe. La présente consultation est lancée auprès d'éditeurs pré-sélectionnés, afin de collecter et comparer les informations sur leurs solutions. Ce questionnaire a pour but de collecter et évaluer ces données sur une base unifiée, construite à partir des attentes et besoins du Groupe Beaumanoir. Nous vous demandons, par conséquent, de reporter vos réponses directement dans les onglets de ce document.
B18: 0. PRESENTATION DE LA SOLUTION
B19: Cet onglet vise à recueillir les informations générales sur votre entreprise et sur l’ERP que vous proposez. Une zone de commentaire libre est prévue à la fin de l’onglet pour vous permettre de nous transmettre toute information complémentaire que vous jugerez pertinente : éléments différenciateurs, contexte d’évolution de votre solution, précisions techniques, etc.
B24: 1. BESOINS FONCTIONNELS
B25: Cet onglet présente les besoins fonctionnels exprimés par les référents métiers du groupe Beaumanoir. Le questionnaire qui s'y trouve doit permettre de confirmer la capacité de la solution à répondre à chacun des besoins, unitairement. Instructions : Chaque ligne correspond à l'un des besoins exprimés par les métiers, qu'il s'agisse d'une fonctionnalité, de critères et d'attributs de gestion ou de paramétrage, ou d'une règle de gestion particulière. Les besoins considérés très standards (ex : création d'un nouvel article, saisie d'une commande de vente) ont été ignorés. Ils sont réputés couverts par tous les ERP de la place. Merci de saisir votre réponse dans les deux champs prévus à cet effet. - Réponse (colonne E) : sélectionner la valeur adéquate parmi les options proposées YES. Couvert en standard (100%) CUS. Couvert avec customization DEV. Développement spécifiques requis TPS. Couvert par application tierce (au catalogue éditeur) FUT. En développement pour release / version ultérieure NON. Non couvert - Estimation coûts supp. (colonne F) : dans le cas où le besoin serait couvert par des développements spécifiques ou de la customization, estimer si possible le coût complémentaire (qui sera ajouté aux estimations budgétaies). - Réponse - compléments (colonne G). - Justifier, si nécessaire / pertinent, votre répons codifiée - Quelques précisions utiles sur les compléments de réponse. - Tout complément d'information est appréciable pour évaluer la qualité de la couverture. - Nous avons ajouté une mention "merci de détailler votre réponse" en face des critères pour lesquels des précisions sont vivement souhaitées. - En cas de réponse partielle au besoin - avec customization, ou développement - merci d'indiquer les limites rencontrées en standard par la solution, et le périmètre des travaux d'adaptation. Nota : nous avons choisi de ne pas donner de référence particulière à chaque ligne (1., 1.1, 1.1.1, etc.) afin de limiter la complexité de lecture. Vous pourrez faire directement référence au numéro de ligne dans nos échanges éventuels. N’hésitez pas à nous contacter pour toute question complémentaire ou besoin de clarification.
B55: 2. INTERFACES
B56: Cet onglet présente les opportunités d'interfaçage entre l'ERP à choisir et les principales applications de l'écosystème du groupe (marques historiques et Boardriders). Le questionnaire doit permettre de recenser les éventuels connecteurs et interfaces pré-développés / pré-paramétrés existants, susceptibles de simplifier la connexion entre systèmes. A noter : certaines applications apparaissent en doublon car elles remplissent les mêmes usages (ex : deux CRM). Ceci est du au fait que les systèmes historiques du groupe et ceux de Boardriders sont aujourd'hui distincts. Le choix des applications conservées sur chacun des domaines n'est pas arrêté et pourrait être influencé par la facilité d'interfaçage. Instructions : Chaque ligne correspond à l'une des applications de l'écosystème actuel du Groupe Beaumanoir. - Réponse (colonne G) : sélectionner la valeur adéquate parmi les options proposées STD. Connecteur standard existant => pas de développement, paramétrage minimal CUS. Connecteur spécifique existant => connecteur spécifique réalisé dans le cadre d'un précédent déploiement, réutilisable moyennant des adaptations / customisation DEV. Interface spécifique à développer => interface à créer en totalité NON. Non couvert => pas d'interfaçage possible - Estimation coûts supp. (colonne H) : estimer la charge de paramétrage / adaptation, ou de développement, pour chaque interface. - Limites de transfert (colonne I) Indiquer, pour chaque interface, si des limites en matière de volumétrie sont à prévoir. Ces limites peuvent être intrinsèques à l'ERP (nombre de lignes limité en entrée), liés à l'interface (technologie utilisée pour interfacer cet outil) ou aux performances (pas de limite de volume, mais temps de traitement trop important pour un batch), par exemple. - Détail des limites de transfert (colonne J). Détailler les limites de transfert : cause, volume maximum.
B81: 3. ARCHITECTURE ET SECURITE
B82: Cet onglet reprend les principaux besoins non fonctionnels que doit couvrir l'ERP. Le questionnaire permet de mieux comprendre les aspects techniques de votre solution (modalité, sécurité, conformité, propriété des données). Instructions : Chaque ligne correspond à une question ou un critère. Saisissez ou sélectionnez la valeur adéquate dans le champ "réponse" (colonne D).
B89: 4. VOLUMETRIE
... B114: Cet onglet doit permettre de collecter de premières estimations macroscopiques, à partir d'abaques et de quelques données relatives au contexte du Groupe Beaumanoir, pour positionner la solution dans une fourchette de prix (dans l'absolu, et par rapport aux autres candidats). il ne s'agit pas d'une propositon commerciale, et les estimations faites ici n'ont pas vocation à se substituer à une propositon en bonne et due forme. Rappel des éléments de contexte du Groupe Beaumanoir susceptibles d'impacter les coûts de déploiement et récurrents. - 15 marques. - Multi-sociétés, multi-canaux, multi-devises, clients français et internationaux. - Volumes important de données référentielles et de transactions (voir ANNEXE 1 - Volumétrie GBM). - 8 instances de STORELAND et 1 instance SAP (globale Boardriders) dont les données sont à reprendre et migrer. - Une dizaine d'interfaces avec les applications existantes du Groupe (ce chiffre sera affiné ultérieurement). - Un fort niveau de customization / personnalisation des règles de gestion attendu, notamment sur : - la gestion des stocks, - la gestion des règles de réassort (déclenchement, calcul du cloisage / des optimums logistiques (colis / bag VS picking)), - la gestion des allocations, et notamment les critères de calcul des priorités et de blocage. - Un fort niveau d'automatisation / simplification dans le traitement en masse de certaines données (recherche et gestion de commandes d'achat). - Le paramétrage / la customization de cockpits et d'outils d'aide au pilotage et à la décision (permettant des simulations et comparaison de scénarios). Instructions : Veuillez saisir les réponses adéquates dans le champ "estimations en K€" (colonne C) et "réponse" (colonne C). Les cases en bleu ciel sont des cellules de calcul dans lesquelles nous vous demandons de ne rien saisir. A noter : nous ne reprenons pas automatiquement les estimations de coûts complémentaires renseignées dans les onglets 1. Besoins fonctionnels (colonne F) et 2. Interfaces (colonne G), pour vous permettre de réaliser les optimisations adéquates. Les estimations en ligne 5 (customization et développements spécifiques) et 6 (connecteurs et interfaces) doivent tout de même être considérées dans le calcul, puisque parties intégrantes de la couverture du besoin.

Sheet 0. Informations générales
A1: DOMAINE | B1: QUESTION | C1: REPONSE | D1: COMMENTAIRE (facultatif)
A2: Informations générales sur la société éditrice | B2: Nom de l’entreprise éditrice | C2: Sap
B3: Chiffre d’affaires annuel total | C3: 34,18 milliards d'euros | D3: Revenus cloud : en hausse de 25 % Revenus de la suite Cloud ERP : +33 % Backlog cloud total : 63,3 milliards d’euros (+43 %) Résultat net : 3,12 milliards d’euros Marge nette : 9,14 %
B4: Chiffre d’affaires annuel en France | C4: 848 millions d'Euros
B5: Effectif total | C5: 92000
B6: Effectif en France | C6: cf tableau ci-contre
B7: Nombre de clients actifs dans le monde | C7: SAP compte plus de 440 000 clients dans 180 pays à travers le monde
B8: Nombre de clients actifs en France | C8: SAP compte environ 1 577 entreprises clientes en France
B9: Principaux secteurs d'activité | C9: L’industrie Le Retail et le Fashion Les services Le secteur public La distribution La santé
A11: Informations générales sur la solution | B11: Nom de la solution ERP | C11: Sap Cloud Erp Pirvate
B12: Version actuelle | C12: La version actuelle de SAP S/4HANA Cloud, Private Edition est la 2023 Release, avec plusieurs Feature Pack Stacks (FPS) publiés au cours de l’année, dont FPS03 est l’un des plus récents SAP S/4HANA Cloud Private Edition suit un cycle de mise à jour annuel, avec des support packages intermédiaire
B13: Date de sortie de la version actuelle | C13: La dernière version de SAP S/4HANA Cloud, Private Edition est la 2023 FPS02 (Feature Pack Stack 02), sortie le 9 octobre 2024
A15: Hébergement et mise à jour | B15: Type d'hébergement | C15: Tous
B16: Fréquence moyenne de mise à jour majeure | C16: une fois par an
B17: Fréquence moyenne de mise à jour mineure | C17: SAP prévoit de publier trois Feature Pack Stacks (FPS) pour chaque version majeure, à raison d’un tous les six mois.

Sheet 1. Besoins fonctionnels 
A1: LISTE DES BESOINS FONCTIONNELS | E1: REPONSE | F1: COMPLEXITE | G1: ESTIMATION COUTS SUPP. | H1: COMPLEMENTS (conseillés)
A3: I. Données référentielles
A4: Habiltations | B4: Gestion multi-sociétés, multi-entités | C4: Mutualisation contrôlée des accès et données : « mono- tenant »​ | E4: YES. Couvert en standard (100%) | G4: =_xlfn.IFNA(VLOOKUP(F4,'Abaques besoins fonctionnels'!$B$3:$C$5,2,0)," ")
C5: Modèle d’habilitations hiérarchisé : par rôle, société, entité juridique, marque, etc.​ | E5: YES. Couvert en standard (100%) | G5: =_xlfn.IFNA(VLOOKUP(F5,'Abaques besoins fonctionnels'!$B$3:$C$5,2,0)," ")
C6: Pilotage centralisé des rôles et autorisations : interface d’administration unique, reporting ​ | E6: YES. Couvert en standard (100%) | G6: =_xlfn.IFNA(VLOOKUP(F6,'Abaques besoins fonctionnels'!$B$3:$C$5,2,0)," ")
A7: Réseaux et clients​ | B7: Gestion des réseaux de vente​ | C7: Prise en charge d’une arborescence réseau de vente (magasins, clients internes) multi- niveaux et multi- vues, en lien avec les systèmes POS | E7: YES. Couvert en standard (100%) | G7: =_xlfn.IFNA(VLOOKUP(F7,'Abaques besoins fonctionnels'!$B$3:$C$5,2,0)," ") | H7: Gestion de hiérarchies de sites et de clients en standard pour gérer différentes vues. Existence de vues TPV de la fiche article dédiées, au niveau client, pour stocker et diffuser les informations articles pour le POS
C8: Gestion d’une organisation FDV (interne / externe, transverse / exclusive ), dont territoires commerciaux | E8: YES. Couvert en standard (100%) | G8: =_xlfn.IFNA(VLOOKUP(F8,'Abaques besoins fonctionnels'!$B$3:$C$5,2,0)," ") | H8: Possibilité de gérer d'autres types de regroupements de sites pour modéliser un découpage territorial propre au client et à son organisation de vente
B9: Hiérarchie comptes clients et données essentielles | C9: Prise en charge d’une hiérarchie de comptes clients multi- niveaux et multi- vues, en lien avec la CRM | E9: YES. Couvert en standard (100%) | G9: =_xlfn.IFNA(VLOOKUP(F9,'Abaques besoins fonctionnels'!$B$3:$C$5,2,0)," ") | H9: SAP couvre le besoin en termes de client B2B. Par contre une segmentzation marketing type B2C est hors périmètre, couverte par des outils de CRM.
C10: Gestion des données essentielles aux transactions et allocations​ | E10: YES. Couvert en standard (100%) | G10: =_xlfn.IFNA(VLOOKUP(F10,'Abaques besoins fonctionnels'!$B$3:$C$5,2,0)," ")
C11: Contrôle de complétion et reporting sur fiches clients non conformes | E11: CUS. Couvert avec customization | G11: =_xlfn.IFNA(VLOOKUP(F11,'Abaques besoins fonctionnels'!$B$3:$C$5,2,0)," ") | H11: Développement de vues CDS suppélementaires requis
A12: Articles | B12: Types d’articles et assortiments​ | C12: Prise en charge de types d’articles multiples (prototypes, samples / CoVoy, etc.) et de paramètres spécifiques​ | E12: YES. Couvert en standard (100%) | G12: =_xlfn.IFNA(VLOOKUP(F12,'Abaques besoins fonctionnels'!$B$3:$C$5,2,0)," ") | H12: Prise en charge de types d'articles multiples (prototypes, samples / CoVoy, etc.) et de paramètres spécifiques. Support natif pour différents types d'articles et scénarios spécifiques via la gestion des catégories et statuts article.
C13: Gestion d’assortiments et critères multiples d’affectation aux magasins / à la hiérarchie magasins (en lien avec PLM et PIM + CRM)​ | E13: YES. Couvert en standard (100%) | G13: =_xlfn.IFNA(VLOOKUP(F13,'Abaques besoins fonctionnels'!$B$3:$C$5,2,0)," ") | H13: Gestion d'assortiments et critères multiples d'affectation aux magasins / à la hiérarchie magasins (en lien avec PLM et PIM + CRM), Gestion intégrée des assortiments avec multiples critères d'affectation via Retail Assortment Management (licence spécifique)
C14: Gestion de catalogues et critères multiples d’affectation aux comptes clients ​ | E14: YES. Couvert en standard (100%) | G14: =_xlfn.IFNA(VLOOKUP(F14,'Abaques besoins fonctionnels'!$B$3:$C$5,2,0)," ") | H14: Gestion de catalogues et critères multiples d'une affectation aux comptes clients, Attribution flexible des catalogues à des clients et magasins avec filtrage multi-critères intégré dans le Master Data.
B15: Variantes articles​ | C15: Prise en charge de variantes articles permettant d’affecter différentes valeurs d’attributs à une même référence (ex : même article tshirt en coton, valeur d’attribut « composition » différente)​ | E15: YES. Couvert en standard (100%) | G15: =_xlfn.IFNA(VLOOKUP(F15,'Abaques besoins fonctionnels'!$B$3:$C$5,2,0)," ") | H15: Prise en charge de variantes articles permettant d'affecter différentes valeurs d'uneattributs à une même référence. Gestion de variantes via des grilles article (matrice Style/Color/Size) et attributs extensibles.
C16: Prise en charge de variantes multiples d’un même article pour une même saison​ | E16: YES. Couvert en standard (100%) | G16: =_xlfn.IFNA(VLOOKUP(F16,'Abaques besoins fonctionnels'!$B$3:$C$5,2,0)," ") | H16: Prise en charge de variantes multiples d'un même article pour une même saison. Lien avec la saison/collection via la hiérarchie merchandising. Les variantes sont associées à des saisons.
C17: Gestion des niveaux « variante » (détaillé) et « référence » (« agrégé ») sur l’ensemble des flux, traitements et données (historiques, commandes et transactions, stocks…) et possibilité de définir le niveau optimum de traitement / gestion, selon les cas​ | E17: YES. Couvert en standard (100%) | G17: =_xlfn.IFNA(VLOOKUP(F17,'Abaques besoins fonctionnels'!$B$3:$C$5,2,0)," ") | H17: Gestion des niveaux " variante " (détaillé) et " référence " (" agrégé ")..., Gestion multi-niveaux (Style > Couleur > Taille) avec flux différenciés selon le niveau géré.
B18: Traçabilité des matières​ | C18: En lien avec la gestion des variantes articles et les nomenclatures (cf achats et réservations matières) :​ - Conserver dans les attributs, de chaque variante utilisée, les informations relatives à la matière : composition, origine, fournisseur, pays, etc.​ - Maintenir la traçabilité sur l’ensemble des flux, traitements et données (historiques, commandes et transactions, stocks…) et possibilité de définir le niveau optimum de traitement / gestion, selon les cas. | E18: YES. Couvert en standard (100%) | G18: =_xlfn.IFNA(VLOOKUP(F18,'Abaques besoins fonctionnels'!$B$3:$C$5,2,0)," ") | H18: Traçabilité des matières : composition, origine, fournisseur, etc.,Attributs matières liés à chaque variante et suivi dans toute la supply chain via les modules MM et SD.
B19: Hiérarchie articles et gestion MCT​ | C19: Prise en charge native d’une hiérarchie articles adaptée au secteur : catégories, familles, groupes… | E19: YES. Couvert en standard (100%) | G19: =_xlfn.IFNA(VLOOKUP(F19,'Abaques besoins fonctionnels'!$B$3:$C$5,2,0)," ") | H19: Prise en charge native d'une hiérarchie articles adaptée au secteur,"Classification hiérarchique personnalisable selon les logiques métier (familles, groupes, classes)."
C20: Prise en charge native d’articles Modèle- Coloris- Taille et des règles de gestion associées (dont références articles / SKU) | E20: YES. Couvert en standard (100%) | G20: =_xlfn.IFNA(VLOOKUP(F20,'Abaques besoins fonctionnels'!$B$3:$C$5,2,0)," ") | H20: Prise en charge native d'articles Modèle- Coloris- Taille et des règles de gestion associées. Support complet du modèle Style/Color/Size avec génération automatique de SKU.
C21: Possibilité de gérer plusieurs hiérarchies Produit​ | E21: YES. Couvert en standard (100%) | G21: =_xlfn.IFNA(VLOOKUP(F21,'Abaques besoins fonctionnels'!$B$3:$C$5,2,0)," ") | H21: Possibilité de gérer plusieurs hiérarchies Produit, Possibilité de créer et gérer plusieurs hiérarchies produit pour des usages différenciés.
B22: Poid des articles | C22: Prise en charge des poids des articles, dans leurs différentes variantes.​ | E22: YES. Couvert en standard (100%) | G22: =_xlfn.IFNA(VLOOKUP(F22,'Abaques besoins fonctionnels'!$B$3:$C$5,2,0)," ") | H22: Prise en charge des poids des articles, dans leurs différentes variantes,Chaque variante possède ses attributs de poids. Poids utilisés dans la logistique et le calcul des coûts.
B23: Articles de regroupements | C23: Prise en charge de types d’articles de regroupement (packs et assimilés, ex : X- t- shirts), à la vente et / ou en gestion sur les différentes étapes du flux​ | E23: YES. Couvert en standard (100%) | G23: =_xlfn.IFNA(VLOOKUP(F23,'Abaques besoins fonctionnels'!$B$3:$C$5,2,0)," ") | H23: Différents types de packs sont possible dépendant de leur comportement dans la chaine logistique et sont géré à travers des catégories d'articles
C24: Gestion de SKU / références spécifiques à ces articles de regroupement (ex : pack de X t- shirts)​ | E24: YES. Couvert en standard (100%) | G24: =_xlfn.IFNA(VLOOKUP(F24,'Abaques besoins fonctionnels'!$B$3:$C$5,2,0)," ") | H24: Gestion de SKU / références spécifiques à ces articles de regroupement.
C25: Conservation des SKU / références unitaires pour les articles regroupés (ex : chaque référence t- shirt entrant dans le pack)​ | E25: YES. Couvert en standard (100%) | G25: =_xlfn.IFNA(VLOOKUP(F25,'Abaques besoins fonctionnels'!$B$3:$C$5,2,0)," ") | H25: Conservation des SKU / références unitaires pour les articles regroupés"SKU composants visibles et gérés individuellement en stock, même dans les packs."
C26: Prise en charge d’attributs et de valeurs spécifiques aux articles de regroupement, dont spécifique (et règle de répartition du prix « packagé » sur les articles unitaires)​ | E26: YES. Couvert en standard (100%) | G26: =_xlfn.IFNA(VLOOKUP(F26,'Abaques besoins fonctionnels'!$B$3:$C$5,2,0)," ") | H26: Prise en charge d'attributs et de valeurs spécifiques aux articles de regroupement. Attributs spécifiques et règles de valorisation du prix packagé réparti selon clés paramétrables.
B27: Autres articles et prestations (upcharges)​ | C27: Prise en charge de prestations de service additionnelles et des différents modes de tarification / facturation associés​ | E27: YES. Couvert en standard (100%) | G27: =_xlfn.IFNA(VLOOKUP(F27,'Abaques besoins fonctionnels'!$B$3:$C$5,2,0)," ") | H27: Prise en charge de prestations de service additionnelles..., Fonctionnalités de service articles intégrées avec gestion tarifaire dédiée.
C28: Gestion de règles d’ajout manuel et automatique de prestations complémentaires, sous conditions / paramètres gérés dans l’ERP | E28: YES. Couvert en standard (100%) | G28: =_xlfn.IFNA(VLOOKUP(F28,'Abaques besoins fonctionnels'!$B$3:$C$5,2,0)," ") | H28: Gestion de règles d'ajout manuel et automatique de prestations complémentaires,"Définition de règles via des conditions (ex : canal, client, seuil) déclenchant ajout automatique."
C29: Définition des prestations / coûts considérés comme « entrée » ou « sortie » (coefficients de calcul du prix de revient).​ | E29: YES. Couvert en standard (100%) | G29: =_xlfn.IFNA(VLOOKUP(F29,'Abaques besoins fonctionnels'!$B$3:$C$5,2,0)," ") | H29: Définition des prestations / coûts considérés comme " entrée " ou " sortie " à travers les schémas de prix. Paramétrage comptable différenciant entrée/sortie selon type de service (ajouté ou détachable).
C30: Déclenchement automatique des évènements de facturation associés | E30: YES. Couvert en standard (100%) | G30: =_xlfn.IFNA(VLOOKUP(F30,'Abaques besoins fonctionnels'!$B$3:$C$5,2,0)," ") | H30: Déclenchement automatique des évènements de facturation associés (upcharges) en lien avec la facturation : événement de facturation déclenché automatiquement selon le paramétrage du flux.
B31: VAS (Value Added Services)​ | C31: Prise en charge de Services à Valeur Ajoutée​ | E31: YES. Couvert en standard (100%) | G31: =_xlfn.IFNA(VLOOKUP(F31,'Abaques besoins fonctionnels'!$B$3:$C$5,2,0)," ") | H31: Prise en charge de Services à Valeur Ajoutée,VAS intégrés comme objets article spécifiques avec règles d'ajout conditionnel.
C32: Gestion de règles d’ajout manuel et automatique de VAS, sous conditions / paramètres gérés dans l’ERP​ | E32: YES. Couvert en standard (100%) | G32: =_xlfn.IFNA(VLOOKUP(F32,'Abaques besoins fonctionnels'!$B$3:$C$5,2,0)," ") | H32: Gestion de règles d'ajout manuel et automatique de VAS,comme pour les upcharges, avec règles liées au client, canal, commande ou segment."
C33: Déclenchement automatique des évènements de facturation associés | E33: YES. Couvert en standard (100%) | G33: =_xlfn.IFNA(VLOOKUP(F33,'Abaques besoins fonctionnels'!$B$3:$C$5,2,0)," ") | H33: Déclenchement automatique des évènements de facturation associés (VAS),Evenements de facturation automatiquement générés si VAS déclenchés.
B34: Grilles de tailles​ | C34: Prise en charge de multiples types, dimensions et unités de taille, adaptées au secteur textile (bonnet, longueur de jambe, demi- pointure, etc). | E34: YES. Couvert en standard (100%) | G34: =_xlfn.IFNA(VLOOKUP(F34,'Abaques besoins fonctionnels'!$B$3:$C$5,2,0)," ") | H34: Prise en charge de multiples types, dimensions et unités de taille,"Grilles tailles multiples supportées (longueur de jambe, bonnet, pointure, etc.)."
C35: Gestion d’une taille principale (ex : taille 40) et de dimensions associées (ex : tour de taille, jambe, cheville, etc.) ​ | E35: YES. Couvert en standard (100%) | G35: =_xlfn.IFNA(VLOOKUP(F35,'Abaques besoins fonctionnels'!$B$3:$C$5,2,0)," ") | H35: Gestion d'uneune taille principale et de dimensions associées,Dimension principale gérée avec dimensions secondaires associées dans la grille article.
C36: Gestion d’index et de valeurs de tailles (ex : 1=XXS, 2=XS, 3=S…) associés aux différentes typologies articles​ | E36: YES. Couvert en standard (100%) | G36: =_xlfn.IFNA(VLOOKUP(F36,'Abaques besoins fonctionnels'!$B$3:$C$5,2,0)," ") | H36: Gestion d'un index et de valeurs de tailles associées aux articles,"Indexation des tailles et codification personnalisable (1=XS, 2=S...)."
C37: Possibilité de modifier les grilles de tailles, y compris l’ajout ou la suppression de tailles (sans création d’un nouvel article / SKU).​ | E37: YES. Couvert en standard (100%) | G37: =_xlfn.IFNA(VLOOKUP(F37,'Abaques besoins fonctionnels'!$B$3:$C$5,2,0)," ") | H37: Possibilité de modifier les grilles de tailles sans créer un nouvel article / SKU,Ajout/suppression de tailles sans recréer un article maitre ou un SKU.
C38: Gestion d’un ordre d’apparition des tailles dans une grille, indépendante de l’index (ex : si XXL = indice 2 = ordre d’apparition 6)​ | E38: YES. Couvert en standard (100%) | G38: =_xlfn.IFNA(VLOOKUP(F38,'Abaques besoins fonctionnels'!$B$3:$C$5,2,0)," ") | H38: Gestion d'uneun ordre d'apparition des tailles dans une grille,Possibilité de gérer ordre d' affichage différent de l'ordre indexé (ordre marché).
C39: Prise en charge de tables et règles de correspondance de tailles entre les différentes normes marchés / pays.​ | E39: YES. Couvert en standard (100%) | G39: =_xlfn.IFNA(VLOOKUP(F39,'Abaques besoins fonctionnels'!$B$3:$C$5,2,0)," ") | H39: Prise en charge de correspondance de tailles entre normes marchés / pays,Mapping entre normes (EU/US/UK/JP) via tables de conversion dans Retail Master.
B40: Gestion des données d’étiquetage | C40: Gestion des données d’étiquetage handtags : template / ID document, valeurs (prix, devises, tailles) et index.​ | E40: YES. Couvert en standard (100%) | G40: =_xlfn.IFNA(VLOOKUP(F40,'Abaques besoins fonctionnels'!$B$3:$C$5,2,0)," ") | H40: Gestion des données d'uneétiquetage handtags : template / ID document...,"Templates configurables avec données dynamiques (prix, tailles, devise) par canal."
C41: Règles multicritères (canal, client, commande, etc.) de sélection des tailles à afficher sur les étiquettes, parmi les tailles disponibles.​ | E41: YES. Couvert en standard (100%) | G41: =_xlfn.IFNA(VLOOKUP(F41,'Abaques besoins fonctionnels'!$B$3:$C$5,2,0)," ") | H41: Règles multicritères pour la sélection des tailles à afficher sur étiquette,Paramétrage de règles multicritères pour afficher la bonne taille selon contexte vente.
A42: Prix et promotions | B42: Gestion des prix et conditions​ | C42: Prise en charge d’une gestion des prix multicritère​ | E42: YES. Couvert en standard (100%) | G42: =_xlfn.IFNA(VLOOKUP(F42,'Abaques besoins fonctionnels'!$B$3:$C$5,2,0)," ") | H42: Gestion de conditions de prix qui peuvent être déclenchées sur des barèmes (poids, montant, quantité…)
C43: Gestion verticale et horizontale sur les canaux, hiérarchies clients et réseaux de vente​ | E43: YES. Couvert en standard (100%) | G43: =_xlfn.IFNA(VLOOKUP(F43,'Abaques besoins fonctionnels'!$B$3:$C$5,2,0)," ") | H43: Gestion d'une structure organisationnelle vente qui permet de gérer des canaux de vente distincts (retail, wholesale), des hiérarchies de client. Permet de gérer des informations divergentes sur les flux de vente et de distribution distincts sans dédoublement de la donnée
C44: Gestion verticale, avec application en masse (nœud parent > enfants) et exceptions (ex : si condition active au nœud enfant, elle remplace le nœud parent).​ | E44: YES. Couvert en standard (100%) | G44: =_xlfn.IFNA(VLOOKUP(F44,'Abaques besoins fonctionnels'!$B$3:$C$5,2,0)," ") | H44: Gestion de priorités dans le schéma de prix de vente et de critères conditionnels de déclenchement de condition de prix (si condition A activée, ne pas déclencher condition B)
C45: Gestion horizontale/ transverse, via des règles de segmentation.​ | E45: YES. Couvert en standard (100%) | G45: =_xlfn.IFNA(VLOOKUP(F45,'Abaques besoins fonctionnels'!$B$3:$C$5,2,0)," ") | H45: Gestion de catégories de client selon des règles de segmentation à la main du client
C46: Gestion à la saison et sur une période donnée (date limite).​ | E46: YES. Couvert en standard (100%) | G46: =_xlfn.IFNA(VLOOKUP(F46,'Abaques besoins fonctionnels'!$B$3:$C$5,2,0)," ") | H46: Les conditions de prix sont forcément gérées sur une période de validité dans le temps. Les conditions de prix liées à une saison sont paramétrées dans un schéma de prix dédié qui n'est activé que via l'objet promotion borné sur la durée de la saison
C47: Prise en charge d’un PVI (Prix de Vente initial) applicable sur tout ou partie des canaux et défini comme prix de référence pour l’article. | E47: YES. Couvert en standard (100%) | G47: =_xlfn.IFNA(VLOOKUP(F47,'Abaques besoins fonctionnels'!$B$3:$C$5,2,0)," ") | H47: Une condition de base peut être stockée au niveau mandant (achat/vente) sur laquelle ensuite on va appliquer des conditions spécifique sur un ou plusieurs canaux
C48: Possibilité d’appliquer des prix différents / spécifiques à certains nœuds (magasin, client, canal…) sans modification du prix de vente initial.​ | E48: YES. Couvert en standard (100%) | G48: =_xlfn.IFNA(VLOOKUP(F48,'Abaques besoins fonctionnels'!$B$3:$C$5,2,0)," ") | H48: Chaque type de prix / remise est stocké dans une condition distincte rattachée à une séquence d'accès qui détermine à quel niveau de granularité la condition sera appliqué. Le prix final appliqué dans la transaction est le résultat de l'application de l'ensemble de ses conditions sans qu'on n'ait à écraser la condition de base
C49: Gestion de la devise de commande: Prise en charge d’index de référence (mise à jour automatique).​ | E49: YES. Couvert en standard (100%) | G49: =_xlfn.IFNA(VLOOKUP(F49,'Abaques besoins fonctionnels'!$B$3:$C$5,2,0)," ") | H49: Oui gestion automatique d'index
C50: Gestion de la devise de commande: Possibilité de gestion / saisie manuelle de taux.​ | E50: YES. Couvert en standard (100%) | G50: =_xlfn.IFNA(VLOOKUP(F50,'Abaques besoins fonctionnels'!$B$3:$C$5,2,0)," ") | H50: Oui gestion manuelle de taux
C51: Gestion de la devise de commande: Possibilité d’ajouter un markup sur les taux appliqués (depuis un index ou un taux saisi manuellement), sur différents niveaux de la hiérarchie produit.​ | E51: YES. Couvert en standard (100%) | G51: =_xlfn.IFNA(VLOOKUP(F51,'Abaques besoins fonctionnels'!$B$3:$C$5,2,0)," ") | H51: Oui
C52: Possibilité de saisir des prix fixes en devise (indépendamment des taux).​ | E52: YES. Couvert en standard (100%) | G52: =_xlfn.IFNA(VLOOKUP(F52,'Abaques besoins fonctionnels'!$B$3:$C$5,2,0)," ") | H52: Oui directement au poste de commande
C53: Gestion des arrondis psychologiques, sur la base de règles de gestion paramétrables.​ - Ajustement automatique / propositions d’ajustement par le système.​ - Règles d’application / de conversion en devises et sur les marchés internationaux. | E53: YES. Couvert en standard (100%) | G53: =_xlfn.IFNA(VLOOKUP(F53,'Abaques besoins fonctionnels'!$B$3:$C$5,2,0)," ") | H53: Oui il est possible de définir dans le paramétrage SAP des intervalles de prix sur 2 décimales auxquels on applique une même règle d'arrondi
C54: Possibilité d’ajouter un markup sur les taux appliqués (depuis un index ou un taux saisi manuellement), sur différents niveaux de la hiérarchie produit.​ | E54: YES. Couvert en standard (100%) | G54: =_xlfn.IFNA(VLOOKUP(F54,'Abaques besoins fonctionnels'!$B$3:$C$5,2,0)," ") | H54: Oui les markup peuvent être saisis au poste de commande ou bien stockés dans une condition de prix sur la séquence d'accès souhaitée, donc au niveau hiérarchique souhaité
... C56: Historisation et traçabilité des prix de vente par modèle- coloris et par devise, aux différents niveaux et nœuds.​ | E56: YES. Couvert en standard (100%) | G56: =_xlfn.IFNA(VLOOKUP(F56,'Abaques besoins fonctionnels'!$B$3:$C$5,2,0)," ") | H56: L'ensemble des conditions de prix sont historisées dans une table standard
B57: Gestion promotionnelle​ | C57: Gestion centralisée et multicritère des opérations promotionnelles (prix, quantités, gratuité, etc.)​ | E57: YES. Couvert en standard (100%) | G57: =_xlfn.IFNA(VLOOKUP(F57,'Abaques besoins fonctionnels'!$B$3:$C$5,2,0)," ") | H57: Les opérations promotionnelles couvrent le paramétrage des conditions de prix et portent les quantités totales qui pourront être allouées à des canaux/magasin via table d'allocation
C58: Gestion verticale et horizontale des conditions sur les canaux, hiérarchies clients et réseaux de vente​ | E58: YES. Couvert en standard (100%) | G58: =_xlfn.IFNA(VLOOKUP(F58,'Abaques besoins fonctionnels'!$B$3:$C$5,2,0)," ") | H58: Gestion identique via des conditions de prix spécfiiques pour les promotions
C59: Gestion verticale, avec application en masse (nœud parent > enfants) et exceptions (ex : si condition active au nœud enfant, elle remplace le nœud parent).​ | E59: YES. Couvert en standard (100%) | G59: =_xlfn.IFNA(VLOOKUP(F59,'Abaques besoins fonctionnels'!$B$3:$C$5,2,0)," ") | H59: Gestion de priorités dans le schéma de prix de vente et de critères conditionnels de déclenchement de condition de prix (si condition A activée, ne pas déclencher condition B)
C60: Gestion horizontale/ transverse, via des règles de segmentation.​ | E60: YES. Couvert en standard (100%) | G60: =_xlfn.IFNA(VLOOKUP(F60,'Abaques besoins fonctionnels'!$B$3:$C$5,2,0)," ") | H60: Gestion de catégories de client selon des règles de segmentation à la main du client
C61: Gestion à la saison et/ou dates de validité définies, et sur les différentes dimensions (organisation, canal, client, article…)​ | E61: YES. Couvert en standard (100%) | G61: =_xlfn.IFNA(VLOOKUP(F61,'Abaques besoins fonctionnels'!$B$3:$C$5,2,0)," ") | H61: Les conditions de prix sont forcément gérées sur une période de validité dans le temps. Les conditions de prix liées à une saison sont paramétrées dans un schéma de prix dédié qui n'est activé que via l'objet promotion borné sur la durée de la saison
C62: Gestion de paliers / niveaux de remises, application en cascade, prix barrés, articles offerts sous conditions… | E62: NON. Non couvert | G62: =_xlfn.IFNA(VLOOKUP(F62,'Abaques besoins fonctionnels'!$B$3:$C$5,2,0)," ") | H62: Le standard SAP ne gère que des conditions de prix de vente type prix barré ou avec des remises en % et en valeur. La gestion de mécaniques promotionnelles complexes type articles offerts sous conditions etc… peut être portée par le module SAP PMR mais sinon par un autre applicatif lié à l'encaissement dans le fashion (UR...)
C63: Possibilité d’appliquer des conditions promotionnelles / de remise sur les prix de référence et / ou sur un prix remisé / promotionnel (conditions en cascade).​ | E63: YES. Couvert en standard (100%) | G63: =_xlfn.IFNA(VLOOKUP(F63,'Abaques besoins fonctionnels'!$B$3:$C$5,2,0)," ") | H63: Chaque type de prix / remise est stocké dans une condition distincte rattachée à une séquence d'accès qui détermine à quel niveau de granularité la condition sera appliqué. Le prix final appliqué dans la transaction est le résultat de l'application de l'ensemble de ses conditions sans qu'on n'ait à écraser la condition de base
B64: Remises et conditions contractuelles​ | C64: Prise en charge de conditions contractuelles et de conditions de remises (sur devis / commande, sur facture ou pied de facture, immédiates ou différées (progression CA, RFA) => automatique, ou simplifiée via des rapports) | E64: TPS. Couvert par application tierce (au catalogue éditeur) | G64: =_xlfn.IFNA(VLOOKUP(F64,'Abaques besoins fonctionnels'!$B$3:$C$5,2,0)," ") | H64: Les conditions de remises avant sur factures/commande sont gérées par le standard SAP. L'automatisation du calcul de montant de remise arrière sur des bases complexes peut nécessiter de prendre la solution VISTEX.
C65: Gestion verticale et horizontale des conditions sur les canaux, hiérarchies clients et réseaux de vente​ | E65: YES. Couvert en standard (100%) | G65: =_xlfn.IFNA(VLOOKUP(F65,'Abaques besoins fonctionnels'!$B$3:$C$5,2,0)," ") | H65: Chaque type de prix / remise est stocké dans une condition distincte rattachée à une séquence d'accès qui détermine à quel niveau de granularité la condition sera appliqué. Le prix final appliqué dans la transaction est le résultat de l'application de l'ensemble de ses conditions sans qu'on n'ait à écraser la condition de base
C66: Gestion verticale, avec application en masse (nœud parent > enfants) et exceptions (ex : si condition active au nœud enfant, elle remplace le nœud parent).​ | E66: YES. Couvert en standard (100%) | G66: =_xlfn.IFNA(VLOOKUP(F66,'Abaques besoins fonctionnels'!$B$3:$C$5,2,0)," ") | H66: Oui cf réponses précédentes
C67: Gestion Horizontale/ transverse, via des règles de segmentation.​ | E67: YES. Couvert en standard (100%) | G67: =_xlfn.IFNA(VLOOKUP(F67,'Abaques besoins fonctionnels'!$B$3:$C$5,2,0)," ") | H67: Oui cf réponses précédentes
C68: Gestion à la saison et sur une période donnée (date limite)​ | E68: YES. Couvert en standard (100%) | G68: =_xlfn.IFNA(VLOOKUP(F68,'Abaques besoins fonctionnels'!$B$3:$C$5,2,0)," ") | H68: Oui cf réponses précédentes
A69: Conditions logistiques | B69: Conditions d’approvisionnement​ | C69: Prise en charge de conditions d’approvisionnement multiples (Fournisseurs, Articles, Route logistique​, Entrepôt et plateforme d’arrivée​ ,Modes de transport​, Conditions de colisage​) | E69: YES. Couvert en standard (100%) | G69: =_xlfn.IFNA(VLOOKUP(F69,'Abaques besoins fonctionnels'!$B$3:$C$5,2,0)," ") | H69: Multi-sources et conditions d’approvisionnement gérées dans le module MM-PUR avec configuration route, hub, fournisseur et colisage.
C70: Prise en charge de jalons multiples : remise transitaire, remise transporteur, arrivée quai, arrivée entrepôt… | E70: YES. Couvert en standard (100%) | G70: =_xlfn.IFNA(VLOOKUP(F70,'Abaques besoins fonctionnels'!$B$3:$C$5,2,0)," ") | H70: Jalons logistiques définis via planification et paramètres lead time : remise transitaire, quai, transporteur.
C71: Calcul automatique des lead times associés (Possibilité de définir / ajouter des buffers et marges d’erreur sur les lead times calculés.) | E71: YES. Couvert en standard (100%) | G71: =_xlfn.IFNA(VLOOKUP(F71,'Abaques besoins fonctionnels'!$B$3:$C$5,2,0)," ") | H71: Calcul dynamique des lead times avec marges de sécurité/buffers configurables dans les données de base.
B72: Conditions de livraison | C72: Prise en charge de conditions de livraison multiples (Clients,Entrepôt et plateforme de départ​,Articles,Route logistique​,Modes de transport​,Conditions de colisage​) | E72: YES. Couvert en standard (100%) | G72: =_xlfn.IFNA(VLOOKUP(F72,'Abaques besoins fonctionnels'!$B$3:$C$5,2,0)," ") | H72: Conditions de livraison paramétrables : plateformes, routes, entrepôts, modes de transport.
C73: Prise en charge de jalons multiples : préparation, mise en expédition, remise transporteur, remise au client estimée…​ | E73: YES. Couvert en standard (100%) | G73: =_xlfn.IFNA(VLOOKUP(F73,'Abaques besoins fonctionnels'!$B$3:$C$5,2,0)," ") | H73: Étapes multi-jalons gérées par scénario de livraison, Possibilité de suivi dynamique des événements de chaque étape dans Track & Trace (licence complémnetaire)
C74: Calcul automatique des lead times associés​ ( Possibilité de définir / ajouter des buffers et marges d’erreur sur les lead times calculés.) | E74: YES. Couvert en standard (100%) | G74: =_xlfn.IFNA(VLOOKUP(F74,'Abaques besoins fonctionnels'!$B$3:$C$5,2,0)," ") | H74: Lead time livraison calculé automatiquement, ajusté par buffers définis dans condition route et shipping point.
B75: Unités logistiques et colisage​ | C75: Prise en charge de différents modes de colisage et des calculs / règles permettant de les déterminer​ | E75: YES. Couvert en standard (100%) | G75: =_xlfn.IFNA(VLOOKUP(F75,'Abaques besoins fonctionnels'!$B$3:$C$5,2,0)," ") | H75: Définition des unités logistiques (HU), règles de packing et calculs auto via Logistics Execution.
C76: Prise en charge de références / d’objets spécifiques permettant d’identifier les articles et quantités en colis (non disponibles en vrac)​ | E76: YES. Couvert en standard (100%) | G76: =_xlfn.IFNA(VLOOKUP(F76,'Abaques besoins fonctionnels'!$B$3:$C$5,2,0)," ") | H76: Identification articles/quantités par numéro HU, étiquette palette/colis, gestion serialisation.
C77: Prise en charge des articles de regroupement et de leurs spécificités dans le calcul des colisages (référence spécifique, non- séparable, etc.) | E77: YES. Couvert en standard (100%) | G77: =_xlfn.IFNA(VLOOKUP(F77,'Abaques besoins fonctionnels'!$B$3:$C$5,2,0)," ") | H77: Articles regroupés gérés comme kits/packs : calcul spécifique via Bill of Materials (BOM).
C78: Possibilité de définir des modes de colisage réservés aux packs, au vrac, hybrides, etc.​ | E78: YES. Couvert en standard (100%) | G78: =_xlfn.IFNA(VLOOKUP(F78,'Abaques besoins fonctionnels'!$B$3:$C$5,2,0)," ") | H78: Règles de colisage par type (pack, vrac) définies dans Master Data et Logistics Execution.
C79: Calcul des poids des articles colisés, à partir des poids des articles unitaires et d’un poids d’emballage.​ | E79: YES. Couvert en standard (100%) | G79: =_xlfn.IFNA(VLOOKUP(F79,'Abaques besoins fonctionnels'!$B$3:$C$5,2,0)," ") | H79: Poids colisés calculés automatiquement : poids net + emballage via conditionnement logistique.
B80: Mode de conditionnement​ | C80: Prise en charge de différents modes de conditionnement (à plat, suspendu, sans emballage, etc.). ==> Lors des différentes étapes : transport, entrepôt, magasin…​ | E80: YES. Couvert en standard (100%) | G80: =_xlfn.IFNA(VLOOKUP(F80,'Abaques besoins fonctionnels'!$B$3:$C$5,2,0)," ") | H80: Modes conditionnement standardisés paramétrés dans données article/logistique.
C81: Prise en charge de notions de « standard » et « hors standard » pour chacun des modes de conditionnement.​ | E81: YES. Couvert en standard (100%) | G81: =_xlfn.IFNA(VLOOKUP(F81,'Abaques besoins fonctionnels'!$B$3:$C$5,2,0)," ") | H81: Distinction standard / hors standard définie par type de conditionnement dans le Master Data.
C82: Gestion des paramètres et attributs associés, permettant les calculs et traitements logistiques associés (modes de transport, prix, lead time, etc.).​ | E82: YES. Couvert en standard (100%) | G82: =_xlfn.IFNA(VLOOKUP(F82,'Abaques besoins fonctionnels'!$B$3:$C$5,2,0)," ") | H82: Attributs conditionnement intégrés au calcul transport, coût, délai via LE et SD.
C83: Calcul des poids ajustés par type de conditionnement.​ | E83: YES. Couvert en standard (100%) | G83: =_xlfn.IFNA(VLOOKUP(F83,'Abaques besoins fonctionnels'!$B$3:$C$5,2,0)," ") | H83: Poids ajusté selon type et unité logistique, visible dans document logistique.
A84: ADV et facturation | B84: Données de facturation client​ | C84: Prise en charge d’un champ dédié à l’acceptation des CGV (en lien avec la CRM) => si non géré à chaque commande.​ | E84: YES. Couvert en standard (100%) | G84: =_xlfn.IFNA(VLOOKUP(F84,'Abaques besoins fonctionnels'!$B$3:$C$5,2,0)," ") | H84: Champ CGV intégré à la fiche client/contrat, lié au Sales Order dans SD.
C85: Gestion des templates de factures par client / typologie de client : ID template, champs standards et spécifiques.​ | E85: YES. Couvert en standard (100%) | G85: =_xlfn.IFNA(VLOOKUP(F85,'Abaques besoins fonctionnels'!$B$3:$C$5,2,0)," ") | H85: Templates facture paramétrés par client/segment, ID et champs dans SD Billing. Chaque formulaire spécifique doit être développé
C86: Gestion de la devise de commande et de facturation (cf gestion des prix dans cette section et « ADV, finance et comptabilité).​ | E86: YES. Couvert en standard (100%) | G86: =_xlfn.IFNA(VLOOKUP(F86,'Abaques besoins fonctionnels'!$B$3:$C$5,2,0)," ") | H86: Devise transactionnelle gérée dans SD/MM avec taux de change auto.
C87: Mode d’envoi de la facture au client (direct, coffre- fort électronique, via CRM / portail client).​ | E87: YES. Couvert en standard (100%) | G87: =_xlfn.IFNA(VLOOKUP(F87,'Abaques besoins fonctionnels'!$B$3:$C$5,2,0)," ") | H87: Envoi automatisé via Output Management / BRF+ : direct, portail, coffre-fort.
A88: Général | B88: Workflow de mise à jour des données​ | C88: Prise en charge de workflows de mise à jour des données, selon le niveau de sensibilité​ (En lien avec la gestion des habilitations​) | E88: YES. Couvert en standard (100%) | G88: =_xlfn.IFNA(VLOOKUP(F88,'Abaques besoins fonctionnels'!$B$3:$C$5,2,0)," ") | H88: Workflows de mise à jour paramétrés via BRF+ et autorisations (habilitations).
B89: Contrôle de cohérence des données ERP-autres sources​ | C89: Prise en charge d’un contrôle de cohérence entre les données présentes dans l’ERP et les données arrivant (par chargement ou interfaces) d’autres sources (données institutionnelles / invariables / sensibles).​ | E89: YES. Couvert en standard (100%) | G89: =_xlfn.IFNA(VLOOKUP(F89,'Abaques besoins fonctionnels'!$B$3:$C$5,2,0)," ") | H89: Fonctions standard de contrôle d’intégrité pour vérification données entrantes (Data Services, interfaces). Interface à développer
C90: Etat de reporting / cockpit de revue des anomalies et écarts.​ | E90: YES. Couvert en standard (100%) | G90: =_xlfn.IFNA(VLOOKUP(F90,'Abaques besoins fonctionnels'!$B$3:$C$5,2,0)," ")
C91: Possibilité de déclencher ou bloquer des traitements (ex : commande) en cas d’écart sur certaines données.​ | E91: YES. Couvert en standard (100%) | G91: =_xlfn.IFNA(VLOOKUP(F91,'Abaques besoins fonctionnels'!$B$3:$C$5,2,0)," ") | H91: Règles de blocage/validation conditionnelle configurables par type d’écart.
A93: II. Saisons, Permanents et carry-overs
A94: Articles saisonniers​ | B94: Dimensions Saison​ | C94: Possibilité de créer des Saisons de gestion indépendantes​ | E94: YES. Couvert en standard (100%) | G94: =_xlfn.IFNA(VLOOKUP(F94,'Abaques besoins fonctionnels'!$B$3:$C$5,2,0)," ") | H94: Saisons créées comme attributs de classification avec validité paramétrée dans Master Data.
C95: Dates de validité par Saison, avec possibilité de chevauchement​ ( Point d’attention : prévoir, pour un même produit, des saisons différentes de commande, vente, achat, catalogue…) | E95: YES. Couvert en standard (100%) | G95: =_xlfn.IFNA(VLOOKUP(F95,'Abaques besoins fonctionnels'!$B$3:$C$5,2,0)," ") | H95: Dates valides par saison configurables, chevauchement géré par période de validité.
C96: Possibilité de rattachement multi- saisons (actives en même temps)​ | E96: YES. Couvert en standard (100%) | G96: =_xlfn.IFNA(VLOOKUP(F96,'Abaques besoins fonctionnels'!$B$3:$C$5,2,0)," ") | H96: Rattachement multi-saisons possible via associations de variantes / assortiments.
C97: Prise en charge de saisons croisées (ex : SS Europe vs AW Océanie)​ | E97: YES. Couvert en standard (100%) | G97: =_xlfn.IFNA(VLOOKUP(F97,'Abaques besoins fonctionnels'!$B$3:$C$5,2,0)," ") | H97: Saisons croisées gérées avec zones géographiques dans la hiérarchie merchandising.
B98: Données référentielles à la saison​ | C98: Articles et attributs (Point d’attention : plusieurs variantes / valeurs d’attributs possibles au sein d’une même saison​) | E98: YES. Couvert en standard (100%) | G98: =_xlfn.IFNA(VLOOKUP(F98,'Abaques besoins fonctionnels'!$B$3:$C$5,2,0)," ") | H98: Il est possible de gérer des attributs articles avec des champs personnalisés pour la saison
C99: Fournisseurs | E99: YES. Couvert en standard (100%) | G99: =_xlfn.IFNA(VLOOKUP(F99,'Abaques besoins fonctionnels'!$B$3:$C$5,2,0)," ") | H99: Il est possible de déterminer des sources d'approvisionnement spécifiques à la maille d'une saison soit en gérant des périodes de validité correspondant à la saison dans le répertoire des sources d'approvisionnement ou en créant des fiches info achat spécifiques pour la saison
C100: Clients | E100: YES. Couvert en standard (100%) | G100: =_xlfn.IFNA(VLOOKUP(F100,'Abaques besoins fonctionnels'!$B$3:$C$5,2,0)," ") | H100: Il est possible de gérer des segments de client saisonniers avec des types de classification client spécifiques ou des groupes de client spécifiques
C101: Prix de vente / conditions de vente, dont remises​ | E101: YES. Couvert en standard (100%) | G101: =_xlfn.IFNA(VLOOKUP(F101,'Abaques besoins fonctionnels'!$B$3:$C$5,2,0)," ") | H101: Il est possible de déterminer des conditions de prix (dont remise) activables uniquement à la maille saison
C102: Prix d’achat / conditions d’achat, dont remises​ | E102: YES. Couvert en standard (100%) | G102: =_xlfn.IFNA(VLOOKUP(F102,'Abaques besoins fonctionnels'!$B$3:$C$5,2,0)," ") | H102: Même fonctionnement conditions d'achat que pour conditions de vente
B103: Paramètres de gestion à la saison​ | C103: Conditions et paramètres logistiques​ | E103: YES. Couvert en standard (100%) | G103: =_xlfn.IFNA(VLOOKUP(F103,'Abaques besoins fonctionnels'!$B$3:$C$5,2,0)," ") | H103: SAP peut déterminer des lead time spécifiques pour une saison, avec une gestion de mode de transports préférés par saison et des notions de quantité min/max dans la vue sit de la fiche article ou via des FIA spécifiques ou encore avec des SLA saisonniers
...

Sheet Abaques besoins fonctionnels
A1: Type de développement | B1: Niveau de complexité | C1: Total
A3: Enh / Exits / Badi | B3: Low | C3: 10
A4: Enh / Exits / Badi | B4: Medium | C4: 18
A5: Enh / Exits / Badi | B5: High | C5: 28

Sheet 2. Interfaces 
A1: DOMAINE | B1: APPLICATION | C1: ROLE | D1: PRINCIPALES DONNEES ENVOYEES PAR L'ERP | E1: PRINCIPALES DONNEES RECUES PAR L'ERP | F1: REPONSE SANS INTEGRATION SUITE | G1: REPONSE AVEC INTEGRATION SUITE | H1: ESTIMATION COUTS MISE EN ŒUVRE | I1: LIMITE DE VOLUME DE TRANSFERT O/N | J1: DETAIL DES LIMITES DE TRANSFERT | K1: COMMENTAIRE (facultatif) | L1: ESTIMATION COUTS MISE EN ŒUVRE (Numérique)
A2: Planification des achats | B2: OPTIMATE | C2: Calcule les budgets d'achats à partir des budgets de ventes Etablit les planning hebdomadaires d'achats | D2: - | E2: - Demandes d'achats (à la semaine) - par Modèle Coloris Taille - par client (Beaumanoir découpe ses commandes d'achat par canal et client) | F2: DEV. Interface spécifique à développer | G2: DEV. Interface spécifique à développer | H2: 44J | I2: NON | K2: 2 interfaces entrantes | L2: 44
A3: Développement des produits | B3: CENTRIX PLM | C3: Définit la liste des Articles et leurs données / attributs Gère les assortiments (segmentation client et magasins) | D3: - | E3: - Données articles détaillées : codes, désignations, attributs | F3: DEV. Interface spécifique à développer | G3: CUS. Connecteur spécifique existant | H3: 66J | I3: NON | K3: 3 interfaces entrantes , accélérateurs delaware pour SAP Intégration Suite | L3: 66
A4: Portail fournisseurs et partenaires | B4: SAP SNC | C4: Met à jour les commandes d'achat (saisie fournisseurs via portail) Transmet des données relatives aux commandes d'achat (messages transitaire, étiquettes au partenaire dédiée, etc.) | D4: - Données de commandes détaillées (à la ligne) - Références articles et données essentielles (pour étiquettes composition) - Données d'étiquettage retail (index et donnés tailles et prix) | E4: - Mise à jour de commandes d'achats | F4: DEV. Interface spécifique à développer | G4: DEV. Interface spécifique à développer | H4: 70J | I4: NON | K4: 3 interfaces sortantes 1 interface entrante | L4: 70
A5: Gestion d'entrepôts | B5: INCONSO WMS MANHATTAN WMS REFLEX WMS | C5: Pilote les opérations entrepôt (stocks, commandes) en lien avec l'ERP | D5: - Données articles détaillées - Données de commandes d'achat détaillées - Données de commandes de vente détaillées | E5: - Mouvements de stocks - Mise à jour statuts de commandes de vente - Mise à jour statuts de commandes d'achat | F5: DEV. Interface spécifique à développer | G5: DEV. Interface spécifique à développer | H5: 361J | I5: NON | K5: 9 interfaces sortantes 9 interfaces entrantes | L5: 361
A6: Calcul des optimums de stocks magasins | B6: SCOR-TEX | C6: Calcule les stocks magasin idéaux sur la base des données de ventes et de stocks Peut calculer des propositions de réapprovisionnement à partir des données de ventes et d'écoulement et des stocks | D6: - Données de stocks centraux, par Modèle Coloris Taille | E6: - Réception des optimum de stocks magasins calculés par SCOR-TEX, au niveau MCT / magasin | F6: DEV. Interface spécifique à développer | G6: DEV. Interface spécifique à développer | H6: 38J | I6: NON | K6: 1 interface entrante 1 interface sortante | L6: 38
A7: Gestion des points de vente (POS) | B7: CEGID Y2 | C7: Gère l'ensemble des opérations des magasins, dont émission des demandes de réassort, réception des commandes de réassort et stocks magasins au détail | D7: - Données articles détaillées - Données de prix détaillées - Données d'opérations promotionnelles - Données de commandes de vente détaillées (MEP et réassort) - Messages et annonces logistiques (livraisons, retours) | E7: - Ventes magasins (consolidées) - Valeurs des stocks magasins - Demandes de réassort | F7: DEV. Interface spécifique à développer | G7: DEV. Interface spécifique à développer | H7: 183J | I7: NON | K7: 6 interfaces sortantes 4 interfaces entrantes | L7: 183
A8: Gestion des points de vente (POS) | B8: UNIVERS RETAIL | C8: Gère l'ensemble des opérations des magasins, dont réception des commandes de réassort et stocks magasins au détail | D8: - Données articles détaillées - Données de prix détaillées - Données d'opérations promotionnelles - Données de commandes de vente détaillées (MEP et réassort) - Messages et annonces logistiques (livraisons, retours) | E8: - Ventes magasins (consolidées) - Valeurs des stocks magasins - Demandes de réassort | F8: DEV. Interface spécifique à développer | G8: DEV. Interface spécifique à développer | H8: 183J | I8: NON | K8: 6 interfaces sortantes 4 interfaces entrantes | L8: 183
A9: Relation client (CRM) | B9: ZOHO CRM | C9: Pilote la relation client et la passation des commandes wholesale et e-commerce (appuyé par Elastic Search) Publie les catalogues clients Gère certaines opérations promotionnelles | D9: - Organisation commerciale - Données articles détaillées - Données de prix détaillées (dont conditions de vente) - Données d'opérations promotionnelles - Données de commandes détaillées (B2B, e-commerce) - Messages et annonces logistiques (livraisons, retours) | E9: - Données clients essentielles (référentielles) - Détail des commandes de vente à créer - Détail des demandes de retours à traiter | F9: DEV. Interface spécifique à développer | G9: DEV. Interface spécifique à développer | H9: 178J | I9: NON | K9: 7 interfaces sortantes 3 interfaces entrantes | L9: 178
A10: Relation client (CRM) | B10: SALESFORCE CRM | C10: Pilote la relation client et la passation des commandes wholesale et e-commerce (appuyé par Elastic Search) Publie les catalogues clients Gère certaines opérations promotionnelles | D10: - Organisation commerciale - Données articles détaillées - Données de prix détaillées (dont conditions de vente) - Données d'opérations promotionnelles - Données de commandes détaillées (B2B, e-commerce) - Messages et annonces logistiques (livraisons, retours) | E10: - Données clients essentielles (référentielles) - Détail des commandes de vente à créer - Détail des demandes de retours à traiter | F10: DEV. Interface spécifique à développer | G10: STD. Connecteur standard existant | H10: 178J | I10: NON | K10: 7 interfaces sortantes 3 interfaces entrantes 'Package SAP Integration Suite pour Salesforce. | L10: 178
A11: Commissionnement | B11: SAP VISTEX | C11: Calcule les factures de commission (force de vente partenaire) | D11: - Organisation commerciale - Données clients essentielles (référentielles) - Données essentielles de commandes de vente (chiffre d'affaires et données de calcul) | E11: - Détail des "commandes de commissionnement" à régler (par partenaire FDV) | F11: STD. Connecteur standard existant | G11: STD. Connecteur standard existant | H11: 124J | I11: NON | K11: Connecteur standard de Vistex 5 flux sortantes et 2 entrants | L11: 124
A12: Finance et comptabilité | B12: SAP FICO | C12: Génère et enregistre les factures Assure la gestion financière et comptable | D12: - Données clients / tiers à facturer détaillées - Données spécifiques à la facturation : template à utiliser, mentions particulières, etc. - Données d'éditique : template complet, valeurs de champs - Conditions contractuelles et conditions de remise détaillées - Données de commandes de ventes détaillées (articles et prestations, prix, devise) | E12: - | F12: STD. Connecteur standard existant | G12: STD. Connecteur standard existant | H12: 80J | I12: NON | K12: Connexion RFC avec paramétrage d'IDOC standard. Vérifier si un DEV est à prévoir sur les données d'editique. 5 interfaces sortantes | L12: 80
L13: =SUM(L1:L12) -> 1505 | M13: Jours de développement des interfaces.
B14: * il s'agit ici de recenser les données essentielles et susceptibles de représenter la volumétrie la plus importante

Sheet 3. Architecture et sécurité
A1: LISTE DES CRITERES NON FONCTIONNELS | D1: REPONSE | E1: COMPLEMENTS
A2: Architecture | B2: Généralités | C2: Quels langages de programmation sont utilisés pour le développement de votre ERP? | D2: Cf compléments | E2: Le développement de SAP S/4HANA repose sur un ensemble de langages de programmation et de technologies adaptés à différents niveaux de la plateforme (backend, frontend, intégration, extensions). Voici les principaux : 1. ABAP (Advanced Business Application Programming) Langage principal pour le développement backend dans SAP S/4HANA Utilisé pour : La logique métier Les rapports Les extensions personnalisées (via ABAP RESTful Application Programming Model) ABAP est exécuté sur la SAP NetWeaver Application Server ou SAP BTP ABAP Environment 2. JavaScript / TypeScript Utilisés côté frontend, notamment avec SAP Fiori (interface utilisateur moderne) Développement d’applications avec SAPUI5 (framework basé sur JavaScript) TypeScript est souvent utilisé dans les projets Fiori Elements ou CAP (Cloud Application Programming) 3. Java Utilisé dans certains services de la SAP Business Technology Platform (BTP) Présent dans les microservices, les intégrations, ou les extensions cloud 4. SQLScript Langage de requête utilisé dans SAP HANA pour écrire des procédures stockées et des vues calculées Optimisé pour le traitement in-memory 5. Node.js / Python (dans certains cas) Utilisés pour des extensions cloud, des API, ou des intégrations personnalisées via SAP BTP Pas natifs à SAP S/4HANA, mais compatibles via des environnements comme SAP Kyma ou SAP Cloud Foundry 🔧 Environnement de développement Eclipse avec ABAP Development Tools (ADT) pour le backend SAP Business Application Studio ou Visual Studio Code pour le frontend et les extensions cloud
C3: Quelles sont les bases de données actuellement supportées par votre ERP? | D3: HANA | E3: SAP S/4HANA est conçu pour fonctionner exclusivement avec la base de données SAP HANA, qui est une base de données en mémoire (In-Memory) développée par SAP.
B4: Modularité | C4: Votre solution permet-elle des développements spécifiques ? Si oui, dans quel langage ? | D4: OUI | E4: Oui, SAP S/4HANA permet des développements spécifiques, appelés aussi extensions ou custom developments, pour répondre aux besoins métiers particuliers d’une entreprise. 🧩 Types de développements spécifiques possibles 1. Développements dans le core (In-App) Réalisés directement dans le système SAP S/4HANA Utilisent le langage ABAP (Advanced Business Application Programming) Exemples : Ajout de champs personnalisés Création de rapports spécifiques Développement de modules fonctionnels sur mesure 2. Développements en dehors du core (Side-by-Side) Réalisés sur la SAP Business Technology Platform (SAP BTP) Permettent de ne pas impacter le cœur standard de S/4HANA Utilisent des langages modernes comme : JavaScript / TypeScript (via SAP Fiori / SAPUI5) Java (pour les microservices) Node.js ou Python (dans des environnements comme SAP Kyma ou Cloud Foundry) SQLScript (pour les traitements dans SAP HANA) 🛠️ Outils de développement Eclipse avec ABAP Development Tools (ADT) : pour le backend ABAP SAP Business Application Studio : pour les applications Fiori, CAP, extensions cloud SAP Web IDE (ancien, en voie de remplacement)
C5: Les domaines fonctionnels suivants sont-ils couverts par le socle principal, ou des modules / solutions annexes ?
C6: - Planning (amont) | D6: SOC. Socle central | E6: La fonctionnalité de planning amont est bien intégrée dans SAP S/4HANA, notamment via les modules PP/DS (Production Planning and Detailed Scheduling) et SAP Integrated Business Planning (IBP). 🧠 1. Planning amont dans SAP S/4HANA (PP/DS intégré) Depuis les dernières versions, PP/DS est intégré nativement dans le cœur de SAP S/4HANA, ce qui permet : De planifier la production en amont, en tenant compte des contraintes de capacité, de ressources et de disponibilité des composants. D’utiliser des outils comme : Le detailed scheduling planning board (planification graphique). Le product planning table. Des heuristiques standard et des optimisations automatiques pour ajuster les séquences de production 1. 🔄 2. Synchronisation avec la planification globale SAP S/4HANA permet une planification intégrée entre les achats, la production, les ventes et la logistique. Le planning amont est synchronisé avec : Les prévisions de demande. Les contraintes de production. Les engagements clients (ATP – Available to Promise). 🌐 3. Extension avec SAP IBP (optionnel) Pour des scénarios plus complexes ou multi-sites : SAP Integrated Business Planning (IBP) peut être utilisé en complément. Il permet une planification stratégique et tactique (S&OP, planification de la demande, planification des approvisionnements). Intégration fluide avec S/4HANA via des connecteurs standards 2. ✅ En résumé : SAP S/4HANA intègre nativement des fonctionnalités de planning amont, via PP/DS, avec des capacités avancées de planification, d’optimisation et de synchronisation des processus industriels.
C7: - Gestion des achats | D7: SOC. Socle central | E7: a gestion des achats est entièrement intégrée dans SAP S/4HANA. Elle fait partie du module central de gestion des approvisionnements, appelé SAP S/4HANA Sourcing and Procurement. 🛒 Fonctionnalités principales de la gestion des achats dans SAP S/4HANA ✅ 1. Gestion des fournisseurs Création et gestion des fiches fournisseurs. Évaluation des performances fournisseurs. Intégration avec des portails fournisseurs (ex. : SAP Ariba). ✅ 2. Demandes et commandes d’achat Création de demandes d’achat (DA) manuelles ou automatiques. Transformation en commandes d’achat. Suivi des confirmations, livraisons et factures. ✅ 3. Contrats et accords-cadres Gestion des contrats d’achat à long terme. Suivi des consommations et des engagements. ✅ 4. Intégration logistique et financière Intégration avec : La gestion des stocks (réceptions, mouvements). La comptabilité fournisseurs (facturation, paiements). Le contrôle budgétaire. ✅ 5. Analyse et pilotage Tableaux de bord Fiori pour : Suivre les dépenses. Identifier les fournisseurs critiques. Optimiser les délais et les coûts. 🧠 Extensions possibles SAP Ariba : pour la gestion collaborative des achats (sourcing, appels d’offres, catalogues). SAP Fieldglass : pour les achats de prestations externes. SAP Central Procurement : pour centraliser les achats dans des environnements multi-ERP.
C8: - Portail fournisseur (avec workflow intégré) | D8: MOD. Module complémentaire (MDD partagé avec socle principal) | E8: Le portail fournisseur n’est pas directement intégré au cœur de SAP S/4HANA, mais il peut être étroitement connecté à l’ERP via des solutions complémentaires de l’écosystème SAP, notamment : 🔗 1. SAP Ariba – Portail fournisseur principal SAP Ariba est la solution dédiée de SAP pour la gestion des fournisseurs, des appels d’offres, des contrats et des commandes. Elle est intégrée nativement avec SAP S/4HANA, notamment via des connecteurs standards. Elle permet aux fournisseurs de : Répondre à des appels d’offres. Gérer les commandes et les factures. Suivre les paiements et les litiges. 🧩 2. Intégration avec SAP S/4HANA Dans SAP S/4HANA, les modules Achats (MM) et Gestion des fournisseurs permettent de gérer les données fournisseurs, les commandes, les réceptions et les paiements. Le portail fournisseur (via Ariba ou autre) s’appuie sur ces modules pour afficher les données en temps réel. L’intégration est facilitée par des API standardisées et des interfaces Fiori. 🛠️ 3. Alternatives personnalisées Il est aussi possible de créer un portail fournisseur personnalisé directement connecté à SAP S/4HANA via : SAP Fiori apps. SAP Business Technology Platform (BTP). SAP Integration Suite. ✅ En résumé : Le portail fournisseur n’est pas dans le cœur natif de SAP S/4HANA, mais il est pleinement intégré via SAP Ariba ou des solutions personnalisées, avec une synchronisation en temps réel des données ERP.
C9: - Gestion des stocks | D9: SOC. Socle central | E9: Oui, la gestion des stocks est bien intégrée dans SAP S/4HANA. Elle fait partie du module SAP Materials Management (MM), plus précisément dans la composante Inventory Management (IM). 📦 Fonctionnalités principales de la gestion des stocks dans SAP S/4HANA ✅ 1. Suivi des mouvements de stock Entrées et sorties de marchandises (réceptions, livraisons, transferts internes). Mouvements automatiques liés aux commandes d’achat, de production ou de vente. Gestion des types de mouvements (101, 201, 301, etc.). ✅ 2. Gestion multi-emplacements Suivi des stocks par : Site (plant), Magasin (storage location), Lot, numéro de série, unité de manutention. ✅ 3. Inventaire physique Planification et exécution des comptages d’inventaire. Ajustements automatiques des écarts. Historique et traçabilité des écarts. ✅ 4. Intégration avec d'autres modules Achats : réception de marchandises. Ventes : sorties de stock. Production : consommation de composants. Finance : valorisation des stocks en temps réel. ✅ 5. Gestion des stocks spéciaux Stocks consignés, en transit, bloqués, en sous-traitance, etc. 🧠 Extensions possibles SAP Extended Warehouse Management (EWM) : pour une gestion avancée des entrepôts. SAP Fiori apps : pour une gestion moderne et mobile des stocks
C10: - Gestion des ventes | D10: SOC. Socle central | E10: La gestion des ventes est intégrée dans SAP S/4HANA, via le module Sales and Distribution (SD), qui fait partie du cœur fonctionnel de l’ERP. 🛍️ Fonctionnalités principales de la gestion des ventes dans SAP S/4HANA ✅ 1. Gestion du cycle de vente complet Création de devis, commandes clients, livraisons, factures. Suivi des conditions commerciales (remises, frais, taxes). Gestion des retours et avoirs. ✅ 2. Intégration logistique et financière Coordination avec : La gestion des stocks pour les livraisons. La comptabilité clients pour la facturation et les paiements. La planification de la production pour les produits fabriqués à la commande. ✅ 3. Disponibilité produit et promesse client (ATP) Fonction Available-to-Promise (ATP) pour vérifier la disponibilité des produits en temps réel. Planification des livraisons selon les capacités logistiques. ✅ 4. Analyse des ventes Tableaux de bord Fiori pour : Suivre les performances commerciales. Analyser les marges, volumes, délais. Identifier les clients et produits stratégiques. ✅ 5. Gestion des contrats et abonnements Contrats-cadres, commandes périodiques. Intégration possible avec SAP Subscription Billing pour les modèles récurrents. 🧠 Extensions possibles SAP Customer Experience (CX) : pour CRM, e-commerce, marketing. SAP CPQ : pour la configuration de produits complexes. SAP Commerce Cloud : pour les ventes en ligne.
C11: - Transport | D11: SOC. Socle central | E11: La gestion du transport est bien prise en charge dans SAP S/4HANA, mais elle dépend du niveau de complexité requis et du module utilisé. 🚚 1. Gestion de base du transport dans SAP S/4HANA (core ERP) SAP S/4HANA intègre des fonctionnalités de logistique de transport dans les modules suivants : Sales and Distribution (SD) : pour la planification des livraisons, la création de documents de transport, la gestion des expéditions. Materials Management (MM) : pour les mouvements de marchandises liés aux achats et transferts. Warehouse Management (WM) ou Stock Room Management : pour la coordination des mouvements internes. Ces fonctions couvrent : La création de livraisons. L’affectation de transporteurs. Le suivi des expéditions. La gestion des coûts de transport (via conditions de prix). 🚛 2. SAP Transportation Management (SAP TM) Pour des besoins plus avancés, SAP propose SAP Transportation Management, qui peut être : Intégré nativement dans SAP S/4HANA (Embedded TM). Ou utilisé comme solution autonome (side-car). SAP TM permet : La planification optimisée des transports (multi-modal, multi-étapes). La gestion des transporteurs et des contrats. Le suivi en temps réel des expéditions. La facturation du fret et la gestion des litiges. 🧩 3. Intégration avec d'autres modules SAP TM s’intègre avec : SAP EWM (gestion d’entrepôt avancée). SAP GTS (gestion du commerce international). SAP Event Management (suivi des événements logistiques). ✅ En résumé : SAP S/4HANA prend en charge la gestion du transport, soit via des fonctions de base intégrées, soit via SAP Transportation Management pour des processus logistiques complexes.
C12: - Portail / communication prestataires transport (avec workflow intégré) | D12: MOD. Module complémentaire (MDD partagé avec socle principal) | E12: Oui, SAP S/4HANA peut couvrir la communication avec les prestataires de transport via un portail, avec des workflows intégrés, mais cela dépend de la solution utilisée et de son niveau d’intégration. 🚚 1. SAP S/4HANA avec SAP Transportation Management (SAP TM) SAP TM, intégré à SAP S/4HANA (en version Embedded TM), permet : La gestion complète des opérations de transport (planification, exécution, suivi). L’intégration avec les prestataires de transport via des interfaces EDI/API. La gestion des workflows pour l’approbation, la validation des coûts de transport, ou la gestion des litiges. 🌐 2. Portail fournisseur / transporteur (via SAP Business Network ou Ariba Network) SAP propose des portails collaboratifs pour les fournisseurs et transporteurs : SAP Business Network for Logistics (anciennement Ariba Network Logistics). Permet aux transporteurs de : Recevoir des ordres de transport. Confirmer les livraisons. Suivre les expéditions. Gérer les documents (CMR, factures, etc.). Ces portails sont connectés à SAP S/4HANA et peuvent déclencher des workflows intégrés (ex. : validation de réception, approbation de facture). 🔄 3. Workflows intégrés dans SAP S/4HANA SAP S/4HANA propose des workflows flexibles (via Fiori) pour : La gestion des commandes de transport. L’approbation des coûts logistiques. La validation des prestations de transport. Ces workflows peuvent être personnalisés et transportés entre environnements (DEV → QAS → PROD) via l’outil Adaptation Transport Organizer (ATO) 1. ✅ En résumé : SAP S/4HANA permet la gestion des prestataires de transport via un portail connecté, avec des workflows intégrés, notamment grâce à SAP TM et SAP Business Network for Logistics
C13: - ADV | D13: SOC. Socle central | E13: Oui, SAP peut tout à fait gérer l’ADV (Administration Des Ventes). Dans SAP, cette fonction est généralement couverte par le module SD (Sales and Distribution). Voici ce que le module SD permet de gérer pour l’ADV : 📦 Fonctions principales de l’ADV dans SAP SD : Gestion des devis et commandes clients : création, modification, suivi. Disponibilité des produits (ATP) : vérification des stocks en temps réel. Livraisons : préparation, expédition, gestion des bons de livraison. Facturation : génération automatique des factures à partir des livraisons. Suivi des paiements : en lien avec le module FI (Finance). Gestion des retours : retours produits, avoirs, etc. Reporting : tableaux de bord, analyses des ventes, délais, etc. 🔗 Intégration avec d'autres modules : MM (Materials Management) : pour la gestion des stocks. FI (Financial Accounting) : pour la facturation et le suivi des paiements. CO (Contrôle de gestion) : pour l’analyse de la rentabilité. CRM : pour la gestion de la relation client
A14: Sécurité et conformité | B14: Sécurité | C14: La localisation des serveurs est elle en France ? | D14: OUI | E14: Dépend de l'hyperscaler
C15: Possibilité de gérer des accès basés sur les rôles (Role-Based Access Control) | D15: OUI | E15: Oui, SAP S/4HANA prend en charge la gestion des accès basée sur les rôles, via un mécanisme appelé Role-Based Access Control (RBAC). C’est un pilier fondamental de la sécurité dans les environnements SAP. 🔐 Fonctionnement du RBAC dans SAP S/4HANA 1. Objets de sécurité clés Rôles (Roles) : regroupent des autorisations liées à des tâches ou fonctions spécifiques (ex. : comptable, acheteur, RH) Profils d’autorisations (Authorization Profiles) : définissent les droits d’accès à des objets SAP (transactions, vues, champs) Utilisateurs (Users) : se voient attribuer un ou plusieurs rôles 2. Types de rôles Rôles SAP standard : fournis par SAP pour les fonctions classiques (FI, MM, SD, etc.) Rôles personnalisés : créés par les administrateurs pour répondre aux besoins spécifiques de l’entreprise 3. Outils utilisés PFCG (Profile Generator) : outil principal pour créer et gérer les rôles et autorisations SU01 : gestion des utilisateurs SUIM : rapports sur les autorisations SAP Fiori Launchpad : permet de gérer les accès aux applications Fiori via des catalogues et groupes liés aux rôles ✅ Exemples d’usage Un responsable achats peut avoir accès uniquement aux transactions de commande (ME21N, ME22N) Un utilisateur Fiori peut voir uniquement les tuiles correspondant à ses rôles (ex. : "Créer une commande", "Consulter les fournisseurs")
C16: Possibilité de gérer le MFA (Multi-Factor Authentication) | D16: OUI | E16: Oui, SAP S/4HANA prend en charge l’authentification multifacteur (MFA), notamment dans les environnements cloud et hybrides, via des intégrations avec des solutions d’identité et de sécurité. 🔐 Fonctionnalités MFA dans SAP S/4HANA ✅ 1. Intégration avec SAP Identity Authentication Service (IAS) SAP IAS permet de configurer : MFA native (via application mobile, SMS, email, etc.) Authentification unique (SSO) avec MFA en amont Compatible avec SAP S/4HANA Cloud et SAP Fiori Launchpad ✅ 2. Intégration avec des fournisseurs tiers (IdP) SAP peut être intégré avec des solutions comme : Microsoft Entra ID (ex-Azure AD) Okta Ping Identity Google Workspace Ces fournisseurs peuvent imposer une MFA centralisée pour tous les accès SAP ✅ 3. Support via SAP Business Technology Platform (BTP) Pour les extensions ou applications connectées à S/4HANA via BTP, la MFA peut être activée au niveau de la gestion des identités cloud 🛠️ Exemples de méthodes MFA supportées Application mobile (TOTP) SMS ou email avec code à usage unique Clé de sécurité (FIDO2, YubiKey) Authentification biométrique (via IdP)
C17: Le système permet-il de gérer l’approbation des demandes d’accès (workflows d’approbation pour la création ou modification de rôles) ? | D17: OUI | E17: Oui, SAP permet de gérer les workflows d’approbation pour les demandes d’accès, y compris la création ou la modification de rôles, via plusieurs modules et outils intégrés : 1. SAP GRC Access Control Le module SAP GRC (Governance, Risk, and Compliance), en particulier Access Control, est conçu pour : Gérer les demandes d’accès utilisateurs. Définir des workflows d’approbation personnalisés. Automatiser les contrôles de séparation des tâches (SoD). Suivre et auditer les modifications de rôles et d’autorisations 1. 2. Workflows d’approbation dans SAP SAP propose des outils pour créer et modifier des procédures d’approbation : Utilisation d’un éditeur graphique pour concevoir des workflows complexes (approbateurs en série ou parallèles). Possibilité de définir des approbateurs ou réviseurs directement dans les tâches. Intégration avec des règles de gestion pour déclencher des approbations conditionnelles (ex. : selon le niveau de risque ou le type de rôle demandé) 2. 3. SAP Business Technology Platform (BTP) – Workflow Management Pour des besoins plus avancés ou personnalisés, SAP BTP permet de : Créer des workflows entièrement digitalisés. Intégrer des règles métiers complexes. Suivre l’état des demandes en temps réel
C18: Des mécanismes existent-ils pour revoir et actualiser régulièrement les autorisations d’accès ? | D18: OUI | E18: Voici les principaux mécanismes : 🔁 1. Revue des accès (Access Review) via SAP GRC Access Control Le module Access Risk Analysis (ARA) et Access Request Management (ARM) de SAP GRC permet de : Planifier des campagnes de revue des accès (périodiques ou ad hoc). Impliquer les managers ou propriétaires d’applications pour valider ou révoquer les accès. Générer des rapports d’audit sur les décisions prises. Automatiser les rappels et escalades en cas de non-réponse. 🧩 2. Segregation of Duties (SoD) et analyse des risques SAP GRC permet aussi de : Détecter les conflits d’autorisations (SoD). Proposer des mesures correctives ou des compensations. Mettre à jour les rôles pour éviter les risques futurs. 📅 3. Expiration automatique des autorisations Il est possible de configurer : Des dates d’expiration pour certains rôles ou accès temporaires. Des workflows de renouvellement si l’accès est encore nécessaire. 🛠️ 4. SAP Identity Management (IdM) SAP IdM permet : Une gestion centralisée du cycle de vie des identités. Des revues périodiques automatisées des rôles et autorisations. L’intégration avec des systèmes externes pour synchroniser les accès
C19: Possibilité de chiffrement des données critiques | D19: OUI | E19: Oui, SAP propose plusieurs mécanismes de chiffrement pour protéger les données critiques, que ce soit au repos, en transit ou dans les bases de données. Voici un aperçu des principales options disponibles : 🔐 1. Chiffrement des données au repos (Data at Rest) SAP prend en charge : SAP NetWeaver Secure Store and Forward (SSF) : pour chiffrer les fichiers sensibles. SAP HANA Native Encryption : Chiffrement des volumes de données et de journaux avec AES-256. Gestion des clés via SAP HANA Secure Store ou SAP Data Custodian. SAP ASE (Adaptive Server Enterprise) et SAP MaxDB offrent également des options de chiffrement natif. 🔄 2. Chiffrement des données en transit (Data in Transit) Utilisation de TLS/SSL pour sécuriser les communications entre : Clients SAP GUI et serveurs SAP. SAP Gateway, SAP Web Dispatcher, SAP Fiori, etc. Prise en charge de SAML 2.0, OAuth 2.0, et OpenID Connect pour l’authentification sécurisée. 🧩 3. SAP Data Custodian Un service cloud de SAP pour : Gérer les clés de chiffrement (Key Management Service). Appliquer des politiques de souveraineté des données. Fournir une traçabilité complète des accès et des opérations sur les données. 🛡️ 4. Intégration avec des solutions tierces SAP peut s’intégrer avec : HSM (Hardware Security Modules) pour la gestion sécurisée des clés. Solutions de chiffrement d’entreprise comme Thales, Vormetric, ou Microsoft Azure Key Vault.
C20: Possibilité de duplication des données | D20: OUI | E20: Oui, SAP permet la duplication des données, mais cela dépend du contexte fonctionnel et des outils utilisés. Voici les principales options disponibles : 📄 1. Duplication de données dans SAP ERP / S/4HANA SAP permet de dupliquer des objets métiers (clients, fournisseurs, articles, etc.) via : Fonctions de copie standard dans les transactions (ex. : copier une fiche article ou un rôle). LTMC (Legacy Transfer Migration Cockpit) ou SAP Data Services pour migrer ou dupliquer des ensembles de données. BDC (Batch Data Communication) ou LSMW (Legacy System Migration Workbench) pour automatiser la duplication de données en masse. 🧰 2. SAP Data Intelligence / SAP BTP Pour des scénarios plus complexes : SAP Data Intelligence permet de créer des pipelines de duplication, transformation et transfert de données entre systèmes SAP et non-SAP. SAP BTP (Business Technology Platform) permet de répliquer des données via des services comme SAP HANA Smart Data Integration ou Smart Data Access. 🔄 3. SAP Landscape Transformation (SLT) SLT permet : La réplication en temps réel de données entre systèmes SAP (ou vers des bases HANA). La duplication de tables entières ou de sous-ensembles filtrés. L’intégration avec des outils d’analyse ou de reporting. ☁️ 4. SAP Cloud Integration / CPI Dans un environnement cloud, SAP Cloud Platform Integration permet : La duplication ou synchronisation de données entre applications cloud (ex. : SAP SuccessFactors, Ariba, etc.). L’orchestration de flux de données avec transformation à la volée.
C21: Le système conserve-t-il un journal des accès utilisateur (logs de connexion et actions critiques) ? | D21: OUI | E21: Oui, SAP conserve un journal des accès utilisateur, y compris les connexions et les actions critiques, grâce à plusieurs mécanismes intégrés. Voici les principaux composants : 📘 1. Security Audit Log (SAL) Le Security Audit Log est l’outil principal pour tracer : Les connexions et déconnexions des utilisateurs. Les échecs d’authentification. Les modifications critiques (rôles, profils, mots de passe, etc.). Les accès aux transactions sensibles. 🔧 Il est configurable pour : Définir les événements à tracer. Choisir les utilisateurs ou groupes à surveiller. Exporter les logs pour audit ou analyse. 🧾 2. Change Documents (CDHDR/CDPOS) SAP enregistre les modifications de données (clients, fournisseurs, rôles, etc.) dans des tables de documents de modification, notamment : CDHDR : en-tête du changement (qui, quand, quoi). CDPOS : détails du changement (ancienne et nouvelle valeur). 🧠 3. SAP GRC Audit Management Pour les environnements réglementés, SAP GRC permet : De centraliser les logs d’audit. De générer des rapports sur les accès et les actions critiques. D’automatiser les alertes en cas d’activité suspecte. ☁️ 4. SAP Cloud Identity Services & SAP BTP Audit Logs Dans les environnements cloud : SAP Cloud Identity Authentication trace les connexions, tentatives échouées, MFA, etc. SAP BTP fournit des Audit Logs pour toutes les applications et services utilisés
C22: L’audit trail est-il consultable via une interface utilisateur ou exportable à des fins d’audit ? | D22: OUI | E22: Oui, l’audit trail dans SAP est consultable via une interface utilisateur et exportable à des fins d’audit, selon les outils utilisés. Voici comment cela fonctionne : 🖥️ 1. Consultation via interface utilisateur 🔹 Security Audit Log (SAL) Accessible via la transaction SM20 (consultation des logs) et SM19 (configuration). Permet de filtrer par : Utilisateur Type d’événement (connexion, modification, échec, etc.) Date/heure Système cible Interface conviviale avec affichage des événements sous forme de liste. 🔹 Change Documents Consultables via des transactions spécifiques selon l’objet (ex. : SUIM pour les rôles, XD03 pour les clients). Affichage des anciennes et nouvelles valeurs, avec date et utilisateur. 🔹 SAP GRC Access Control Interface web (NWBC ou Fiori) pour : Visualiser les logs d’accès. Suivre les workflows d’approbation. Générer des rapports d’audit. 📤 2. Exportation des logs 🔸 Formats disponibles : CSV, TXT, PDF selon le module. Export possible depuis : SM20 (via bouton d’export) SAP GRC (rapports personnalisés ou standard) SAP Solution Manager (via EWA ou Root Cause Analysis) 🔸 Automatisation possible : Planification de rapports périodiques. Intégration avec des outils SIEM (ex. : Splunk, QRadar) via SAP Enterprise Threat Detection ou SAP BTP Audit Log Service.
C23: Est-il possible d’identifier précisément l’utilisateur, la date et l’heure de chaque action critique ? | D23: OUI | E23: 🔍 1. Security Audit Log (SAL) Chaque événement enregistré contient : Nom d’utilisateur Horodatage précis (date et heure) Type d’action (connexion, modification, accès à une transaction sensible) Adresse IP ou terminal (si configuré) Exemple d’événement : User: JDOE | Date: 08.07.2025 | Time: 14:32:10 | Action: SU01 - Modification de rôle 🧾 2. Change Documents (CDHDR/CDPOS) Pour les objets métiers (clients, fournisseurs, rôles, etc.), chaque modification est enregistrée avec : Utilisateur ayant effectué l’action Date et heure Ancienne et nouvelle valeur Type d’opération (création, modification, suppression) 🛡️ 3. SAP GRC Access Control Les workflows d’approbation et les demandes d’accès incluent : Trace complète des étapes (demande, approbation, provisionnement) Identité des intervenants Horodatage de chaque étape Rapports disponibles pour audit interne ou externe. ☁️ 4. SAP BTP Audit Logs / Cloud Identity Services Dans les environnements cloud : Chaque action est loggée avec identifiant utilisateur, timestamp, application concernée, et résultat (succès/échec). Export possible vers des outils d’analyse ou SIEM.
C24: Disposez-vous d’une politique formelle de gestion des incidents de sécurité ? | D24: OUI
B25: Conformité | C25: La solution est elle en conformité avec la RGPD? | D25: OUI | E25: SAP S/4HANA est conçu pour être conforme au Règlement Général sur la Protection des Données (RGPD), mais cette conformité dépend aussi de la manière dont l’entreprise configure et utilise la solution. Voici les éléments clés : ✅ 1. Conformité intégrée dans SAP S/4HANA SAP a intégré dans S/4HANA plusieurs fonctionnalités pour répondre aux exigences du RGPD : Gestion du cycle de vie des données personnelles : suppression, anonymisation, archivage. SAP Information Lifecycle Management (ILM) : permet de définir des règles de conservation et de suppression des données personnelles. Contrôle d’accès et traçabilité : journalisation des accès, gestion des autorisations, séparation des tâches. Fonctionnalités de blocage et de destruction des données : pour répondre aux demandes de suppression ou de limitation du traitement 1. 🛡️ 2. Engagement de SAP en matière de protection des données SAP a mis en place un Data Protection Management System (DPMS) conforme aux standards internationaux, et applique les principes de "privacy by design" et "by default" dans ses produits 2. SAP a également : Adhéré au EU Cloud Code of Conduct, approuvé par le Comité européen de la protection des données. Intégré les clauses contractuelles types de la Commission européenne pour les transferts de données hors UE. ⚠️ 3. Responsabilité partagée Même si SAP fournit les outils, la conformité RGPD dépend aussi de l’entreprise utilisatrice, notamment pour : Configurer correctement les règles de conservation. Répondre aux demandes d’accès ou de suppression des données. Former les utilisateurs et documenter les traitements.
C26: L'hébergement des données est il en Europe? | D26: OUI | E26: Ce point est traité par les hyperscaler
C27: Votre solution ERP est-elle certifiée selon la norme ISO/IEC 27001 | E27: Oui, SAP S/4HANA est certifié conforme à la norme ISO/IEC 27001, qui est la norme internationale de référence pour les systèmes de management de la sécurité de l'information (ISMS). 🔐 Ce que cela signifie concrètement : SAP applique une approche systématique et documentée pour gérer les risques liés à la sécurité de l'information. La certification couvre : La confidentialité, intégrité et disponibilité des données. La gestion des accès, la surveillance, et la réponse aux incidents. Des contrôles techniques et organisationnels pour protéger les données clients. 📄 SAP Trust Center SAP publie ses certifications, y compris ISO/IEC 27001, sur son Trust Center officiel 1. On y trouve également : ISO/IEC 27017 (sécurité dans le cloud) ISO/IEC 27018 (protection des données personnelles dans le cloud) SOC 1, SOC 2, et autres attestations de conformité ☁️ Important à noter : La certification ISO/IEC 27001 s’applique à SAP en tant que fournisseur de services cloud (ex. : SAP S/4HANA Cloud). Pour les déploiements on-premise, la conformité dépend aussi de l’organisation cliente, qui doit mettre en œuvre ses propres contrôles de sécurité.
C28: Disposez-vous d’un rapport SOC 1 pour votre solution ERP ? | D28: OUI | E28: Oui, SAP dispose bien d’un rapport SOC 1 (ISAE 3402) pour SAP S/4HANA Cloud, notamment dans le cadre de l’offre RISE with SAP et SAP Enterprise Cloud Services. 📄 Détails du rapport SOC 1 pour SAP S/4HANA Le rapport couvre : SAP S/4HANA Cloud, Private Edition SAP S/4HANA Cloud, Extended Edition SAP HANA Enterprise Cloud Il est conforme à la norme ISAE 3402, qui est l’équivalent international du SOC 1 Type II. Il fournit des garanties sur les contrôles internes liés à la sécurité, la disponibilité et l’intégrité des données, en lien avec les états financiers des clients. 🔍 Où le trouver ? Le rapport est disponible via le SAP Trust Center ou via le portail client SAP for Me, réservé aux clients SAP authentifiés 1. 📌 Important à noter : Le rapport n’est pas public : il est accessible uniquement aux clients SAP ou sur demande via le support ou votre Customer Engagement Executive. Il est mis à jour deux fois par an (H1 et H2).
C29: Disposez-vous d'un rapport SOC 2 pour votre solution ERP? | D29: OUI | E29: Oui, SAP S/4HANA Cloud dispose d’un rapport SOC 2 Type 2, préparé par un auditeur indépendant, couvrant les principes de sécurité, disponibilité et confidentialité. 📄 Détails du rapport SOC 2 pour SAP S/4HANA Le rapport est conforme à la norme AT-C Section 205 (AICPA) et à l’ISAE 3000. Il couvre la période du 1er avril 2024 au 31 mars 2025. Il s’applique aux services SAP Enterprise Management Cloud, y compris SAP S/4HANA Cloud dans le cadre de SAP Central Cloud Services. Il évalue : La description du système. La conception et l’efficacité opérationnelle des contrôles internes. Les critères de sécurité, disponibilité et confidentialité. 🔐 Accès au rapport Le rapport est disponible pour tous les clients SAP (et prospects) sous accord de confidentialité (NDA). Il peut être demandé via : Le SAP Trust Center 1. Votre Customer Success Partner ou Account Executive. L’adresse email : CloudAudits@sap.com.
C30: Votre solution respecte-t-elle d'autres normes ou cadres de sécurité ? | D30: OUI | E30: Oui, SAP S/4HANA respecte plusieurs normes et cadres de sécurité internationaux, en plus du RGPD, afin de garantir un haut niveau de protection des données et de conformité réglementaire. Voici les principaux : ✅ Normes et certifications de sécurité respectées par SAP S/4HANA 🔐 1. ISO/IEC 27001 Norme internationale pour les systèmes de management de la sécurité de l'information (ISMS). SAP est certifié ISO/IEC 27001 pour ses services cloud, y compris SAP S/4HANA Cloud 1. ☁️ 2. ISO/IEC 27017 & 27018 ISO 27017 : bonnes pratiques pour la sécurité dans le cloud. ISO 27018 : protection des données personnelles dans les environnements cloud publics 1. 🔄 3. ISO 22301 Norme pour la gestion de la continuité d’activité, garantissant la résilience des services SAP face aux interruptions 1. 📋 4. BS 10012 Norme britannique pour la gestion des informations personnelles, complémentaire au RGPD 1. 🧠 Cadres de cybersécurité adoptés 🛡️ 5. NIST Cybersecurity Framework (CSF) SAP a implémenté le cadre NIST CSF v1.1 pour structurer sa gestion des risques cyber et renforcer sa posture de sécurité dans le cloud 2. Ce cadre est reconnu mondialement pour sa flexibilité et son adaptabilité aux environnements technologiques évolutifs. 📄 Autres attestations disponibles SOC 1 Type II (ISAE 3402) SOC 2 Type II (AT-C 205) EU Cloud Code of Conduct (niveau 3, le plus élevé) Conformité avec DORA (Digital Operational Resilience Act) et NIS2 (directive européenne sur la cybersécurité) 1
B31: Propriété des données | C31: L'utilisateur conserve-t-il la propriété légale exclusive de ses données ? | D31: OUI | E31: Oui, dans SAP S/4HANA, l’utilisateur (le client de SAP) conserve la propriété légale exclusive de ses données. ⚖️ Voici ce que cela signifie concrètement : ✅ 1. Propriété des données SAP agit en tant que sous-traitant au sens du RGPD. Le client SAP (l’entreprise utilisatrice) reste le responsable du traitement et propriétaire légal des données. Cela inclut toutes les données personnelles, commerciales, financières ou opérationnelles hébergées dans SAP S/4HANA. 🔐 2. Engagement contractuel de SAP SAP s’engage contractuellement à : Ne pas utiliser les données à d’autres fins que celles définies par le client. Ne pas transférer les données à des tiers sans autorisation. Fournir des outils pour l’accès, la rectification, la suppression et la portabilité des données 1. 🧰 3. Fonctionnalités RGPD intégrées SAP S/4HANA intègre des outils pour garantir cette maîtrise : Consent Management : gestion des consentements des personnes concernées. Read Access Logging (RAL) : journalisation des accès aux données personnelles. Information Retrieval Framework : extraction des données personnelles sur demande. Suppression et anonymisation : suppression automatisée après la durée de conservation 1. 📌 En résumé : Oui, vous conservez la pleine propriété de vos données dans SAP S/4HANA. SAP fournit l’infrastructure et les outils, mais vous contrôlez l’accès, l’usage et la durée de conservation.
C32: En cas de résiliation, garantissez-vous la restitution complète des données ? | D32: OUI | E32: Oui, SAP S/4HANA Cloud garantit la restitution complète des données en cas de résiliation, mais cela se fait à l’initiative du client et via des outils spécifiques fournis par SAP. 📦 Restitution des données à la résiliation : ce que propose SAP ✅ 1. Outil dédié : Customer Data Return App SAP met à disposition l’application Customer Data Return, qui permet aux clients de : Extraire l’ensemble de leurs données métier (données de base, données transactionnelles). Télécharger les données dans un format exploitable. Cette application est conçue pour faciliter la migration vers un autre système ou la conservation des données après résiliation 1. 🔄 2. SAP S/4HANA Migration Cockpit Peut être utilisé pour transférer les données extraites vers un autre environnement SAP ou non-SAP. Permet de structurer les données selon les modèles cibles. 📋 Conditions à respecter Le client doit initier la demande de restitution avant la fin du contrat. SAP recommande de planifier cette extraction avec le support ou le gestionnaire de compte. Les données sont restituées dans un format brut ou structuré, selon les outils utilisés (CDS Views, extracteurs, etc.). ⚠️ À noter SAP ne conserve pas les données après la résiliation, sauf obligation légale ou contractuelle. Il est de la responsabilité du client de sauvegarder les données extraites avant la suppression définitive.
C33: En cas de résiliation, garantissez-vous la suppression définitive des données de vos serveurs ? | D33: OUI | E33: Oui, SAP S/4HANA garantit la suppression définitive des données des clients en cas de résiliation, conformément aux engagements contractuels et aux exigences réglementaires comme le RGPD. 🧹 Voici comment cela fonctionne : ✅ 1. Suppression via SAP Information Lifecycle Management (ILM) SAP utilise ILM pour gérer la suppression des données selon des règles de conservation définies. Une fois la période de conservation expirée (ou à la demande du client), les données sont : Archivée temporairement (si nécessaire), Puis supprimées définitivement de la base de données et des archives 1. 🔐 2. Suppression des données personnelles SAP permet de bloquer puis supprimer les données personnelles lorsqu’elles ne sont plus nécessaires (ex. : après résiliation ou expiration des obligations légales). Cela inclut les données de contrat, les données RH, les données clients, etc. 2. 📋 3. Engagement contractuel SAP s’engage à ne pas conserver les données au-delà de la durée du contrat, sauf obligation légale. Le client peut demander la confirmation écrite de la suppression. La suppression est documentée et traçable. ⚠️ À noter : Le client doit initier la demande de suppression ou s’assurer que les règles ILM sont bien configurées. Dans certains cas (SAP S/4HANA Cloud Public Edition), la suppression peut être plus encadrée et nécessite une planification spécifique
C34: Est-il possible d'exporter les données à tout moment? | D34: OUI | E34: SAP S/4HANA permet aux clients d’exporter leurs données à tout moment, sous réserve de disposer des droits d’accès appropriés et des outils nécessaires. 📤 Fonctionnalités d’exportation disponibles ✅ 1. SAP HANA Cockpit (ou Migration Cockpit) Accessible via l’interface Fiori. Permet d’extraire les données de base et transactionnelles (clients, fournisseurs, commandes, factures, etc.). Utilise des modèles de migration pour structurer les exports. Adapté aux environnements Cloud Public, Cloud Privé et On-Premise 1. ✅ 2. Exportation manuelle ou automatisée Les utilisateurs peuvent exporter des données via : CDS Views (Core Data Services) SAP Query / SQVI Rapports standards avec export Excel/CSV Possibilité de planifier des exports réguliers via des jobs de fond. ✅ 3. SAP Data Intelligence ou SAP BTP Pour des besoins plus complexes (intégration avec d’autres systèmes, entrepôts de données, etc.). Permet des exports automatisés, filtrés et transformés. 🔐 Conditions d’accès L’exportation est soumise aux autorisations utilisateur. Certaines données sensibles peuvent nécessiter des droits spécifiques ou des journaux d’accès (RAL).
C35: La récupération des données est elle possible de manière automatisée? | D35: OUI | E35: Oui, la récupération des données dans SAP S/4HANA peut être automatisée, à condition d’utiliser les bons outils et d’avoir les autorisations nécessaires. Voici les principales options : 🔄 1. SAP APIs (OData / REST / SOAP) SAP expose de nombreuses API standardisées pour accéder aux données en temps réel. Ces API permettent d’automatiser : L’extraction de données clients, fournisseurs, commandes, etc. L’intégration avec des outils tiers (BI, CRM, entrepôts de données). Utilisation possible avec des outils comme Postman, SAP API Business Hub, ou via des scripts personnalisés. 🧰 2. SAP Data Intelligence / SAP BTP Integration Suite Permet de créer des pipelines automatisés pour extraire, transformer et charger (ETL) les données. Intégration possible avec des systèmes non-SAP (Azure, AWS, Snowflake, etc.). Planification des flux de données (quotidien, horaire, événementiel). 📦 3. SAP S/4HANA Migration Cockpit (en mode extraction) Peut être utilisé pour automatiser l’export de données vers un autre système SAP ou non-SAP. Fonctionne avec des modèles prédéfinis et peut être intégré dans des scripts. 📊 4. SAP BW/4HANA ou SAP Analytics Cloud Pour les environnements analytiques, les données peuvent être extraites automatiquement via des requêtes planifiées ou des connecteurs directs. 🔐 Conditions L’automatisation nécessite : Des droits d’accès appropriés. Une configuration sécurisée (authentification, journalisation). Parfois, l’intervention de l’équipe technique SAP ou d’un intégrateur.
C36: L'intégralité des données peut-elles être exportée ? | D36: OUI | E36: Oui, il est possible d’exporter l’intégralité des données dans SAP S/4HANA, mais cela dépend du type de déploiement (Cloud Public, Cloud Privé ou On-Premise) et des outils utilisés. ✅ Outils permettant l’exportation complète des données 1. Customer Data Return App Permet aux clients de récupérer toutes leurs données métier (données de base, transactionnelles, etc.) en cas de résiliation ou à tout moment. Données exportées dans un format structuré, lisible et réutilisable. Disponible dans SAP S/4HANA Cloud Public Edition 1. 2. Customer Data Browser + CDS Views Permet d’accéder à toutes les données visibles par le client, y compris via des Custom CDS Views (vues personnalisées). Ces vues peuvent être utilisées pour extraire automatiquement des ensembles complets de données. Compatible avec des outils d’intégration ou d’analyse externes 2. 3. SAP S/4HANA Migration Cockpit Utilisé pour extraire ou charger des données dans ou depuis SAP S/4HANA. Prend en charge des modèles de données complets (clients, fournisseurs, commandes, etc.). Fonctionne aussi bien pour les migrations que pour les exports planifiés 2. ⚠️ Points d’attention L’exportation complète nécessite : Des droits d’accès étendus. Une planification technique (surtout pour les très grands volumes). Parfois, l’assistance de SAP ou d’un intégrateur.

Sheet 4. Volumétrie
A1: VOLUMES D'ACTIVITE | C1: REPONSE | D1: COMMENTAIRES
A2: Volumes de données référentielles et transactionnelles | B2: En vous référant au fichier ANNEXE - Volumétrie, La solution peut-elle prendre en charge tous les volumes de données, de transactions et d'activité du Groupe Beaumanoir tels que décrits, sans dégradation des performances ? | D2: Merci de détailler votre réponse
B3: La solution peut-elle prendre gérer des traitements de reporting, import et export sur les volumes suivants, sans dégradation des performances ?
B4: - Références articles Modèles-Coloris : 30 000 | C4: OUI | D4: Ces points seront à rediscuter pour préciser notre réponse en fonction de différents paramètres. Un technical assesment devra être fait. dans un cadre S4 Private: Pour déterminer si SAP S/4HANA Private Cloud peut gérer les volumes de données, de transactions et d'activité du Groupe Beaumanoir sans dégradation des performances, il est essentiel de considérer plusieurs facteurs clés, notamment la configuration matérielle, l'optimisation du système et les meilleures pratiques de gestion des données. Volumes de Données Référentielles et Transactionnelles Références articles Modèles-Coloris : 30 000 Gestion : Ce volume est relativement modéré et devrait être facilement gérable par SAP S/4HANA. Performance : Les opérations de création, de mise à jour et de consultation de ces références devraient être rapides et efficaces.
B5: - Référence articles Modèle-Coloris-Taille : 260 000 | C5: OUI | D5: Référence articles Modèle-Coloris-Taille : 260 000 Gestion : Ce volume est plus important mais reste gérable par SAP S/4HANA grâce à son architecture in-memory. Performance : L'architecture in-memory de HANA permet des opérations rapides même sur des volumes de données plus importants. Des indexations appropriées et des optimisations de base de données seront nécessaires.
B6: - Fournisseur actifs : 1 000 | C6: OUI | D6: Fournisseurs actifs : 1 000 Gestion : Ce volume est relativement faible et ne devrait poser aucun problème de performance. Performance : Les opérations liées aux fournisseurs devraient être rapides et efficaces.
B7: - Clients WholeSale : 10 000 | C7: OUI | D7: Clients Wholesale : 10 000 Gestion : Ce volume est modéré et devrait être facilement gérable. Performance : Les opérations de gestion des clients devraient être performantes.
B8: - Dépôts logiques : 160 | C8: OUI | D8: Dépôts logiques : 160 Gestion : Ce volume est relativement faible et ne devrait poser aucun problème de performance. Performance : Les opérations de gestion des dépôts devraient être rapides et efficaces. Traitements de Reporting, Import et Export Reporting : Capacité : SAP S/4HANA est conçu pour fournir des rapports en temps réel et peut gérer des volumes de données importants pour le reporting. Performance : L'utilisation de l'architecture in-memory permet des opérations de reporting rapides et efficaces. Import : Capacité : SAP S/4HANA peut gérer des imports volumineux grâce à ses capacités de traitement en mémoire. Performance : L'utilisation de techniques de batching et de parallélisation peut améliorer les performances des imports. Export : Capacité : De même, les exports peuvent être gérés efficacement. Performance : L'utilisation de batching et de parallélisation peut également améliorer les performances des exports. Recommandations Générales Dimensionnement Approprié : Assurez-vous que l'infrastructure matérielle (CPU, mémoire, stockage) est correctement dimensionnée pour gérer les volumes de données et les transactions attendus. Optimisation des Processus : Optimisez les processus métiers et les configurations du système pour améliorer l'efficacité et réduire les temps de traitement. Tests de Charge : Effectuez des tests de charge pour valider les performances du système sous des conditions de charge élevées. Répartition des Charges : Utilisez des techniques de répartition des charges et de load balancing pour distribuer les requêtes de manière égale sur les ressources disponibles. Surveillance et Réglage : Mettez en place une surveillance proactive des performances et des alertes pour détecter et résoudre rapidement les problèmes de performance. Conclusion SAP S/4HANA Private Cloud est conçu pour gérer des volumes de données et des transactions importants sans dégradation des performances. Les volumes de données référentielles et transactionnelles décrits pour le Groupe Beaumanoir sont gérables avec une configuration et une optimisation appropriées. Cependant, il est crucial de suivre les meilleures pratiques de gestion des données, de réaliser des tests de charge et de surveiller les performances de manière proactive pour garantir une expérience utilisateur optimale. Il est recommandé de consulter des experts en infrastructure SAP pour s'assurer que la solution est correctement configurée et optimisée pour les besoins spécifiques du Groupe Beaumanoir.
A9: Gestion des pics de charge | B9: La solution peut-elle prendre en charge des pics de charge tels qu'indiqués ci-dessous, sans dégradation des performances ?
B10: - Utilisateurs simultanés : 950 | C10: OUI | D10: Le technical assesment devra le confirmer. Les montées en charge doivent être anticipées pour s'assurer que Sap S/4 poura répondre à ces pics de charges dans les temps attendus. SAP S/4HANA Private Cloud est conçu pour être très performant et capable de gérer des pics de charge importants grâce à sa capacité de traitement en temps réel et à sa base de données in-memory HANA. Cependant, la capacité à gérer des pics de charge sans dégradation des performances dépend de plusieurs facteurs, notamment la configuration matérielle, l'optimisation du système, la stratégie de gestion des charges de travail et les configurations spécifiques de l'application. Utilisateurs simultanés : 950 Capacité de Base : SAP S/4HANA Private Cloud peut généralement gérer un nombre élevé d'utilisateurs simultanés, surtout si le système est correctement dimensionné et optimisé. Optimisations : L'utilisation de techniques de mise en cache, de load balancing et de répartition des charges de travail peut aider à gérer efficacement un grand nombre d'utilisateurs. Tests de Charge : Il est crucial de réaliser des tests de charge pour s'assurer que le système peut gérer ce nombre d'utilisateurs sans dégradation des performances.
B11: - Commandes de vente créées en une journée : 400 000 | C11: OUI | D11: Commandes de vente créées en une journée : 400 000 Performance de la Base de Données : La base de données SAP HANA est conçue pour gérer de très grandes quantités de données en temps réel. Les opérations de lecture et d'écriture sont rapides grâce à l'architecture in-memory. Optimisation des Processus : L'utilisation de batch jobs optimisés et de techniques de traitement parallèle peut aider à gérer un grand nombre de commandes de vente. Scalabilité : Assurez-vous que le système est configuré pour être scalable, avec des ressources matérielles adéquates pour gérer les pics de charge.
B12: - Commandes d'achat créées en une journée : 11 000 | C12: OUI | D12: Commandes d'achat créées en une journée : 11 000 Volume Relatif : Comparativement aux commandes de vente, ce volume est moins élevé et devrait être gérable sans problème par SAP S/4HANA Private Cloud. Intégration des Processus : Assurez-vous que les processus de commande d'achat sont bien intégrés et optimisés pour éviter les goulots d'étranglement. Surveillance et Réglage : Utilisez des outils de surveillance pour suivre les performances en temps réel et effectuer des ajustements si nécessaire. Recommandations Générales Dimensionnement Approprié : Assurez-vous que l'infrastructure matérielle (CPU, mémoire, stockage) est correctement dimensionnée pour gérer les pics de charge attendus. Optimisation des Processus : Optimisez les processus métiers et les configurations du système pour améliorer l'efficacité et réduire les temps de traitement. Tests de Charge : Effectuez des tests de charge réguliers pour valider les performances du système sous des conditions de charge élevées. Répartition des Charges : Utilisez des techniques de répartition des charges et de load balancing pour distribuer les requêtes de manière égale sur les ressources disponibles. Surveillance et Réglage : Mettez en place une surveillance proactive des performances et des alertes pour détecter et résoudre rapidement les problèmes de performance. En conclusion, SAP S/4HANA Private Cloud est conçu pour gérer des pics de charge élevés, mais une planification et une optimisation rigoureuses sont essentielles pour garantir des performances optimales.
A13: Volumes en entrée et sortie | B13: Indiquer ci-après les limites éventuelles, en nombre de lignes, pour le traitement d'un FICHIER PLAT en import direct (sur un même fichier) :
B14: - Limites de lignes de traitement en entrée / import | C14: oui | D14: Les limites de traitement de données en entrée et en sortie pour les fichiers plats et les API peuvent varier en fonction de plusieurs facteurs, notamment la configuration du système, les ressources disponibles et les spécifications des logiciels utilisés. Voici quelques lignes directrices générales pour vous aider à comprendre ces limites dans le cadre de SAP S/4HANA Private Cloud Edition (S4 Private): Fichiers Plats (Fichiers PLATS) Limites de lignes de traitement en entrée / import : Les limites peuvent varier en fonction de la taille des enregistrements et de la configuration du système. En général, SAP S/4HANA peut gérer des fichiers plats volumineux, mais il est recommandé de limiter les fichiers à quelques millions de lignes pour éviter des temps de traitement excessifs et des problèmes de performance. Il est également important de considérer la taille maximale des fichiers supportés par le système de fichiers et les limitations de mémoire.
B15: - Limites de lignes de traitement en sortie / export | C15: oui | D15: Limites de lignes de traitement en sortie / export : Les mêmes considérations s'appliquent pour l'export. Les fichiers volumineux peuvent être gérés, mais il est conseillé de diviser les fichiers en plusieurs parties pour améliorer la gestion et la performance. Les formats de sortie et les exigences de reporting peuvent également influencer les limites.
B16: Indiquer ci-après les limites éventuelles, en nombre de lignes, pour le traitement de données via API (sur un même fichier / batch / traitement) :
B17: - Limites de lignes de traitement en entrée / import | D17: Traitement via API Limites de lignes de traitement en entrée / import : Les API de SAP S/4HANA sont généralement conçues pour gérer des lots de données plus petits par rapport aux fichiers plats. Les limites spécifiques peuvent varier en fonction de l'API utilisée, mais il est courant de voir des limites de quelques milliers à quelques dizaines de milliers de lignes par appel. Il est souvent nécessaire de paginer les appels API pour traiter de grands volumes de données.
B18: - Limites de lignes de traitement en sortie / export | D18: Limites de lignes de traitement en sortie / export : Les API d'export peuvent également avoir des limites similaires. Les données de sortie sont souvent paginées, avec des limites de quelques milliers à quelques dizaines de milliers de lignes par appel. Il est important de consulter la documentation spécifique de chaque API pour connaître les limites exactes et les meilleures pratiques pour la pagination et la gestion des lots. Recommandations Générales Optimisation des Performances : Utilisez des techniques de batching et de pagination pour optimiser les performances et la gestion des données. Test et Validation : Effectuez des tests de performance pour valider les limites en fonction de votre configuration spécifique et des volumes de données attendus. Documentation : Consultez la documentation officielle de SAP S/4HANA et les notes de support pour obtenir des informations précises sur les limites et les meilleures pratiques. En résumé, bien que SAP S/4HANA soit capable de gérer des volumes de données importants, il est essentiel de prendre en compte les limites spécifiques des fichiers plats et des API pour optimiser les performances et éviter les problèmes de traitement.
A21: MONTEE EN CHARGE - SCENARIO 1 | C21: REPONSE | D21: COMMENTAIRES
A22: Montée en charge : x3 | B22: Etes-vous capable de gérer ce scénario (hypothétique) de montée en charge ?
B23: - Références articles Modèles-Coloris : 90 000 | C23: oui | D23: Nous pourrons valider ces points lors du technical assessment. Nous aurons besoin d'identifier dans quelles conditions ces pics de charges auront lieu. Montée en charge *3 Gérer une montée en charge de cette ampleur dans SAP S/4HANA Private Cloud nécessite une planification minutieuse, une optimisation des processus et une infrastructure robuste. Voici une analyse détaillée de chaque composant pour évaluer la faisabilité de ce scénario hypothétique : Références Articles Modèles-Coloris : 90 000 Gestion : Ce volume est plus important mais reste gérable par SAP S/4HANA grâce à son architecture in-memory et ses capacités de traitement en temps réel. Performance : Les opérations de création, de mise à jour et de consultation de ces références devraient rester performantes, surtout si le système est correctement optimisé.
B24: - Référence articles Modèle-Coloris-Taille : 780 000 | C24: oui | D24: Références Articles Modèle-Coloris-Taille : 780 000 Gestion : Ce volume est substantiel mais peut être géré par SAP S/4HANA. Performance : L'architecture in-memory de HANA permet des opérations rapides même sur des volumes de données plus importants. Des indexations appropriées et des optimisations de base de données seront nécessaires.
B25: - Fournisseur actifs : 3 000 | C25: oui | D25: Fournisseurs Actifs : 3 000 Gestion : Ce volume est modéré et ne devrait pas poser de problème majeur. Performance : Les opérations liées aux fournisseurs devraient rester rapides et efficaces.
B26: - Clients WholeSale : 30 000 | C26: oui | D26: Clients Wholesale : 30 000 Gestion : Ce volume est plus important mais reste gérable. Performance : Les opérations de gestion des clients devraient rester performantes, surtout si des stratégies de partitionnement et de cache sont mises en place.
B27: - Dépôts logiques : 480 | C27: oui | D27: Dépôts Logiques : 480 Gestion : Ce volume est modéré et ne devrait pas poser de problème majeur. Performance : Les opérations de gestion des dépôts devraient rester rapides et efficaces.
B28: - Utilisateurs simultanés : 2 850 | C28: oui | D28: Utilisateurs Simultanés : 2 850 Gestion : Gérer un tel nombre d'utilisateurs simultanés nécessite une infrastructure robuste et bien dimensionnée. Performance : L'utilisation de techniques de load balancing, de mise en cache et de répartition des charges de travail est cruciale pour maintenir des performances optimales.
B29: - Commandes de vente créées en une journée : 1 200 000 | C29: oui | D29: Commandes de Vente Créées en une Journée : 1 200 000 Gestion : Ce volume est très élevé et nécessite une optimisation rigoureuse. Performance : L'utilisation de batch jobs optimisés, de traitement parallèle et de stratégies de partitionnement est essentielle pour gérer efficacement ce nombre de commandes de vente.
B30: - Commandes d'achat créées en une journée : 33 000 | C30: oui | D30: Commandes d'Achat Créées en une Journée : 33 000 Gestion : Ce volume est plus important mais reste gérable. Performance : Les opérations de gestion des commandes d'achat devraient rester performantes si le système est bien optimisé. Recommandations Générales Dimensionnement Approprié : Assurez-vous que l'infrastructure matérielle (CPU, mémoire, stockage) est correctement dimensionnée pour gérer les volumes de données et les transactions attendus. Une analyse de capacité détaillée est nécessaire. Optimisation des Processus : Optimisez les processus métiers et les configurations du système pour améliorer l'efficacité et réduire les temps de traitement. Tests de Charge : Effectuez des tests de charge rigoureux pour valider les performances du système sous des conditions de charge élevées. Répartition des Charges : Utilisez des techniques de répartition des charges et de load balancing pour distribuer les requêtes de manière égale sur les ressources disponibles. Surveillance et Réglage : Mettez en place une surveillance proactive des performances et des alertes pour détecter et résoudre rapidement les problèmes de performance. Scalabilité : Assurez-vous que la solution est conçue pour être évolutive, permettant d'ajouter des ressources matérielles et logicielles au besoin. Conclusion SAP S/4HANA Private Cloud est capable de gérer des volumes de données et des transactions importants, mais une montée en charge de cette ampleur nécessite une planification minutieuse et une optimisation rigoureuse. Il est fortement recommandé de consulter des experts en infrastructure SAP pour s'assurer que la solution est correctement configurée et optimisée pour les besoins spécifiques du Groupe Beaumanoir. Des tests de charge et une surveillance continue sont essentiels pour garantir des performances optimales et éviter les dégradations.
A33: MONTEE EN CHARGE - SCENARIO 2 | C33: REPONSE | D33: COMMENTAIRES
A34: Montée en charge : x10 | B34: Etes-vous capable de gérer ce scénario (hypothétique) de montée en charge ?
B35: - Références articles Modèles-Coloris : 300 000 | C35: oui | D35: Nous pourrons valider ces points lors du technical assessment. Montée en charge : x10 Gérer une montée en charge de cette ampleur (x10) dans SAP S/4HANA Private Cloud représente un défi significatif et nécessite une planification minutieuse, une optimisation rigoureuse et une infrastructure robuste. Voici une analyse détaillée de chaque composant pour évaluer la faisabilité de ce scénario hypothétique : Références Articles Modèles-Coloris : 300 000 Gestion : Ce volume est très élevé et nécessite une optimisation rigoureuse. Performance : Les opérations de création, de mise à jour et de consultation de ces références devraient rester performantes, mais cela nécessitera une optimisation des index, des partitions et des configurations de la base de données.
B36: - Référence articles Modèle-Coloris-Taille : 2 600 000 | C36: oui | D36: Références Articles Modèle-Coloris-Taille : 2 600 000 Gestion : Ce volume est extrêmement élevé et nécessite une architecture de base de données très bien optimisée. Performance : L'architecture in-memory de HANA peut gérer des volumes de données importants, mais des optimisations spécifiques seront nécessaires pour maintenir les performances.
B37: - Fournisseur actifs : 10 000 | C37: oui | D37: Fournisseurs Actifs : 10 000 Gestion : Ce volume est modéré mais nécessite une gestion efficace. Performance : Les opérations liées aux fournisseurs devraient rester rapides et efficaces avec une optimisation appropriée.
B38: - Clients WholeSale : 100 000 | C38: oui | D38: Clients Wholesale : 100 000 Gestion : Ce volume est élevé et nécessite une gestion et une optimisation rigoureuses. Performance : Les opérations de gestion des clients devraient rester performantes, surtout si des stratégies de partitionnement et de cache sont mises en place.
B39: - Dépôts logiques : 1 600 | C39: oui | D39: Dépôts Logiques : 1 600 Gestion : Ce volume est élevé et nécessite une gestion efficace. Performance : Les opérations de gestion des dépôts devraient rester rapides et efficaces avec une optimisation appropriée.
B40: - Utilisateurs simultanés : 9 500 | C40: oui | D40: Utilisateurs Simultanés : 9 500 Gestion : Gérer un tel nombre d'utilisateurs simultanés nécessite une infrastructure très robuste et bien dimensionnée. Performance : L'utilisation de techniques de load balancing, de mise en cache et de répartition des charges de travail est cruciale pour maintenir des performances optimales.
B41: - Commandes de vente créées en une journée : 4 000 000 | C41: oui | D41: Commandes de Vente Créées en une Journée : 4 000 000 Gestion : Ce volume est extrêmement élevé et nécessite une optimisation rigoureuse. Performance : L'utilisation de batch jobs optimisés, de traitement parallèle et de stratégies de partitionnement est essentielle pour gérer efficacement ce nombre de commandes de vente.
B42: - Commandes d'achat créées en une journée : 110 000 | C42: oui | D42: Commandes d'Achat Créées en une Journée : 110 000 Gestion : Ce volume est élevé mais gérable avec une optimisation appropriée. Performance : Les opérations de gestion des commandes d'achat devraient rester performantes si le système est bien optimisé. Recommandations Générales Dimensionnement Approprié : Assurez-vous que l'infrastructure matérielle (CPU, mémoire, stockage) est correctement dimensionnée pour gérer les volumes de données et les transactions attendus. Une analyse de capacité détaillée est nécessaire. Optimisation des Processus : Optimisez les processus métiers et les configurations du système pour améliorer l'efficacité et réduire les temps de traitement. Tests de Charge : Effectuez des tests de charge rigoureux pour valider les performances du système sous des conditions de charge élevées. Répartition des Charges : Utilisez des techniques de répartition des charges et de load balancing pour distribuer les requêtes de manière égale sur les ressources disponibles. Surveillance et Réglage : Mettez en place une surveillance proactive des performances et des alertes pour détecter et résoudre rapidement les problèmes de performance. Scalabilité : Assurez-vous que la solution est conçue pour être évolutive, permettant d'ajouter des ressources matérielles et logicielles au besoin. Conclusion SAP S/4HANA Private Cloud est capable de gérer des volumes de données et des transactions importants, mais une montée en charge de cette ampleur (x10) nécessite une planification minutieuse, une optimisation rigoureuse et une infrastructure très robuste. Il est fortement recommandé de consulter des experts en infrastructure SAP pour s'assurer que la solution est correctement configurée et optimisée pour les besoins spécifiques du Groupe Beaumanoir. Des tests de charge et une surveillance continue sont essentiels pour garantir des performances optimales et éviter les dégradations.

Sheet 5. Support et disponibilité
A1: LISTE DES CRITERES SUPPORT & DISPONIBILITE | D1: REPONSE | E1: COMMENTAIRES
A2: Aide | B2: Documentation | C2: Existe-t-il une documentation technique destinée aux développeurs tiers ? | D2: OUI | E2: Oui, SAP met à disposition une documentation technique complète destinée aux développeurs tiers via plusieurs plateformes officielles : 🔹 1. SAP Help Portal Documentation officielle pour tous les produits SAP Guides d’installation, d’administration, de configuration et de développement Recherche par produit (ex. : SAP S/4HANA, SAP BTP, SAP Fiori, etc.) 🔹 2. SAP Developers Portal Ressources pour développeurs : tutoriels, guides pratiques, vidéos SAP CodeTalk Accès à des API, SDKs, exemples de code, et projets open source Environnement de test via SAP Business Technology Platform (BTP) 🔹 3. SAP Support Portal Accès aux outils de support, correctifs, notes SAP, et documentation technique avancée Réservé aux clients et partenaires avec un S-User ID 🔹 4. SAP API Business Hub Plateforme pour explorer et tester les API SAP (REST, OData, SOAP) Documentation interactive avec exemples d’appels API Lien : https://api.sap.com
C3: Existe-t-il une documentation pour les utilisateurs? | D3: NON | E3: Oui, SAP propose une documentation complète pour les utilisateurs finaux, accessible via plusieurs canaux officiels : 📘 1. SAP Help Portal C’est la plateforme centrale pour toute la documentation SAP. On y trouve des guides utilisateurs, des manuels de navigation, des Learning Journeys (parcours d’apprentissage interactifs), et des FAQ. La documentation est organisée par produit (ex. : SAP S/4HANA, SAP SuccessFactors, SAP Ariba, etc.) et par rôle (utilisateur, administrateur, développeur). 📄 2. Exemples de guides utilisateurs Voici un exemple concret : Guide utilisateur SAP Financial Consolidation (PDF) : ce document explique comment naviguer dans l’application, gérer les objets, personnaliser l’interface, etc. 📚 3. SAP Resource Library Bibliothèque de ressources SAP : brochures, présentations, guides utilisateurs, vidéos, etc. Utile pour les utilisateurs métiers souhaitant comprendre les fonctionnalités sans entrer dans les détails techniques.
A4: Support | B4: Informations générales | C4: En tant qu'éditeur, disposez-vous d'un support local / francophone ? | D4: OUI | E4: Oui, SAP dispose bien d’un support local et francophone, notamment pour les clients basés en France ou dans les pays francophones. Voici les principales options disponibles : 1, Support SAP en français SAP France – Services & Support SAP propose des services localisés en français, incluant : Support de base pour les solutions cloud Plans de réussite personnalisés Engagements premium avec des experts dédiés L’objectif est d’accompagner les entreprises tout au long de leur transformation digitale avec des ressources adaptées à leur contexte local 2. SAP Support Portal Portail global avec accès aux outils de support, notes SAP, et services en ligne Disponible en plusieurs langues, dont le français Requiert un S-User ID pour accéder aux services personnalisés
C5: Votre support est-il disponible 24/7 ? | D5: OUI | E5: Oui, le support SAP est disponible 24h/24, 7j/7, 365 jours par an, y compris pour les clients francophones
C6: Quelles prestations sont en option ou soumises à facturation supplémentaire ? | D6: OUI | E6: Oui, certaines prestations SAP sont optionnelles ou soumises à facturation supplémentaire, en fonction du type de contrat de support ou de l’offre souscrite (cloud, on-premise, support standard ou premium). Voici un aperçu : 💼 Inclus dans le support standard (SAP Enterprise Support) Accès au SAP Support Portal et à SAP for Me Gestion des incidents (selon les SLA) Expert Chat et sessions guidées (EGI) pour certains produits cloud Accès aux notes SAP, mises à jour logicielles, et correctifs Outils d’analyse comme SAP EarlyWatch Alert 💰 Prestations optionnelles ou facturées en supplément Prestation Détails Facturation SAP MaxAttention / SAP ActiveAttention Accompagnement stratégique, experts dédiés, innovation co-pilotée Oui, contrat premium Support 24/7 prioritaire Pour les incidents critiques (P1) avec temps de réponse accéléré Inclus dans certains contrats, sinon en option Services de conseil SAP (SAP Services) Implémentation, migration, architecture, etc. Oui Formations SAP Learning Hub Accès à des parcours certifiants, e-learning, examens Oui SAP Preferred Success Suivi proactif, KPIs, gestion du changement Oui, pour les clients cloud Support local personnalisé Assistance francophone, monitoring, maintenance évolutive Oui, selon le prestataire
B7: Customer success management | C7: Proposez-vous un dispositif de Customer Success Management / "guichet unique" pour chaque client ? | D7: OUI
C8: Le CSM est-il inclus dans le contrat de licence ou proposé en option ? | D8: NON | E8: Le Customer Success Manager (CSM) chez SAP n’est pas systématiquement inclus dans tous les contrats de licence. Il est généralement : ✅ Inclus : Dans certaines offres cloud premium, comme : SAP Preferred Success SAP Enterprise Support, cloud editions (selon le niveau) Pour les grands comptes ou projets stratégiques, SAP peut affecter un CSM de manière proactive 💼 En option / facturé séparément : Pour les clients avec un contrat standard cloud ou on-premise, le CSM est souvent proposé en option, via : SAP Preferred Success (offre payante) SAP MaxAttention ou SAP ActiveAttention (services premium avec accompagnement stratégique) Dans ces cas, le CSM agit comme un point de contact dédié, chargé de : Suivre les KPIs de succès Coordonner les services SAP Faciliter l’adoption des solutions
B9: Support de niveau 1 | C9: Proposez-vous un support de niveau 1 ? | D9: OUI | E9: Oui, SAP propose bien un support de niveau 1, mais sa disponibilité dépend du type de contrat et de l’offre souscrite. 🧩 Support de niveau 1 chez SAP – Détails ✅ Inclus dans certaines offres Le support de niveau 1 est généralement inclus dans les offres SAP Enterprise Support et SAP Preferred Success, notamment pour les solutions cloud. Il couvre : La prise en charge initiale des incidents L’orientation vers les bonnes ressources L’escalade vers les niveaux supérieurs si nécessaire 💼 Externalisation possible Certaines entreprises choisissent de confier le niveau 1 à un partenaire SAP certifié (comme PASàPAS ou SOA People), qui agit comme point de contact utilisateur et filtre les demandes avant de les transmettre à SAP. 💰 En option dans certains cas Pour les clients on-premise ou avec un contrat standard, le support de niveau 1 peut être : Géré en interne par l’équipe IT Proposé en option par SAP ou ses partenaires, via des services managés ou des contrats de support étendus
C10: Ce niveau de support est-il assuré par l'éditeur ou par un partenaire/intégrateur ? | D10: EDI. Editeur | E10: Le support de niveau 1 peut être assuré soit par SAP directement, soit par un partenaire/intégrateur, selon le modèle d’organisation choisi par le client et le type de contrat. 🧩 Deux modèles possibles : ✅ 1. Support de niveau 1 assuré par SAP Cas typique : clients cloud avec SAP Preferred Success ou SAP Enterprise Support, cloud edition SAP prend en charge : La réception des incidents Le diagnostic initial L’escalade vers les niveaux supérieurs si nécessaire Ce modèle est courant pour les solutions SaaS (ex. : SAP SuccessFactors, Ariba, etc.) 🤝 2. Support de niveau 1 assuré par un partenaire/intégrateur Cas fréquent pour les clients on-premise ou en mode hybride Le partenaire agit comme point de contact utilisateur : Réception des tickets Résolution des problèmes simples Interface avec SAP pour les incidents complexes Avantage : langue locale, connaissance métier, proximité client 📝 Exemple concret : Une entreprise peut confier le niveau 1 à un intégrateur, qui filtre les demandes et ne transmet à SAP que les incidents nécessitant une expertise éditeur (niveau 2 ou 3).
C11: Ce niveau de support est-il inclus dans le prix de la licence utilisateur (prix d'entrée / plancher) ? | D11: NON | E11: Le support de niveau 1 n’est généralement pas inclus dans le prix de la licence utilisateur de base (prix d’entrée ou plancher), sauf dans certains cas spécifiques liés aux solutions cloud. 🧾 Détail selon le type de contrat : ✅ Inclus dans certaines offres cloud Pour les solutions SAP Cloud (ex. : SuccessFactors, Ariba, etc.), un support de base est inclus dans le prix de la licence. Ce support comprend : Accès au portail SAP Documentation Gestion des incidents simples Formation guidée et contenu personnalisé 1 💼 Non inclus pour les solutions on-premise ou hybrides Pour les solutions on-premise (comme SAP S/4HANA sur site), le support de niveau 1 est souvent géré par le client ou externalisé à un partenaire. Dans ce cas : Le coût du support de niveau 1 est séparé de la licence utilisateur Il peut être intégré dans un contrat de support global ou facturé à la carte par un intégrateur
B12: Support de niveau 2 | C12: Proposez-vous un support de niveau 2 ? | D12: OUI | E12: Oui, SAP propose bien un support de niveau 2, mais sa mise en œuvre dépend du modèle de support choisi (éditeur ou partenaire) et du type de contrat (cloud, on-premise, premium, etc.). 🧩 Support de niveau 2 – Détails ✅ Assuré par SAP (éditeur) Dans les contrats SAP Enterprise Support ou SAP Preferred Success, SAP prend en charge : Les incidents techniques complexes Les problèmes nécessitant une analyse approfondie Les interventions sur le code standard ou les intégrations Ce niveau est généralement inclus dans les offres cloud, ou accessible via escalade depuis le niveau 1 1. 🤝 Assuré par un partenaire/intégrateur Dans les environnements on-premise ou hybrides, le support de niveau 2 est souvent : Externalisé à un intégrateur SAP certifié Géré par des consultants fonctionnels ou techniques capables de traiter des incidents plus complexes (ex. : erreurs de configuration, bugs spécifiques, ajustements ABAP) Le partenaire peut ensuite escalader vers SAP si nécessaire (niveau 3) 💡 Exemple de répartition : Niveau de support Qui intervient ? Type de problème Niveau 1 Service desk interne ou partenaire Problèmes simples, accès, navigation Niveau 2 Consultant SAP ou partenaire Problèmes fonctionnels ou techniques complexes Niveau 3 SAP (éditeur) Bugs produits, correctifs, escalades officielles
C13: Ce niveau de support est-il assuré par l'éditeur ou par un partenaire/intégrateur ? | D13: EDI. Editeur | E13: Le support de niveau 2 peut être assuré soit par l’éditeur SAP, soit par un partenaire/intégrateur, selon le modèle de support choisi par l’entreprise. 🧩 Voici les deux cas de figure : ✅ 1. Support de niveau 2 assuré par un partenaire/intégrateur Très courant dans les environnements on-premise ou hybrides Des partenaires certifiés PCoE (Partner Center of Expertise) comme Seenovate ou Keyrus assurent : L’analyse des erreurs complexes Le diagnostic technique approfondi La reproduction des incidents La proposition de solutions ou de contournements Ce modèle permet de filtrer les incidents avant de les escalader à SAP (niveau 3) 1 2 🧠 2. Support de niveau 2 assuré par SAP (éditeur) Dans les contrats SAP Enterprise Support ou SAP Preferred Success, SAP peut intervenir directement sur les incidents de niveau 2, notamment pour les solutions cloud. Cela inclut : L’analyse technique L’accès aux logs et aux systèmes La coordination avec les équipes produit 🔄 Modèle hybride Dans la plupart des cas, les entreprises adoptent un modèle hybride : Niveau 1 et 2 : assurés par un partenaire/intégrateur Niveau 3 : assuré par SAP, après escalade
C14: Ce niveau de support est-il inclus dans le prix de la licence utilisateur (prix d'entrée / plancher) ? | D14: NON | E14: Le support de niveau 2 n’est généralement pas inclus dans le prix de la licence utilisateur de base (prix d’entrée ou plancher). Voici les éléments clés à connaître : 🧾 1. Ce que couvre la licence utilisateur Le prix d’entrée d’une licence SAP (par exemple licence "Employee" ou "Professional") donne accès à : L’utilisation des fonctionnalités du logiciel Les mises à jour logicielles (si maintenance active) L’accès au portail SAP et à la documentation Mais : ce prix ne couvre pas automatiquement un support technique approfondi (niveau 2 ou 3) 💼 2. Support de niveau 2 – généralement en option Le support de niveau 2 est souvent : Inclus dans des offres premium comme SAP Enterprise Support ou SAP Preferred Success Facturé séparément si vous passez par un partenaire/intégrateur pour ce niveau de service Il couvre : Les problèmes techniques complexes Les incidents nécessitant une analyse approfondie L’interface avec SAP niveau 3 si besoin
B15: Support de niveau 3 | C15: Proposez-vous un support de niveau 3 ? | D15: OUI | E15: Oui, SAP propose un support de niveau 3, mais il est exclusivement assuré par l’éditeur lui-même, et non par les partenaires ou intégrateurs. 🧠 Support de niveau 3 – Détails ✅ Assuré par SAP (éditeur) Le support de niveau 3 intervient lorsque : L’incident est complexe ou critique Il nécessite une analyse du code source standard SAP Il faut créer ou modifier une SAP Note, un correctif, ou un patch SAP peut : Accéder au système du client via SAP ONE Support Launchpad Analyser les traces système, logs, dumps Proposer des solutions de contournement ou des correctifs officiels Escalader en interne vers les équipes produit si nécessaire 1 🤝 Rôle des partenaires: Les partenaires assurent généralement : Niveau 1 : réception et qualification des tickets Niveau 2 : analyse fonctionnelle ou technique approfondie Si l’incident dépasse leur périmètre, ils escaladent au niveau 3, géré par SAP 2 1 🔄 Exemple de cycle : Client crée un ticket Partenaire (ex. Keyrus) traite en niveau 1 ou 2 Si non résolu → escalade vers SAP (niveau 3) via le portail officiel
C16: Ce niveau de support est-il assuré par l'éditeur ou par un partenaire/intégrateur ? | D16: EDI. Editeur
C17: Ce niveau de support est-il inclus dans le prix de la licence utilisateur (prix d'entrée / plancher) ? | D17: NON | E17: Le support de niveau 3 n’est généralement pas inclus dans le prix de la licence utilisateur de base (prix d’entrée ou plancher). Voici les éléments clés à retenir : 🧾 Ce que couvre la licence utilisateur Le prix d’entrée d’une licence SAP (par exemple, pour un utilisateur "Professional" ou "Limited") donne accès : Aux fonctionnalités du logiciel Aux mises à jour (si la maintenance est active) À un support de base (niveau 1 ou portail en libre-service) Mais : il n’inclut pas automatiquement le support de niveau 3, qui est plus technique et spécialisé 1. 🧠 Support de niveau 3 – Facturation Ce niveau est assuré exclusivement par SAP (éditeur), et il est : Inclus dans des contrats comme SAP Enterprise Support, SAP Preferred Success, ou SAP MaxAttention Non inclus dans les licences de base ou les contrats standards sans maintenance ou support premium Il couvre : Les bugs du code standard Les correctifs SAP Notes Les escalades vers les équipes produit
A18: Disponibilité | B18: Disponibilité et interruption | C18: Quel est le taux de disponibilité garanti de votre solution ? | E18: Le taux de disponibilité garanti pour SAP S/4HANA Cloud (édition publique) est de 99,7 %, selon les Service Level Agreements (SLA) publiés sur le SAP Trust Center 1. 📊 Ce que cela signifie : 99,7 % de disponibilité équivaut à un maximum d’environ : 2h11 d’indisponibilité par mois 26h17 d’indisponibilité par an Ce taux n’inclut pas les fenêtres de maintenance planifiée, qui sont annoncées à l’avance et ne sont pas comptabilisées dans le SLA.
C19: Quel est le temps maximal d’interruption ? | E19: Pour SAP S/4HANA Cloud, le temps maximal d’interruption est directement lié au taux de disponibilité garanti, qui est de 99,7 % selon le contrat de niveau de service (SLA) officiel de SAP. 📊 Calcul du temps maximal d’interruption : Période Temps d’interruption maximal (hors maintenance planifiée) Par mois Environ 2h11 Par an Environ 26h17 Ce calcul est basé sur le fait que 99,7 % de disponibilité signifie que le service peut être indisponible 0,3 % du temps sur la période considérée. 🛠️ À noter : Les fenêtres de maintenance planifiée ne sont pas comptabilisées dans ce temps d’interruption. En cas de dépassement du SLA, SAP peut accorder des crédits de service au client, selon les conditions du contrat.
E20: .
E23: 📊 Ce que cela signifie :
E24: 99,7 % de disponibilité équivaut à un maximum d’environ :
E25: 2h11 d’indisponibilité par mois
E26: 26h17 d’indisponibilité par an
E27: Ce taux n’inclut pas les fenêtres de maintenance planifiée, qui sont annoncées à l’avance et ne sont pas comptabilisées dans le SLA.

Sheet 6. Références clients
A1: CLIENT | B1: NOMBRE D'UTILISATEURS ACTIFS | C1: PERIMETRE FONCTIONNEL DEPLOYE | N1: PARTENAIRE INTEGRATEUR SUR LE PROJET | O1: DUREE DU PROJET (approx.) | P1: BUDGET DE DEPLOIEMENT (approx.) | Q1: COMMENTAIRES | R1: PRISE DE CONTACT AUTORISEE | S1: EMAIL DU CONTACT
C2: Gestion du référentiel | D2: Gestion des saisons | E2: Planning | F2: Production | G2: Gestion des achats | H2: Gestion des ventes | I2: Allocations | J2: Gestion des stocks | K2: Expédition, livraison, suivi, retours | L2: ADV | M2: Autre (préciser)
A3: BEAUMANOIR
A4: BRICOMAN | B4: 574 ME de CA | C4: OUI | D4: NON | E4: NON | F4: NON | G4: OUI | H4: OUI | I4: NON | J4: OUI | K4: OUI | L4: OUI | M4: Logistique&finance
A5: CELIO | B5: 430 ME de CA | C5: OUI | D5: OUI | E5: NON | F5: NON | G5: OUI | H5: OUI | I5: NON | J5: OUI | K5: OUI | L5: OUI | M5: Finance & Back Office Magasin
A6: DECATHLON | B6: 16,2 Mds de CA | C6: OUI | D6: OUI | E6: OUI | F6: OUI | G6: OUI | H6: OUI | I6: OUI | J6: OUI | K6: OUI | L6: OUI | M6: Finance
A7: ETAM | B7: 850 ME de CA | C7: OUI | D7: OUI | E7: OUI | F7: NON | G7: OUI | H7: OUI | I7: NON | J7: OUI | K7: OUI | L7: OUI | M7: Finance
A8: GEMO - Groupe ERAM | B8: 890 ME de CA | C8: OUI | D8: OUI | E8: OUI | F8: NON | G8: OUI | H8: OUI | I8: OUI | J8: OUI | K8: OUI | L8: OUI | O8: 36 mois
A9: INVIVO RETAIL | B9: 61 ME de CA | C9: OUI | D9: OUI | E9: OUI | F9: NON | G9: NON | H9: NON | I9: NON | J9: NON | K9: NON | L9: NON
A10: LE BHV MARAIS | B10: 430 ME de CA | C10: OUI | D10: OUI | E10: OUI | F10: NON | G10: OUI | H10: OUI | I10: OUI | J10: OUI | K10: OUI | L10: OUI | M10: BAck Office Magasin
A11: LONGCHAMP | B11: 463 ME de CA | C11: OUI | D11: OUI | E11: NON | F11: OUI | G11: OUI | H11: OUI | I11: OUI | J11: OUI | K11: OUI | L11: OUI | M11: Logistique entrepot
A12: PICARD | B12: 1,7 MDs de CA | C12: OUI | D12: NON | E12: NON | F12: OUI | G12: OUI | H12: OUI | I12: NON | J12: OUI | K12: OUI | L12: OUI | M12: BAck Office Magasin
A13: PIMKIE | B13: 216 ME de CA | C13: OUI | D13: NON | E13: NON | F13: NON | G13: OUI | H13: OUI | I13: NON | J13: OUI | K13: OUI | L13: OUI
A14: PRINTEMPS | B14: 1,28 Mds de CA | C14: OUI | D14: OUI | E14: NON | F14: NON | G14: OUI | H14: OUI | I14: NON | J14: OUI | K14: OUI | L14: OUI
A15: SCHIEVER | B15: 889 ME de CA | C15: OUI | D15: OUI | E15: NON | F15: NON | G15: OUI | H15: OUI | I15: NON | J15: OUI | K15: OUI | L15: NON | O15: 15 mois
A16: TAPE A L ŒIL | B16: 163 ME de CA | C16: OUI | D16: OUI | E16: OUI | F16: NON | G16: OUI | H16: OUI | I16: OUI | J16: OUI | K16: OUI | L16: OUI

Sheet 7. Partenaires et écosystème
A1: INFORMATIONS RELATIVES A L'INTEGRATION DE LA SOLUTION | C1: REPONSE | D1: COMMENTAIRES
A2: Ecosystème d'intégrateurs | B2: Quels sont les différents niveaux de certification d'un intégrateur sur votre solution ? | C2: En plus du niveau Platinum, SAP classe ses partenaires intégrateurs selon plusieurs niveaux de certification dans le cadre de son programme SAP PartnerEdge. Ces niveaux reflètent l’expertise, l’engagement et les résultats obtenus par les partenaires dans la vente, l’implémentation et le support des solutions SAP. 🌟 Niveaux de certification des partenaires SAP : Platinum Partner - Niveau le plus élevé. Partenaires globaux avec une forte présence internationale. Exemples : delaware, Deloitte, Accenture, Capgemini, IBM. Gold Partner - Partenaires très expérimentés avec un fort historique de projets réussis. Expertise sectorielle ou technologique reconnue. Souvent actifs dans plusieurs pays ou régions. Silver Partner - Partenaires avec une expertise solide, mais à un niveau plus local ou régional. Moins de projets ou de certifications que les Gold. Open Ecosystem Partner Niveau d’entrée dans l’écosystème SAP. Accès limité aux ressources SAP. Idéal pour les jeunes entreprises ou les partenaires en phase de démarrage.
B3: Des formations (initiales et mise à niveau) sont-elles requises pour obtenir la certification ? | C3: Oui, des formations sont fortement recommandées — voire nécessaires — pour obtenir une certification SAP, que ce soit en formation initiale ou en mise à niveau. 🎓 1. Formation initiale (avant la certification) Pour les certifications Associate, SAP recommande : Une formation officielle SAP via le SAP Learning Hub ou des cours en présentiel/virtuel. Des cours spécifiques selon le module (ex. : S/4HANA Finance, SAP Analytics Cloud, SuccessFactors…). Une expérience pratique sur des environnements SAP (via des sandbox ou des projets). 👉 Ces formations permettent de se préparer aux examens en maîtrisant les concepts, les processus et les outils SAP. 🔁 2. Mise à niveau (après la certification) SAP propose des évaluations de mise à jour pour : Rester certifié sur les dernières versions (ex. : S/4HANA 2023 → 2025). Suivre l’évolution des fonctionnalités, surtout dans le cloud. Accéder aux Learning Journeys pour chaque rôle (consultant, développeur, architecte…). Ces mises à jour sont disponibles via : SAP Learning Hub SAP Certification Hub Des webinaires et workshops organisés par SAP ou ses partenaires
B4: Nombre de partenaires intégrateurs en France | C4: Grands intégrateurs internationaux présents en France Capgemini, delaware, IBM, Cap Gemini, Accenture, Deloitte Partenaire Platinum de SAP Présent sur tous les modules SAP (S/4HANA, SuccessFactors, Ariba, etc.) Très actif dans les secteurs public, industrie, retail, énergie Partenaire stratégique mondial de SAP Spécialiste des projets de transformation à grande échelle Forte expertise cloud et RISE with SAP Partenaire global SAP Très présent dans les projets S/4HANA et SAP BTP Expertise sectorielle forte (finance, santé, industrie) IBM Consulting, delaware, Cap Gemini Intégrateur historique SAP Spécialiste des migrations vers S/4HANA et de l’intégration cloud hybride 🥈 Intégrateurs français ou mondiaux de référence Delaware Présent en France via Delaware France Spécialiste SAP S/4HANA, SAP Analytics Cloud, SAP CX Actif dans le retail, l’industrie, la santé, l'agro-alimentaire Applium Intégrateur SAP français reconnu Spécialiste de S/4HANA, SAP Business Technology Platform Forte présence dans les ETI et PME Augusta Reeves Intégrateur SAP Gold Partner Présent à Paris, Nantes, Lyon, Toulouse Spécialiste S/4HANA, gestion à l’affaire, ingénierie, services TeamWork Groupe franco-suisse Présent dans l’intégration SAP, l’hébergement et le conseil Actif dans l’industrie, la distribution, la pharma Kardol Intégrateur SAP Business One et SAP S/4HANA Cloud Ciblé sur les PME et ETI industrielles Be One Solutions Spécialiste SAP Business One et S/4HANA Cloud Présent à l’international, avec une forte expertise sur les déploiements 2-tier
B5: Nombre de partenaires intégrateurs certifiés en France (plus haut niveau de certification) | C5: 11
B6: Nombre de partenaires intégrateurs en Europe | C6: Le SAP Partner Finder recense plus de 1 000 partenaires en Europe, incluant des intégrateurs, revendeurs, hébergeurs et spécialistes cloud. Ces partenaires sont répartis entre les niveaux Platinum, Gold, Silver et Open Ecosystem, et couvrent des pays comme la France, l’Allemagne, les Pays-Bas, l’Espagne, l’Italie, la Belgique, etc. Les plus grands groupes (Accenture, Capgemini, Deloitte, IBM, NTT Data…) sont présents dans plusieurs pays européens avec des équipes locales certifiées.
B7: Nombre de partenaires intégrateurs certifiés en Europe (plus haut niveau de certification) | C7: SAP compte actuellement 11 partenaires certifiés Platinum dans le monde, et seulement une partie d’entre eux opèrent en Europe 1. 🌍 En Europe, les partenaires SAP Platinum incluent notamment : Delaware (présent en France, Belgique, Pays-Bas, etc.) Capgemini Accenture Deloitte IBM NTT Data Business Solutions Ces partenaires sont reconnus pour : Leur portée internationale Leur volume de projets SAP réussis Leur niveau d’expertise certifié sur les solutions SAP (S/4HANA, BTP, SuccessFactors, etc.)
B8: Nombre de partenaires intégrateurs dans le Monde | C8: Voici la liste des partenaires Platinum SAP en 2025, selon les dernières informations disponibles : Les partenaires Platinum sont les plus hauts niveaux de partenariat chez SAP. Ils sont reconnus pour leur expertise, leur portée mondiale et leur capacité à fournir des solutions SAP à grande échelle. En 2025, les 11 partenaires Platinum SAP sont généralement les suivants (liste sujette à de légères variations selon les régions et les mises à jour de SAP) : Accenture Capgemini delaware consulting Deloitte Ernst & Young (EY) IBM Infosys NTT Data PwC (PricewaterhouseCoopers) Tata Consultancy Services (TCS) Tech Mahindra Wipro Ces entreprises ont une présence mondiale et sont souvent impliquées dans des projets de transformation numérique à grande échelle avec SAP S/4HANA, SAP BTP, SAP SuccessFactors, etc.
B9: Nombre de partenaires intégrateurs certifiés dans le Monde (plus haut niveau de certification) | C9: 12
A10: Implication de l'éditeur | B10: En tant qu'EDITEUR, intégrez-vous / prenez-vous directement en charge certains projets avec des équipes internes dédiées ? | C10: Oui, SAP, en tant qu'éditeur de logiciels, prend directement en charge certains projets via des équipes internes dédiées, notamment dans le cadre de l’implémentation de ses solutions ERP comme SAP S/4HANA, SAP Fiori, ou encore SAP IBP. 1. Rôle d’éditeur et d’intégrateur SAP agit principalement comme éditeur de solutions logicielles, mais il peut aussi intervenir en tant qu’intégrateur ou co-pilote sur certains projets stratégiques, notamment via ses entités de conseil comme SAP Services ou SAP Consulting. Ces équipes accompagnent les clients dans : La conception de la solution (cadrage, architecture fonctionnelle et technique) L’implémentation (paramétrage, développement spécifique, intégration) Le pilotage du changement et la formation des utilisateurs 2. Équipes internes dédiées SAP mobilise des équipes projet composées de : Chefs de projet SAP Consultants fonctionnels et techniques Experts produits (par exemple, pour S/4HANA ou SAP SuccessFactors) Architectes de solutions Spécialistes de la migration de données et de l’intégration Ces équipes peuvent être internes à SAP ou hybrides, en collaboration avec des partenaires intégrateurs ou les équipes du client 1. 3. Exemples de projets pris en charge SAP peut intervenir directement sur : Des projets de transformation digitale à grande échelle Des déploiements internationaux Des projets pilotes ou innovants (ex. : intégration de l’IA ou de la blockchain dans SAP) Des migrations vers le cloud SAP (RISE with SAP)
B11: En tant qu'EDITEUR, participez-vous activement à certains projets conduits par des partenaires (support / expertise technique, etc.) ? | C11: Oui, SAP participe activement à certains projets conduits par des partenaires, notamment en apportant du support, de l’expertise technique et des ressources spécialisées. Voici comment cela se manifeste : 🔧 1. Support technique et expertise directe SAP met à disposition des partenaires : Des experts produits (par exemple pour SAP S/4HANA, SAP SuccessFactors, etc.) Des architectes de solutions pour valider les choix techniques Un support de niveau avancé via le programme Partner Center of Expertise (PCoE) 1 Ces ressources permettent aux partenaires de garantir la qualité des projets tout en bénéficiant de l’appui direct de l’éditeur. 🤝 2. Collaboration étroite avec les partenaires SAP considère ses partenaires comme une extension de son activité : Ils élaborent, personnalisent et mettent en œuvre les solutions SAP SAP supervise et certifie leurs compétences via des programmes de qualité stricts 2 L’éditeur peut intervenir en co-traitance ou en appui ponctuel sur des projets complexes ou critiques 🌍 3. Écosystème structuré et certifié SAP dispose d’un vaste réseau de partenaires certifiés (Gold, Platinum, etc.) qui peuvent : Intégrer plusieurs technologies SAP Offrir des services de conseil, d’implémentation, de support et de formation Être accompagnés par SAP dans des projets à forte valeur ajoutée ou à dimension internationale

Sheet 8. Estimations budgétaires
A1: ESTIMATIONS BUDGETAIRES MACROSCOPIQUES | C1: ESTIMATION EN k€ | D1: COMPLEMENTS (conseillés)
A2: I. BUDGET DE MISE EN ŒUVRE
A3: Budget de mise en œuvre (setup et projet) | B3: Budget (en K€) estimé pour la mise en œuvre dans le contexte du Groupe Beaumanoir | C3: =SUM(C4:C8) -> 16100000 | D3: <-- Ne pas saisir, calculé à partir des lignes du dessous | E3: Cout mensuel sur 30 mois de projet
B4: Estimation du coût de déploiement socle standard (pilotage projet, paramétrage, environnements dev + qual + prod, QA, migration / reprise de données, roll out) hors customisation et développements spécifiques hos interfaces hors licences | C4: 13000000 | E4: =C4/30 -> 433333.33
B5: Estimation du coût de customization et développements spécifiques à partir de l'onglet 1. Besoins fonctionnels, et autres postes de coûts que vous auriez identifiés | C5: 950000 | F5: =(E4*18)+C5+C6+(E8*18) -> 10310000
B6: Estimation du coût de customization et développements des connecteurs et interfaces à partir de l'onglet 2. Interfaces, et autres postes de coûts que vous auriez identifiés | C6: 1050000
B7: Estimation du coût des licences pour la 1e année (en cours de projet) | C7: 250000 | D7: Complément de licences estimé par rapport à la base de licence existente pour Beaumanoir
B8: Estimation d'autres coûts à provisionner | C8: 850000 | D8: Frais de déplacements | E8: =C8/30 -> 28333.333
A10: II. BUDGET RECURRENT
A11: Budget annuel récurrent (OPEX) | B11: Budget ANNUEL (en K€) estimé pour l'utilisation de la solution | C11: =SUM(C12:C15) -> 1477500 | D11: <-- Ne pas saisir, calculé à partir des lignes du dessous
B12: Estimation du coût ANNUEL des abonnements - base 1 000 utilisateurs en production hors prestations annexes (support utilisateurs étendu, maintenance applicative / évolutive, etc.) | C12: =2.5*30*12*475 -> 427500 | D12: licences et infrastructures
B13: Estimation du coût ANNUEL de support utilisateur étendu (niveaux hotline -> expert technique), si pertinent | C13: 450000 | D13: Monitoring des flux
B14: Estimation du coût ANNUEL de maintenance applicative, si pertinent | C14: 250000 | D14: MCO hors évolutions une fois la solution stabilisée
B15: Estimation ANNUEL d'autres coûts à provisionner | C15: 350000 | D15: Enveloppe évolutions
A18: AUTRES INFORMATIONS RELATIVES AU DEPLOIEMENT ET A L'UTILISATION | C18: REPONSE | D18: COMPLEMENTS (conseillés)
A19: I. MISE EN ŒUVRE
A20: Planning et méthodologie | B20: Estimation du délai (en mois) de mise en œuvre pour un MVP / socle minimum | C20: 18 mois | D20: Mise en oeuvre Core Model et déploiement sur Boardrider suivit par le déploiement de Beaumanoir
B21: Estimation du délai (en mois) de mise en œuvre total estimé | C21: 30 mois
B22: Proposez-vous des modèles de déploiement type, permettant de simplifier et accélerer la mise en œuvre ? | C22: Oui
B23: Ces méthodologies sont-elles applicables dans le contexte du Groupe Beaumanoir (2 ERP distincts, multiples instances de Storeland) | C23: Oui
A25: II. RECURRENCE
A26: Autres éléments budgétaires | B26: Des coûts additionnels sont-ils à prévoir pour le maintien d'environnements supplémentaires (hors production)? | C26: Non | D26: inclus dans le coût de licences
B27: D'autres options de tarification sont-elles disponibles (packs forfaitaires, lifetime access…) ? | C27: Non
B28: Des coûts de montée de version (majeure) sont-ils à prévoir ? | C28: Tous les 7 ans et en 2040 | D28: L'ERP doit être upgradée au moins 1 fois tous les 7 ans (recommandé tous les 2 à 4 ans). La fin de maintenance de la solution S/4 Hana est en 2040. Les solutions Public cloud sont (OMSA, OSTA, …) sont en intégration continue et ne nécessite pas d'upgrades.

Sheet LISTES
A1: OUI / NON
A2: OUI
A3: NON
A6: TYPE HEBERGEMENT
A7: Saas
A8: Paas
A9: On Premise
A10: Tous
A13: 1. BESOINS FONCTIONNELS
A14: YES. Couvert en standard (100%)
A15: CUS. Couvert avec customization
A16: DEV. Développement spécifiques requis
... A37: PAR. Partenaire - intégrateur
