Workbook
Name ActiveCallVolumeScenarioIndex: iControl!$I$14
Name ActiveCostScenarioIndex: iControl!$I$24
Name cstArea: SysConfig!$G$40
Name cstConstantUnit: SysConfig!$G$37
Name cstDaysInWk: SysConfig!$G$30
Name cstFlag: SysConfig!$G$46
Name cstFTE: SysConfig!$G$41
Name cstHours: SysConfig!$G$45
Name cstMil: SysConfig!$G$29
Name cstMonthsInQtr: SysConfig!$G$32
Name cstMonthsInYr: SysConfig!$G$33
Name cstNominalUnit: SysConfig!$G$38
Name cstNum: SysConfig!$G$42
Name cstPercent: SysConfig!$G$43
Name cstProjectName: SysConfig!$G$12
Name cstProtectiveMarking: SysConfig!$G$18
Name cstRealUnit: SysConfig!$G$39
Name cstThou: SysConfig!$G$28
Name cstWeeksInYr: SysConfig!$G$31
Name cstYears: SysConfig!$G$44
Name eTol: SysConfig!$G$50
Name Heading1: MAX(cCosts!A$1:A1048576)+1
Name Heading1: MAX(cFactors!A$1:A1048576)+1
Name Heading1: MAX(cOutputs!A$1:A1048576)+1
Name Heading1: MAX(cVolumetrics!A$1:A1048576)+1
Name Heading1: MAX(iControl!A$1:A1048576)+1
Name Heading1: MAX(iIndices!A$1:A1048576)+1
Name Heading1: MAX(Introduction!A$1:A1048576)+1
Name Heading1: MAX(iOptions!A$1:A1048576)+1
Name Heading1: MAX(oDashboard!A$1:A1048576)+1
Name Heading1: MAX(oFinancials!A$1:A1048576)+1
Name Heading1: MAX(SysConfig!A$1:A1048576)+1
Name Heading1: MAX(SysTime!A$1:A1048576)+1
Name Heading2: MAX(cCosts!XFD$1:XFD1)&"."&COUNTIFS(cCosts!A$1:A1048576,MAX(cCosts!XFD$1:XFD1)&".*")+1
Name Heading2: MAX(cFactors!XFD$1:XFD1)&"."&COUNTIFS(cFactors!A$1:A1048576,MAX(cFactors!XFD$1:XFD1)&".*")+1
Name Heading2: MAX(cOutputs!XFD$1:XFD1)&"."&COUNTIFS(cOutputs!A$1:A1048576,MAX(cOutputs!XFD$1:XFD1)&".*")+1
Name Heading2: MAX(cVolumetrics!XFD$1:XFD1)&"."&COUNTIFS(cVolumetrics!A$1:A1048576,MAX(cVolumetrics!XFD$1:XFD1)&".*")+1
Name Heading2: MAX(iControl!XFD$1:XFD1)&"."&COUNTIFS(iControl!A$1:A1048576,MAX(iControl!XFD$1:XFD1)&".*")+1
Name Heading2: MAX(iIndices!XFD$1:XFD1)&"."&COUNTIFS(iIndices!A$1:A1048576,MAX(iIndices!XFD$1:XFD1)&".*")+1
Name Heading2: MAX(Introduction!XFD$1:XFD1)&"."&COUNTIFS(Introduction!A$1:A1048576,MAX(Introduction!XFD$1:XFD1)&".*")+1
Name Heading2: MAX(iOptions!XFD$1:XFD1)&"."&COUNTIFS(iOptions!A$1:A1048576,MAX(iOptions!XFD$1:XFD1)&".*")+1
Name Heading2: MAX(oDashboard!XFD$1:XFD1)&"."&COUNTIFS(oDashboard!A$1:A1048576,MAX(oDashboard!XFD$1:XFD1)&".*")+1
Name Heading2: MAX(oFinancials!XFD$1:XFD1)&"."&COUNTIFS(oFinancials!A$1:A1048576,MAX(oFinancials!XFD$1:XFD1)&".*")+1
Name Heading2: MAX(SysConfig!XFD$1:XFD1)&"."&COUNTIFS(SysConfig!A$1:A1048576,MAX(SysConfig!XFD$1:XFD1)&".*")+1
Name Heading2: MAX(SysTime!XFD$1:XFD1)&"."&COUNTIFS(SysTime!A$1:A1048576,MAX(SysTime!XFD$1:XFD1)&".*")+1
Name lstInflationRates: iIndices!$F$16:$F$20
Name lstScenariosCallVolume: SysConfig!$F$95:$F$97
Name lstScenariosCost: SysConfig!$F$101:$F$103
Name rngBoA: #REF!
Name rngChangeLog: #REF!
Name rngContents: Contents!$E$12:$I$25
Name rngNamedRanges: SysConfig!$F$56:$H$89
Name rngNewChange: #REF!
Name sysChk: Contents!$H$27
Name sysChkWord: SysConfig!$G$52
Name sysWarn: Contents!$I$27

Sheet Introduction
C1: THIS CASE STUDY MODEL IS FOR ILLUSTRATIVE PURPOSES
C2: =cstProjectName -> Should Cost Modelling Case Study - Illustrative SCM
C3: =MID(CELL("filename",A1),FIND("]",CELL("filename",A1))+1,256)&" Sheet" -> Introduction Sheet
C4: =IF(ISBLANK(cstProtectiveMarking),"",cstProtectiveMarking) -> Not Protectively Marked
C5: =HYPERLINK("#'Contents'!A1",sysChkWord) -> All Checks OK
C6: =HYPERLINK("#'Contents'!A1","Click for Contents") -> Click for Contents
C10: Foreward
C65: HMT Aqua Book
C66: HM Treasury’s Macpherson report
C67: Green Book
C68: SCM Guidance Note
C69: SCM Development Guidance
C70: SCM Technical Build Guidance
C71: SCM Templates & Tools
B73: END OF WORKSHEET - INSERT ROWS ABOVE

Sheet Contents
C1: THIS CASE STUDY MODEL IS FOR ILLUSTRATIVE PURPOSES
C2: =cstProjectName -> Should Cost Modelling Case Study - Illustrative SCM
C3: =MID(CELL("filename",A1),FIND("]",CELL("filename",A1))+1,256)&" Sheet" -> Contents Sheet
C4: =IF(ISBLANK(cstProtectiveMarking),"",cstProtectiveMarking) -> Not Protectively Marked
C5: =HYPERLINK("#'Contents'!A1",sysChkWord) -> All Checks OK
A8: =SUM(A9:A54) -> 0 | B8: =SUM(B9:B54) -> 0
D10: Contents
E12: Worksheet | F12: Link | G12: Sheet Description | H12: Errors | I12: Warnings
E13: Introduction | F13: Link | G13: Introduction to this this case study
E14: iControl | F14: Link | G14: Scenario selection set up sheet | H14: =iControl!A8 -> 0 | I14: =iControl!B8 -> 0
E15: iOptions | F15: Link | G15: General inputs sheet | H15: =iOptions!A8 -> 0 | I15: =iOptions!B8 -> 0
E16: iIndices | F16: Link | G16: Input sheet for indices | H16: =iIndices!A8 -> 0 | I16: =iIndices!B8 -> 0
E17: cFactors | F17: Link | G17: Calculation sheet for indexation calculations | H17: =cFactors!A8 -> 0 | I17: =cFactors!B8 -> 0
E18: cVolumetrics | F18: Link | G18: Calculation sheet for volumetrics | H18: =cVolumetrics!A8 -> 0 | I18: =cVolumetrics!B8 -> 0
E19: cCosts | F19: Link | G19: Calculation sheet for costs | H19: =cCosts!A8 -> 0 | I19: =cCosts!B8 -> 0
E20: cOutputs | F20: Link | G20: Calculation sheet for outputs | H20: =cOutputs!A8 -> 0 | I20: =cOutputs!B8 -> 0
E21: oFinancials | F21: Link | G21: Financials output sheet | H21: =oFinancials!A8 -> 0 | I21: =oFinancials!B8 -> 0
E22: oDashboard | F22: Link | G22: Dashboard including graphic representation of costs | H22: =oDashboard!A8 -> 0 | I22: =oDashboard!B8 -> 0
E23: SysConfig | F23: Link | G23: Model setup sheet including lists, named ranges and constants | H23: =SysConfig!A8 -> 0 | I23: =SysConfig!B8 -> 0
E24: SysTime | F24: Link | G24: The model timeline and timing flags are generated on this sheet | H24: =SysTime!A8 -> 0 | I24: =SysTime!B8 -> 0
E25: INSERT NEW ROWS ABOVE THIS ROW
E27: Master Control Check | H27: =IFERROR(SUM(H12:H25),1) -> 0 | I27: =IFERROR(SUM(I12:I25),1) -> 0
D29: Model Map
E31: The map below indicates the flow between worksheets within the Model
D54: END OF WORKSHEET - INSERT ROWS ABOVE

Sheet Inputs>>

Sheet iControl
C1: THIS CASE STUDY MODEL IS FOR ILLUSTRATIVE PURPOSES
C2: =cstProjectName -> Should Cost Modelling Case Study - Illustrative SCM
C3: =MID(CELL("filename",A1),FIND("]",CELL("filename",A1))+1,256)&" Sheet" -> iControl Sheet
C4: =IF(ISBLANK(cstProtectiveMarking),"",cstProtectiveMarking) -> Not Protectively Marked
C5: =HYPERLINK("#'Contents'!A1",sysChkWord) -> All Checks OK
C6: =HYPERLINK("#'Contents'!A1","Click for Contents") -> Click for Contents
A8: =SUM(A9:A26) -> 0 | B8: =SUM(B9:B26) -> 0
D10: 1 | E10: Planned Maximum Call Volumes Scenarios
F12: Active Scenario | M12: <<<Select from Drop Down List
A14: =IF(ActiveCallVolumeScenarioIndex=0,1,0) -> 0 | F14: ActiveCallVolumeScenarioIndex | G14: # | I14: 1
F16: Annual Call Volume Reduction | G16: =cstPercent -> % | I16: 0.1
F18: Annual Call Volumes | G18: =cstHours -> Hrs | I18: =cVolumetrics!$K$39 -> 90000
D20: 2 | E20: Cost Scenarios
F22: Active Scenario | M22: <<<Select from Drop Down List
A24: =IF(ActiveCostScenarioIndex=0,1,0) -> 0 | F24: ActiveCostScenarioIndex | G24: # | I24: 2
D26: END OF WORKSHEET - INSERT ROWS ABOVE

Sheet iOptions
C1: THIS CASE STUDY MODEL IS FOR ILLUSTRATIVE PURPOSES
C2: =cstProjectName -> Should Cost Modelling Case Study - Illustrative SCM
C3: =MID(CELL("filename",A1),FIND("]",CELL("filename",A1))+1,256)&" Sheet" -> iOptions Sheet
C4: =IF(ISBLANK(cstProtectiveMarking),"",cstProtectiveMarking) -> Not Protectively Marked
C5: =HYPERLINK("#'Contents'!A1",sysChkWord) -> All Checks OK
C6: =HYPERLINK("#'Contents'!A1","Click for Contents") -> Click for Contents
N7: Time Independent
A8: =SUM(A9:A181) -> 0 | B8: =SUM(B9:B181) -> 0 | G8: Units | I8: BoA / DL Ref | K8: Comments | M8: =SysConfig!F101 -> Low Case | N8: =SysConfig!F102 -> Base Case | O8: =SysConfig!F103 -> High Case | Q8: Inflation Rate
D10: 1 | E10: Call Volumes (All Options)
E12: 1.1 | F12: Planned Call Volumes
F14: Planned Maximum Annual Call Volume Capacity
F16: =SysConfig!F95 -> Scenario A | G16: =cstHours -> Hrs | I16: 1 | N16: 100000
F17: =SysConfig!F96 -> Scenario B | G17: =cstHours -> Hrs | I17: 1 | N17: 150000
F18: =SysConfig!F97 -> Scenario C | G18: =cstHours -> Hrs | I18: 1 | N18: 200000
D20: 2 | E20: Staffing Inputs
E22: 2.1 | F22: Agents
F24: Annualised Hours & Productivity
A26: =IF(N26=0,1,0) -> 0 | F26: Agent Annualised Hours | G26: =cstHours -> Hrs | I26: 2 | N26: 1912
A28: =IF(OR(M28<=0,M28>1,N28<=0,N28>1,O28<=0,O28>1),1,0) -> 0 | F28: Agent Productivity Rate | G28: =cstPercent -> % | I28: 3 | M28: 0.75 | N28: 0.8 | O28: 0.85
E30: 2.2 | F30: Supervisors
F32: Agent to Supervisor Ratio
A34: =IF(OR(M34=0,N34=0,O34=0),1,0) -> 0 | F34: Agent to Supervisor Ratio | G34: =cstNum -> # | I34: 4 | M34: 13 | N34: 15 | O34: 17
E36: 2.3 Admin & Support
F38: Staff Numbers
F40: Reception & Admin Support | G40: =cstNum -> # | I40: 5 | N40: 3
F41: IT Support | G41: =cstNum -> # | I41: 5 | N41: 2
F42: Office Manager | G42: =cstNum -> # | I42: 5 | N42: 1
F43: Office Deputy | G43: =cstNum -> # | I43: 5 | N43: 1
E45: 2.4 Staff Costs by Role
F47: Fully Loaded Annual Staff Costs by Role
A49: =IF(ISNA(MATCH(Q49,iIndices!$F$16:$F$21,0)),1,0) -> 0 | F49: Agents | G49: =cstConstantUnit -> £ 2022/23 | I49: 6 | M49: 26000 | N49: 29000 | O49: 33000 | Q49: Wage Inflation
A50: =IF(ISNA(MATCH(Q50,iIndices!$F$16:$F$21,0)),1,0) -> 0 | F50: Supervisors | G50: =cstConstantUnit -> £ 2022/23 | I50: 6 | M50: 34000 | N50: 38000 | O50: 44000 | Q50: Wage Inflation
A51: =IF(ISNA(MATCH(Q51,iIndices!$F$16:$F$21,0)),1,0) -> 0 | F51: Reception & Admin Support | G51: =cstConstantUnit -> £ 2022/23 | I51: 6 | M51: 24000 | N51: 27000 | O51: 31000 | Q51: Wage Inflation
A52: =IF(ISNA(MATCH(Q52,iIndices!$F$16:$F$21,0)),1,0) -> 0 | F52: IT Support | G52: =cstConstantUnit -> £ 2022/23 | I52: 6 | M52: 32000 | N52: 36000 | O52: 41000 | Q52: Wage Inflation
A53: =IF(ISNA(MATCH(Q53,iIndices!$F$16:$F$21,0)),1,0) -> 0 | F53: Office Manager | G53: =cstConstantUnit -> £ 2022/23 | I53: 6 | M53: 46000 | N53: 51000 | O53: 59000 | Q53: Wage Inflation
A54: =IF(ISNA(MATCH(Q54,iIndices!$F$16:$F$21,0)),1,0) -> 0 | F54: Office Deputy | G54: =cstConstantUnit -> £ 2022/23 | I54: 6 | M54: 36000 | N54: 40000 | O54: 46000 | Q54: Wage Inflation
D56: 3 | E56: Software & Hardware Costs (Lease & Operate and Build & Operate Options)
E58: 3.1 | F58: Telephony Costs
F60: Software
A62: =IF(ISNA(MATCH(Q62,iIndices!$F$16:$F$21,0)),1,0) -> 0 | F62: Application Cost | G62: =cstConstantUnit -> £ 2022/23 | I62: 7 | M62: 175000 | N62: 200000 | O62: 225000 | Q62: Other Inflation
A63: =IF(OR(M63<0,N63<0,O63<0),1,0) -> 0 | F63: Vendor Support & Maintenance | G63: =cstPercent -> % | I63: 8 | K63: % of Application Cost | M63: 0.18 | N63: 0.2 | O63: 0.23
F64: Cost per License per Year | G64: =cstConstantUnit -> £ 2022/23 | I64: 9 | M64: 300 | N64: 400 | O64: 500
F66: Hardware
A68: =IF(ISNA(MATCH(Q68,iIndices!$F$16:$F$21,0)),1,0) -> 0 | F68: Initial Capital Cost | G68: =cstConstantUnit -> £ 2022/23 | I68: =MAX(I61:I67)+1 -> 10 | M68: 20000 | N68: 25000 | O68: 30000 | Q68: Other Inflation
A69: =IF(N69<0,1,0) -> 0 | F69: Replacement Factor | G69: =cstPercent -> % | I69: =MAX(I62:I68)+1 -> 11 | N69: 0.5
A70: =IF(N70<=0,1,0) -> 0 | F70: Replacement Periodicity | G70: =cstYears -> Yrs | I70: =MAX(I63:I69)+1 -> 12 | N70: 5
F72: Implementation
A74: =IF(ISNA(MATCH(Q74,iIndices!$F$16:$F$21,0)),1,0) -> 0 | F74: Initial Cost | G74: =cstConstantUnit -> £ 2022/23 | I74: =MAX(I67:I73)+1 -> 13 | M74: 175000 | N74: 200000 | O74: 225000 | Q74: Other Inflation
A75: =IF(N75<0,1,0) -> 0 | F75: Replacement Factor | G75: =cstPercent -> % | I75: =MAX(I68:I74)+1 -> 14 | N75: 0.5
A76: =IF(N76<=0,1,0) -> 0 | F76: Replacement Periodicity | G76: =cstYears -> Yrs | I76: =MAX(I69:I75)+1 -> 15 | N76: 5
F78: Periodic Training
A80: =IF(ISNA(MATCH(Q80,iIndices!$F$16:$F$21,0)),1,0) -> 0 | F80: Initial Cost | G80: =cstConstantUnit -> £ 2022/23 | I80: =MAX(I73:I79)+1 -> 16 | M80: 30000 | N80: 40000 | O80: 45000 | Q80: Other Inflation
A81: =IF(N81<0,1,0) -> 0 | F81: Periodic Factor | G81: =cstPercent -> % | I81: =MAX(I74:I80)+1 -> 17 | N81: 0.5
A82: =IF(N82<=0,1,0) -> 0 | F82: Periodicity | G82: =cstYears -> Yrs | I82: =MAX(I75:I81)+1 -> 18 | N82: 5
A84: =IF(ISNA(MATCH(Q84,iIndices!$F$16:$F$21,0)),1,0) -> 0 | F84: Annual Cost per User | G84: =cstConstantUnit -> £ 2022/23 | I84: =MAX(I77:I83)+1 -> 19 | M84: 800 | N84: 1000 | O84: 1200 | Q84: Other Inflation
E86: 3.2 Other IT Costs
F88: Software
A90: =IF(ISNA(MATCH(Q90,iIndices!$F$16:$F$21,0)),1,0) -> 0 | F90: Licencing per User per Year | G90: =cstConstantUnit -> £ 2022/23 | I90: =MAX(I83:I89)+1 -> 20 | M90: 300 | N90: 400 | O90: 500 | Q90: Other Inflation
F92: Hardware (Terminals & Ancillaries)
A94: =IF(ISNA(MATCH(Q94,iIndices!$F$16:$F$21,0)),1,0) -> 0 | F94: Initial Capital Cost | G94: =cstConstantUnit -> £ 2022/23 | I94: =MAX(I87:I93)+1 -> 21 | M94: 1200 | N94: 1500 | O94: 1700 | Q94: Other Inflation
A95: =IF(N95<0,1,0) -> 0 | F95: Replacement Factor | G95: =cstPercent -> % | I95: =MAX(I88:I94)+1 -> 22 | N95: 0.5
A96: =IF(N96<=0,1,0) -> 0 | F96: Replacement Periodicity | G96: =cstYears -> Yrs | I96: =MAX(I89:I95)+1 -> 23 | N96: 3
F98: Infrastructure & Maintenance
A100: =IF(ISNA(MATCH(Q100,iIndices!$F$16:$F$21,0)),1,0) -> 0 | F100: Cost per User per Year | G100: =cstConstantUnit -> £ 2022/23 | I100: =MAX(I93:I99)+1 -> 24 | M100: 150 | N100: 200 | O100: 250 | Q100: Other Inflation
E102: 3.3 Backup Power
F104: Standby Generator Costs
A106: =IF(ISNA(MATCH(Q106,iIndices!$F$16:$F$21,0)),1,0) -> 0 | F106: Initial Capital Cost | G106: =cstConstantUnit -> £ 2022/23 | I106: =MAX(I99:I105)+1 -> 25 | M106: 300000 | N106: 350000 | O106: 500000 | Q106: Other Inflation
A107: =IF(N107<0,1,0) -> 0 | F107: Installation & Maintenance | G107: =cstPercent -> % | I107: =MAX(I100:I106)+1 -> 26 | M107: 0.05 | N107: 0.07 | O107: 0.09
D109: 4 | E109: Operating Costs (Outsource Option)
E111: 4.1 | F111: Annual Operating Costs
F113: Cost per Call Hour
A115: =IF(ISNA(MATCH(Q115,iIndices!$F$16:$F$21,0)),1,0) -> 0 | F115: Cost per Call Hour | G115: =cstConstantUnit -> £ 2022/23 | I115: =MAX(I58:I114)+1 -> 27 | M115: 25 | N115: 30 | O115: 40 | Q115: Other Inflation
D117: 5 | E117: Lease Costs (Lease & Operate)
E119: 5.1 | F119: Annual Serviced Office Costs
F121: Lease Costs
A123: =IF(ISNA(MATCH(Q123,iIndices!$F$16:$F$21,0)),1,0) -> 0 | F123: Cost per FTE per Year | G123: =cstConstantUnit -> £ 2022/23 | I123: =MAX(I66:I122)+1 -> 28 | M123: 600 | N123: 850 | O123: 1100 | Q123: Other Inflation
D125: 6 | E125: Build & Maintenance Costs (Build & Operate Option)
E127: 6.1 | F127: Office Footprint
F129: Floor Area
F131: Staff Space Standard | G131: {=cstArea&"/"&cstFTE} -> m2/FTE | I131: =MAX(I74:I130)+1 -> 29 | M131: 10 | N131: 15 | O131: 20
E133: 6.2 Design & Build Costs
F135: Design Costs
A137: =IF(N137<0,1,0) -> 0 | F137: Design/Build Cost Ratio | G137: =cstPercent -> % | I137: =MAX(I80:I136)+1 -> 30 | M137: 0.02 | N137: 0.03 | O137: 0.04
F139: Build Costs (cost per total building sqaure metres)
A141: =IF(ISNA(MATCH(Q141,iIndices!$F$16:$F$21,0)),1,0) -> 0 | F141: Substructure | G141: =cstConstantUnit&" per "&cstArea -> £ 2022/23 per m2 | I141: =MAX(I84:I140)+1 -> 31 | M141: 123.5 | N141: 137.8 | O141: 158.6 | Q141: Other Inflation
A142: =IF(ISNA(MATCH(Q142,iIndices!$F$16:$F$21,0)),1,0) -> 0 | F142: Frame | G142: =cstConstantUnit&" per "&cstArea -> £ 2022/23 per m2 | I142: =I141 -> 31 | M142: 163.8 | N142: 182 | O142: 209.3 | Q142: Other Inflation
A143: =IF(ISNA(MATCH(Q143,iIndices!$F$16:$F$21,0)),1,0) -> 0 | F143: Upper Floors | G143: =cstConstantUnit&" per "&cstArea -> £ 2022/23 per m2 | I143: =I142 -> 31 | M143: 32.5 | N143: 36.4 | O143: 41.6 | Q143: Other Inflation
A144: =IF(ISNA(MATCH(Q144,iIndices!$F$16:$F$21,0)),1,0) -> 0 | F144: Roof | G144: =cstConstantUnit&" per "&cstArea -> £ 2022/23 per m2 | I144: =I143 -> 31 | M144: 135.2 | N144: 149.5 | O144: 171.6 | Q144: Other Inflation
A145: =IF(ISNA(MATCH(Q145,iIndices!$F$16:$F$21,0)),1,0) -> 0 | F145: Stairs | G145: =cstConstantUnit&" per "&cstArea -> £ 2022/23 per m2 | I145: =I144 -> 31 | M145: 14.3 | N145: 15.6 | O145: 18.2 | Q145: Other Inflation
A146: =IF(ISNA(MATCH(Q146,iIndices!$F$16:$F$21,0)),1,0) -> 0 | F146: Ext Walls, Windows & Doors | G146: =cstConstantUnit&" per "&cstArea -> £ 2022/23 per m2 | I146: =I145 -> 31 | M146: 228.8 | N146: 253.5 | O146: 291.2 | Q146: Other Inflation
A147: =IF(ISNA(MATCH(Q147,iIndices!$F$16:$F$21,0)),1,0) -> 0 | F147: Int Walls & Partitions | G147: =cstConstantUnit&" per "&cstArea -> £ 2022/23 per m2 | I147: =I146 -> 31 | M147: 111.8 | N147: 123.5 | O147: 141.7 | Q147: Other Inflation
A148: =IF(ISNA(MATCH(Q148,iIndices!$F$16:$F$21,0)),1,0) -> 0 | F148: Int Doors | G148: =cstConstantUnit&" per "&cstArea -> £ 2022/23 per m2 | I148: =I147 -> 31 | M148: 33.8 | N148: 37.7 | O148: 42.9 | Q148: Other Inflation
A149: =IF(ISNA(MATCH(Q149,iIndices!$F$16:$F$21,0)),1,0) -> 0 | F149: Wall Finishes | G149: =cstConstantUnit&" per "&cstArea -> £ 2022/23 per m2 | I149: =I148 -> 31 | M149: 36.4 | N149: 40.3 | O149: 46.8 | Q149: Other Inflation
A150: =IF(ISNA(MATCH(Q150,iIndices!$F$16:$F$21,0)),1,0) -> 0 | F150: Floor Finishes | G150: =cstConstantUnit&" per "&cstArea -> £ 2022/23 per m2 | I150: =I149 -> 31 | M150: 166.4 | N150: 184.6 | O150: 211.9 | Q150: Other Inflation
A151: =IF(ISNA(MATCH(Q151,iIndices!$F$16:$F$21,0)),1,0) -> 0 | F151: Ceiling Finishes | G151: =cstConstantUnit&" per "&cstArea -> £ 2022/23 per m2 | I151: =I150 -> 31 | M151: 31.2 | N151: 35.1 | O151: 40.3 | Q151: Other Inflation
A152: =IF(ISNA(MATCH(Q152,iIndices!$F$16:$F$21,0)),1,0) -> 0 | F152: Furniture & Fittings | G152: =cstConstantUnit&" per "&cstArea -> £ 2022/23 per m2 | I152: =I151 -> 31 | M152: 80.6 | N152: 89.7 | O152: 102.7 | Q152: Other Inflation
A153: =IF(ISNA(MATCH(Q153,iIndices!$F$16:$F$21,0)),1,0) -> 0 | F153: Sanitary Fittings | G153: =cstConstantUnit&" per "&cstArea -> £ 2022/23 per m2 | I153: =I152 -> 31 | M153: 11.7 | N153: 13 | O153: 15.6 | Q153: Other Inflation
... A164: =IF(ISNA(MATCH(Q164,iIndices!$F$16:$F$21,0)),1,0) -> 0 | F164: Preliminaries & Contingencies | G164: =cstConstantUnit&" per "&cstArea -> £ 2022/23 per m2 | I164: =I163 -> 31 | M164: 364 | N164: 404.3 | O164: 465.4 | Q164: Other Inflation
A165: =IF(ISNA(MATCH(Q165,iIndices!$F$16:$F$21,0)),1,0) -> 0 | F165: Spare | G165: =cstConstantUnit&" per "&cstArea -> £ 2022/23 per m2 | Q165: Other Inflation
F167: Site Preparation Costs
...

Sheet iIndices
C1: THIS CASE STUDY MODEL IS FOR ILLUSTRATIVE PURPOSES
C2: =cstProjectName -> Should Cost Modelling Case Study - Illustrative SCM | Z2: =SysTime!Z2 -> Period Start | AA2: =SysTime!AA2 -> 44652 | AB2: =SysTime!AB2 -> 45017 | AC2: =SysTime!AC2 -> 45383 | AD2: =SysTime!AD2 -> 45748 | AE2: =SysTime!AE2 -> 46113 | AF2: =SysTime!AF2 -> 46478 | AG2: =SysTime!AG2 -> 46844 | ... BE2: =SysTime!BE2 -> 55610 | BG2: =SysTime!BG2 -> 44652 | BH2: =SysTime!BH2 -> 45017 | BI2: =SysTime!BI2 -> 46844 | BJ2: =SysTime!BJ2 -> 48670 | BK2: =SysTime!BK2 -> 50496 | BL2: =SysTime!BL2 -> 52322 | BM2: =SysTime!BM2 -> 54149
C3: =MID(CELL("filename",A1),FIND("]",CELL("filename",A1))+1,256)&" Sheet" -> iIndices Sheet | Z3: =SysTime!Z3 -> Period End | AA3: =SysTime!AA3 -> 45016 | AB3: =SysTime!AB3 -> 45382 | AC3: =SysTime!AC3 -> 45747 | AD3: =SysTime!AD3 -> 46112 | AE3: =SysTime!AE3 -> 46477 | AF3: =SysTime!AF3 -> 46843 | AG3: =SysTime!AG3 -> 47208 | ... BE3: =SysTime!BE3 -> 55974 | BG3: =SysTime!BG3 -> 45016 | BH3: =SysTime!BH3 -> 46843 | BI3: =SysTime!BI3 -> 48669 | BJ3: =SysTime!BJ3 -> 50495 | BK3: =SysTime!BK3 -> 52321 | BL3: =SysTime!BL3 -> 54148 | BM3: =SysTime!BM3 -> 55974
C4: =IF(ISBLANK(cstProtectiveMarking),"",cstProtectiveMarking) -> Not Protectively Marked | Z4: =SysTime!Z4 -> Timeline | AA4: =SysTime!AA4 -> Annual | AB4: =SysTime!AB4 -> Annual | AC4: =SysTime!AC4 -> Annual | AD4: =SysTime!AD4 -> Annual | AE4: =SysTime!AE4 -> Annual | AF4: =SysTime!AF4 -> Annual | AG4: =SysTime!AG4 -> Annual | ... BE4: =SysTime!BE4 -> Annual | BG4: =SysTime!BG4 -> Annual | BH4: =SysTime!BH4 -> 5 Yearly | BI4: =SysTime!BI4 -> 5 Yearly | BJ4: =SysTime!BJ4 -> 5 Yearly | BK4: =SysTime!BK4 -> 5 Yearly | BL4: =SysTime!BL4 -> 5 Yearly | BM4: =SysTime!BM4 -> 5 Yearly
C5: =HYPERLINK("#'Contents'!A1",sysChkWord) -> All Checks OK | Z5: =SysTime!Z5 -> Period index | AA5: =SysTime!AA5 -> 1 | AB5: =SysTime!AB5 -> 2 | AC5: =SysTime!AC5 -> 3 | AD5: =SysTime!AD5 -> 4 | AE5: =SysTime!AE5 -> 5 | AF5: =SysTime!AF5 -> 6 | AG5: =SysTime!AG5 -> 7 | ... BE5: =SysTime!BE5 -> 31 | BG5: =SysTime!BG5 -> 1 | BH5: =SysTime!BH5 -> 2 | BI5: =SysTime!BI5 -> 3 | BJ5: =SysTime!BJ5 -> 4 | BK5: =SysTime!BK5 -> 5 | BL5: =SysTime!BL5 -> 6 | BM5: =SysTime!BM5 -> 7
C6: =HYPERLINK("#'Contents'!A1","Click for Contents") -> Click for Contents | Z6: =SysTime!Z6 -> Year index | AA6: =SysTime!AA6 -> 1 | AB6: =SysTime!AB6 -> 2 | AC6: =SysTime!AC6 -> 3 | AD6: =SysTime!AD6 -> 4 | AE6: =SysTime!AE6 -> 5 | AF6: =SysTime!AF6 -> 6 | AG6: =SysTime!AG6 -> 7 | ... BE6: =SysTime!BE6 -> 31 | BG6: =SysTime!BG6 -> 0 | BH6: =SysTime!BH6 -> 0 | BI6: =SysTime!BI6 -> 0 | BJ6: =SysTime!BJ6 -> 0 | BK6: =SysTime!BK6 -> 0 | BL6: =SysTime!BL6 -> 0 | BM6: =SysTime!BM6 -> 0
Z7: =SysTime!Z7 -> Relative period | AA7: =SysTime!AA7 -> 1 | AB7: =SysTime!AB7 -> 2 | AC7: =SysTime!AC7 -> 3 | AD7: =SysTime!AD7 -> 4 | AE7: =SysTime!AE7 -> 5 | AF7: =SysTime!AF7 -> 6 | AG7: =SysTime!AG7 -> 7 | ... BE7: =SysTime!BE7 -> 31 | BG7: =SysTime!BG7 -> 1 | BH7: =SysTime!BH7 -> 2 | BI7: =SysTime!BI7 -> 3 | BJ7: =SysTime!BJ7 -> 4 | BK7: =SysTime!BK7 -> 5 | BL7: =SysTime!BL7 -> 6 | BM7: =SysTime!BM7 -> 7
A8: =SUM(A9:A29) -> 0 | B8: =SUM(B9:B29) -> 0 | G8: Units | I8: BoA / DL Ref | K8: Comments
D10: 1 | E10: Indexes
E12: 1.1 | F12: Inflation Assumptions
F14: Annual Inflation Rates
F15: Named range
F16: Wage Inflation | G16: % | I16: 36 | AB16: 0.025 | AC16: 0.025 | AD16: 0.025 | AE16: 0.025 | AF16: 0.025 | AG16: 0.025 | AH16: 0.025 | AI16: 0.025 | AJ16: 0.025 | AK16: 0.025 | AL16: 0.025 | AM16: 0.025 | AN16: 0.025 | AO16: 0.025 | AP16: 0.025 | AQ16: 0.025 | AR16: 0.025 | AS16: 0.025 | AT16: 0.025 | AU16: 0.025 | AV16: 0.025 | AW16: 0.025 | AX16: 0.025 | AY16: 0.025 | AZ16: 0.025 | BA16: 0.025 | BB16: 0.025 | BC16: 0.025 | BD16: 0.025 | BE16: 0.025
F17: Other Inflation | G17: % | I17: 36 | AB17: 0.03 | AC17: 0.03 | AD17: 0.03 | AE17: 0.03 | AF17: 0.03 | AG17: 0.03 | AH17: 0.03 | AI17: 0.03 | AJ17: 0.03 | AK17: 0.03 | AL17: 0.03 | AM17: 0.03 | AN17: 0.03 | AO17: 0.03 | AP17: 0.03 | AQ17: 0.03 | AR17: 0.03 | AS17: 0.03 | AT17: 0.03 | AU17: 0.03 | AV17: 0.03 | AW17: 0.03 | AX17: 0.03 | AY17: 0.03 | AZ17: 0.03 | BA17: 0.03 | BB17: 0.03 | BC17: 0.03 | BD17: 0.03 | BE17: 0.03
F18: Inflation Type C | G18: % | I18: 36 | AB18: 0.02 | AC18: 0.02 | AD18: 0.02 | AE18: 0.02 | AF18: 0.02 | AG18: 0.02 | AH18: 0.02 | AI18: 0.02 | AJ18: 0.02 | AK18: 0.02 | AL18: 0.02 | AM18: 0.02 | AN18: 0.02 | AO18: 0.02 | AP18: 0.02 | AQ18: 0.02 | AR18: 0.02 | AS18: 0.02 | AT18: 0.02 | AU18: 0.02 | AV18: 0.02 | AW18: 0.02 | AX18: 0.02 | AY18: 0.02 | AZ18: 0.02 | BA18: 0.02 | BB18: 0.02 | BC18: 0.02 | BD18: 0.02 | BE18: 0.02
F19: Inflation Type D | G19: % | I19: 36 | AB19: 0.02 | AC19: 0.02 | AD19: 0.02 | AE19: 0.02 | AF19: 0.02 | AG19: 0.02 | AH19: 0.02 | AI19: 0.02 | AJ19: 0.02 | AK19: 0.02 | AL19: 0.02 | AM19: 0.02 | AN19: 0.02 | AO19: 0.02 | AP19: 0.02 | AQ19: 0.02 | AR19: 0.02 | AS19: 0.02 | AT19: 0.02 | AU19: 0.02 | AV19: 0.02 | AW19: 0.02 | AX19: 0.02 | AY19: 0.02 | AZ19: 0.02 | BA19: 0.02 | BB19: 0.02 | BC19: 0.02 | BD19: 0.02 | BE19: 0.02
F20: Inflation Type E | G20: % | I20: 36 | AB20: 0.02 | AC20: 0.02 | AD20: 0.02 | AE20: 0.02 | AF20: 0.02 | AG20: 0.02 | AH20: 0.02 | AI20: 0.02 | AJ20: 0.02 | AK20: 0.02 | AL20: 0.02 | AM20: 0.02 | AN20: 0.02 | AO20: 0.02 | AP20: 0.02 | AQ20: 0.02 | AR20: 0.02 | AS20: 0.02 | AT20: 0.02 | AU20: 0.02 | AV20: 0.02 | AW20: 0.02 | AX20: 0.02 | AY20: 0.02 | AZ20: 0.02 | BA20: 0.02 | BB20: 0.02 | BC20: 0.02 | BD20: 0.02 | BE20: 0.02
E22: 1.2 | F22: Discount Factors
F24: Treasury Rates
F26: GDP Deflator (General Price Inflation) | G26: % | I26: 37 | AB26: 0.013 | AC26: 0.017 | AD26: 0.019 | AE26: 0.019 | AF26: 0.02 | AG26: 0.02 | AH26: 0.02 | AI26: 0.02 | AJ26: 0.02 | AK26: 0.02 | AL26: 0.02 | AM26: 0.02 | AN26: 0.02 | AO26: 0.02 | AP26: 0.02 | AQ26: 0.02 | AR26: 0.02 | AS26: 0.02 | AT26: 0.02 | AU26: 0.02 | AV26: 0.02 | AW26: 0.02 | AX26: 0.02 | AY26: 0.02 | AZ26: 0.02 | BA26: 0.02 | BB26: 0.02 | BC26: 0.02 | BD26: 0.02 | BE26: 0.02
F27: Treasury Real Discount Rate | G27: % | I27: 38 | AB27: 0.035 | AC27: 0.035 | AD27: 0.035 | AE27: 0.035 | AF27: 0.035 | AG27: 0.035 | AH27: 0.035 | AI27: 0.035 | AJ27: 0.035 | AK27: 0.035 | AL27: 0.035 | AM27: 0.035 | AN27: 0.035 | AO27: 0.035 | AP27: 0.035 | AQ27: 0.035 | AR27: 0.035 | AS27: 0.035 | AT27: 0.035 | AU27: 0.035 | AV27: 0.035 | AW27: 0.035 | AX27: 0.035 | AY27: 0.035 | AZ27: 0.035 | BA27: 0.035 | BB27: 0.035 | BC27: 0.035 | BD27: 0.035 | BE27: 0.03
D29: END OF WORKSHEET - INSERT ROWS ABOVE

Sheet Calcs>>

Sheet cFactors
C1: THIS CASE STUDY MODEL IS FOR ILLUSTRATIVE PURPOSES
C2: =cstProjectName -> Should Cost Modelling Case Study - Illustrative SCM | Z2: =SysTime!Z2 -> Period Start | AA2: =SysTime!AA2 -> 44652 | AB2: =SysTime!AB2 -> 45017 | AC2: =SysTime!AC2 -> 45383 | AD2: =SysTime!AD2 -> 45748 | AE2: =SysTime!AE2 -> 46113 | AF2: =SysTime!AF2 -> 46478 | AG2: =SysTime!AG2 -> 46844 | ... BE2: =SysTime!BE2 -> 55610 | BG2: =SysTime!BG2 -> 44652 | BH2: =SysTime!BH2 -> 45017 | BI2: =SysTime!BI2 -> 46844 | BJ2: =SysTime!BJ2 -> 48670 | BK2: =SysTime!BK2 -> 50496 | BL2: =SysTime!BL2 -> 52322 | BM2: =SysTime!BM2 -> 54149
C3: =MID(CELL("filename",A1),FIND("]",CELL("filename",A1))+1,256)&" Sheet" -> cFactors Sheet | Z3: =SysTime!Z3 -> Period End | AA3: =SysTime!AA3 -> 45016 | AB3: =SysTime!AB3 -> 45382 | AC3: =SysTime!AC3 -> 45747 | AD3: =SysTime!AD3 -> 46112 | AE3: =SysTime!AE3 -> 46477 | AF3: =SysTime!AF3 -> 46843 | AG3: =SysTime!AG3 -> 47208 | ... BE3: =SysTime!BE3 -> 55974 | BG3: =SysTime!BG3 -> 45016 | BH3: =SysTime!BH3 -> 46843 | BI3: =SysTime!BI3 -> 48669 | BJ3: =SysTime!BJ3 -> 50495 | BK3: =SysTime!BK3 -> 52321 | BL3: =SysTime!BL3 -> 54148 | BM3: =SysTime!BM3 -> 55974
C4: =IF(ISBLANK(cstProtectiveMarking),"",cstProtectiveMarking) -> Not Protectively Marked | Z4: =SysTime!Z4 -> Timeline | AA4: =SysTime!AA4 -> Annual | AB4: =SysTime!AB4 -> Annual | AC4: =SysTime!AC4 -> Annual | AD4: =SysTime!AD4 -> Annual | AE4: =SysTime!AE4 -> Annual | AF4: =SysTime!AF4 -> Annual | AG4: =SysTime!AG4 -> Annual | ... BE4: =SysTime!BE4 -> Annual | BG4: =SysTime!BG4 -> Annual | BH4: =SysTime!BH4 -> 5 Yearly | BI4: =SysTime!BI4 -> 5 Yearly | BJ4: =SysTime!BJ4 -> 5 Yearly | BK4: =SysTime!BK4 -> 5 Yearly | BL4: =SysTime!BL4 -> 5 Yearly | BM4: =SysTime!BM4 -> 5 Yearly
C5: =HYPERLINK("#'Contents'!A1",sysChkWord) -> All Checks OK | Z5: =SysTime!Z5 -> Period index | AA5: =SysTime!AA5 -> 1 | AB5: =SysTime!AB5 -> 2 | AC5: =SysTime!AC5 -> 3 | AD5: =SysTime!AD5 -> 4 | AE5: =SysTime!AE5 -> 5 | AF5: =SysTime!AF5 -> 6 | AG5: =SysTime!AG5 -> 7 | ... BE5: =SysTime!BE5 -> 31 | BG5: =SysTime!BG5 -> 1 | BH5: =SysTime!BH5 -> 2 | BI5: =SysTime!BI5 -> 3 | BJ5: =SysTime!BJ5 -> 4 | BK5: =SysTime!BK5 -> 5 | BL5: =SysTime!BL5 -> 6 | BM5: =SysTime!BM5 -> 7
C6: =HYPERLINK("#'Contents'!A1","Click for Contents") -> Click for Contents | Z6: =SysTime!Z6 -> Year index | AA6: =SysTime!AA6 -> 1 | AB6: =SysTime!AB6 -> 2 | AC6: =SysTime!AC6 -> 3 | AD6: =SysTime!AD6 -> 4 | AE6: =SysTime!AE6 -> 5 | AF6: =SysTime!AF6 -> 6 | AG6: =SysTime!AG6 -> 7 | ... BE6: =SysTime!BE6 -> 31 | BG6: =SysTime!BG6 -> 0 | BH6: =SysTime!BH6 -> 0 | BI6: =SysTime!BI6 -> 0 | BJ6: =SysTime!BJ6 -> 0 | BK6: =SysTime!BK6 -> 0 | BL6: =SysTime!BL6 -> 0 | BM6: =SysTime!BM6 -> 0
Z7: =SysTime!Z7 -> Relative period | AA7: =SysTime!AA7 -> 1 | AB7: =SysTime!AB7 -> 2 | AC7: =SysTime!AC7 -> 3 | AD7: =SysTime!AD7 -> 4 | AE7: =SysTime!AE7 -> 5 | AF7: =SysTime!AF7 -> 6 | AG7: =SysTime!AG7 -> 7 | ... BE7: =SysTime!BE7 -> 31 | BG7: =SysTime!BG7 -> 1 | BH7: =SysTime!BH7 -> 2 | BI7: =SysTime!BI7 -> 3 | BJ7: =SysTime!BJ7 -> 4 | BK7: =SysTime!BK7 -> 5 | BL7: =SysTime!BL7 -> 6 | BM7: =SysTime!BM7 -> 7
A8: =SUM(A9:A48) -> 0 | B8: =SUM(B9:B48) -> 0 | G8: Units
D10: 1 | E10: Call-Ups
E12: 1.1 | F12: Inflation Assumptions
F14: Annual Inflation Rates
F16: Wage Inflation | G16: % | AA16: =iIndices!AA16 -> 0 | AB16: =iIndices!AB16 -> 0.025 | AC16: =iIndices!AC16 -> 0.025 | AD16: =iIndices!AD16 -> 0.025 | AE16: =iIndices!AE16 -> 0.025 | AF16: =iIndices!AF16 -> 0.025 | AG16: =iIndices!AG16 -> 0.025 | AH16: =iIndices!AH16 -> 0.025 | ... BE16: =iIndices!BE16 -> 0.025
F17: Other Inflation | G17: % | AA17: =iIndices!AA17 -> 0 | AB17: =iIndices!AB17 -> 0.03 | AC17: =iIndices!AC17 -> 0.03 | AD17: =iIndices!AD17 -> 0.03 | AE17: =iIndices!AE17 -> 0.03 | AF17: =iIndices!AF17 -> 0.03 | AG17: =iIndices!AG17 -> 0.03 | AH17: =iIndices!AH17 -> 0.03 | ... BE17: =iIndices!BE17 -> 0.03
F18: Inflation Type C | G18: % | AA18: =iIndices!AA18 -> 0 | AB18: =iIndices!AB18 -> 0.02 | AC18: =iIndices!AC18 -> 0.02 | AD18: =iIndices!AD18 -> 0.02 | AE18: =iIndices!AE18 -> 0.02 | AF18: =iIndices!AF18 -> 0.02 | AG18: =iIndices!AG18 -> 0.02 | AH18: =iIndices!AH18 -> 0.02 | ... BE18: =iIndices!BE18 -> 0.02
F19: Inflation Type D | G19: % | AA19: =iIndices!AA19 -> 0 | AB19: =iIndices!AB19 -> 0.02 | AC19: =iIndices!AC19 -> 0.02 | AD19: =iIndices!AD19 -> 0.02 | AE19: =iIndices!AE19 -> 0.02 | AF19: =iIndices!AF19 -> 0.02 | AG19: =iIndices!AG19 -> 0.02 | AH19: =iIndices!AH19 -> 0.02 | ... BE19: =iIndices!BE19 -> 0.02
F20: Inflation Type E | G20: % | AA20: =iIndices!AA20 -> 0 | AB20: =iIndices!AB20 -> 0.02 | AC20: =iIndices!AC20 -> 0.02 | AD20: =iIndices!AD20 -> 0.02 | AE20: =iIndices!AE20 -> 0.02 | AF20: =iIndices!AF20 -> 0.02 | AG20: =iIndices!AG20 -> 0.02 | AH20: =iIndices!AH20 -> 0.02 | ... BE20: =iIndices!BE20 -> 0.02
E22: 1.2 | F22: Discount Rate
F24: Treasury Rates
F26: GDP Deflator (General Price Inflation) | G26: % | AA26: =iIndices!AA26 -> 0 | AB26: =iIndices!AB26 -> 0.013 | AC26: =iIndices!AC26 -> 0.017 | AD26: =iIndices!AD26 -> 0.019 | AE26: =iIndices!AE26 -> 0.019 | AF26: =iIndices!AF26 -> 0.02 | AG26: =iIndices!AG26 -> 0.02 | AH26: =iIndices!AH26 -> 0.02 | ... BE26: =iIndices!BE26 -> 0.02
F27: Treasury Real Discount Rate | G27: % | AA27: =iIndices!AA27 -> 0 | AB27: =iIndices!AB27 -> 0.035 | AC27: =iIndices!AC27 -> 0.035 | AD27: =iIndices!AD27 -> 0.035 | AE27: =iIndices!AE27 -> 0.035 | AF27: =iIndices!AF27 -> 0.035 | AG27: =iIndices!AG27 -> 0.035 | AH27: =iIndices!AH27 -> 0.035 | ... BE27: =iIndices!BE27 -> 0.03
D29: 2 | E29: Calculations
E31: 2.1 | F31: Inflation Index
F33: Annual Inflation Index
A35: =IF(MIN(AA35:BE35)<0,1,0) -> 0 | F35: Wage Inflation | G35: % | AA35: =IF(AA$5=1,1,Z35)*(1+AA16) -> 1 | AB35: =IF(AB$5=1,1,AA35)*(1+AB16) -> 1.025 | AC35: =IF(AC$5=1,1,AB35)*(1+AC16) -> 1.050625 | AD35: =IF(AD$5=1,1,AC35)*(1+AD16) -> 1.0768906 | AE35: =IF(AE$5=1,1,AD35)*(1+AE16) -> 1.1038129 | AF35: =IF(AF$5=1,1,AE35)*(1+AF16) -> 1.1314082 | AG35: =IF(AG$5=1,1,AF35)*(1+AG16) -> 1.1596934 | AH35: =IF(AH$5=1,1,AG35)*(1+AH16) -> 1.1886858 | ... BE35: =IF(BE$5=1,1,BD35)*(1+BE16) -> 2.0975676
A36: =IF(MIN(AA36:BE36)<0,1,0) -> 0 | F36: Other Inflation | G36: % | AA36: =IF(AA$5=1,1,Z36)*(1+AA17) -> 1 | AB36: =IF(AB$5=1,1,AA36)*(1+AB17) -> 1.03 | AC36: =IF(AC$5=1,1,AB36)*(1+AC17) -> 1.0609 | AD36: =IF(AD$5=1,1,AC36)*(1+AD17) -> 1.092727 | AE36: =IF(AE$5=1,1,AD36)*(1+AE17) -> 1.1255088 | AF36: =IF(AF$5=1,1,AE36)*(1+AF17) -> 1.1592741 | AG36: =IF(AG$5=1,1,AF36)*(1+AG17) -> 1.1940523 | AH36: =IF(AH$5=1,1,AG36)*(1+AH17) -> 1.2298739 | ... BE36: =IF(BE$5=1,1,BD36)*(1+BE17) -> 2.4272625
A37: =IF(MIN(AA37:BE37)<0,1,0) -> 0 | F37: Inflation Type C | G37: % | AA37: =IF(AA$5=1,1,Z37)*(1+AA18) -> 1 | AB37: =IF(AB$5=1,1,AA37)*(1+AB18) -> 1.02 | AC37: =IF(AC$5=1,1,AB37)*(1+AC18) -> 1.0404 | AD37: =IF(AD$5=1,1,AC37)*(1+AD18) -> 1.061208 | AE37: =IF(AE$5=1,1,AD37)*(1+AE18) -> 1.0824322 | AF37: =IF(AF$5=1,1,AE37)*(1+AF18) -> 1.1040808 | AG37: =IF(AG$5=1,1,AF37)*(1+AG18) -> 1.1261624 | AH37: =IF(AH$5=1,1,AG37)*(1+AH18) -> 1.1486857 | ... BE37: =IF(BE$5=1,1,BD37)*(1+BE18) -> 1.8113616
A38: =IF(MIN(AA38:BE38)<0,1,0) -> 0 | F38: Inflation Type D | G38: % | AA38: =IF(AA$5=1,1,Z38)*(1+AA19) -> 1 | AB38: =IF(AB$5=1,1,AA38)*(1+AB19) -> 1.02 | AC38: =IF(AC$5=1,1,AB38)*(1+AC19) -> 1.0404 | AD38: =IF(AD$5=1,1,AC38)*(1+AD19) -> 1.061208 | AE38: =IF(AE$5=1,1,AD38)*(1+AE19) -> 1.0824322 | AF38: =IF(AF$5=1,1,AE38)*(1+AF19) -> 1.1040808 | AG38: =IF(AG$5=1,1,AF38)*(1+AG19) -> 1.1261624 | AH38: =IF(AH$5=1,1,AG38)*(1+AH19) -> 1.1486857 | ... BE38: =IF(BE$5=1,1,BD38)*(1+BE19) -> 1.8113616
A39: =IF(MIN(AA39:BE39)<0,1,0) -> 0 | F39: Inflation Type E | G39: % | AA39: =IF(AA$5=1,1,Z39)*(1+AA20) -> 1 | AB39: =IF(AB$5=1,1,AA39)*(1+AB20) -> 1.02 | AC39: =IF(AC$5=1,1,AB39)*(1+AC20) -> 1.0404 | AD39: =IF(AD$5=1,1,AC39)*(1+AD20) -> 1.061208 | AE39: =IF(AE$5=1,1,AD39)*(1+AE20) -> 1.0824322 | AF39: =IF(AF$5=1,1,AE39)*(1+AF20) -> 1.1040808 | AG39: =IF(AG$5=1,1,AF39)*(1+AG20) -> 1.1261624 | AH39: =IF(AH$5=1,1,AG39)*(1+AH20) -> 1.1486857 | ... BE39: =IF(BE$5=1,1,BD39)*(1+BE20) -> 1.8113616
E41: 2.2 | F41: Discount Factors
F43: Treasury Rates
A45: =IF(MIN(AA45:BE45)<0,1,0) -> 0 | F45: GDP Deflator (General Price Inflation) | G45: % | AA45: =IF(AA$5=1,1,Z45)/(1+AA26) -> 1 | AB45: =IF(AB$5=1,1,AA45)/(1+AB26) -> 0.98716683 | AC45: =IF(AC$5=1,1,AB45)/(1+AC26) -> 0.97066552 | AD45: =IF(AD$5=1,1,AC45)/(1+AD26) -> 0.95256675 | AE45: =IF(AE$5=1,1,AD45)/(1+AE26) -> 0.93480545 | AF45: =IF(AF$5=1,1,AE45)/(1+AF26) -> 0.91647593 | AG45: =IF(AG$5=1,1,AF45)/(1+AG26) -> 0.89850581 | AH45: =IF(AH$5=1,1,AG45)/(1+AH26) -> 0.88088805 | ... BE45: =IF(BE$5=1,1,BD45)/(1+BE26) -> 0.55862037
A46: =IF(MIN(AA46:BE46)<0,1,0) -> 0 | F46: Treasury Real Discount Rate | G46: % | AA46: =IF(AA$5=1,1,Z46)/(1+AA27) -> 1 | AB46: =IF(AB$5=1,1,AA46)/(1+AB27) -> 0.96618357 | AC46: =IF(AC$5=1,1,AB46)/(1+AC27) -> 0.9335107 | AD46: =IF(AD$5=1,1,AC46)/(1+AD27) -> 0.90194271 | AE46: =IF(AE$5=1,1,AD46)/(1+AE27) -> 0.87144223 | AF46: =IF(AF$5=1,1,AE46)/(1+AF27) -> 0.84197317 | AG46: =IF(AG$5=1,1,AF46)/(1+AG27) -> 0.81350064 | AH46: =IF(AH$5=1,1,AG46)/(1+AH27) -> 0.78599096 | ... BE46: =IF(BE$5=1,1,BD46)/(1+BE27) -> 0.35800792
D48: END OF WORKSHEET - INSERT ROWS ABOVE

Sheet cVolumetrics
C1: THIS CASE STUDY MODEL IS FOR ILLUSTRATIVE PURPOSES
C2: =cstProjectName -> Should Cost Modelling Case Study - Illustrative SCM | Z2: =SysTime!Z2 -> Period Start | AA2: =SysTime!AA2 -> 44652 | AB2: =SysTime!AB2 -> 45017 | AC2: =SysTime!AC2 -> 45383 | AD2: =SysTime!AD2 -> 45748 | AE2: =SysTime!AE2 -> 46113 | AF2: =SysTime!AF2 -> 46478 | AG2: =SysTime!AG2 -> 46844 | ... BE2: =SysTime!BE2 -> 55610 | BG2: =SysTime!BG2 -> 44652 | BH2: =SysTime!BH2 -> 45017 | BI2: =SysTime!BI2 -> 46844 | BJ2: =SysTime!BJ2 -> 48670 | BK2: =SysTime!BK2 -> 50496 | BL2: =SysTime!BL2 -> 52322 | BM2: =SysTime!BM2 -> 54149
C3: =MID(CELL("filename",A1),FIND("]",CELL("filename",A1))+1,256)&" Sheet" -> cVolumetrics Sheet | Z3: =SysTime!Z3 -> Period End | AA3: =SysTime!AA3 -> 45016 | AB3: =SysTime!AB3 -> 45382 | AC3: =SysTime!AC3 -> 45747 | AD3: =SysTime!AD3 -> 46112 | AE3: =SysTime!AE3 -> 46477 | AF3: =SysTime!AF3 -> 46843 | AG3: =SysTime!AG3 -> 47208 | ... BE3: =SysTime!BE3 -> 55974 | BG3: =SysTime!BG3 -> 45016 | BH3: =SysTime!BH3 -> 46843 | BI3: =SysTime!BI3 -> 48669 | BJ3: =SysTime!BJ3 -> 50495 | BK3: =SysTime!BK3 -> 52321 | BL3: =SysTime!BL3 -> 54148 | BM3: =SysTime!BM3 -> 55974
C4: =IF(ISBLANK(cstProtectiveMarking),"",cstProtectiveMarking) -> Not Protectively Marked | Z4: =SysTime!Z4 -> Timeline | AA4: =SysTime!AA4 -> Annual | AB4: =SysTime!AB4 -> Annual | AC4: =SysTime!AC4 -> Annual | AD4: =SysTime!AD4 -> Annual | AE4: =SysTime!AE4 -> Annual | AF4: =SysTime!AF4 -> Annual | AG4: =SysTime!AG4 -> Annual | ... BE4: =SysTime!BE4 -> Annual | BG4: =SysTime!BG4 -> Annual | BH4: =SysTime!BH4 -> 5 Yearly | BI4: =SysTime!BI4 -> 5 Yearly | BJ4: =SysTime!BJ4 -> 5 Yearly | BK4: =SysTime!BK4 -> 5 Yearly | BL4: =SysTime!BL4 -> 5 Yearly | BM4: =SysTime!BM4 -> 5 Yearly
C5: =HYPERLINK("#'Contents'!A1",sysChkWord) -> All Checks OK | Z5: =SysTime!Z5 -> Period index | AA5: =SysTime!AA5 -> 1 | AB5: =SysTime!AB5 -> 2 | AC5: =SysTime!AC5 -> 3 | AD5: =SysTime!AD5 -> 4 | AE5: =SysTime!AE5 -> 5 | AF5: =SysTime!AF5 -> 6 | AG5: =SysTime!AG5 -> 7 | ... BE5: =SysTime!BE5 -> 31 | BG5: =SysTime!BG5 -> 1 | BH5: =SysTime!BH5 -> 2 | BI5: =SysTime!BI5 -> 3 | BJ5: =SysTime!BJ5 -> 4 | BK5: =SysTime!BK5 -> 5 | BL5: =SysTime!BL5 -> 6 | BM5: =SysTime!BM5 -> 7
C6: =HYPERLINK("#'Contents'!A1","Click for Contents") -> Click for Contents | Z6: =SysTime!Z6 -> Year index | AA6: =SysTime!AA6 -> 1 | AB6: =SysTime!AB6 -> 2 | AC6: =SysTime!AC6 -> 3 | AD6: =SysTime!AD6 -> 4 | AE6: =SysTime!AE6 -> 5 | AF6: =SysTime!AF6 -> 6 | AG6: =SysTime!AG6 -> 7 | ... BE6: =SysTime!BE6 -> 31 | BG6: =SysTime!BG6 -> 0 | BH6: =SysTime!BH6 -> 0 | BI6: =SysTime!BI6 -> 0 | BJ6: =SysTime!BJ6 -> 0 | BK6: =SysTime!BK6 -> 0 | BL6: =SysTime!BL6 -> 0 | BM6: =SysTime!BM6 -> 0
Z7: =SysTime!Z7 -> Relative period | AA7: =SysTime!AA7 -> 1 | AB7: =SysTime!AB7 -> 2 | AC7: =SysTime!AC7 -> 3 | AD7: =SysTime!AD7 -> 4 | AE7: =SysTime!AE7 -> 5 | AF7: =SysTime!AF7 -> 6 | AG7: =SysTime!AG7 -> 7 | ... BE7: =SysTime!BE7 -> 31 | BG7: =SysTime!BG7 -> 1 | BH7: =SysTime!BH7 -> 2 | BI7: =SysTime!BI7 -> 3 | BJ7: =SysTime!BJ7 -> 4 | BK7: =SysTime!BK7 -> 5 | BL7: =SysTime!BL7 -> 6 | BM7: =SysTime!BM7 -> 7
A8: =SUM(A9:A101) -> 0 | B8: =SUM(B9:B101) -> 0 | G8: Units
D10: 1 | E10: Active Scenarios
E12: 1.1 | F12: Scenarios
F14: Planned Maximum Call Volumes Scenario
F16: Cost Scenario
D18: 2 | E18: Date Flags
F20: Operation Flag | G20: Flag | AA20: =SysTime!AA22 -> 0 | AB20: =SysTime!AB22 -> 1 | AC20: =SysTime!AC22 -> 1 | AD20: =SysTime!AD22 -> 1 | AE20: =SysTime!AE22 -> 1 | AF20: =SysTime!AF22 -> 1 | AG20: =SysTime!AG22 -> 1 | AH20: =SysTime!AH22 -> 1 | ... BE20: =SysTime!BE22 -> 1
F22: First Year of Operation | G22: Flag | AA22: =SysTime!AA24 -> 0 | AB22: =SysTime!AB24 -> 1 | AC22: =SysTime!AC24 -> 0 | AD22: =SysTime!AD24 -> 0 | AE22: =SysTime!AE24 -> 0 | AF22: =SysTime!AF24 -> 0 | AG22: =SysTime!AG24 -> 0 | AH22: =SysTime!AH24 -> 0 | ... BE22: =SysTime!BE24 -> 0
F24: First Period of Operation | G24: # | K24: =SysTime!K26 -> 2
F26: Build Year Flag | G26: =cstFlag -> Flag | AA26: =SysTime!AA28 -> 1 | AB26: =SysTime!AB28 -> 0 | AC26: =SysTime!AC28 -> 0 | AD26: =SysTime!AD28 -> 0 | AE26: =SysTime!AE28 -> 0 | AF26: =SysTime!AF28 -> 0 | AG26: =SysTime!AG28 -> 0 | AH26: =SysTime!AH28 -> 0 | ... BE26: =SysTime!BE28 -> 0
D28: 3 | E28: Call Volumes
E30: 3.1 | F30: Annual Call Volumes
F32: Call-Ups
F34: Planned Maximum Annual Call Volume Capacity | G34: =cstHours -> Hrs | K34: {=INDEX(iOptions!$N$16:$N$18,ActiveCallVolumeScenarioIndex)} -> 100000
F35: Annual Call Volume Reduction | G35: =cstPercent -> % | K35: =iControl!$I$16 -> 0.1
F37: Calculations
Z38: Total
A39: =IF(ABS(SUM(AA39:BE39)-SUM(BG39:BM39))<eTol,0,1) -> 0 | F39: Annual Call Volume | G39: =cstHours -> Hrs | K39: =$K34*(1-$K35) -> 90000 | Z39: =SUM(AA39:BE39) -> 2700000 | AA39: =$K$39*AA20 -> 0 | AB39: =$K$39*AB20 -> 90000 | AC39: =$K$39*AC20 -> 90000 | AD39: =$K$39*AD20 -> 90000 | AE39: =$K$39*AE20 -> 90000 | AF39: =$K$39*AF20 -> 90000 | AG39: =$K$39*AG20 -> 90000 | AH39: =$K$39*AH20 -> 90000 | ... BE39: =$K$39*BE20 -> 90000 | BG39: =SUMIFS($AA39:$BE39,$AA$2:$BE$2,">="&BG$2,$AA$3:$BE$3,"<="&BG$3) -> 0 | BH39: =SUMIFS($AA39:$BE39,$AA$2:$BE$2,">="&BH$2,$AA$3:$BE$3,"<="&BH$3) -> 450000 | BI39: =SUMIFS($AA39:$BE39,$AA$2:$BE$2,">="&BI$2,$AA$3:$BE$3,"<="&BI$3) -> 450000 | BJ39: =SUMIFS($AA39:$BE39,$AA$2:$BE$2,">="&BJ$2,$AA$3:$BE$3,"<="&BJ$3) -> 450000 | BK39: =SUMIFS($AA39:$BE39,$AA$2:$BE$2,">="&BK$2,$AA$3:$BE$3,"<="&BK$3) -> 450000 | BL39: =SUMIFS($AA39:$BE39,$AA$2:$BE$2,">="&BL$2,$AA$3:$BE$3,"<="&BL$3) -> 450000 | BM39: =SUMIFS($AA39:$BE39,$AA$2:$BE$2,">="&BM$2,$AA$3:$BE$3,"<="&BM$3) -> 450000
D41: 4 | E41: Staff Volumes
E43: 4.1 | F43: Agents
F45: Call-Ups
F47: Agent Annualised Hours | G47: =cstHours -> Hrs | K47: =iOptions!$N$26 -> 1912
F48: Agent Productivity Rate | G48: =cstPercent -> % | K48: {=INDEX(iOptions!$M$28:$O$28,1,ActiveCostScenarioIndex)} -> 0.8
F50: Calculations
F52: Annual Hours per Agent | G52: =cstNum -> # | AA52: =$K47 -> 1912 | AB52: =$K47 -> 1912 | AC52: =$K47 -> 1912 | AD52: =$K47 -> 1912 | AE52: =$K47 -> 1912 | AF52: =$K47 -> 1912 | AG52: =$K47 -> 1912 | AH52: =$K47 -> 1912 | ... BE52: =$K47 -> 1912
A54: =IF(MIN(AA54:BE54)<0,1,0) -> 0 | F54: Active Number of Agents | G54: =cstNum -> # | AA54: =AA39/AA52 -> 0 | AB54: =AB39/AB52 -> 47.07113 | AC54: =AC39/AC52 -> 47.07113 | AD54: =AD39/AD52 -> 47.07113 | AE54: =AE39/AE52 -> 47.07113 | AF54: =AF39/AF52 -> 47.07113 | AG54: =AG39/AG52 -> 47.07113 | AH54: =AH39/AH52 -> 47.07113 | ... BE54: =BE39/BE52 -> 47.07113
A56: =IF(MIN(AA56:BE56)<0,1,0) -> 0 | F56: Number of Agents | G56: =cstNum -> # | AA56: =AA54/$K48 -> 0 | AB56: =AB54/$K48 -> 58.838912 | AC56: =AC54/$K48 -> 58.838912 | AD56: =AD54/$K48 -> 58.838912 | AE56: =AE54/$K48 -> 58.838912 | AF56: =AF54/$K48 -> 58.838912 | AG56: =AG54/$K48 -> 58.838912 | AH56: =AH54/$K48 -> 58.838912 | ... BE56: =BE54/$K48 -> 58.838912
E58: 4.2 | F58: Supervisors
F60: Call-Ups
F62: Agent to Supervisor Ratio | G62: =cstNum -> # | K62: {=INDEX(iOptions!$M$34:$O$34,1,ActiveCostScenarioIndex)} -> 15
F64: Calculations
A66: =IF(MIN(AA66:BE66)<0,1,0) -> 0 | F66: Active Number of Supervisors | G66: =cstNum -> # | AA66: =AA54/$K62 -> 0 | AB66: =AB54/$K62 -> 3.1380753 | AC66: =AC54/$K62 -> 3.1380753 | AD66: =AD54/$K62 -> 3.1380753 | AE66: =AE54/$K62 -> 3.1380753 | AF66: =AF54/$K62 -> 3.1380753 | AG66: =AG54/$K62 -> 3.1380753 | AH66: =AH54/$K62 -> 3.1380753 | ... BE66: =BE54/$K62 -> 3.1380753
A68: =IF(MIN(AA68:BE68)<0,1,0) -> 0 | F68: Number of Supervisors | G68: =cstNum -> # | AA68: =AA56/$K62 -> 0 | AB68: =AB56/$K62 -> 3.9225941 | AC68: =AC56/$K62 -> 3.9225941 | AD68: =AD56/$K62 -> 3.9225941 | AE68: =AE56/$K62 -> 3.9225941 | AF68: =AF56/$K62 -> 3.9225941 | AG68: =AG56/$K62 -> 3.9225941 | AH68: =AH56/$K62 -> 3.9225941 | ... BE68: =BE56/$K62 -> 3.9225941
E70: 4.3 | F70: Agent & Support Staff
F72: Call-Ups
F74: Reception & Admin Support | G74: =cstNum -> # | K74: =iOptions!$N40 -> 3
F75: IT Support | G75: =cstNum -> # | K75: =iOptions!$N41 -> 2
F76: Office Manager | G76: =cstNum -> # | K76: =iOptions!$N42 -> 1
F77: Office Deputy | G77: =cstNum -> # | K77: =iOptions!$N43 -> 1
F79: Calculations
A81: =IF(MIN(AA81:BE81)<0,1,0) -> 0 | F81: Number of Admin & Support Staff | G81: =cstNum -> # | AA81: =SUM($K$74:$K$77)*AA20 -> 0 | AB81: =SUM($K$74:$K$77)*AB20 -> 7 | AC81: =SUM($K$74:$K$77)*AC20 -> 7 | AD81: =SUM($K$74:$K$77)*AD20 -> 7 | AE81: =SUM($K$74:$K$77)*AE20 -> 7 | AF81: =SUM($K$74:$K$77)*AF20 -> 7 | AG81: =SUM($K$74:$K$77)*AG20 -> 7 | AH81: =SUM($K$74:$K$77)*AH20 -> 7 | ... BE81: =SUM($K$74:$K$77)*BE20 -> 7
E83: 4.4 | F83: Office Capacity
F85: Calculations
K86: Max
A87: =IF(MIN(AA87:BE87)<0,1,0) -> 0 | F87: Office Capacity | G87: =cstNum -> # | K87: =MAX(AA87:BE87) -> 57.209205 | AA87: =SUM(AA54,AA66,AA81) -> 0 | AB87: =SUM(AB54,AB66,AB81) -> 57.209205 | AC87: =SUM(AC54,AC66,AC81) -> 57.209205 | AD87: =SUM(AD54,AD66,AD81) -> 57.209205 | AE87: =SUM(AE54,AE66,AE81) -> 57.209205 | AF87: =SUM(AF54,AF66,AF81) -> 57.209205 | AG87: =SUM(AG54,AG66,AG81) -> 57.209205 | AH87: =SUM(AH54,AH66,AH81) -> 57.209205 | ... BE87: =SUM(BE54,BE66,BE81) -> 57.209205
D89: 5 | E89: Building Size
E91: 5.1 | F91: Building Size
F93: Call-Ups
F95: Staff Space Standard | G95: {=cstArea&"/"&cstFTE} -> m2/FTE | K95: {=INDEX(iOptions!$M$131:$O$131,1,ActiveCostScenarioIndex)} -> 15
F97: Calculations
K98: Max
A99: =IF(MIN(AA99:BE99)<0,1,0) -> 0 | F99: Floor Area | G99: =cstArea -> m2 | K99: =$K95*K87 -> 858.13808 | AA99: =$K$99 -> 858.13808 | AB99: =$K$99 -> 858.13808 | AC99: =$K$99 -> 858.13808 | AD99: =$K$99 -> 858.13808 | AE99: =$K$99 -> 858.13808 | AF99: =$K$99 -> 858.13808 | AG99: =$K$99 -> 858.13808 | AH99: =$K$99 -> 858.13808 | ... BE99: =$K$99 -> 858.13808
D101: END OF WORKSHEET - INSERT ROWS ABOVE

Sheet cCosts
C1: THIS CASE STUDY MODEL IS FOR ILLUSTRATIVE PURPOSES
C2: =cstProjectName -> Should Cost Modelling Case Study - Illustrative SCM | Z2: =SysTime!Z2 -> Period Start | AA2: =SysTime!AA2 -> 44652 | AB2: =SysTime!AB2 -> 45017 | AC2: =SysTime!AC2 -> 45383 | AD2: =SysTime!AD2 -> 45748 | AE2: =SysTime!AE2 -> 46113 | AF2: =SysTime!AF2 -> 46478 | AG2: =SysTime!AG2 -> 46844 | ... BE2: =SysTime!BE2 -> 55610 | BG2: =SysTime!BG2 -> 44652 | BH2: =SysTime!BH2 -> 45017 | BI2: =SysTime!BI2 -> 46844 | BJ2: =SysTime!BJ2 -> 48670 | BK2: =SysTime!BK2 -> 50496 | BL2: =SysTime!BL2 -> 52322 | BM2: =SysTime!BM2 -> 54149
C3: =MID(CELL("filename",A1),FIND("]",CELL("filename",A1))+1,256)&" Sheet" -> cCosts Sheet | Z3: =SysTime!Z3 -> Period End | AA3: =SysTime!AA3 -> 45016 | AB3: =SysTime!AB3 -> 45382 | AC3: =SysTime!AC3 -> 45747 | AD3: =SysTime!AD3 -> 46112 | AE3: =SysTime!AE3 -> 46477 | AF3: =SysTime!AF3 -> 46843 | AG3: =SysTime!AG3 -> 47208 | ... BE3: =SysTime!BE3 -> 55974 | BG3: =SysTime!BG3 -> 45016 | BH3: =SysTime!BH3 -> 46843 | BI3: =SysTime!BI3 -> 48669 | BJ3: =SysTime!BJ3 -> 50495 | BK3: =SysTime!BK3 -> 52321 | BL3: =SysTime!BL3 -> 54148 | BM3: =SysTime!BM3 -> 55974
C4: =IF(ISBLANK(cstProtectiveMarking),"",cstProtectiveMarking) -> Not Protectively Marked | Z4: =SysTime!Z4 -> Timeline | AA4: =SysTime!AA4 -> Annual | AB4: =SysTime!AB4 -> Annual | AC4: =SysTime!AC4 -> Annual | AD4: =SysTime!AD4 -> Annual | AE4: =SysTime!AE4 -> Annual | AF4: =SysTime!AF4 -> Annual | AG4: =SysTime!AG4 -> Annual | ... BE4: =SysTime!BE4 -> Annual | BG4: =SysTime!BG4 -> Annual | BH4: =SysTime!BH4 -> 5 Yearly | BI4: =SysTime!BI4 -> 5 Yearly | BJ4: =SysTime!BJ4 -> 5 Yearly | BK4: =SysTime!BK4 -> 5 Yearly | BL4: =SysTime!BL4 -> 5 Yearly | BM4: =SysTime!BM4 -> 5 Yearly
C5: =HYPERLINK("#'Contents'!A1",sysChkWord) -> All Checks OK | Z5: =SysTime!Z5 -> Period index | AA5: =SysTime!AA5 -> 1 | AB5: =SysTime!AB5 -> 2 | AC5: =SysTime!AC5 -> 3 | AD5: =SysTime!AD5 -> 4 | AE5: =SysTime!AE5 -> 5 | AF5: =SysTime!AF5 -> 6 | AG5: =SysTime!AG5 -> 7 | ... BE5: =SysTime!BE5 -> 31 | BG5: =SysTime!BG5 -> 1 | BH5: =SysTime!BH5 -> 2 | BI5: =SysTime!BI5 -> 3 | BJ5: =SysTime!BJ5 -> 4 | BK5: =SysTime!BK5 -> 5 | BL5: =SysTime!BL5 -> 6 | BM5: =SysTime!BM5 -> 7
C6: =HYPERLINK("#'Contents'!A1","Click for Contents") -> Click for Contents | Z6: =SysTime!Z6 -> Year index | AA6: =SysTime!AA6 -> 1 | AB6: =SysTime!AB6 -> 2 | AC6: =SysTime!AC6 -> 3 | AD6: =SysTime!AD6 -> 4 | AE6: =SysTime!AE6 -> 5 | AF6: =SysTime!AF6 -> 6 | AG6: =SysTime!AG6 -> 7 | ... BE6: =SysTime!BE6 -> 31 | BG6: =SysTime!BG6 -> 0 | BH6: =SysTime!BH6 -> 0 | BI6: =SysTime!BI6 -> 0 | BJ6: =SysTime!BJ6 -> 0 | BK6: =SysTime!BK6 -> 0 | BL6: =SysTime!BL6 -> 0 | BM6: =SysTime!BM6 -> 0
Z7: =SysTime!Z7 -> Relative period | AA7: =SysTime!AA7 -> 1 | AB7: =SysTime!AB7 -> 2 | AC7: =SysTime!AC7 -> 3 | AD7: =SysTime!AD7 -> 4 | AE7: =SysTime!AE7 -> 5 | AF7: =SysTime!AF7 -> 6 | AG7: =SysTime!AG7 -> 7 | ... BE7: =SysTime!BE7 -> 31 | BG7: =SysTime!BG7 -> 1 | BH7: =SysTime!BH7 -> 2 | BI7: =SysTime!BI7 -> 3 | BJ7: =SysTime!BJ7 -> 4 | BK7: =SysTime!BK7 -> 5 | BL7: =SysTime!BL7 -> 6 | BM7: =SysTime!BM7 -> 7
A8: =SUM(A9:A484) -> 0 | B8: =SUM(B9:B484) -> 0 | G8: Units
D10: 1 | E10: Active Scenarios
E12: 1.1 | F12: Scenarios
F14: Planned Maximum Call Volumes Scenario
F16: Cost Scenario
D18: 2 | E18: Date Flags
F20: Operation Flag | G20: Flag | AA20: =SysTime!AA22 -> 0 | AB20: =SysTime!AB22 -> 1 | AC20: =SysTime!AC22 -> 1 | AD20: =SysTime!AD22 -> 1 | AE20: =SysTime!AE22 -> 1 | AF20: =SysTime!AF22 -> 1 | AG20: =SysTime!AG22 -> 1 | AH20: =SysTime!AH22 -> 1 | ... BE20: =SysTime!BE22 -> 1
F22: First Year of Operation | G22: Flag | AA22: =SysTime!AA24 -> 0 | AB22: =SysTime!AB24 -> 1 | AC22: =SysTime!AC24 -> 0 | AD22: =SysTime!AD24 -> 0 | AE22: =SysTime!AE24 -> 0 | AF22: =SysTime!AF24 -> 0 | AG22: =SysTime!AG24 -> 0 | AH22: =SysTime!AH24 -> 0 | ... BE22: =SysTime!BE24 -> 0
F24: First Period of Operation | G24: # | K24: =SysTime!K26 -> 2
F26: Build Year Flag | G26: =cstFlag -> Flag | AA26: =SysTime!AA28 -> 1 | AB26: =SysTime!AB28 -> 0 | AC26: =SysTime!AC28 -> 0 | AD26: =SysTime!AD28 -> 0 | AE26: =SysTime!AE28 -> 0 | AF26: =SysTime!AF28 -> 0 | AG26: =SysTime!AG28 -> 0 | AH26: =SysTime!AH28 -> 0 | ... BE26: =SysTime!BE28 -> 0
D28: 3 | E28: Inflation Call-Ups
E30: 3.1 | F30: Inflation Index
F32: Annual Inflation Index
F34: =iIndices!F16 -> Wage Inflation | G34: % | AA34: =cFactors!AA35 -> 1 | AB34: =cFactors!AB35 -> 1.025 | AC34: =cFactors!AC35 -> 1.050625 | AD34: =cFactors!AD35 -> 1.0768906 | AE34: =cFactors!AE35 -> 1.1038129 | AF34: =cFactors!AF35 -> 1.1314082 | AG34: =cFactors!AG35 -> 1.1596934 | AH34: =cFactors!AH35 -> 1.1886858 | ... BE34: =cFactors!BE35 -> 2.0975676
F35: =iIndices!F17 -> Other Inflation | G35: % | AA35: =cFactors!AA36 -> 1 | AB35: =cFactors!AB36 -> 1.03 | AC35: =cFactors!AC36 -> 1.0609 | AD35: =cFactors!AD36 -> 1.092727 | AE35: =cFactors!AE36 -> 1.1255088 | AF35: =cFactors!AF36 -> 1.1592741 | AG35: =cFactors!AG36 -> 1.1940523 | AH35: =cFactors!AH36 -> 1.2298739 | ... BE35: =cFactors!BE36 -> 2.4272625
F36: =iIndices!F18 -> Inflation Type C | G36: % | AA36: =cFactors!AA37 -> 1 | AB36: =cFactors!AB37 -> 1.02 | AC36: =cFactors!AC37 -> 1.0404 | AD36: =cFactors!AD37 -> 1.061208 | AE36: =cFactors!AE37 -> 1.0824322 | AF36: =cFactors!AF37 -> 1.1040808 | AG36: =cFactors!AG37 -> 1.1261624 | AH36: =cFactors!AH37 -> 1.1486857 | ... BE36: =cFactors!BE37 -> 1.8113616
F37: =iIndices!F19 -> Inflation Type D | G37: % | AA37: =cFactors!AA38 -> 1 | AB37: =cFactors!AB38 -> 1.02 | AC37: =cFactors!AC38 -> 1.0404 | AD37: =cFactors!AD38 -> 1.061208 | AE37: =cFactors!AE38 -> 1.0824322 | AF37: =cFactors!AF38 -> 1.1040808 | AG37: =cFactors!AG38 -> 1.1261624 | AH37: =cFactors!AH38 -> 1.1486857 | ... BE37: =cFactors!BE38 -> 1.8113616
F38: =iIndices!F20 -> Inflation Type E | G38: % | AA38: =cFactors!AA39 -> 1 | AB38: =cFactors!AB39 -> 1.02 | AC38: =cFactors!AC39 -> 1.0404 | AD38: =cFactors!AD39 -> 1.061208 | AE38: =cFactors!AE39 -> 1.0824322 | AF38: =cFactors!AF39 -> 1.1040808 | AG38: =cFactors!AG39 -> 1.1261624 | AH38: =cFactors!AH39 -> 1.1486857 | ... BE38: =cFactors!BE39 -> 1.8113616
D40: 4 | E40: Operating Costs
E42: 4.1 | F42: Operating Costs
F44: Call-Ups
F46: Cost Per Call Hour | G46: =cstConstantUnit -> £ 2022/23 | K46: {=INDEX(iOptions!$M$115:$O$115,1,ActiveCostScenarioIndex)} -> 30
F47: Annual Call Volume | G47: =cstHours -> Hrs | AA47: =cVolumetrics!AA39 -> 0 | AB47: =cVolumetrics!AB39 -> 90000 | AC47: =cVolumetrics!AC39 -> 90000 | AD47: =cVolumetrics!AD39 -> 90000 | AE47: =cVolumetrics!AE39 -> 90000 | AF47: =cVolumetrics!AF39 -> 90000 | AG47: =cVolumetrics!AG39 -> 90000 | AH47: =cVolumetrics!AH39 -> 90000 | ... BE47: =cVolumetrics!BE39 -> 90000
F49: Calculations (Pre-Inflation)
F51: Annual Call Cost | G51: =cstConstantUnit -> £ 2022/23 | AA51: =AA47*$K46*AA20 -> 0 | AB51: =AB47*$K46*AB20 -> 2700000 | AC51: =AC47*$K46*AC20 -> 2700000 | AD51: =AD47*$K46*AD20 -> 2700000 | AE51: =AE47*$K46*AE20 -> 2700000 | AF51: =AF47*$K46*AF20 -> 2700000 | AG51: =AG47*$K46*AG20 -> 2700000 | AH51: =AH47*$K46*AH20 -> 2700000 | ... BE51: =BE47*$K46*BE20 -> 2700000 | BG51: =SUMIFS($AA51:$BE51,$AA$2:$BE$2,">="&BG$2,$AA$3:$BE$3,"<="&BG$3) -> 0 | BH51: =SUMIFS($AA51:$BE51,$AA$2:$BE$2,">="&BH$2,$AA$3:$BE$3,"<="&BH$3) -> 13500000 | BI51: =SUMIFS($AA51:$BE51,$AA$2:$BE$2,">="&BI$2,$AA$3:$BE$3,"<="&BI$3) -> 13500000 | BJ51: =SUMIFS($AA51:$BE51,$AA$2:$BE$2,">="&BJ$2,$AA$3:$BE$3,"<="&BJ$3) -> 13500000 | BK51: =SUMIFS($AA51:$BE51,$AA$2:$BE$2,">="&BK$2,$AA$3:$BE$3,"<="&BK$3) -> 13500000 | BL51: =SUMIFS($AA51:$BE51,$AA$2:$BE$2,">="&BL$2,$AA$3:$BE$3,"<="&BL$3) -> 13500000 | BM51: =SUMIFS($AA51:$BE51,$AA$2:$BE$2,">="&BM$2,$AA$3:$BE$3,"<="&BM$3) -> 13500000
F53: Calculations (Nominal)
F55: Annual Call Cost | G55: =cstNominalUnit -> £ Nominal | I55: =iOptions!Q115 -> Other Inflation | AA55: =AA51*_xlfn.IFNA(INDEX(AA$34:AA$38,MATCH($I55,$F$34:$F$38,0)),0) -> 0 | AB55: =AB51*_xlfn.IFNA(INDEX(AB$34:AB$38,MATCH($I55,$F$34:$F$38,0)),0) -> 2781000 | AC55: =AC51*_xlfn.IFNA(INDEX(AC$34:AC$38,MATCH($I55,$F$34:$F$38,0)),0) -> 2864430 | AD55: =AD51*_xlfn.IFNA(INDEX(AD$34:AD$38,MATCH($I55,$F$34:$F$38,0)),0) -> 2950362.9 | AE55: =AE51*_xlfn.IFNA(INDEX(AE$34:AE$38,MATCH($I55,$F$34:$F$38,0)),0) -> 3038873.8 | AF55: =AF51*_xlfn.IFNA(INDEX(AF$34:AF$38,MATCH($I55,$F$34:$F$38,0)),0) -> 3130040 | AG55: =AG51*_xlfn.IFNA(INDEX(AG$34:AG$38,MATCH($I55,$F$34:$F$38,0)),0) -> 3223941.2 | AH55: =AH51*_xlfn.IFNA(INDEX(AH$34:AH$38,MATCH($I55,$F$34:$F$38,0)),0) -> 3320659.4 | ... BE55: =BE51*_xlfn.IFNA(INDEX(BE$34:BE$38,MATCH($I55,$F$34:$F$38,0)),0) -> 6553608.7 | BG55: =SUMIFS($AA55:$BE55,$AA$2:$BE$2,">="&BG$2,$AA$3:$BE$3,"<="&BG$3) -> 0 | BH55: =SUMIFS($AA55:$BE55,$AA$2:$BE$2,">="&BH$2,$AA$3:$BE$3,"<="&BH$3) -> 14764707 | BI55: =SUMIFS($AA55:$BE55,$AA$2:$BE$2,">="&BI$2,$AA$3:$BE$3,"<="&BI$3) -> 17116342 | BJ55: =SUMIFS($AA55:$BE55,$AA$2:$BE$2,">="&BJ$2,$AA$3:$BE$3,"<="&BJ$3) -> 19842531 | BK55: =SUMIFS($AA55:$BE55,$AA$2:$BE$2,">="&BK$2,$AA$3:$BE$3,"<="&BK$3) -> 23002932 | BL55: =SUMIFS($AA55:$BE55,$AA$2:$BE$2,">="&BL$2,$AA$3:$BE$3,"<="&BL$3) -> 26666703 | BM55: =SUMIFS($AA55:$BE55,$AA$2:$BE$2,">="&BM$2,$AA$3:$BE$3,"<="&BM$3) -> 30914017
D57: 5 | E57: Staff Costs
E59: 5.1 | F59: Agents
F61: Call-Ups
F63: Agents | G63: =cstNum -> # | AA63: =cVolumetrics!AA56 -> 0 | AB63: =cVolumetrics!AB56 -> 58.838912 | AC63: =cVolumetrics!AC56 -> 58.838912 | AD63: =cVolumetrics!AD56 -> 58.838912 | AE63: =cVolumetrics!AE56 -> 58.838912 | AF63: =cVolumetrics!AF56 -> 58.838912 | AG63: =cVolumetrics!AG56 -> 58.838912 | AH63: =cVolumetrics!AH56 -> 58.838912 | ... BE63: =cVolumetrics!BE56 -> 58.838912
F65: Agents Salary Cost | G65: =cstConstantUnit -> £ 2022/23 | K65: {=INDEX(iOptions!$M$49:$O$49,1,ActiveCostScenarioIndex)} -> 29000
F67: Calculations (Pre-Inflation)
F69: Agent Staff Costs | G69: =cstConstantUnit -> £ 2022/23 | AA69: =AA63*$K65*AA20 -> 0 | AB69: =AB63*$K65*AB20 -> 1706328.5 | AC69: =AC63*$K65*AC20 -> 1706328.5 | AD69: =AD63*$K65*AD20 -> 1706328.5 | AE69: =AE63*$K65*AE20 -> 1706328.5 | AF69: =AF63*$K65*AF20 -> 1706328.5 | AG69: =AG63*$K65*AG20 -> 1706328.5 | AH69: =AH63*$K65*AH20 -> 1706328.5 | ... BE69: =BE63*$K65*BE20 -> 1706328.5 | BG69: =SUMIFS($AA69:$BE69,$AA$2:$BE$2,">="&BG$2,$AA$3:$BE$3,"<="&BG$3) -> 0 | BH69: =SUMIFS($AA69:$BE69,$AA$2:$BE$2,">="&BH$2,$AA$3:$BE$3,"<="&BH$3) -> 8531642.3 | BI69: =SUMIFS($AA69:$BE69,$AA$2:$BE$2,">="&BI$2,$AA$3:$BE$3,"<="&BI$3) -> 8531642.3 | BJ69: =SUMIFS($AA69:$BE69,$AA$2:$BE$2,">="&BJ$2,$AA$3:$BE$3,"<="&BJ$3) -> 8531642.3 | BK69: =SUMIFS($AA69:$BE69,$AA$2:$BE$2,">="&BK$2,$AA$3:$BE$3,"<="&BK$3) -> 8531642.3 | BL69: =SUMIFS($AA69:$BE69,$AA$2:$BE$2,">="&BL$2,$AA$3:$BE$3,"<="&BL$3) -> 8531642.3 | BM69: =SUMIFS($AA69:$BE69,$AA$2:$BE$2,">="&BM$2,$AA$3:$BE$3,"<="&BM$3) -> 8531642.3
F71: Calculations (Nominal)
F73: Agent Staff Costs | G73: =cstNominalUnit -> £ Nominal | I73: =iOptions!Q49 -> Wage Inflation | AA73: =AA69*_xlfn.IFNA(INDEX(AA$34:AA$38,MATCH($I73,$F$34:$F$38,0)),0) -> 0 | AB73: =AB69*_xlfn.IFNA(INDEX(AB$34:AB$38,MATCH($I73,$F$34:$F$38,0)),0) -> 1748986.7 | AC73: =AC69*_xlfn.IFNA(INDEX(AC$34:AC$38,MATCH($I73,$F$34:$F$38,0)),0) -> 1792711.3 | AD73: =AD69*_xlfn.IFNA(INDEX(AD$34:AD$38,MATCH($I73,$F$34:$F$38,0)),0) -> 1837529.1 | AE73: =AE69*_xlfn.IFNA(INDEX(AE$34:AE$38,MATCH($I73,$F$34:$F$38,0)),0) -> 1883467.3 | AF73: =AF69*_xlfn.IFNA(INDEX(AF$34:AF$38,MATCH($I73,$F$34:$F$38,0)),0) -> 1930554 | AG73: =AG69*_xlfn.IFNA(INDEX(AG$34:AG$38,MATCH($I73,$F$34:$F$38,0)),0) -> 1978817.9 | AH73: =AH69*_xlfn.IFNA(INDEX(AH$34:AH$38,MATCH($I73,$F$34:$F$38,0)),0) -> 2028288.3 | ... BE73: =BE69*_xlfn.IFNA(INDEX(BE$34:BE$38,MATCH($I73,$F$34:$F$38,0)),0) -> 3579139.2 | BG73: =SUMIFS($AA73:$BE73,$AA$2:$BE$2,">="&BG$2,$AA$3:$BE$3,"<="&BG$3) -> 0 | BH73: =SUMIFS($AA73:$BE73,$AA$2:$BE$2,">="&BH$2,$AA$3:$BE$3,"<="&BH$3) -> 9193248.5 | BI73: =SUMIFS($AA73:$BE73,$AA$2:$BE$2,">="&BI$2,$AA$3:$BE$3,"<="&BI$3) -> 10401317 | BJ73: =SUMIFS($AA73:$BE73,$AA$2:$BE$2,">="&BJ$2,$AA$3:$BE$3,"<="&BJ$3) -> 11768135 | BK73: =SUMIFS($AA73:$BE73,$AA$2:$BE$2,">="&BK$2,$AA$3:$BE$3,"<="&BK$3) -> 13314565 | BL73: =SUMIFS($AA73:$BE73,$AA$2:$BE$2,">="&BL$2,$AA$3:$BE$3,"<="&BL$3) -> 15064208 | BM73: =SUMIFS($AA73:$BE73,$AA$2:$BE$2,">="&BM$2,$AA$3:$BE$3,"<="&BM$3) -> 17043769
E75: 5.2 | F75: Supervisors
F77: Call-Ups
F79: Supervisors | G79: =cstNum -> # | AA79: =cVolumetrics!AA68 -> 0 | AB79: =cVolumetrics!AB68 -> 3.9225941 | AC79: =cVolumetrics!AC68 -> 3.9225941 | AD79: =cVolumetrics!AD68 -> 3.9225941 | AE79: =cVolumetrics!AE68 -> 3.9225941 | AF79: =cVolumetrics!AF68 -> 3.9225941 | AG79: =cVolumetrics!AG68 -> 3.9225941 | AH79: =cVolumetrics!AH68 -> 3.9225941 | ... BE79: =cVolumetrics!BE68 -> 3.9225941
F81: Supervisors Salary Cost | G81: =cstConstantUnit -> £ 2022/23 | K81: {=INDEX(iOptions!$M$50:$O$50,1,ActiveCostScenarioIndex)} -> 38000
F83: Calculations (Pre-Inflation)
F85: Supervisor Staff Costs | G85: =cstConstantUnit -> £ 2022/23 | AA85: =AA79*$K81*AA20 -> 0 | AB85: =AB79*$K81*AB20 -> 149058.58 | AC85: =AC79*$K81*AC20 -> 149058.58 | AD85: =AD79*$K81*AD20 -> 149058.58 | AE85: =AE79*$K81*AE20 -> 149058.58 | AF85: =AF79*$K81*AF20 -> 149058.58 | AG85: =AG79*$K81*AG20 -> 149058.58 | AH85: =AH79*$K81*AH20 -> 149058.58 | ... BE85: =BE79*$K81*BE20 -> 149058.58 | BG85: =SUMIFS($AA85:$BE85,$AA$2:$BE$2,">="&BG$2,$AA$3:$BE$3,"<="&BG$3) -> 0 | BH85: =SUMIFS($AA85:$BE85,$AA$2:$BE$2,">="&BH$2,$AA$3:$BE$3,"<="&BH$3) -> 745292.89 | BI85: =SUMIFS($AA85:$BE85,$AA$2:$BE$2,">="&BI$2,$AA$3:$BE$3,"<="&BI$3) -> 745292.89 | BJ85: =SUMIFS($AA85:$BE85,$AA$2:$BE$2,">="&BJ$2,$AA$3:$BE$3,"<="&BJ$3) -> 745292.89 | BK85: =SUMIFS($AA85:$BE85,$AA$2:$BE$2,">="&BK$2,$AA$3:$BE$3,"<="&BK$3) -> 745292.89 | BL85: =SUMIFS($AA85:$BE85,$AA$2:$BE$2,">="&BL$2,$AA$3:$BE$3,"<="&BL$3) -> 745292.89 | BM85: =SUMIFS($AA85:$BE85,$AA$2:$BE$2,">="&BM$2,$AA$3:$BE$3,"<="&BM$3) -> 745292.89
F87: Calculations (Nominal)
F89: Supervisor Staff Costs | G89: =cstNominalUnit -> £ Nominal | I89: =iOptions!Q50 -> Wage Inflation | AA89: =AA85*_xlfn.IFNA(INDEX(AA$34:AA$38,MATCH($I89,$F$34:$F$38,0)),0) -> 0 | AB89: =AB85*_xlfn.IFNA(INDEX(AB$34:AB$38,MATCH($I89,$F$34:$F$38,0)),0) -> 152785.04 | AC89: =AC85*_xlfn.IFNA(INDEX(AC$34:AC$38,MATCH($I89,$F$34:$F$38,0)),0) -> 156604.67 | AD89: =AD85*_xlfn.IFNA(INDEX(AD$34:AD$38,MATCH($I89,$F$34:$F$38,0)),0) -> 160519.78 | AE89: =AE85*_xlfn.IFNA(INDEX(AE$34:AE$38,MATCH($I89,$F$34:$F$38,0)),0) -> 164532.78 | AF89: =AF85*_xlfn.IFNA(INDEX(AF$34:AF$38,MATCH($I89,$F$34:$F$38,0)),0) -> 168646.1 | AG89: =AG85*_xlfn.IFNA(INDEX(AG$34:AG$38,MATCH($I89,$F$34:$F$38,0)),0) -> 172862.25 | AH89: =AH85*_xlfn.IFNA(INDEX(AH$34:AH$38,MATCH($I89,$F$34:$F$38,0)),0) -> 177183.81 | ... BE89: =BE85*_xlfn.IFNA(INDEX(BE$34:BE$38,MATCH($I89,$F$34:$F$38,0)),0) -> 312660.44 | BG89: =SUMIFS($AA89:$BE89,$AA$2:$BE$2,">="&BG$2,$AA$3:$BE$3,"<="&BG$3) -> 0 | BH89: =SUMIFS($AA89:$BE89,$AA$2:$BE$2,">="&BH$2,$AA$3:$BE$3,"<="&BH$3) -> 803088.37 | BI89: =SUMIFS($AA89:$BE89,$AA$2:$BE$2,">="&BI$2,$AA$3:$BE$3,"<="&BI$3) -> 908620.78 | BJ89: =SUMIFS($AA89:$BE89,$AA$2:$BE$2,">="&BJ$2,$AA$3:$BE$3,"<="&BJ$3) -> 1028021 | BK89: =SUMIFS($AA89:$BE89,$AA$2:$BE$2,">="&BK$2,$AA$3:$BE$3,"<="&BK$3) -> 1163111.4 | BL89: =SUMIFS($AA89:$BE89,$AA$2:$BE$2,">="&BL$2,$AA$3:$BE$3,"<="&BL$3) -> 1315953.8 | BM89: =SUMIFS($AA89:$BE89,$AA$2:$BE$2,">="&BM$2,$AA$3:$BE$3,"<="&BM$3) -> 1488880.9
E91: 5.3 | F91: Admin & Support Staff Costs
F93: Call-Ups
F95: Reception & Admin Support | G95: =cstNum -> # | K95: =cVolumetrics!K74 -> 3
F96: IT Support | G96: =cstNum -> # | K96: =cVolumetrics!K75 -> 2
F97: Office Manager | G97: =cstNum -> # | K97: =cVolumetrics!K76 -> 1
F98: Office Deputy | G98: =cstNum -> # | K98: =cVolumetrics!K77 -> 1
F100: Reception & Admin Support Salary Cost | G100: =cstConstantUnit -> £ 2022/23 | K100: {=INDEX(iOptions!$M51:$O51,1,ActiveCostScenarioIndex)} -> 27000
F101: IT Support Salary Cost | G101: =cstConstantUnit -> £ 2022/23 | K101: {=INDEX(iOptions!$M52:$O52,1,ActiveCostScenarioIndex)} -> 36000
F102: Office Manager Salary Cost | G102: =cstConstantUnit -> £ 2022/23 | K102: {=INDEX(iOptions!$M53:$O53,1,ActiveCostScenarioIndex)} -> 51000
F103: Office Deputy Salary Cost | G103: =cstConstantUnit -> £ 2022/23 | K103: {=INDEX(iOptions!$M54:$O54,1,ActiveCostScenarioIndex)} -> 40000
F105: Calculations (Pre-Inflation)
F107: Reception & Admin Support Cost | G107: =cstConstantUnit -> £ 2022/23 | K107: =K95*K100 -> 81000 | AA107: =$K107*AA$20 -> 0 | AB107: =$K107*AB$20 -> 81000 | AC107: =$K107*AC$20 -> 81000 | AD107: =$K107*AD$20 -> 81000 | AE107: =$K107*AE$20 -> 81000 | AF107: =$K107*AF$20 -> 81000 | AG107: =$K107*AG$20 -> 81000 | AH107: =$K107*AH$20 -> 81000 | ... BE107: =$K107*BE$20 -> 81000 | BG107: =SUMIFS($AA107:$BE107,$AA$2:$BE$2,">="&BG$2,$AA$3:$BE$3,"<="&BG$3) -> 0 | BH107: =SUMIFS($AA107:$BE107,$AA$2:$BE$2,">="&BH$2,$AA$3:$BE$3,"<="&BH$3) -> 405000 | BI107: =SUMIFS($AA107:$BE107,$AA$2:$BE$2,">="&BI$2,$AA$3:$BE$3,"<="&BI$3) -> 405000 | BJ107: =SUMIFS($AA107:$BE107,$AA$2:$BE$2,">="&BJ$2,$AA$3:$BE$3,"<="&BJ$3) -> 405000 | BK107: =SUMIFS($AA107:$BE107,$AA$2:$BE$2,">="&BK$2,$AA$3:$BE$3,"<="&BK$3) -> 405000 | BL107: =SUMIFS($AA107:$BE107,$AA$2:$BE$2,">="&BL$2,$AA$3:$BE$3,"<="&BL$3) -> 405000 | BM107: =SUMIFS($AA107:$BE107,$AA$2:$BE$2,">="&BM$2,$AA$3:$BE$3,"<="&BM$3) -> 405000
F108: IT Support Cost | G108: =cstConstantUnit -> £ 2022/23 | K108: =K96*K101 -> 72000 | AA108: =$K108*AA$20 -> 0 | AB108: =$K108*AB$20 -> 72000 | AC108: =$K108*AC$20 -> 72000 | AD108: =$K108*AD$20 -> 72000 | AE108: =$K108*AE$20 -> 72000 | AF108: =$K108*AF$20 -> 72000 | AG108: =$K108*AG$20 -> 72000 | AH108: =$K108*AH$20 -> 72000 | ... BE108: =$K108*BE$20 -> 72000 | BG108: =SUMIFS($AA108:$BE108,$AA$2:$BE$2,">="&BG$2,$AA$3:$BE$3,"<="&BG$3) -> 0 | BH108: =SUMIFS($AA108:$BE108,$AA$2:$BE$2,">="&BH$2,$AA$3:$BE$3,"<="&BH$3) -> 360000 | BI108: =SUMIFS($AA108:$BE108,$AA$2:$BE$2,">="&BI$2,$AA$3:$BE$3,"<="&BI$3) -> 360000 | BJ108: =SUMIFS($AA108:$BE108,$AA$2:$BE$2,">="&BJ$2,$AA$3:$BE$3,"<="&BJ$3) -> 360000 | BK108: =SUMIFS($AA108:$BE108,$AA$2:$BE$2,">="&BK$2,$AA$3:$BE$3,"<="&BK$3) -> 360000 | BL108: =SUMIFS($AA108:$BE108,$AA$2:$BE$2,">="&BL$2,$AA$3:$BE$3,"<="&BL$3) -> 360000 | BM108: =SUMIFS($AA108:$BE108,$AA$2:$BE$2,">="&BM$2,$AA$3:$BE$3,"<="&BM$3) -> 360000
F109: Office Manager Cost | G109: =cstConstantUnit -> £ 2022/23 | K109: =K97*K102 -> 51000 | AA109: =$K109*AA$20 -> 0 | AB109: =$K109*AB$20 -> 51000 | AC109: =$K109*AC$20 -> 51000 | AD109: =$K109*AD$20 -> 51000 | AE109: =$K109*AE$20 -> 51000 | AF109: =$K109*AF$20 -> 51000 | AG109: =$K109*AG$20 -> 51000 | AH109: =$K109*AH$20 -> 51000 | ... BE109: =$K109*BE$20 -> 51000 | BG109: =SUMIFS($AA109:$BE109,$AA$2:$BE$2,">="&BG$2,$AA$3:$BE$3,"<="&BG$3) -> 0 | BH109: =SUMIFS($AA109:$BE109,$AA$2:$BE$2,">="&BH$2,$AA$3:$BE$3,"<="&BH$3) -> 255000 | BI109: =SUMIFS($AA109:$BE109,$AA$2:$BE$2,">="&BI$2,$AA$3:$BE$3,"<="&BI$3) -> 255000 | BJ109: =SUMIFS($AA109:$BE109,$AA$2:$BE$2,">="&BJ$2,$AA$3:$BE$3,"<="&BJ$3) -> 255000 | BK109: =SUMIFS($AA109:$BE109,$AA$2:$BE$2,">="&BK$2,$AA$3:$BE$3,"<="&BK$3) -> 255000 | BL109: =SUMIFS($AA109:$BE109,$AA$2:$BE$2,">="&BL$2,$AA$3:$BE$3,"<="&BL$3) -> 255000 | BM109: =SUMIFS($AA109:$BE109,$AA$2:$BE$2,">="&BM$2,$AA$3:$BE$3,"<="&BM$3) -> 255000
F110: Office Deputy Cost | G110: =cstConstantUnit -> £ 2022/23 | K110: =K98*K103 -> 40000 | AA110: =$K110*AA$20 -> 0 | AB110: =$K110*AB$20 -> 40000 | AC110: =$K110*AC$20 -> 40000 | AD110: =$K110*AD$20 -> 40000 | AE110: =$K110*AE$20 -> 40000 | AF110: =$K110*AF$20 -> 40000 | AG110: =$K110*AG$20 -> 40000 | AH110: =$K110*AH$20 -> 40000 | ... BE110: =$K110*BE$20 -> 40000 | BG110: =SUMIFS($AA110:$BE110,$AA$2:$BE$2,">="&BG$2,$AA$3:$BE$3,"<="&BG$3) -> 0 | BH110: =SUMIFS($AA110:$BE110,$AA$2:$BE$2,">="&BH$2,$AA$3:$BE$3,"<="&BH$3) -> 200000 | BI110: =SUMIFS($AA110:$BE110,$AA$2:$BE$2,">="&BI$2,$AA$3:$BE$3,"<="&BI$3) -> 200000 | BJ110: =SUMIFS($AA110:$BE110,$AA$2:$BE$2,">="&BJ$2,$AA$3:$BE$3,"<="&BJ$3) -> 200000 | BK110: =SUMIFS($AA110:$BE110,$AA$2:$BE$2,">="&BK$2,$AA$3:$BE$3,"<="&BK$3) -> 200000 | BL110: =SUMIFS($AA110:$BE110,$AA$2:$BE$2,">="&BL$2,$AA$3:$BE$3,"<="&BL$3) -> 200000 | BM110: =SUMIFS($AA110:$BE110,$AA$2:$BE$2,">="&BM$2,$AA$3:$BE$3,"<="&BM$3) -> 200000
F112: Admin & Support Staff Costs | G112: =cstConstantUnit -> £ 2022/23 | AA112: =SUM(AA107:AA111) -> 0 | AB112: =SUM(AB107:AB111) -> 244000 | AC112: =SUM(AC107:AC111) -> 244000 | AD112: =SUM(AD107:AD111) -> 244000 | AE112: =SUM(AE107:AE111) -> 244000 | AF112: =SUM(AF107:AF111) -> 244000 | AG112: =SUM(AG107:AG111) -> 244000 | AH112: =SUM(AH107:AH111) -> 244000 | ... BE112: =SUM(BE107:BE111) -> 244000 | BG112: =SUMIFS($AA112:$BE112,$AA$2:$BE$2,">="&BG$2,$AA$3:$BE$3,"<="&BG$3) -> 0 | BH112: =SUMIFS($AA112:$BE112,$AA$2:$BE$2,">="&BH$2,$AA$3:$BE$3,"<="&BH$3) -> 1220000 | BI112: =SUMIFS($AA112:$BE112,$AA$2:$BE$2,">="&BI$2,$AA$3:$BE$3,"<="&BI$3) -> 1220000 | BJ112: =SUMIFS($AA112:$BE112,$AA$2:$BE$2,">="&BJ$2,$AA$3:$BE$3,"<="&BJ$3) -> 1220000 | BK112: =SUMIFS($AA112:$BE112,$AA$2:$BE$2,">="&BK$2,$AA$3:$BE$3,"<="&BK$3) -> 1220000 | BL112: =SUMIFS($AA112:$BE112,$AA$2:$BE$2,">="&BL$2,$AA$3:$BE$3,"<="&BL$3) -> 1220000 | BM112: =SUMIFS($AA112:$BE112,$AA$2:$BE$2,">="&BM$2,$AA$3:$BE$3,"<="&BM$3) -> 1220000
A114: =SUM(C114:BM114) -> 0 | F114: Error Check | BG114: =IF(ABS(SUM(BG107:BG111)-BG112)<eTol,0,1) -> 0 | BH114: =IF(ABS(SUM(BH107:BH111)-BH112)<eTol,0,1) -> 0 | BI114: =IF(ABS(SUM(BI107:BI111)-BI112)<eTol,0,1) -> 0 | BJ114: =IF(ABS(SUM(BJ107:BJ111)-BJ112)<eTol,0,1) -> 0 | BK114: =IF(ABS(SUM(BK107:BK111)-BK112)<eTol,0,1) -> 0 | BL114: =IF(ABS(SUM(BL107:BL111)-BL112)<eTol,0,1) -> 0 | BM114: =IF(ABS(SUM(BM107:BM111)-BM112)<eTol,0,1) -> 0
F116: Calculations (Nominal)
F118: Reception & Admin Support Cost | G118: =cstNominalUnit -> £ Nominal | I118: =iOptions!Q51 -> Wage Inflation | AA118: =AA107*_xlfn.IFNA(INDEX(AA$34:AA$38,MATCH($I118,$F$34:$F$38,0)),0) -> 0 | AB118: =AB107*_xlfn.IFNA(INDEX(AB$34:AB$38,MATCH($I118,$F$34:$F$38,0)),0) -> 83025 | AC118: =AC107*_xlfn.IFNA(INDEX(AC$34:AC$38,MATCH($I118,$F$34:$F$38,0)),0) -> 85100.625 | AD118: =AD107*_xlfn.IFNA(INDEX(AD$34:AD$38,MATCH($I118,$F$34:$F$38,0)),0) -> 87228.141 | AE118: =AE107*_xlfn.IFNA(INDEX(AE$34:AE$38,MATCH($I118,$F$34:$F$38,0)),0) -> 89408.844 | AF118: =AF107*_xlfn.IFNA(INDEX(AF$34:AF$38,MATCH($I118,$F$34:$F$38,0)),0) -> 91644.065 | AG118: =AG107*_xlfn.IFNA(INDEX(AG$34:AG$38,MATCH($I118,$F$34:$F$38,0)),0) -> 93935.167 | AH118: =AH107*_xlfn.IFNA(INDEX(AH$34:AH$38,MATCH($I118,$F$34:$F$38,0)),0) -> 96283.546 | ... BE118: =BE107*_xlfn.IFNA(INDEX(BE$34:BE$38,MATCH($I118,$F$34:$F$38,0)),0) -> 169902.97 | BG118: =SUMIFS($AA118:$BE118,$AA$2:$BE$2,">="&BG$2,$AA$3:$BE$3,"<="&BG$3) -> 0 | BH118: =SUMIFS($AA118:$BE118,$AA$2:$BE$2,">="&BH$2,$AA$3:$BE$3,"<="&BH$3) -> 436406.68 | BI118: =SUMIFS($AA118:$BE118,$AA$2:$BE$2,">="&BI$2,$AA$3:$BE$3,"<="&BI$3) -> 493754.1 | BJ118: =SUMIFS($AA118:$BE118,$AA$2:$BE$2,">="&BJ$2,$AA$3:$BE$3,"<="&BJ$3) -> 558637.44 | BK118: =SUMIFS($AA118:$BE118,$AA$2:$BE$2,">="&BK$2,$AA$3:$BE$3,"<="&BK$3) -> 632046.99 | BL118: =SUMIFS($AA118:$BE118,$AA$2:$BE$2,">="&BL$2,$AA$3:$BE$3,"<="&BL$3) -> 715103.15 | BM118: =SUMIFS($AA118:$BE118,$AA$2:$BE$2,">="&BM$2,$AA$3:$BE$3,"<="&BM$3) -> 809073.58
F119: IT Support Cost | G119: =cstNominalUnit -> £ Nominal | I119: =iOptions!Q52 -> Wage Inflation | AA119: =AA108*_xlfn.IFNA(INDEX(AA$34:AA$38,MATCH($I119,$F$34:$F$38,0)),0) -> 0 | AB119: =AB108*_xlfn.IFNA(INDEX(AB$34:AB$38,MATCH($I119,$F$34:$F$38,0)),0) -> 73800 | AC119: =AC108*_xlfn.IFNA(INDEX(AC$34:AC$38,MATCH($I119,$F$34:$F$38,0)),0) -> 75645 | AD119: =AD108*_xlfn.IFNA(INDEX(AD$34:AD$38,MATCH($I119,$F$34:$F$38,0)),0) -> 77536.125 | AE119: =AE108*_xlfn.IFNA(INDEX(AE$34:AE$38,MATCH($I119,$F$34:$F$38,0)),0) -> 79474.528 | AF119: =AF108*_xlfn.IFNA(INDEX(AF$34:AF$38,MATCH($I119,$F$34:$F$38,0)),0) -> 81461.391 | AG119: =AG108*_xlfn.IFNA(INDEX(AG$34:AG$38,MATCH($I119,$F$34:$F$38,0)),0) -> 83497.926 | AH119: =AH108*_xlfn.IFNA(INDEX(AH$34:AH$38,MATCH($I119,$F$34:$F$38,0)),0) -> 85585.374 | ... BE119: =BE108*_xlfn.IFNA(INDEX(BE$34:BE$38,MATCH($I119,$F$34:$F$38,0)),0) -> 151024.87 | BG119: =SUMIFS($AA119:$BE119,$AA$2:$BE$2,">="&BG$2,$AA$3:$BE$3,"<="&BG$3) -> 0 | BH119: =SUMIFS($AA119:$BE119,$AA$2:$BE$2,">="&BH$2,$AA$3:$BE$3,"<="&BH$3) -> 387917.04 | BI119: =SUMIFS($AA119:$BE119,$AA$2:$BE$2,">="&BI$2,$AA$3:$BE$3,"<="&BI$3) -> 438892.53 | BJ119: =SUMIFS($AA119:$BE119,$AA$2:$BE$2,">="&BJ$2,$AA$3:$BE$3,"<="&BJ$3) -> 496566.61 | BK119: =SUMIFS($AA119:$BE119,$AA$2:$BE$2,">="&BK$2,$AA$3:$BE$3,"<="&BK$3) -> 561819.54 | BL119: =SUMIFS($AA119:$BE119,$AA$2:$BE$2,">="&BL$2,$AA$3:$BE$3,"<="&BL$3) -> 635647.25 | BM119: =SUMIFS($AA119:$BE119,$AA$2:$BE$2,">="&BM$2,$AA$3:$BE$3,"<="&BM$3) -> 719176.52
F120: Office Manager Cost | G120: =cstNominalUnit -> £ Nominal | I120: =iOptions!Q53 -> Wage Inflation | AA120: =AA109*_xlfn.IFNA(INDEX(AA$34:AA$38,MATCH($I120,$F$34:$F$38,0)),0) -> 0 | AB120: =AB109*_xlfn.IFNA(INDEX(AB$34:AB$38,MATCH($I120,$F$34:$F$38,0)),0) -> 52275 | AC120: =AC109*_xlfn.IFNA(INDEX(AC$34:AC$38,MATCH($I120,$F$34:$F$38,0)),0) -> 53581.875 | AD120: =AD109*_xlfn.IFNA(INDEX(AD$34:AD$38,MATCH($I120,$F$34:$F$38,0)),0) -> 54921.422 | AE120: =AE109*_xlfn.IFNA(INDEX(AE$34:AE$38,MATCH($I120,$F$34:$F$38,0)),0) -> 56294.457 | AF120: =AF109*_xlfn.IFNA(INDEX(AF$34:AF$38,MATCH($I120,$F$34:$F$38,0)),0) -> 57701.819 | AG120: =AG109*_xlfn.IFNA(INDEX(AG$34:AG$38,MATCH($I120,$F$34:$F$38,0)),0) -> 59144.364 | AH120: =AH109*_xlfn.IFNA(INDEX(AH$34:AH$38,MATCH($I120,$F$34:$F$38,0)),0) -> 60622.973 | ... BE120: =BE109*_xlfn.IFNA(INDEX(BE$34:BE$38,MATCH($I120,$F$34:$F$38,0)),0) -> 106975.95 | BG120: =SUMIFS($AA120:$BE120,$AA$2:$BE$2,">="&BG$2,$AA$3:$BE$3,"<="&BG$3) -> 0 | BH120: =SUMIFS($AA120:$BE120,$AA$2:$BE$2,">="&BH$2,$AA$3:$BE$3,"<="&BH$3) -> 274774.57 | BI120: =SUMIFS($AA120:$BE120,$AA$2:$BE$2,">="&BI$2,$AA$3:$BE$3,"<="&BI$3) -> 310882.21 | BJ120: =SUMIFS($AA120:$BE120,$AA$2:$BE$2,">="&BJ$2,$AA$3:$BE$3,"<="&BJ$3) -> 351734.68 | BK120: =SUMIFS($AA120:$BE120,$AA$2:$BE$2,">="&BK$2,$AA$3:$BE$3,"<="&BK$3) -> 397955.51 | BL120: =SUMIFS($AA120:$BE120,$AA$2:$BE$2,">="&BL$2,$AA$3:$BE$3,"<="&BL$3) -> 450250.13 | BM120: =SUMIFS($AA120:$BE120,$AA$2:$BE$2,">="&BM$2,$AA$3:$BE$3,"<="&BM$3) -> 509416.7
F121: Office Deputy Cost | G121: =cstNominalUnit -> £ Nominal | I121: =iOptions!Q54 -> Wage Inflation | AA121: =AA110*_xlfn.IFNA(INDEX(AA$34:AA$38,MATCH($I121,$F$34:$F$38,0)),0) -> 0 | AB121: =AB110*_xlfn.IFNA(INDEX(AB$34:AB$38,MATCH($I121,$F$34:$F$38,0)),0) -> 41000 | AC121: =AC110*_xlfn.IFNA(INDEX(AC$34:AC$38,MATCH($I121,$F$34:$F$38,0)),0) -> 42025 | AD121: =AD110*_xlfn.IFNA(INDEX(AD$34:AD$38,MATCH($I121,$F$34:$F$38,0)),0) -> 43075.625 | AE121: =AE110*_xlfn.IFNA(INDEX(AE$34:AE$38,MATCH($I121,$F$34:$F$38,0)),0) -> 44152.516 | AF121: =AF110*_xlfn.IFNA(INDEX(AF$34:AF$38,MATCH($I121,$F$34:$F$38,0)),0) -> 45256.329 | AG121: =AG110*_xlfn.IFNA(INDEX(AG$34:AG$38,MATCH($I121,$F$34:$F$38,0)),0) -> 46387.737 | AH121: =AH110*_xlfn.IFNA(INDEX(AH$34:AH$38,MATCH($I121,$F$34:$F$38,0)),0) -> 47547.43 | ... BE121: =BE110*_xlfn.IFNA(INDEX(BE$34:BE$38,MATCH($I121,$F$34:$F$38,0)),0) -> 83902.703 | BG121: =SUMIFS($AA121:$BE121,$AA$2:$BE$2,">="&BG$2,$AA$3:$BE$3,"<="&BG$3) -> 0 | BH121: =SUMIFS($AA121:$BE121,$AA$2:$BE$2,">="&BH$2,$AA$3:$BE$3,"<="&BH$3) -> 215509.47 | BI121: =SUMIFS($AA121:$BE121,$AA$2:$BE$2,">="&BI$2,$AA$3:$BE$3,"<="&BI$3) -> 243829.18 | BJ121: =SUMIFS($AA121:$BE121,$AA$2:$BE$2,">="&BJ$2,$AA$3:$BE$3,"<="&BJ$3) -> 275870.34 | BK121: =SUMIFS($AA121:$BE121,$AA$2:$BE$2,">="&BK$2,$AA$3:$BE$3,"<="&BK$3) -> 312121.97 | BL121: =SUMIFS($AA121:$BE121,$AA$2:$BE$2,">="&BL$2,$AA$3:$BE$3,"<="&BL$3) -> 353137.36 | BM121: =SUMIFS($AA121:$BE121,$AA$2:$BE$2,">="&BM$2,$AA$3:$BE$3,"<="&BM$3) -> 399542.51
F123: Admin & Support Staff Costs | G123: =cstNominalUnit -> £ Nominal | AA123: =SUM(AA118:AA122) -> 0 | AB123: =SUM(AB118:AB122) -> 250100 | AC123: =SUM(AC118:AC122) -> 256352.5 | AD123: =SUM(AD118:AD122) -> 262761.31 | AE123: =SUM(AE118:AE122) -> 269330.35 | AF123: =SUM(AF118:AF122) -> 276063.6 | AG123: =SUM(AG118:AG122) -> 282965.19 | AH123: =SUM(AH118:AH122) -> 290039.32 | ... BE123: =SUM(BE118:BE122) -> 511806.49 | BG123: =SUMIFS($AA123:$BE123,$AA$2:$BE$2,">="&BG$2,$AA$3:$BE$3,"<="&BG$3) -> 0 | BH123: =SUMIFS($AA123:$BE123,$AA$2:$BE$2,">="&BH$2,$AA$3:$BE$3,"<="&BH$3) -> 1314607.8 | BI123: =SUMIFS($AA123:$BE123,$AA$2:$BE$2,">="&BI$2,$AA$3:$BE$3,"<="&BI$3) -> 1487358 | BJ123: =SUMIFS($AA123:$BE123,$AA$2:$BE$2,">="&BJ$2,$AA$3:$BE$3,"<="&BJ$3) -> 1682809.1 | BK123: =SUMIFS($AA123:$BE123,$AA$2:$BE$2,">="&BK$2,$AA$3:$BE$3,"<="&BK$3) -> 1903944 | BL123: =SUMIFS($AA123:$BE123,$AA$2:$BE$2,">="&BL$2,$AA$3:$BE$3,"<="&BL$3) -> 2154137.9 | BM123: =SUMIFS($AA123:$BE123,$AA$2:$BE$2,">="&BM$2,$AA$3:$BE$3,"<="&BM$3) -> 2437209.3
A125: =SUM(C125:BM125) -> 0 | F125: Error Check | BG125: =IF(ABS(SUM(BG118:BG122)-BG123)<eTol,0,1) -> 0 | BH125: =IF(ABS(SUM(BH118:BH122)-BH123)<eTol,0,1) -> 0 | BI125: =IF(ABS(SUM(BI118:BI122)-BI123)<eTol,0,1) -> 0 | BJ125: =IF(ABS(SUM(BJ118:BJ122)-BJ123)<eTol,0,1) -> 0 | BK125: =IF(ABS(SUM(BK118:BK122)-BK123)<eTol,0,1) -> 0 | BL125: =IF(ABS(SUM(BL118:BL122)-BL123)<eTol,0,1) -> 0 | BM125: =IF(ABS(SUM(BM118:BM122)-BM123)<eTol,0,1) -> 0
E127: 5.4 | F127: Staff Cost Totals (Nominal)
F129: Agent Staff Costs | G129: =cstNominalUnit -> £ Nominal | AA129: =AA73 -> 0 | AB129: =AB73 -> 1748986.7 | AC129: =AC73 -> 1792711.3 | AD129: =AD73 -> 1837529.1 | AE129: =AE73 -> 1883467.3 | AF129: =AF73 -> 1930554 | AG129: =AG73 -> 1978817.9 | AH129: =AH73 -> 2028288.3 | ... BE129: =BE73 -> 3579139.2 | BG129: =SUMIFS($AA129:$BE129,$AA$2:$BE$2,">="&BG$2,$AA$3:$BE$3,"<="&BG$3) -> 0 | BH129: =SUMIFS($AA129:$BE129,$AA$2:$BE$2,">="&BH$2,$AA$3:$BE$3,"<="&BH$3) -> 9193248.5 | BI129: =SUMIFS($AA129:$BE129,$AA$2:$BE$2,">="&BI$2,$AA$3:$BE$3,"<="&BI$3) -> 10401317 | BJ129: =SUMIFS($AA129:$BE129,$AA$2:$BE$2,">="&BJ$2,$AA$3:$BE$3,"<="&BJ$3) -> 11768135 | BK129: =SUMIFS($AA129:$BE129,$AA$2:$BE$2,">="&BK$2,$AA$3:$BE$3,"<="&BK$3) -> 13314565 | BL129: =SUMIFS($AA129:$BE129,$AA$2:$BE$2,">="&BL$2,$AA$3:$BE$3,"<="&BL$3) -> 15064208 | BM129: =SUMIFS($AA129:$BE129,$AA$2:$BE$2,">="&BM$2,$AA$3:$BE$3,"<="&BM$3) -> 17043769
F130: Supervisor Staff Costs | G130: =cstNominalUnit -> £ Nominal | AA130: =AA89 -> 0 | AB130: =AB89 -> 152785.04 | AC130: =AC89 -> 156604.67 | AD130: =AD89 -> 160519.78 | AE130: =AE89 -> 164532.78 | AF130: =AF89 -> 168646.1 | AG130: =AG89 -> 172862.25 | AH130: =AH89 -> 177183.81 | ... BE130: =BE89 -> 312660.44 | BG130: =SUMIFS($AA130:$BE130,$AA$2:$BE$2,">="&BG$2,$AA$3:$BE$3,"<="&BG$3) -> 0 | BH130: =SUMIFS($AA130:$BE130,$AA$2:$BE$2,">="&BH$2,$AA$3:$BE$3,"<="&BH$3) -> 803088.37 | BI130: =SUMIFS($AA130:$BE130,$AA$2:$BE$2,">="&BI$2,$AA$3:$BE$3,"<="&BI$3) -> 908620.78 | BJ130: =SUMIFS($AA130:$BE130,$AA$2:$BE$2,">="&BJ$2,$AA$3:$BE$3,"<="&BJ$3) -> 1028021 | BK130: =SUMIFS($AA130:$BE130,$AA$2:$BE$2,">="&BK$2,$AA$3:$BE$3,"<="&BK$3) -> 1163111.4 | BL130: =SUMIFS($AA130:$BE130,$AA$2:$BE$2,">="&BL$2,$AA$3:$BE$3,"<="&BL$3) -> 1315953.8 | BM130: =SUMIFS($AA130:$BE130,$AA$2:$BE$2,">="&BM$2,$AA$3:$BE$3,"<="&BM$3) -> 1488880.9
F131: Admin & Support Staff Costs | G131: =cstNominalUnit -> £ Nominal | AA131: =AA123 -> 0 | AB131: =AB123 -> 250100 | AC131: =AC123 -> 256352.5 | AD131: =AD123 -> 262761.31 | AE131: =AE123 -> 269330.35 | AF131: =AF123 -> 276063.6 | AG131: =AG123 -> 282965.19 | AH131: =AH123 -> 290039.32 | ... BE131: =BE123 -> 511806.49 | BG131: =SUMIFS($AA131:$BE131,$AA$2:$BE$2,">="&BG$2,$AA$3:$BE$3,"<="&BG$3) -> 0 | BH131: =SUMIFS($AA131:$BE131,$AA$2:$BE$2,">="&BH$2,$AA$3:$BE$3,"<="&BH$3) -> 1314607.8 | BI131: =SUMIFS($AA131:$BE131,$AA$2:$BE$2,">="&BI$2,$AA$3:$BE$3,"<="&BI$3) -> 1487358 | BJ131: =SUMIFS($AA131:$BE131,$AA$2:$BE$2,">="&BJ$2,$AA$3:$BE$3,"<="&BJ$3) -> 1682809.1 | BK131: =SUMIFS($AA131:$BE131,$AA$2:$BE$2,">="&BK$2,$AA$3:$BE$3,"<="&BK$3) -> 1903944 | BL131: =SUMIFS($AA131:$BE131,$AA$2:$BE$2,">="&BL$2,$AA$3:$BE$3,"<="&BL$3) -> 2154137.9 | BM131: =SUMIFS($AA131:$BE131,$AA$2:$BE$2,">="&BM$2,$AA$3:$BE$3,"<="&BM$3) -> 2437209.3
F133: Total Staff Costs | G133: =cstNominalUnit -> £ Nominal | AA133: =SUM(AA129:AA132) -> 0 | AB133: =SUM(AB129:AB132) -> 2151871.7 | AC133: =SUM(AC129:AC132) -> 2205668.5 | AD133: =SUM(AD129:AD132) -> 2260810.2 | AE133: =SUM(AE129:AE132) -> 2317330.5 | AF133: =SUM(AF129:AF132) -> 2375263.7 | AG133: =SUM(AG129:AG132) -> 2434645.3 | AH133: =SUM(AH129:AH132) -> 2495511.5 | ... BE133: =SUM(BE129:BE132) -> 4403606.2 | BG133: =SUMIFS($AA133:$BE133,$AA$2:$BE$2,">="&BG$2,$AA$3:$BE$3,"<="&BG$3) -> 0 | BH133: =SUMIFS($AA133:$BE133,$AA$2:$BE$2,">="&BH$2,$AA$3:$BE$3,"<="&BH$3) -> 11310945 | BI133: =SUMIFS($AA133:$BE133,$AA$2:$BE$2,">="&BI$2,$AA$3:$BE$3,"<="&BI$3) -> 12797296 | BJ133: =SUMIFS($AA133:$BE133,$AA$2:$BE$2,">="&BJ$2,$AA$3:$BE$3,"<="&BJ$3) -> 14478965 | BK133: =SUMIFS($AA133:$BE133,$AA$2:$BE$2,">="&BK$2,$AA$3:$BE$3,"<="&BK$3) -> 16381620 | BL133: =SUMIFS($AA133:$BE133,$AA$2:$BE$2,">="&BL$2,$AA$3:$BE$3,"<="&BL$3) -> 18534300 | BM133: =SUMIFS($AA133:$BE133,$AA$2:$BE$2,">="&BM$2,$AA$3:$BE$3,"<="&BM$3) -> 20969859
A135: =SUM(C135:BM135) -> 0 | F135: Error Check | BG135: =IF(ABS(SUM(BG129:BG132)-BG133)<eTol,0,1) -> 0 | BH135: =IF(ABS(SUM(BH129:BH132)-BH133)<eTol,0,1) -> 0 | BI135: =IF(ABS(SUM(BI129:BI132)-BI133)<eTol,0,1) -> 0 | BJ135: =IF(ABS(SUM(BJ129:BJ132)-BJ133)<eTol,0,1) -> 0 | BK135: =IF(ABS(SUM(BK129:BK132)-BK133)<eTol,0,1) -> 0 | BL135: =IF(ABS(SUM(BL129:BL132)-BL133)<eTol,0,1) -> 0 | BM135: =IF(ABS(SUM(BM129:BM132)-BM133)<eTol,0,1) -> 0
D137: 6 | E137: Software & Hardware Costs
E139: 6.1 | F139: Telephony Costs
F141: Call-Ups
F143: Application Cost | G143: =cstConstantUnit -> £ 2022/23 | K143: {=INDEX(iOptions!$M62:$O62,1,ActiveCostScenarioIndex)} -> 200000
F144: Vendor Support & Maintenance | G144: =cstPercent -> % | K144: {=INDEX(iOptions!$M63:$O63,1,ActiveCostScenarioIndex)} -> 0.2
F145: Cost per License per Year | G145: =cstConstantUnit -> £ 2022/23 | K145: {=INDEX(iOptions!$M64:$O64,1,ActiveCostScenarioIndex)} -> 400
F147: Number of Active Agents | G147: =cstNum -> # | AA147: =cVolumetrics!AA54 -> 0 | AB147: =cVolumetrics!AB54 -> 47.07113 | AC147: =cVolumetrics!AC54 -> 47.07113 | AD147: =cVolumetrics!AD54 -> 47.07113 | AE147: =cVolumetrics!AE54 -> 47.07113 | AF147: =cVolumetrics!AF54 -> 47.07113 | AG147: =cVolumetrics!AG54 -> 47.07113 | AH147: =cVolumetrics!AH54 -> 47.07113 | ... BE147: =cVolumetrics!BE54 -> 47.07113
F149: Initial Hardware Cost | G149: =cstConstantUnit -> £ 2022/23 | K149: {=INDEX(iOptions!$M68:$O68,1,ActiveCostScenarioIndex)} -> 25000
F150: Replacement Factor | G150: =cstPercent -> % | K150: =iOptions!N69 -> 0.5
F151: Replacement Periodicity | G151: =cstYears -> Yrs | K151: =iOptions!N70 -> 5
F153: Initial Implementation Cost | G153: =cstConstantUnit -> £ 2022/23 | K153: {=INDEX(iOptions!$M$74:$O$74,1,ActiveCostScenarioIndex)} -> 200000
F154: Replacement Factor | G154: =cstPercent -> % | K154: =iOptions!N75 -> 0.5
F155: Replacement Periodicity | G155: =cstYears -> Yrs | K155: =iOptions!N76 -> 5
F157: Calculations (Pre-Inflation)
F159: Application Cost | G159: =cstConstantUnit -> £ 2022/23 | AA159: =AA$22*$K143 -> 0 | AB159: =AB$22*$K143 -> 200000 | AC159: =AC$22*$K143 -> 0 | AD159: =AD$22*$K143 -> 0 | AE159: =AE$22*$K143 -> 0 | AF159: =AF$22*$K143 -> 0 | AG159: =AG$22*$K143 -> 0 | AH159: =AH$22*$K143 -> 0 | ... BE159: =BE$22*$K143 -> 0 | BG159: =SUMIFS($AA159:$BE159,$AA$2:$BE$2,">="&BG$2,$AA$3:$BE$3,"<="&BG$3) -> 0 | BH159: =SUMIFS($AA159:$BE159,$AA$2:$BE$2,">="&BH$2,$AA$3:$BE$3,"<="&BH$3) -> 200000 | BI159: =SUMIFS($AA159:$BE159,$AA$2:$BE$2,">="&BI$2,$AA$3:$BE$3,"<="&BI$3) -> 0 | BJ159: =SUMIFS($AA159:$BE159,$AA$2:$BE$2,">="&BJ$2,$AA$3:$BE$3,"<="&BJ$3) -> 0 | BK159: =SUMIFS($AA159:$BE159,$AA$2:$BE$2,">="&BK$2,$AA$3:$BE$3,"<="&BK$3) -> 0 | BL159: =SUMIFS($AA159:$BE159,$AA$2:$BE$2,">="&BL$2,$AA$3:$BE$3,"<="&BL$3) -> 0 | BM159: =SUMIFS($AA159:$BE159,$AA$2:$BE$2,">="&BM$2,$AA$3:$BE$3,"<="&BM$3) -> 0
F161: Vendor Support & Maintenance Cost | G161: =cstConstantUnit -> £ 2022/23 | AA161: =$K143*$K144*AA20 -> 0 | AB161: =$K143*$K144*AB20 -> 40000 | AC161: =$K143*$K144*AC20 -> 40000 | AD161: =$K143*$K144*AD20 -> 40000 | AE161: =$K143*$K144*AE20 -> 40000 | AF161: =$K143*$K144*AF20 -> 40000 | AG161: =$K143*$K144*AG20 -> 40000 | AH161: =$K143*$K144*AH20 -> 40000 | ... BE161: =$K143*$K144*BE20 -> 40000 | BG161: =SUMIFS($AA161:$BE161,$AA$2:$BE$2,">="&BG$2,$AA$3:$BE$3,"<="&BG$3) -> 0 | BH161: =SUMIFS($AA161:$BE161,$AA$2:$BE$2,">="&BH$2,$AA$3:$BE$3,"<="&BH$3) -> 200000 | BI161: =SUMIFS($AA161:$BE161,$AA$2:$BE$2,">="&BI$2,$AA$3:$BE$3,"<="&BI$3) -> 200000 | BJ161: =SUMIFS($AA161:$BE161,$AA$2:$BE$2,">="&BJ$2,$AA$3:$BE$3,"<="&BJ$3) -> 200000 | BK161: =SUMIFS($AA161:$BE161,$AA$2:$BE$2,">="&BK$2,$AA$3:$BE$3,"<="&BK$3) -> 200000 | BL161: =SUMIFS($AA161:$BE161,$AA$2:$BE$2,">="&BL$2,$AA$3:$BE$3,"<="&BL$3) -> 200000 | BM161: =SUMIFS($AA161:$BE161,$AA$2:$BE$2,">="&BM$2,$AA$3:$BE$3,"<="&BM$3) -> 200000
F163: Licence Costs | G163: =cstConstantUnit -> £ 2022/23 | AA163: =AA147*$K145*AA20 -> 0 | AB163: =AB147*$K145*AB20 -> 18828.452 | AC163: =AC147*$K145*AC20 -> 18828.452 | AD163: =AD147*$K145*AD20 -> 18828.452 | AE163: =AE147*$K145*AE20 -> 18828.452 | AF163: =AF147*$K145*AF20 -> 18828.452 | AG163: =AG147*$K145*AG20 -> 18828.452 | AH163: =AH147*$K145*AH20 -> 18828.452 | ... BE163: =BE147*$K145*BE20 -> 18828.452 | BG163: =SUMIFS($AA163:$BE163,$AA$2:$BE$2,">="&BG$2,$AA$3:$BE$3,"<="&BG$3) -> 0 | BH163: =SUMIFS($AA163:$BE163,$AA$2:$BE$2,">="&BH$2,$AA$3:$BE$3,"<="&BH$3) -> 94142.259 | BI163: =SUMIFS($AA163:$BE163,$AA$2:$BE$2,">="&BI$2,$AA$3:$BE$3,"<="&BI$3) -> 94142.259 | BJ163: =SUMIFS($AA163:$BE163,$AA$2:$BE$2,">="&BJ$2,$AA$3:$BE$3,"<="&BJ$3) -> 94142.259 | BK163: =SUMIFS($AA163:$BE163,$AA$2:$BE$2,">="&BK$2,$AA$3:$BE$3,"<="&BK$3) -> 94142.259 | BL163: =SUMIFS($AA163:$BE163,$AA$2:$BE$2,">="&BL$2,$AA$3:$BE$3,"<="&BL$3) -> 94142.259 | BM163: =SUMIFS($AA163:$BE163,$AA$2:$BE$2,">="&BM$2,$AA$3:$BE$3,"<="&BM$3) -> 94142.259
F165: Hardware Replacement Flag | G165: =cstFlag -> Flag | AA165: =IF(MOD(AA$5,$K151)=$K$24,1,0) -> 0 | AB165: =IF(MOD(AB$5,$K151)=$K$24,1,0) -> 1 | AC165: =IF(MOD(AC$5,$K151)=$K$24,1,0) -> 0 | AD165: =IF(MOD(AD$5,$K151)=$K$24,1,0) -> 0 | AE165: =IF(MOD(AE$5,$K151)=$K$24,1,0) -> 0 | AF165: =IF(MOD(AF$5,$K151)=$K$24,1,0) -> 0 | AG165: =IF(MOD(AG$5,$K151)=$K$24,1,0) -> 1 | AH165: =IF(MOD(AH$5,$K151)=$K$24,1,0) -> 0 | ... BE165: =IF(MOD(BE$5,$K151)=$K$24,1,0) -> 0
F167: Initial Hardware Costs | G167: =cstConstantUnit -> £ 2022/23 | AA167: =IF(AA$22=1,$K149,0) -> 0 | AB167: =IF(AB$22=1,$K149,0) -> 25000 | AC167: =IF(AC$22=1,$K149,0) -> 0 | AD167: =IF(AD$22=1,$K149,0) -> 0 | AE167: =IF(AE$22=1,$K149,0) -> 0 | AF167: =IF(AF$22=1,$K149,0) -> 0 | AG167: =IF(AG$22=1,$K149,0) -> 0 | AH167: =IF(AH$22=1,$K149,0) -> 0 | ... BE167: =IF(BE$22=1,$K149,0) -> 0 | BG167: =SUMIFS($AA167:$BE167,$AA$2:$BE$2,">="&BG$2,$AA$3:$BE$3,"<="&BG$3) -> 0 | BH167: =SUMIFS($AA167:$BE167,$AA$2:$BE$2,">="&BH$2,$AA$3:$BE$3,"<="&BH$3) -> 25000 | BI167: =SUMIFS($AA167:$BE167,$AA$2:$BE$2,">="&BI$2,$AA$3:$BE$3,"<="&BI$3) -> 0 | BJ167: =SUMIFS($AA167:$BE167,$AA$2:$BE$2,">="&BJ$2,$AA$3:$BE$3,"<="&BJ$3) -> 0 | BK167: =SUMIFS($AA167:$BE167,$AA$2:$BE$2,">="&BK$2,$AA$3:$BE$3,"<="&BK$3) -> 0 | BL167: =SUMIFS($AA167:$BE167,$AA$2:$BE$2,">="&BL$2,$AA$3:$BE$3,"<="&BL$3) -> 0 | BM167: =SUMIFS($AA167:$BE167,$AA$2:$BE$2,">="&BM$2,$AA$3:$BE$3,"<="&BM$3) -> 0
...

Sheet cOutputs
C1: THIS CASE STUDY MODEL IS FOR ILLUSTRATIVE PURPOSES
C2: =cstProjectName -> Should Cost Modelling Case Study - Illustrative SCM | Z2: =SysTime!Z2 -> Period Start | AA2: =SysTime!AA2 -> 44652 | AB2: =SysTime!AB2 -> 45017 | AC2: =SysTime!AC2 -> 45383 | AD2: =SysTime!AD2 -> 45748 | AE2: =SysTime!AE2 -> 46113 | AF2: =SysTime!AF2 -> 46478 | AG2: =SysTime!AG2 -> 46844 | ... BE2: =SysTime!BE2 -> 55610 | BG2: =SysTime!BG2 -> 44652 | BH2: =SysTime!BH2 -> 45017 | BI2: =SysTime!BI2 -> 46844 | BJ2: =SysTime!BJ2 -> 48670 | BK2: =SysTime!BK2 -> 50496 | BL2: =SysTime!BL2 -> 52322 | BM2: =SysTime!BM2 -> 54149
C3: =MID(CELL("filename",A1),FIND("]",CELL("filename",A1))+1,256)&" Sheet" -> cOutputs Sheet | Z3: =SysTime!Z3 -> Period End | AA3: =SysTime!AA3 -> 45016 | AB3: =SysTime!AB3 -> 45382 | AC3: =SysTime!AC3 -> 45747 | AD3: =SysTime!AD3 -> 46112 | AE3: =SysTime!AE3 -> 46477 | AF3: =SysTime!AF3 -> 46843 | AG3: =SysTime!AG3 -> 47208 | ... BE3: =SysTime!BE3 -> 55974 | BG3: =SysTime!BG3 -> 45016 | BH3: =SysTime!BH3 -> 46843 | BI3: =SysTime!BI3 -> 48669 | BJ3: =SysTime!BJ3 -> 50495 | BK3: =SysTime!BK3 -> 52321 | BL3: =SysTime!BL3 -> 54148 | BM3: =SysTime!BM3 -> 55974
C4: =IF(ISBLANK(cstProtectiveMarking),"",cstProtectiveMarking) -> Not Protectively Marked | Z4: =SysTime!Z4 -> Timeline | AA4: =SysTime!AA4 -> Annual | AB4: =SysTime!AB4 -> Annual | AC4: =SysTime!AC4 -> Annual | AD4: =SysTime!AD4 -> Annual | AE4: =SysTime!AE4 -> Annual | AF4: =SysTime!AF4 -> Annual | AG4: =SysTime!AG4 -> Annual | ... BE4: =SysTime!BE4 -> Annual | BG4: =SysTime!BG4 -> Annual | BH4: =SysTime!BH4 -> 5 Yearly | BI4: =SysTime!BI4 -> 5 Yearly | BJ4: =SysTime!BJ4 -> 5 Yearly | BK4: =SysTime!BK4 -> 5 Yearly | BL4: =SysTime!BL4 -> 5 Yearly | BM4: =SysTime!BM4 -> 5 Yearly
C5: =HYPERLINK("#'Contents'!A1",sysChkWord) -> All Checks OK | Z5: =SysTime!Z5 -> Period index | AA5: =SysTime!AA5 -> 1 | AB5: =SysTime!AB5 -> 2 | AC5: =SysTime!AC5 -> 3 | AD5: =SysTime!AD5 -> 4 | AE5: =SysTime!AE5 -> 5 | AF5: =SysTime!AF5 -> 6 | AG5: =SysTime!AG5 -> 7 | ... BE5: =SysTime!BE5 -> 31 | BG5: =SysTime!BG5 -> 1 | BH5: =SysTime!BH5 -> 2 | BI5: =SysTime!BI5 -> 3 | BJ5: =SysTime!BJ5 -> 4 | BK5: =SysTime!BK5 -> 5 | BL5: =SysTime!BL5 -> 6 | BM5: =SysTime!BM5 -> 7
C6: =HYPERLINK("#'Contents'!A1","Click for Contents") -> Click for Contents | Z6: =SysTime!Z6 -> Year index | AA6: =SysTime!AA6 -> 1 | AB6: =SysTime!AB6 -> 2 | AC6: =SysTime!AC6 -> 3 | AD6: =SysTime!AD6 -> 4 | AE6: =SysTime!AE6 -> 5 | AF6: =SysTime!AF6 -> 6 | AG6: =SysTime!AG6 -> 7 | ... BE6: =SysTime!BE6 -> 31 | BG6: =SysTime!BG6 -> 0 | BH6: =SysTime!BH6 -> 0 | BI6: =SysTime!BI6 -> 0 | BJ6: =SysTime!BJ6 -> 0 | BK6: =SysTime!BK6 -> 0 | BL6: =SysTime!BL6 -> 0 | BM6: =SysTime!BM6 -> 0
Z7: =SysTime!Z7 -> Relative period | AA7: =SysTime!AA7 -> 1 | AB7: =SysTime!AB7 -> 2 | AC7: =SysTime!AC7 -> 3 | AD7: =SysTime!AD7 -> 4 | AE7: =SysTime!AE7 -> 5 | AF7: =SysTime!AF7 -> 6 | AG7: =SysTime!AG7 -> 7 | ... BE7: =SysTime!BE7 -> 31 | BG7: =SysTime!BG7 -> 1 | BH7: =SysTime!BH7 -> 2 | BI7: =SysTime!BI7 -> 3 | BJ7: =SysTime!BJ7 -> 4 | BK7: =SysTime!BK7 -> 5 | BL7: =SysTime!BL7 -> 6 | BM7: =SysTime!BM7 -> 7
A8: =SUM(A9:A197) -> 0 | B8: =SUM(B9:B197) -> 0 | G8: Units
D10: 1 | E10: Inflation Call-Ups
E12: 1.1 | F12: Discount Factors
F14: Treasury Rates
F16: GDP Deflator (General Price Inflation) | G16: % | AA16: =cFactors!AA45 -> 1 | AB16: =cFactors!AB45 -> 0.98716683 | AC16: =cFactors!AC45 -> 0.97066552 | AD16: =cFactors!AD45 -> 0.95256675 | AE16: =cFactors!AE45 -> 0.93480545 | AF16: =cFactors!AF45 -> 0.91647593 | AG16: =cFactors!AG45 -> 0.89850581 | AH16: =cFactors!AH45 -> 0.88088805 | ... BE16: =cFactors!BE45 -> 0.55862037
F17: Treasury Real Discount Rate | G17: % | AA17: =cFactors!AA46 -> 1 | AB17: =cFactors!AB46 -> 0.96618357 | AC17: =cFactors!AC46 -> 0.9335107 | AD17: =cFactors!AD46 -> 0.90194271 | AE17: =cFactors!AE46 -> 0.87144223 | AF17: =cFactors!AF46 -> 0.84197317 | AG17: =cFactors!AG46 -> 0.81350064 | AH17: =cFactors!AH46 -> 0.78599096 | ... BE17: =cFactors!BE46 -> 0.35800792
D19: 2 | E19: Costs (Nominal)
E21: 2.1 | F21: In year costs
F23: Nominal Costs | I23: 31 Yr Total
F25: Build & Operate | G25: =cstNominalUnit -> £ Nominal | I25: =SUM(AA25:BE25) -> 1.0891999e+08 | AA25: =SUM(AA26:AA31) -> 3045073 | AB25: =SUM(AB26:AB31) -> 2910738.8 | AC25: =SUM(AC26:AC31) -> 2402943.2 | AD25: =SUM(AD26:AD31) -> 2464003.1 | AE25: =SUM(AE26:AE31) -> 2574911.3 | AF25: =SUM(AF26:AF31) -> 2590831.1 | AG25: =SUM(AG26:AG31) -> 2814891.6 | AH25: =SUM(AH26:AH31) -> 2776977 | ... BE25: =SUM(BE26:BE31) -> 4854956.4 | BG25: =SUMIFS($AA25:$BE25,$AA$2:$BE$2,">="&BG$2,$AA$3:$BE$3,"<="&BG$3) -> 3045073 | BH25: =SUMIFS($AA25:$BE25,$AA$2:$BE$2,">="&BH$2,$AA$3:$BE$3,"<="&BH$3) -> 12943427 | BI25: =SUMIFS($AA25:$BE25,$AA$2:$BE$2,">="&BI$2,$AA$3:$BE$3,"<="&BI$3) -> 14244752 | BJ25: =SUMIFS($AA25:$BE25,$AA$2:$BE$2,">="&BJ$2,$AA$3:$BE$3,"<="&BJ$3) -> 16091951 | BK25: =SUMIFS($AA25:$BE25,$AA$2:$BE$2,">="&BK$2,$AA$3:$BE$3,"<="&BK$3) -> 18322558 | BL25: =SUMIFS($AA25:$BE25,$AA$2:$BE$2,">="&BL$2,$AA$3:$BE$3,"<="&BL$3) -> 20789389 | BM25: =SUMIFS($AA25:$BE25,$AA$2:$BE$2,">="&BM$2,$AA$3:$BE$3,"<="&BM$3) -> 23482839
F26: Operating Costs | G26: =cstNominalUnit -> £ Nominal | I26: =SUM(AA26:BE26) -> 0 | BG26: =SUMIFS($AA26:$BE26,$AA$2:$BE$2,">="&BG$2,$AA$3:$BE$3,"<="&BG$3) -> 0 | BH26: =SUMIFS($AA26:$BE26,$AA$2:$BE$2,">="&BH$2,$AA$3:$BE$3,"<="&BH$3) -> 0 | BI26: =SUMIFS($AA26:$BE26,$AA$2:$BE$2,">="&BI$2,$AA$3:$BE$3,"<="&BI$3) -> 0 | BJ26: =SUMIFS($AA26:$BE26,$AA$2:$BE$2,">="&BJ$2,$AA$3:$BE$3,"<="&BJ$3) -> 0 | BK26: =SUMIFS($AA26:$BE26,$AA$2:$BE$2,">="&BK$2,$AA$3:$BE$3,"<="&BK$3) -> 0 | BL26: =SUMIFS($AA26:$BE26,$AA$2:$BE$2,">="&BL$2,$AA$3:$BE$3,"<="&BL$3) -> 0 | BM26: =SUMIFS($AA26:$BE26,$AA$2:$BE$2,">="&BM$2,$AA$3:$BE$3,"<="&BM$3) -> 0
F27: Staff Costs | G27: =cstNominalUnit -> £ Nominal | I27: =SUM(AA27:BE27) -> 94472985 | AA27: =cCosts!AA133 -> 0 | AB27: =cCosts!AB133 -> 2151871.7 | AC27: =cCosts!AC133 -> 2205668.5 | AD27: =cCosts!AD133 -> 2260810.2 | AE27: =cCosts!AE133 -> 2317330.5 | AF27: =cCosts!AF133 -> 2375263.7 | AG27: =cCosts!AG133 -> 2434645.3 | AH27: =cCosts!AH133 -> 2495511.5 | ... BE27: =cCosts!BE133 -> 4403606.2 | BG27: =SUMIFS($AA27:$BE27,$AA$2:$BE$2,">="&BG$2,$AA$3:$BE$3,"<="&BG$3) -> 0 | BH27: =SUMIFS($AA27:$BE27,$AA$2:$BE$2,">="&BH$2,$AA$3:$BE$3,"<="&BH$3) -> 11310945 | BI27: =SUMIFS($AA27:$BE27,$AA$2:$BE$2,">="&BI$2,$AA$3:$BE$3,"<="&BI$3) -> 12797296 | BJ27: =SUMIFS($AA27:$BE27,$AA$2:$BE$2,">="&BJ$2,$AA$3:$BE$3,"<="&BJ$3) -> 14478965 | BK27: =SUMIFS($AA27:$BE27,$AA$2:$BE$2,">="&BK$2,$AA$3:$BE$3,"<="&BK$3) -> 16381620 | BL27: =SUMIFS($AA27:$BE27,$AA$2:$BE$2,">="&BL$2,$AA$3:$BE$3,"<="&BL$3) -> 18534300 | BM27: =SUMIFS($AA27:$BE27,$AA$2:$BE$2,">="&BM$2,$AA$3:$BE$3,"<="&BM$3) -> 20969859
F28: Software & Hardware Costs | G28: =cstNominalUnit -> £ Nominal | I28: =SUM(AA28:BE28) -> 9930144 | AA28: =cCosts!AA293 -> 0 | AB28: =cCosts!AB293 -> 727931.17 | AC28: =cCosts!AC293 -> 165410.73 | AD28: =cCosts!AD293 -> 170373.06 | AE28: =cCosts!AE293 -> 223776.35 | AF28: =cCosts!AF293 -> 180748.78 | AG28: =cCosts!AG293 -> 344383.17 | AH28: =cCosts!AH293 -> 244526.46 | ... BE28: =cCosts!BE293 -> 378447.8 | BG28: =SUMIFS($AA28:$BE28,$AA$2:$BE$2,">="&BG$2,$AA$3:$BE$3,"<="&BG$3) -> 0 | BH28: =SUMIFS($AA28:$BE28,$AA$2:$BE$2,">="&BH$2,$AA$3:$BE$3,"<="&BH$3) -> 1468240.1 | BI28: =SUMIFS($AA28:$BE28,$AA$2:$BE$2,">="&BI$2,$AA$3:$BE$3,"<="&BI$3) -> 1257053.7 | BJ28: =SUMIFS($AA28:$BE28,$AA$2:$BE$2,">="&BJ$2,$AA$3:$BE$3,"<="&BJ$3) -> 1392257.4 | BK28: =SUMIFS($AA28:$BE28,$AA$2:$BE$2,">="&BK$2,$AA$3:$BE$3,"<="&BK$3) -> 1685052.3 | BL28: =SUMIFS($AA28:$BE28,$AA$2:$BE$2,">="&BL$2,$AA$3:$BE$3,"<="&BL$3) -> 1958448.7 | BM28: =SUMIFS($AA28:$BE28,$AA$2:$BE$2,">="&BM$2,$AA$3:$BE$3,"<="&BM$3) -> 2169091.7
F29: Lease Costs | G29: =cstNominalUnit -> £ Nominal | I29: =SUM(AA29:BE29) -> 0 | BG29: =SUMIFS($AA29:$BE29,$AA$2:$BE$2,">="&BG$2,$AA$3:$BE$3,"<="&BG$3) -> 0 | BH29: =SUMIFS($AA29:$BE29,$AA$2:$BE$2,">="&BH$2,$AA$3:$BE$3,"<="&BH$3) -> 0 | BI29: =SUMIFS($AA29:$BE29,$AA$2:$BE$2,">="&BI$2,$AA$3:$BE$3,"<="&BI$3) -> 0 | BJ29: =SUMIFS($AA29:$BE29,$AA$2:$BE$2,">="&BJ$2,$AA$3:$BE$3,"<="&BJ$3) -> 0 | BK29: =SUMIFS($AA29:$BE29,$AA$2:$BE$2,">="&BK$2,$AA$3:$BE$3,"<="&BK$3) -> 0 | BL29: =SUMIFS($AA29:$BE29,$AA$2:$BE$2,">="&BL$2,$AA$3:$BE$3,"<="&BL$3) -> 0 | BM29: =SUMIFS($AA29:$BE29,$AA$2:$BE$2,">="&BM$2,$AA$3:$BE$3,"<="&BM$3) -> 0
F30: Build & Maintenance Costs | G30: =cstNominalUnit -> £ Nominal | I30: =SUM(AA30:BE30) -> 4516860.2 | AA30: =cCosts!AA480 -> 3045073 | AB30: =cCosts!AB480 -> 30935.878 | AC30: =cCosts!AC480 -> 31863.954 | AD30: =cCosts!AD480 -> 32819.873 | AE30: =cCosts!AE480 -> 33804.469 | AF30: =cCosts!AF480 -> 34818.603 | AG30: =cCosts!AG480 -> 35863.161 | AH30: =cCosts!AH480 -> 36939.056 | ... BE30: =cCosts!BE480 -> 72902.422 | BG30: =SUMIFS($AA30:$BE30,$AA$2:$BE$2,">="&BG$2,$AA$3:$BE$3,"<="&BG$3) -> 3045073 | BH30: =SUMIFS($AA30:$BE30,$AA$2:$BE$2,">="&BH$2,$AA$3:$BE$3,"<="&BH$3) -> 164242.78 | BI30: =SUMIFS($AA30:$BE30,$AA$2:$BE$2,">="&BI$2,$AA$3:$BE$3,"<="&BI$3) -> 190402.39 | BJ30: =SUMIFS($AA30:$BE30,$AA$2:$BE$2,">="&BJ$2,$AA$3:$BE$3,"<="&BJ$3) -> 220728.56 | BK30: =SUMIFS($AA30:$BE30,$AA$2:$BE$2,">="&BK$2,$AA$3:$BE$3,"<="&BK$3) -> 255884.89 | BL30: =SUMIFS($AA30:$BE30,$AA$2:$BE$2,">="&BL$2,$AA$3:$BE$3,"<="&BL$3) -> 296640.72 | BM30: =SUMIFS($AA30:$BE30,$AA$2:$BE$2,">="&BM$2,$AA$3:$BE$3,"<="&BM$3) -> 343887.9
F32: Lease & Operate | G32: =cstNominalUnit -> £ Nominal | I32: =SUM(AA32:BE32) -> 1.0678602e+08 | AA32: =SUM(AA33:AA38) -> 0 | AB32: =SUM(AB33:AB38) -> 2929889.5 | AC32: =SUM(AC33:AC38) -> 2422668.5 | AD32: =SUM(AD33:AD38) -> 2484320.2 | AE32: =SUM(AE33:AE38) -> 2595837.9 | AF32: =SUM(AF33:AF38) -> 2612385.5 | AG32: =SUM(AG33:AG38) -> 2837092.7 | AH32: =SUM(AH33:AH38) -> 2799844 | ... BE32: =SUM(BE33:BE38) -> 4900086.5 | BG32: =SUMIFS($AA32:$BE32,$AA$2:$BE$2,">="&BG$2,$AA$3:$BE$3,"<="&BG$3) -> 0 | BH32: =SUMIFS($AA32:$BE32,$AA$2:$BE$2,">="&BH$2,$AA$3:$BE$3,"<="&BH$3) -> 13045102 | BI32: =SUMIFS($AA32:$BE32,$AA$2:$BE$2,">="&BI$2,$AA$3:$BE$3,"<="&BI$3) -> 14362620 | BJ32: =SUMIFS($AA32:$BE32,$AA$2:$BE$2,">="&BJ$2,$AA$3:$BE$3,"<="&BJ$3) -> 16228593 | BK32: =SUMIFS($AA32:$BE32,$AA$2:$BE$2,">="&BK$2,$AA$3:$BE$3,"<="&BK$3) -> 18480962 | BL32: =SUMIFS($AA32:$BE32,$AA$2:$BE$2,">="&BL$2,$AA$3:$BE$3,"<="&BL$3) -> 20973024 | BM32: =SUMIFS($AA32:$BE32,$AA$2:$BE$2,">="&BM$2,$AA$3:$BE$3,"<="&BM$3) -> 23695722
F33: Operating Costs | G33: =cstNominalUnit -> £ Nominal | I33: =SUM(AA33:BE33) -> 0 | BG33: =SUMIFS($AA33:$BE33,$AA$2:$BE$2,">="&BG$2,$AA$3:$BE$3,"<="&BG$3) -> 0 | BH33: =SUMIFS($AA33:$BE33,$AA$2:$BE$2,">="&BH$2,$AA$3:$BE$3,"<="&BH$3) -> 0 | BI33: =SUMIFS($AA33:$BE33,$AA$2:$BE$2,">="&BI$2,$AA$3:$BE$3,"<="&BI$3) -> 0 | BJ33: =SUMIFS($AA33:$BE33,$AA$2:$BE$2,">="&BJ$2,$AA$3:$BE$3,"<="&BJ$3) -> 0 | BK33: =SUMIFS($AA33:$BE33,$AA$2:$BE$2,">="&BK$2,$AA$3:$BE$3,"<="&BK$3) -> 0 | BL33: =SUMIFS($AA33:$BE33,$AA$2:$BE$2,">="&BL$2,$AA$3:$BE$3,"<="&BL$3) -> 0 | BM33: =SUMIFS($AA33:$BE33,$AA$2:$BE$2,">="&BM$2,$AA$3:$BE$3,"<="&BM$3) -> 0
F34: Staff Costs | G34: =cstNominalUnit -> £ Nominal | I34: =SUM(AA34:BE34) -> 94472985 | AA34: =cCosts!AA133 -> 0 | AB34: =cCosts!AB133 -> 2151871.7 | AC34: =cCosts!AC133 -> 2205668.5 | AD34: =cCosts!AD133 -> 2260810.2 | AE34: =cCosts!AE133 -> 2317330.5 | AF34: =cCosts!AF133 -> 2375263.7 | AG34: =cCosts!AG133 -> 2434645.3 | AH34: =cCosts!AH133 -> 2495511.5 | ... BE34: =cCosts!BE133 -> 4403606.2 | BG34: =SUMIFS($AA34:$BE34,$AA$2:$BE$2,">="&BG$2,$AA$3:$BE$3,"<="&BG$3) -> 0 | BH34: =SUMIFS($AA34:$BE34,$AA$2:$BE$2,">="&BH$2,$AA$3:$BE$3,"<="&BH$3) -> 11310945 | BI34: =SUMIFS($AA34:$BE34,$AA$2:$BE$2,">="&BI$2,$AA$3:$BE$3,"<="&BI$3) -> 12797296 | BJ34: =SUMIFS($AA34:$BE34,$AA$2:$BE$2,">="&BJ$2,$AA$3:$BE$3,"<="&BJ$3) -> 14478965 | BK34: =SUMIFS($AA34:$BE34,$AA$2:$BE$2,">="&BK$2,$AA$3:$BE$3,"<="&BK$3) -> 16381620 | BL34: =SUMIFS($AA34:$BE34,$AA$2:$BE$2,">="&BL$2,$AA$3:$BE$3,"<="&BL$3) -> 18534300 | BM34: =SUMIFS($AA34:$BE34,$AA$2:$BE$2,">="&BM$2,$AA$3:$BE$3,"<="&BM$3) -> 20969859
F35: Software & Hardware Costs | G35: =cstNominalUnit -> £ Nominal | I35: =SUM(AA35:BE35) -> 9930144 | AA35: =cCosts!AA293 -> 0 | AB35: =cCosts!AB293 -> 727931.17 | AC35: =cCosts!AC293 -> 165410.73 | AD35: =cCosts!AD293 -> 170373.06 | AE35: =cCosts!AE293 -> 223776.35 | AF35: =cCosts!AF293 -> 180748.78 | AG35: =cCosts!AG293 -> 344383.17 | AH35: =cCosts!AH293 -> 244526.46 | ... BE35: =cCosts!BE293 -> 378447.8 | BG35: =SUMIFS($AA35:$BE35,$AA$2:$BE$2,">="&BG$2,$AA$3:$BE$3,"<="&BG$3) -> 0 | BH35: =SUMIFS($AA35:$BE35,$AA$2:$BE$2,">="&BH$2,$AA$3:$BE$3,"<="&BH$3) -> 1468240.1 | BI35: =SUMIFS($AA35:$BE35,$AA$2:$BE$2,">="&BI$2,$AA$3:$BE$3,"<="&BI$3) -> 1257053.7 | BJ35: =SUMIFS($AA35:$BE35,$AA$2:$BE$2,">="&BJ$2,$AA$3:$BE$3,"<="&BJ$3) -> 1392257.4 | BK35: =SUMIFS($AA35:$BE35,$AA$2:$BE$2,">="&BK$2,$AA$3:$BE$3,"<="&BK$3) -> 1685052.3 | BL35: =SUMIFS($AA35:$BE35,$AA$2:$BE$2,">="&BL$2,$AA$3:$BE$3,"<="&BL$3) -> 1958448.7 | BM35: =SUMIFS($AA35:$BE35,$AA$2:$BE$2,">="&BM$2,$AA$3:$BE$3,"<="&BM$3) -> 2169091.7
F36: Lease Costs | G36: =cstNominalUnit -> £ Nominal | I36: =SUM(AA36:BE36) -> 2382893.6 | AA36: =cCosts!AA313 -> 0 | AB36: =cCosts!AB313 -> 50086.659 | AC36: =cCosts!AC313 -> 51589.259 | AD36: =cCosts!AD313 -> 53136.937 | AE36: =cCosts!AE313 -> 54731.045 | AF36: =cCosts!AF313 -> 56372.976 | AG36: =cCosts!AG313 -> 58064.165 | AH36: =cCosts!AH313 -> 59806.09 | ... BE36: =cCosts!BE313 -> 118032.49 | BG36: =SUMIFS($AA36:$BE36,$AA$2:$BE$2,">="&BG$2,$AA$3:$BE$3,"<="&BG$3) -> 0 | BH36: =SUMIFS($AA36:$BE36,$AA$2:$BE$2,">="&BH$2,$AA$3:$BE$3,"<="&BH$3) -> 265916.87 | BI36: =SUMIFS($AA36:$BE36,$AA$2:$BE$2,">="&BI$2,$AA$3:$BE$3,"<="&BI$3) -> 308270.54 | BJ36: =SUMIFS($AA36:$BE36,$AA$2:$BE$2,">="&BJ$2,$AA$3:$BE$3,"<="&BJ$3) -> 357370.04 | BK36: =SUMIFS($AA36:$BE36,$AA$2:$BE$2,">="&BK$2,$AA$3:$BE$3,"<="&BK$3) -> 414289.83 | BL36: =SUMIFS($AA36:$BE36,$AA$2:$BE$2,">="&BL$2,$AA$3:$BE$3,"<="&BL$3) -> 480275.46 | BM36: =SUMIFS($AA36:$BE36,$AA$2:$BE$2,">="&BM$2,$AA$3:$BE$3,"<="&BM$3) -> 556770.88
F37: Build & Maintenance Costs | G37: =cstNominalUnit -> £ Nominal | I37: =SUM(AA37:BE37) -> 0 | BG37: =SUMIFS($AA37:$BE37,$AA$2:$BE$2,">="&BG$2,$AA$3:$BE$3,"<="&BG$3) -> 0 | BH37: =SUMIFS($AA37:$BE37,$AA$2:$BE$2,">="&BH$2,$AA$3:$BE$3,"<="&BH$3) -> 0 | BI37: =SUMIFS($AA37:$BE37,$AA$2:$BE$2,">="&BI$2,$AA$3:$BE$3,"<="&BI$3) -> 0 | BJ37: =SUMIFS($AA37:$BE37,$AA$2:$BE$2,">="&BJ$2,$AA$3:$BE$3,"<="&BJ$3) -> 0 | BK37: =SUMIFS($AA37:$BE37,$AA$2:$BE$2,">="&BK$2,$AA$3:$BE$3,"<="&BK$3) -> 0 | BL37: =SUMIFS($AA37:$BE37,$AA$2:$BE$2,">="&BL$2,$AA$3:$BE$3,"<="&BL$3) -> 0 | BM37: =SUMIFS($AA37:$BE37,$AA$2:$BE$2,">="&BM$2,$AA$3:$BE$3,"<="&BM$3) -> 0
F39: Outsource | G39: =cstNominalUnit -> £ Nominal | I39: =SUM(AA39:BE39) -> 1.3230723e+08 | AA39: =SUM(AA40:AA45) -> 0 | AB39: =SUM(AB40:AB45) -> 2781000 | AC39: =SUM(AC40:AC45) -> 2864430 | AD39: =SUM(AD40:AD45) -> 2950362.9 | AE39: =SUM(AE40:AE45) -> 3038873.8 | AF39: =SUM(AF40:AF45) -> 3130040 | AG39: =SUM(AG40:AG45) -> 3223941.2 | AH39: =SUM(AH40:AH45) -> 3320659.4 | ... BE39: =SUM(BE40:BE45) -> 6553608.7 | BG39: =SUMIFS($AA39:$BE39,$AA$2:$BE$2,">="&BG$2,$AA$3:$BE$3,"<="&BG$3) -> 0 | BH39: =SUMIFS($AA39:$BE39,$AA$2:$BE$2,">="&BH$2,$AA$3:$BE$3,"<="&BH$3) -> 14764707 | BI39: =SUMIFS($AA39:$BE39,$AA$2:$BE$2,">="&BI$2,$AA$3:$BE$3,"<="&BI$3) -> 17116342 | BJ39: =SUMIFS($AA39:$BE39,$AA$2:$BE$2,">="&BJ$2,$AA$3:$BE$3,"<="&BJ$3) -> 19842531 | BK39: =SUMIFS($AA39:$BE39,$AA$2:$BE$2,">="&BK$2,$AA$3:$BE$3,"<="&BK$3) -> 23002932 | BL39: =SUMIFS($AA39:$BE39,$AA$2:$BE$2,">="&BL$2,$AA$3:$BE$3,"<="&BL$3) -> 26666703 | BM39: =SUMIFS($AA39:$BE39,$AA$2:$BE$2,">="&BM$2,$AA$3:$BE$3,"<="&BM$3) -> 30914017
F40: Operating Costs | G40: =cstNominalUnit -> £ Nominal | I40: =SUM(AA40:BE40) -> 1.3230723e+08 | AA40: =cCosts!AA55 -> 0 | AB40: =cCosts!AB55 -> 2781000 | AC40: =cCosts!AC55 -> 2864430 | AD40: =cCosts!AD55 -> 2950362.9 | AE40: =cCosts!AE55 -> 3038873.8 | AF40: =cCosts!AF55 -> 3130040 | AG40: =cCosts!AG55 -> 3223941.2 | AH40: =cCosts!AH55 -> 3320659.4 | ... BE40: =cCosts!BE55 -> 6553608.7 | BG40: =SUMIFS($AA40:$BE40,$AA$2:$BE$2,">="&BG$2,$AA$3:$BE$3,"<="&BG$3) -> 0 | BH40: =SUMIFS($AA40:$BE40,$AA$2:$BE$2,">="&BH$2,$AA$3:$BE$3,"<="&BH$3) -> 14764707 | BI40: =SUMIFS($AA40:$BE40,$AA$2:$BE$2,">="&BI$2,$AA$3:$BE$3,"<="&BI$3) -> 17116342 | BJ40: =SUMIFS($AA40:$BE40,$AA$2:$BE$2,">="&BJ$2,$AA$3:$BE$3,"<="&BJ$3) -> 19842531 | BK40: =SUMIFS($AA40:$BE40,$AA$2:$BE$2,">="&BK$2,$AA$3:$BE$3,"<="&BK$3) -> 23002932 | BL40: =SUMIFS($AA40:$BE40,$AA$2:$BE$2,">="&BL$2,$AA$3:$BE$3,"<="&BL$3) -> 26666703 | BM40: =SUMIFS($AA40:$BE40,$AA$2:$BE$2,">="&BM$2,$AA$3:$BE$3,"<="&BM$3) -> 30914017
F41: Staff Costs | G41: =cstNominalUnit -> £ Nominal | I41: =SUM(AA41:BE41) -> 0 | BG41: =SUMIFS($AA41:$BE41,$AA$2:$BE$2,">="&BG$2,$AA$3:$BE$3,"<="&BG$3) -> 0 | BH41: =SUMIFS($AA41:$BE41,$AA$2:$BE$2,">="&BH$2,$AA$3:$BE$3,"<="&BH$3) -> 0 | BI41: =SUMIFS($AA41:$BE41,$AA$2:$BE$2,">="&BI$2,$AA$3:$BE$3,"<="&BI$3) -> 0 | BJ41: =SUMIFS($AA41:$BE41,$AA$2:$BE$2,">="&BJ$2,$AA$3:$BE$3,"<="&BJ$3) -> 0 | BK41: =SUMIFS($AA41:$BE41,$AA$2:$BE$2,">="&BK$2,$AA$3:$BE$3,"<="&BK$3) -> 0 | BL41: =SUMIFS($AA41:$BE41,$AA$2:$BE$2,">="&BL$2,$AA$3:$BE$3,"<="&BL$3) -> 0 | BM41: =SUMIFS($AA41:$BE41,$AA$2:$BE$2,">="&BM$2,$AA$3:$BE$3,"<="&BM$3) -> 0
F42: Software & Hardware Costs | G42: =cstNominalUnit -> £ Nominal | I42: =SUM(AA42:BE42) -> 0 | BG42: =SUMIFS($AA42:$BE42,$AA$2:$BE$2,">="&BG$2,$AA$3:$BE$3,"<="&BG$3) -> 0 | BH42: =SUMIFS($AA42:$BE42,$AA$2:$BE$2,">="&BH$2,$AA$3:$BE$3,"<="&BH$3) -> 0 | BI42: =SUMIFS($AA42:$BE42,$AA$2:$BE$2,">="&BI$2,$AA$3:$BE$3,"<="&BI$3) -> 0 | BJ42: =SUMIFS($AA42:$BE42,$AA$2:$BE$2,">="&BJ$2,$AA$3:$BE$3,"<="&BJ$3) -> 0 | BK42: =SUMIFS($AA42:$BE42,$AA$2:$BE$2,">="&BK$2,$AA$3:$BE$3,"<="&BK$3) -> 0 | BL42: =SUMIFS($AA42:$BE42,$AA$2:$BE$2,">="&BL$2,$AA$3:$BE$3,"<="&BL$3) -> 0 | BM42: =SUMIFS($AA42:$BE42,$AA$2:$BE$2,">="&BM$2,$AA$3:$BE$3,"<="&BM$3) -> 0
F43: Lease Costs | G43: =cstNominalUnit -> £ Nominal | I43: =SUM(AA43:BE43) -> 0 | BG43: =SUMIFS($AA43:$BE43,$AA$2:$BE$2,">="&BG$2,$AA$3:$BE$3,"<="&BG$3) -> 0 | BH43: =SUMIFS($AA43:$BE43,$AA$2:$BE$2,">="&BH$2,$AA$3:$BE$3,"<="&BH$3) -> 0 | BI43: =SUMIFS($AA43:$BE43,$AA$2:$BE$2,">="&BI$2,$AA$3:$BE$3,"<="&BI$3) -> 0 | BJ43: =SUMIFS($AA43:$BE43,$AA$2:$BE$2,">="&BJ$2,$AA$3:$BE$3,"<="&BJ$3) -> 0 | BK43: =SUMIFS($AA43:$BE43,$AA$2:$BE$2,">="&BK$2,$AA$3:$BE$3,"<="&BK$3) -> 0 | BL43: =SUMIFS($AA43:$BE43,$AA$2:$BE$2,">="&BL$2,$AA$3:$BE$3,"<="&BL$3) -> 0 | BM43: =SUMIFS($AA43:$BE43,$AA$2:$BE$2,">="&BM$2,$AA$3:$BE$3,"<="&BM$3) -> 0
F44: Build & Maintenance Costs | G44: =cstNominalUnit -> £ Nominal | I44: =SUM(AA44:BE44) -> 0 | BG44: =SUMIFS($AA44:$BE44,$AA$2:$BE$2,">="&BG$2,$AA$3:$BE$3,"<="&BG$3) -> 0 | BH44: =SUMIFS($AA44:$BE44,$AA$2:$BE$2,">="&BH$2,$AA$3:$BE$3,"<="&BH$3) -> 0 | BI44: =SUMIFS($AA44:$BE44,$AA$2:$BE$2,">="&BI$2,$AA$3:$BE$3,"<="&BI$3) -> 0 | BJ44: =SUMIFS($AA44:$BE44,$AA$2:$BE$2,">="&BJ$2,$AA$3:$BE$3,"<="&BJ$3) -> 0 | BK44: =SUMIFS($AA44:$BE44,$AA$2:$BE$2,">="&BK$2,$AA$3:$BE$3,"<="&BK$3) -> 0 | BL44: =SUMIFS($AA44:$BE44,$AA$2:$BE$2,">="&BL$2,$AA$3:$BE$3,"<="&BL$3) -> 0 | BM44: =SUMIFS($AA44:$BE44,$AA$2:$BE$2,">="&BM$2,$AA$3:$BE$3,"<="&BM$3) -> 0
E46: 2.2 | F46: Cumulative Costs
F48: Options
F50: Build & Operate | G50: =cstNominalUnit -> £ Nominal | AA50: =SUM(AA51:AA56) -> 3045073 | AB50: =SUM(AB51:AB56) -> 5955811.8 | AC50: =SUM(AC51:AC56) -> 8358754.9 | AD50: =SUM(AD51:AD56) -> 10822758 | AE50: =SUM(AE51:AE56) -> 13397669 | AF50: =SUM(AF51:AF56) -> 15988500 | AG50: =SUM(AG51:AG56) -> 18803392 | AH50: =SUM(AH51:AH56) -> 21580369 | ... BE50: =SUM(BE51:BE56) -> 1.0891999e+08 | BG50: =SUMIFS($AA50:$BE50,$AA$3:$BE$3,BG$3) -> 3045073 | BH50: =SUMIFS($AA50:$BE50,$AA$3:$BE$3,BH$3) -> 15988500 | BI50: =SUMIFS($AA50:$BE50,$AA$3:$BE$3,BI$3) -> 30233252 | BJ50: =SUMIFS($AA50:$BE50,$AA$3:$BE$3,BJ$3) -> 46325204 | BK50: =SUMIFS($AA50:$BE50,$AA$3:$BE$3,BK$3) -> 64647761 | BL50: =SUMIFS($AA50:$BE50,$AA$3:$BE$3,BL$3) -> 85437150 | BM50: =SUMIFS($AA50:$BE50,$AA$3:$BE$3,BM$3) -> 1.0891999e+08
F51: Operating Costs | G51: =cstNominalUnit -> £ Nominal | AA51: =Z51+AA26 -> 0 | AB51: =AA51+AB26 -> 0 | AC51: =AB51+AC26 -> 0 | AD51: =AC51+AD26 -> 0 | AE51: =AD51+AE26 -> 0 | AF51: =AE51+AF26 -> 0 | AG51: =AF51+AG26 -> 0 | AH51: =AG51+AH26 -> 0 | ... BE51: =BD51+BE26 -> 0 | BG51: =SUMIFS($AA51:$BE51,$AA$3:$BE$3,BG$3) -> 0 | BH51: =SUMIFS($AA51:$BE51,$AA$3:$BE$3,BH$3) -> 0 | BI51: =SUMIFS($AA51:$BE51,$AA$3:$BE$3,BI$3) -> 0 | BJ51: =SUMIFS($AA51:$BE51,$AA$3:$BE$3,BJ$3) -> 0 | BK51: =SUMIFS($AA51:$BE51,$AA$3:$BE$3,BK$3) -> 0 | BL51: =SUMIFS($AA51:$BE51,$AA$3:$BE$3,BL$3) -> 0 | BM51: =SUMIFS($AA51:$BE51,$AA$3:$BE$3,BM$3) -> 0
F52: Staff Costs | G52: =cstNominalUnit -> £ Nominal | AA52: =Z52+AA27 -> 0 | AB52: =AA52+AB27 -> 2151871.7 | AC52: =AB52+AC27 -> 4357540.2 | AD52: =AC52+AD27 -> 6618350.4 | AE52: =AD52+AE27 -> 8935680.9 | AF52: =AE52+AF27 -> 11310945 | AG52: =AF52+AG27 -> 13745590 | AH52: =AG52+AH27 -> 16241101 | ... BE52: =BD52+BE27 -> 94472985 | BG52: =SUMIFS($AA52:$BE52,$AA$3:$BE$3,BG$3) -> 0 | BH52: =SUMIFS($AA52:$BE52,$AA$3:$BE$3,BH$3) -> 11310945 | BI52: =SUMIFS($AA52:$BE52,$AA$3:$BE$3,BI$3) -> 24108240 | BJ52: =SUMIFS($AA52:$BE52,$AA$3:$BE$3,BJ$3) -> 38587206 | BK52: =SUMIFS($AA52:$BE52,$AA$3:$BE$3,BK$3) -> 54968826 | BL52: =SUMIFS($AA52:$BE52,$AA$3:$BE$3,BL$3) -> 73503126 | BM52: =SUMIFS($AA52:$BE52,$AA$3:$BE$3,BM$3) -> 94472985
F53: Software & Hardware Costs | G53: =cstNominalUnit -> £ Nominal | AA53: =Z53+AA28 -> 0 | AB53: =AA53+AB28 -> 727931.17 | AC53: =AB53+AC28 -> 893341.9 | AD53: =AC53+AD28 -> 1063715 | AE53: =AD53+AE28 -> 1287491.3 | AF53: =AE53+AF28 -> 1468240.1 | AG53: =AF53+AG28 -> 1812623.2 | AH53: =AG53+AH28 -> 2057149.7 | ... BE53: =BD53+BE28 -> 9930144 | BG53: =SUMIFS($AA53:$BE53,$AA$3:$BE$3,BG$3) -> 0 | BH53: =SUMIFS($AA53:$BE53,$AA$3:$BE$3,BH$3) -> 1468240.1 | BI53: =SUMIFS($AA53:$BE53,$AA$3:$BE$3,BI$3) -> 2725293.8 | BJ53: =SUMIFS($AA53:$BE53,$AA$3:$BE$3,BJ$3) -> 4117551.2 | BK53: =SUMIFS($AA53:$BE53,$AA$3:$BE$3,BK$3) -> 5802603.5 | BL53: =SUMIFS($AA53:$BE53,$AA$3:$BE$3,BL$3) -> 7761052.2 | BM53: =SUMIFS($AA53:$BE53,$AA$3:$BE$3,BM$3) -> 9930144
F54: Lease Costs | G54: =cstNominalUnit -> £ Nominal | AA54: =Z54+AA29 -> 0 | AB54: =AA54+AB29 -> 0 | AC54: =AB54+AC29 -> 0 | AD54: =AC54+AD29 -> 0 | AE54: =AD54+AE29 -> 0 | AF54: =AE54+AF29 -> 0 | AG54: =AF54+AG29 -> 0 | AH54: =AG54+AH29 -> 0 | ... BE54: =BD54+BE29 -> 0 | BG54: =SUMIFS($AA54:$BE54,$AA$3:$BE$3,BG$3) -> 0 | BH54: =SUMIFS($AA54:$BE54,$AA$3:$BE$3,BH$3) -> 0 | BI54: =SUMIFS($AA54:$BE54,$AA$3:$BE$3,BI$3) -> 0 | BJ54: =SUMIFS($AA54:$BE54,$AA$3:$BE$3,BJ$3) -> 0 | BK54: =SUMIFS($AA54:$BE54,$AA$3:$BE$3,BK$3) -> 0 | BL54: =SUMIFS($AA54:$BE54,$AA$3:$BE$3,BL$3) -> 0 | BM54: =SUMIFS($AA54:$BE54,$AA$3:$BE$3,BM$3) -> 0
F55: Build & Maintenance Costs | G55: =cstNominalUnit -> £ Nominal | AA55: =Z55+AA30 -> 3045073 | AB55: =AA55+AB30 -> 3076008.9 | AC55: =AB55+AC30 -> 3107872.8 | AD55: =AC55+AD30 -> 3140692.7 | AE55: =AD55+AE30 -> 3174497.2 | AF55: =AE55+AF30 -> 3209315.8 | AG55: =AF55+AG30 -> 3245178.9 | AH55: =AG55+AH30 -> 3282118 | ... BE55: =BD55+BE30 -> 4516860.2 | BG55: =SUMIFS($AA55:$BE55,$AA$3:$BE$3,BG$3) -> 3045073 | BH55: =SUMIFS($AA55:$BE55,$AA$3:$BE$3,BH$3) -> 3209315.8 | BI55: =SUMIFS($AA55:$BE55,$AA$3:$BE$3,BI$3) -> 3399718.2 | BJ55: =SUMIFS($AA55:$BE55,$AA$3:$BE$3,BJ$3) -> 3620446.7 | BK55: =SUMIFS($AA55:$BE55,$AA$3:$BE$3,BK$3) -> 3876331.6 | BL55: =SUMIFS($AA55:$BE55,$AA$3:$BE$3,BL$3) -> 4172972.3 | BM55: =SUMIFS($AA55:$BE55,$AA$3:$BE$3,BM$3) -> 4516860.2
F57: Lease & Operate | G57: =cstNominalUnit -> £ Nominal | AA57: =SUM(AA58:AA63) -> 0 | AB57: =SUM(AB58:AB63) -> 2929889.5 | AC57: =SUM(AC58:AC63) -> 5352558 | AD57: =SUM(AD58:AD63) -> 7836878.2 | AE57: =SUM(AE58:AE63) -> 10432716 | AF57: =SUM(AF58:AF63) -> 13045102 | AG57: =SUM(AG58:AG63) -> 15882194 | AH57: =SUM(AH58:AH63) -> 18682038 | ... BE57: =SUM(BE58:BE63) -> 1.0678602e+08 | BG57: =SUMIFS($AA57:$BE57,$AA$3:$BE$3,BG$3) -> 0 | BH57: =SUMIFS($AA57:$BE57,$AA$3:$BE$3,BH$3) -> 13045102 | BI57: =SUMIFS($AA57:$BE57,$AA$3:$BE$3,BI$3) -> 27407721 | BJ57: =SUMIFS($AA57:$BE57,$AA$3:$BE$3,BJ$3) -> 43636314 | BK57: =SUMIFS($AA57:$BE57,$AA$3:$BE$3,BK$3) -> 62117277 | BL57: =SUMIFS($AA57:$BE57,$AA$3:$BE$3,BL$3) -> 83090301 | BM57: =SUMIFS($AA57:$BE57,$AA$3:$BE$3,BM$3) -> 1.0678602e+08
F58: Operating Costs | G58: =cstNominalUnit -> £ Nominal | AA58: =Z58+AA33 -> 0 | AB58: =AA58+AB33 -> 0 | AC58: =AB58+AC33 -> 0 | AD58: =AC58+AD33 -> 0 | AE58: =AD58+AE33 -> 0 | AF58: =AE58+AF33 -> 0 | AG58: =AF58+AG33 -> 0 | AH58: =AG58+AH33 -> 0 | ... BE58: =BD58+BE33 -> 0 | BG58: =SUMIFS($AA58:$BE58,$AA$3:$BE$3,BG$3) -> 0 | BH58: =SUMIFS($AA58:$BE58,$AA$3:$BE$3,BH$3) -> 0 | BI58: =SUMIFS($AA58:$BE58,$AA$3:$BE$3,BI$3) -> 0 | BJ58: =SUMIFS($AA58:$BE58,$AA$3:$BE$3,BJ$3) -> 0 | BK58: =SUMIFS($AA58:$BE58,$AA$3:$BE$3,BK$3) -> 0 | BL58: =SUMIFS($AA58:$BE58,$AA$3:$BE$3,BL$3) -> 0 | BM58: =SUMIFS($AA58:$BE58,$AA$3:$BE$3,BM$3) -> 0
F59: Staff Costs | G59: =cstNominalUnit -> £ Nominal | AA59: =Z59+AA34 -> 0 | AB59: =AA59+AB34 -> 2151871.7 | AC59: =AB59+AC34 -> 4357540.2 | AD59: =AC59+AD34 -> 6618350.4 | AE59: =AD59+AE34 -> 8935680.9 | AF59: =AE59+AF34 -> 11310945 | AG59: =AF59+AG34 -> 13745590 | AH59: =AG59+AH34 -> 16241101 | ... BE59: =BD59+BE34 -> 94472985 | BG59: =SUMIFS($AA59:$BE59,$AA$3:$BE$3,BG$3) -> 0 | BH59: =SUMIFS($AA59:$BE59,$AA$3:$BE$3,BH$3) -> 11310945 | BI59: =SUMIFS($AA59:$BE59,$AA$3:$BE$3,BI$3) -> 24108240 | BJ59: =SUMIFS($AA59:$BE59,$AA$3:$BE$3,BJ$3) -> 38587206 | BK59: =SUMIFS($AA59:$BE59,$AA$3:$BE$3,BK$3) -> 54968826 | BL59: =SUMIFS($AA59:$BE59,$AA$3:$BE$3,BL$3) -> 73503126 | BM59: =SUMIFS($AA59:$BE59,$AA$3:$BE$3,BM$3) -> 94472985
F60: Software & Hardware Costs | G60: =cstNominalUnit -> £ Nominal | AA60: =Z60+AA35 -> 0 | AB60: =AA60+AB35 -> 727931.17 | AC60: =AB60+AC35 -> 893341.9 | AD60: =AC60+AD35 -> 1063715 | AE60: =AD60+AE35 -> 1287491.3 | AF60: =AE60+AF35 -> 1468240.1 | AG60: =AF60+AG35 -> 1812623.2 | AH60: =AG60+AH35 -> 2057149.7 | ... BE60: =BD60+BE35 -> 9930144 | BG60: =SUMIFS($AA60:$BE60,$AA$3:$BE$3,BG$3) -> 0 | BH60: =SUMIFS($AA60:$BE60,$AA$3:$BE$3,BH$3) -> 1468240.1 | BI60: =SUMIFS($AA60:$BE60,$AA$3:$BE$3,BI$3) -> 2725293.8 | BJ60: =SUMIFS($AA60:$BE60,$AA$3:$BE$3,BJ$3) -> 4117551.2 | BK60: =SUMIFS($AA60:$BE60,$AA$3:$BE$3,BK$3) -> 5802603.5 | BL60: =SUMIFS($AA60:$BE60,$AA$3:$BE$3,BL$3) -> 7761052.2 | BM60: =SUMIFS($AA60:$BE60,$AA$3:$BE$3,BM$3) -> 9930144
F61: Lease Costs | G61: =cstNominalUnit -> £ Nominal | AA61: =Z61+AA36 -> 0 | AB61: =AA61+AB36 -> 50086.659 | AC61: =AB61+AC36 -> 101675.92 | AD61: =AC61+AD36 -> 154812.85 | AE61: =AD61+AE36 -> 209543.9 | AF61: =AE61+AF36 -> 265916.87 | AG61: =AF61+AG36 -> 323981.04 | AH61: =AG61+AH36 -> 383787.13 | ... BE61: =BD61+BE36 -> 2382893.6 | BG61: =SUMIFS($AA61:$BE61,$AA$3:$BE$3,BG$3) -> 0 | BH61: =SUMIFS($AA61:$BE61,$AA$3:$BE$3,BH$3) -> 265916.87 | BI61: =SUMIFS($AA61:$BE61,$AA$3:$BE$3,BI$3) -> 574187.41 | BJ61: =SUMIFS($AA61:$BE61,$AA$3:$BE$3,BJ$3) -> 931557.46 | BK61: =SUMIFS($AA61:$BE61,$AA$3:$BE$3,BK$3) -> 1345847.3 | BL61: =SUMIFS($AA61:$BE61,$AA$3:$BE$3,BL$3) -> 1826122.7 | BM61: =SUMIFS($AA61:$BE61,$AA$3:$BE$3,BM$3) -> 2382893.6
F62: Build & Maintenance Costs | G62: =cstNominalUnit -> £ Nominal | AA62: =Z62+AA37 -> 0 | AB62: =AA62+AB37 -> 0 | AC62: =AB62+AC37 -> 0 | AD62: =AC62+AD37 -> 0 | AE62: =AD62+AE37 -> 0 | AF62: =AE62+AF37 -> 0 | AG62: =AF62+AG37 -> 0 | AH62: =AG62+AH37 -> 0 | ... BE62: =BD62+BE37 -> 0 | BG62: =SUMIFS($AA62:$BE62,$AA$3:$BE$3,BG$3) -> 0 | BH62: =SUMIFS($AA62:$BE62,$AA$3:$BE$3,BH$3) -> 0 | BI62: =SUMIFS($AA62:$BE62,$AA$3:$BE$3,BI$3) -> 0 | BJ62: =SUMIFS($AA62:$BE62,$AA$3:$BE$3,BJ$3) -> 0 | BK62: =SUMIFS($AA62:$BE62,$AA$3:$BE$3,BK$3) -> 0 | BL62: =SUMIFS($AA62:$BE62,$AA$3:$BE$3,BL$3) -> 0 | BM62: =SUMIFS($AA62:$BE62,$AA$3:$BE$3,BM$3) -> 0
F64: Outsource | G64: =cstNominalUnit -> £ Nominal | AA64: =SUM(AA65:AA70) -> 0 | AB64: =SUM(AB65:AB70) -> 2781000 | AC64: =SUM(AC65:AC70) -> 5645430 | AD64: =SUM(AD65:AD70) -> 8595792.9 | AE64: =SUM(AE65:AE70) -> 11634667 | AF64: =SUM(AF65:AF70) -> 14764707 | AG64: =SUM(AG65:AG70) -> 17988648 | AH64: =SUM(AH65:AH70) -> 21309307 | ... BE64: =SUM(BE65:BE70) -> 1.3230723e+08 | BG64: =SUMIFS($AA64:$BE64,$AA$3:$BE$3,BG$3) -> 0 | BH64: =SUMIFS($AA64:$BE64,$AA$3:$BE$3,BH$3) -> 14764707 | BI64: =SUMIFS($AA64:$BE64,$AA$3:$BE$3,BI$3) -> 31881048 | BJ64: =SUMIFS($AA64:$BE64,$AA$3:$BE$3,BJ$3) -> 51723580 | BK64: =SUMIFS($AA64:$BE64,$AA$3:$BE$3,BK$3) -> 74726511 | BL64: =SUMIFS($AA64:$BE64,$AA$3:$BE$3,BL$3) -> 1.0139321e+08 | BM64: =SUMIFS($AA64:$BE64,$AA$3:$BE$3,BM$3) -> 1.3230723e+08
F65: Operating Costs | G65: =cstNominalUnit -> £ Nominal | AA65: =Z65+AA40 -> 0 | AB65: =AA65+AB40 -> 2781000 | AC65: =AB65+AC40 -> 5645430 | AD65: =AC65+AD40 -> 8595792.9 | AE65: =AD65+AE40 -> 11634667 | AF65: =AE65+AF40 -> 14764707 | AG65: =AF65+AG40 -> 17988648 | AH65: =AG65+AH40 -> 21309307 | ... BE65: =BD65+BE40 -> 1.3230723e+08 | BG65: =SUMIFS($AA65:$BE65,$AA$3:$BE$3,BG$3) -> 0 | BH65: =SUMIFS($AA65:$BE65,$AA$3:$BE$3,BH$3) -> 14764707 | BI65: =SUMIFS($AA65:$BE65,$AA$3:$BE$3,BI$3) -> 31881048 | BJ65: =SUMIFS($AA65:$BE65,$AA$3:$BE$3,BJ$3) -> 51723580 | BK65: =SUMIFS($AA65:$BE65,$AA$3:$BE$3,BK$3) -> 74726511 | BL65: =SUMIFS($AA65:$BE65,$AA$3:$BE$3,BL$3) -> 1.0139321e+08 | BM65: =SUMIFS($AA65:$BE65,$AA$3:$BE$3,BM$3) -> 1.3230723e+08
F66: Staff Costs | G66: =cstNominalUnit -> £ Nominal | AA66: =Z66+AA41 -> 0 | AB66: =AA66+AB41 -> 0 | AC66: =AB66+AC41 -> 0 | AD66: =AC66+AD41 -> 0 | AE66: =AD66+AE41 -> 0 | AF66: =AE66+AF41 -> 0 | AG66: =AF66+AG41 -> 0 | AH66: =AG66+AH41 -> 0 | ... BE66: =BD66+BE41 -> 0 | BG66: =SUMIFS($AA66:$BE66,$AA$3:$BE$3,BG$3) -> 0 | BH66: =SUMIFS($AA66:$BE66,$AA$3:$BE$3,BH$3) -> 0 | BI66: =SUMIFS($AA66:$BE66,$AA$3:$BE$3,BI$3) -> 0 | BJ66: =SUMIFS($AA66:$BE66,$AA$3:$BE$3,BJ$3) -> 0 | BK66: =SUMIFS($AA66:$BE66,$AA$3:$BE$3,BK$3) -> 0 | BL66: =SUMIFS($AA66:$BE66,$AA$3:$BE$3,BL$3) -> 0 | BM66: =SUMIFS($AA66:$BE66,$AA$3:$BE$3,BM$3) -> 0
F67: Software & Hardware Costs | G67: =cstNominalUnit -> £ Nominal | AA67: =Z67+AA42 -> 0 | AB67: =AA67+AB42 -> 0 | AC67: =AB67+AC42 -> 0 | AD67: =AC67+AD42 -> 0 | AE67: =AD67+AE42 -> 0 | AF67: =AE67+AF42 -> 0 | AG67: =AF67+AG42 -> 0 | AH67: =AG67+AH42 -> 0 | ... BE67: =BD67+BE42 -> 0 | BG67: =SUMIFS($AA67:$BE67,$AA$3:$BE$3,BG$3) -> 0 | BH67: =SUMIFS($AA67:$BE67,$AA$3:$BE$3,BH$3) -> 0 | BI67: =SUMIFS($AA67:$BE67,$AA$3:$BE$3,BI$3) -> 0 | BJ67: =SUMIFS($AA67:$BE67,$AA$3:$BE$3,BJ$3) -> 0 | BK67: =SUMIFS($AA67:$BE67,$AA$3:$BE$3,BK$3) -> 0 | BL67: =SUMIFS($AA67:$BE67,$AA$3:$BE$3,BL$3) -> 0 | BM67: =SUMIFS($AA67:$BE67,$AA$3:$BE$3,BM$3) -> 0
F68: Lease Costs | G68: =cstNominalUnit -> £ Nominal | AA68: =Z68+AA43 -> 0 | AB68: =AA68+AB43 -> 0 | AC68: =AB68+AC43 -> 0 | AD68: =AC68+AD43 -> 0 | AE68: =AD68+AE43 -> 0 | AF68: =AE68+AF43 -> 0 | AG68: =AF68+AG43 -> 0 | AH68: =AG68+AH43 -> 0 | ... BE68: =BD68+BE43 -> 0 | BG68: =SUMIFS($AA68:$BE68,$AA$3:$BE$3,BG$3) -> 0 | BH68: =SUMIFS($AA68:$BE68,$AA$3:$BE$3,BH$3) -> 0 | BI68: =SUMIFS($AA68:$BE68,$AA$3:$BE$3,BI$3) -> 0 | BJ68: =SUMIFS($AA68:$BE68,$AA$3:$BE$3,BJ$3) -> 0 | BK68: =SUMIFS($AA68:$BE68,$AA$3:$BE$3,BK$3) -> 0 | BL68: =SUMIFS($AA68:$BE68,$AA$3:$BE$3,BL$3) -> 0 | BM68: =SUMIFS($AA68:$BE68,$AA$3:$BE$3,BM$3) -> 0
F69: Build & Maintenance Costs | G69: =cstNominalUnit -> £ Nominal | AA69: =Z69+AA44 -> 0 | AB69: =AA69+AB44 -> 0 | AC69: =AB69+AC44 -> 0 | AD69: =AC69+AD44 -> 0 | AE69: =AD69+AE44 -> 0 | AF69: =AE69+AF44 -> 0 | AG69: =AF69+AG44 -> 0 | AH69: =AG69+AH44 -> 0 | ... BE69: =BD69+BE44 -> 0 | BG69: =SUMIFS($AA69:$BE69,$AA$3:$BE$3,BG$3) -> 0 | BH69: =SUMIFS($AA69:$BE69,$AA$3:$BE$3,BH$3) -> 0 | BI69: =SUMIFS($AA69:$BE69,$AA$3:$BE$3,BI$3) -> 0 | BJ69: =SUMIFS($AA69:$BE69,$AA$3:$BE$3,BJ$3) -> 0 | BK69: =SUMIFS($AA69:$BE69,$AA$3:$BE$3,BK$3) -> 0 | BL69: =SUMIFS($AA69:$BE69,$AA$3:$BE$3,BL$3) -> 0 | BM69: =SUMIFS($AA69:$BE69,$AA$3:$BE$3,BM$3) -> 0
E71: 2.3 | F71: Average Cost per Call Hour
F73: Call Ups
F75: Call Volume | G75: =cstHours -> Hrs | I75: =cVolumetrics!Z39 -> 2700000
F77: Options
F79: Build & Operate | G79: =cstNominalUnit -> £ Nominal | I79: =I25/$I$75 -> 40.340737
F81: Lease & Operate | G81: =cstNominalUnit -> £ Nominal | I81: =I32/$I$75 -> 39.550379
F83: Outsource | G83: =cstNominalUnit -> £ Nominal | I83: =I39/$I$75 -> 49.002678
D85: 3 | E85: Costs (Real)
E87: 3.1 | F87: In year costs
F89: Real Costs | I89: 31 Yr Total
F91: Build & Operate | G91: =cstRealUnit -> £ Real | I91: =SUM(AA91:BE91) -> 80228511 | AA91: =SUM(AA92:AA97) -> 3045073 | AB91: =SUM(AB92:AB97) -> 2873384.7 | AC91: =SUM(AC92:AC97) -> 2332454.1 | AD91: =SUM(AD92:AD97) -> 2347127.5 | AE91: =SUM(AE92:AE97) -> 2407041.1 | AF91: =SUM(AF92:AF97) -> 2374434.3 | AG91: =SUM(AG92:AG97) -> 2529196.5 | AH91: =SUM(AH92:AH97) -> 2446205.8 | ... BE91: =SUM(BE92:BE97) -> 2712077.5 | BG91: =SUMIFS($AA91:$BE91,$AA$2:$BE$2,">="&BG$2,$AA$3:$BE$3,"<="&BG$3) -> 3045073 | BH91: =SUMIFS($AA91:$BE91,$AA$2:$BE$2,">="&BH$2,$AA$3:$BE$3,"<="&BH$3) -> 12334442 | BI91: =SUMIFS($AA91:$BE91,$AA$2:$BE$2,">="&BI$2,$AA$3:$BE$3,"<="&BI$3) -> 12299226 | BJ91: =SUMIFS($AA91:$BE91,$AA$2:$BE$2,">="&BJ$2,$AA$3:$BE$3,"<="&BJ$3) -> 12585511 | BK91: =SUMIFS($AA91:$BE91,$AA$2:$BE$2,">="&BK$2,$AA$3:$BE$3,"<="&BK$3) -> 12980246 | BL91: =SUMIFS($AA91:$BE91,$AA$2:$BE$2,">="&BL$2,$AA$3:$BE$3,"<="&BL$3) -> 13337444 | BM91: =SUMIFS($AA91:$BE91,$AA$2:$BE$2,">="&BM$2,$AA$3:$BE$3,"<="&BM$3) -> 13646569
F92: Operating Costs | G92: =cstRealUnit -> £ Real | I92: =SUM(AA92:BE92) -> 0 | AA92: =AA26*AA$16 -> 0 | AB92: =AB26*AB$16 -> 0 | AC92: =AC26*AC$16 -> 0 | AD92: =AD26*AD$16 -> 0 | AE92: =AE26*AE$16 -> 0 | AF92: =AF26*AF$16 -> 0 | AG92: =AG26*AG$16 -> 0 | AH92: =AH26*AH$16 -> 0 | ... BE92: =BE26*BE$16 -> 0 | BG92: =SUMIFS($AA92:$BE92,$AA$2:$BE$2,">="&BG$2,$AA$3:$BE$3,"<="&BG$3) -> 0 | BH92: =SUMIFS($AA92:$BE92,$AA$2:$BE$2,">="&BH$2,$AA$3:$BE$3,"<="&BH$3) -> 0 | BI92: =SUMIFS($AA92:$BE92,$AA$2:$BE$2,">="&BI$2,$AA$3:$BE$3,"<="&BI$3) -> 0 | BJ92: =SUMIFS($AA92:$BE92,$AA$2:$BE$2,">="&BJ$2,$AA$3:$BE$3,"<="&BJ$3) -> 0 | BK92: =SUMIFS($AA92:$BE92,$AA$2:$BE$2,">="&BK$2,$AA$3:$BE$3,"<="&BK$3) -> 0 | BL92: =SUMIFS($AA92:$BE92,$AA$2:$BE$2,">="&BL$2,$AA$3:$BE$3,"<="&BL$3) -> 0 | BM92: =SUMIFS($AA92:$BE92,$AA$2:$BE$2,">="&BM$2,$AA$3:$BE$3,"<="&BM$3) -> 0
F93: Staff Costs | G93: =cstRealUnit -> £ Real | I93: =SUM(AA93:BE93) -> 68791697 | AA93: =AA27*AA$16 -> 0 | AB93: =AB27*AB$16 -> 2124256.4 | AC93: =AC27*AC$16 -> 2140966.4 | AD93: =AD27*AD$16 -> 2153572.6 | AE93: =AE27*AE$16 -> 2166253.1 | AF93: =AF27*AF$16 -> 2176872 | AG93: =AG27*AG$16 -> 2187543 | AH93: =AH27*AH$16 -> 2198266.2 | ... BE93: =BE27*BE$16 -> 2459944.1 | BG93: =SUMIFS($AA93:$BE93,$AA$2:$BE$2,">="&BG$2,$AA$3:$BE$3,"<="&BG$3) -> 0 | BH93: =SUMIFS($AA93:$BE93,$AA$2:$BE$2,">="&BH$2,$AA$3:$BE$3,"<="&BH$3) -> 10761921 | BI93: =SUMIFS($AA93:$BE93,$AA$2:$BE$2,">="&BI$2,$AA$3:$BE$3,"<="&BI$3) -> 11045474 | BJ93: =SUMIFS($AA93:$BE93,$AA$2:$BE$2,">="&BJ$2,$AA$3:$BE$3,"<="&BJ$3) -> 11318864 | BK93: =SUMIFS($AA93:$BE93,$AA$2:$BE$2,">="&BK$2,$AA$3:$BE$3,"<="&BK$3) -> 11599020 | BL93: =SUMIFS($AA93:$BE93,$AA$2:$BE$2,">="&BL$2,$AA$3:$BE$3,"<="&BL$3) -> 11886111 | BM93: =SUMIFS($AA93:$BE93,$AA$2:$BE$2,">="&BM$2,$AA$3:$BE$3,"<="&BM$3) -> 12180307
F94: Software & Hardware Costs | G94: =cstRealUnit -> £ Real | I94: =SUM(AA94:BE94) -> 7327618.8 | AA94: =AA28*AA$16 -> 0 | AB94: =AB28*AB$16 -> 718589.5 | AC94: =AC28*AC$16 -> 160558.5 | AD94: =AD28*AD$16 -> 162291.71 | AE94: =AE28*AE$16 -> 209187.35 | AF94: =AF28*AF$16 -> 165651.9 | AG94: =AG28*AG$16 -> 309430.28 | AH94: =AH28*AH$16 -> 215400.43 | ... BE94: =BE28*BE$16 -> 211408.65 | BG94: =SUMIFS($AA94:$BE94,$AA$2:$BE$2,">="&BG$2,$AA$3:$BE$3,"<="&BG$3) -> 0 | BH94: =SUMIFS($AA94:$BE94,$AA$2:$BE$2,">="&BH$2,$AA$3:$BE$3,"<="&BH$3) -> 1416279 | BI94: =SUMIFS($AA94:$BE94,$AA$2:$BE$2,">="&BI$2,$AA$3:$BE$3,"<="&BI$3) -> 1089444.9 | BJ94: =SUMIFS($AA94:$BE94,$AA$2:$BE$2,">="&BJ$2,$AA$3:$BE$3,"<="&BJ$3) -> 1094127.1 | BK94: =SUMIFS($AA94:$BE94,$AA$2:$BE$2,">="&BK$2,$AA$3:$BE$3,"<="&BK$3) -> 1200080.8 | BL94: =SUMIFS($AA94:$BE94,$AA$2:$BE$2,">="&BL$2,$AA$3:$BE$3,"<="&BL$3) -> 1261133.5 | BM94: =SUMIFS($AA94:$BE94,$AA$2:$BE$2,">="&BM$2,$AA$3:$BE$3,"<="&BM$3) -> 1266553.6
F95: Lease Costs | G95: =cstRealUnit -> £ Real | I95: =SUM(AA95:BE95) -> 0 | AA95: =AA29*AA$16 -> 0 | AB95: =AB29*AB$16 -> 0 | AC95: =AC29*AC$16 -> 0 | AD95: =AD29*AD$16 -> 0 | AE95: =AE29*AE$16 -> 0 | AF95: =AF29*AF$16 -> 0 | AG95: =AG29*AG$16 -> 0 | AH95: =AH29*AH$16 -> 0 | ... BE95: =BE29*BE$16 -> 0 | BG95: =SUMIFS($AA95:$BE95,$AA$2:$BE$2,">="&BG$2,$AA$3:$BE$3,"<="&BG$3) -> 0 | BH95: =SUMIFS($AA95:$BE95,$AA$2:$BE$2,">="&BH$2,$AA$3:$BE$3,"<="&BH$3) -> 0 | BI95: =SUMIFS($AA95:$BE95,$AA$2:$BE$2,">="&BI$2,$AA$3:$BE$3,"<="&BI$3) -> 0 | BJ95: =SUMIFS($AA95:$BE95,$AA$2:$BE$2,">="&BJ$2,$AA$3:$BE$3,"<="&BJ$3) -> 0 | BK95: =SUMIFS($AA95:$BE95,$AA$2:$BE$2,">="&BK$2,$AA$3:$BE$3,"<="&BK$3) -> 0 | BL95: =SUMIFS($AA95:$BE95,$AA$2:$BE$2,">="&BL$2,$AA$3:$BE$3,"<="&BL$3) -> 0 | BM95: =SUMIFS($AA95:$BE95,$AA$2:$BE$2,">="&BM$2,$AA$3:$BE$3,"<="&BM$3) -> 0
F96: Build & Maintenance Costs | G96: =cstRealUnit -> £ Real | I96: =SUM(AA96:BE96) -> 4109195 | AA96: =AA30*AA$16 -> 3045073 | AB96: =AB30*AB$16 -> 30538.872 | AC96: =AC30*AC$16 -> 30929.241 | AD96: =AD30*AD$16 -> 31263.119 | AE96: =AE30*AE$16 -> 31600.601 | AF96: =AF30*AF$16 -> 31910.411 | AG96: =AG30*AG$16 -> 32223.258 | AH96: =AH30*AH$16 -> 32539.173 | ... BE96: =BE30*BE$16 -> 40724.778 | BG96: =SUMIFS($AA96:$BE96,$AA$2:$BE$2,">="&BG$2,$AA$3:$BE$3,"<="&BG$3) -> 3045073 | BH96: =SUMIFS($AA96:$BE96,$AA$2:$BE$2,">="&BH$2,$AA$3:$BE$3,"<="&BH$3) -> 156242.25 | BI96: =SUMIFS($AA96:$BE96,$AA$2:$BE$2,">="&BI$2,$AA$3:$BE$3,"<="&BI$3) -> 164306.56 | BJ96: =SUMIFS($AA96:$BE96,$AA$2:$BE$2,">="&BJ$2,$AA$3:$BE$3,"<="&BJ$3) -> 172520.28 | BK96: =SUMIFS($AA96:$BE96,$AA$2:$BE$2,">="&BK$2,$AA$3:$BE$3,"<="&BK$3) -> 181144.62 | BL96: =SUMIFS($AA96:$BE96,$AA$2:$BE$2,">="&BL$2,$AA$3:$BE$3,"<="&BL$3) -> 190200.08 | BM96: =SUMIFS($AA96:$BE96,$AA$2:$BE$2,">="&BM$2,$AA$3:$BE$3,"<="&BM$3) -> 199708.23
F98: Lease & Operate | G98: =cstRealUnit -> £ Real | I98: =SUM(AA98:BE98) -> 77842180 | AA98: =SUM(AA99:AA104) -> 0 | AB98: =SUM(AB99:AB104) -> 2892289.8 | AC98: =SUM(AC99:AC104) -> 2351600.8 | AD98: =SUM(AD99:AD104) -> 2366480.8 | AE98: =SUM(AE99:AE104) -> 2426603.4 | AF98: =SUM(AF99:AF104) -> 2394188.4 | AG98: =SUM(AG99:AG104) -> 2549144.2 | AH98: =SUM(AH99:AH104) -> 2466349.1 | ... BE98: =SUM(BE99:BE104) -> 2737288.1 | BG98: =SUMIFS($AA98:$BE98,$AA$2:$BE$2,">="&BG$2,$AA$3:$BE$3,"<="&BG$3) -> 0 | BH98: =SUMIFS($AA98:$BE98,$AA$2:$BE$2,">="&BH$2,$AA$3:$BE$3,"<="&BH$3) -> 12431163 | BI98: =SUMIFS($AA98:$BE98,$AA$2:$BE$2,">="&BI$2,$AA$3:$BE$3,"<="&BI$3) -> 12400939 | BJ98: =SUMIFS($AA98:$BE98,$AA$2:$BE$2,">="&BJ$2,$AA$3:$BE$3,"<="&BJ$3) -> 12692310 | BK98: =SUMIFS($AA98:$BE98,$AA$2:$BE$2,">="&BK$2,$AA$3:$BE$3,"<="&BK$3) -> 13092383 | BL98: =SUMIFS($AA98:$BE98,$AA$2:$BE$2,">="&BL$2,$AA$3:$BE$3,"<="&BL$3) -> 13455187 | BM98: =SUMIFS($AA98:$BE98,$AA$2:$BE$2,">="&BM$2,$AA$3:$BE$3,"<="&BM$3) -> 13770198
F99: Operating Costs | G99: =cstRealUnit -> £ Real | I99: =SUM(AA99:BE99) -> 0 | AA99: =AA33*AA$16 -> 0 | AB99: =AB33*AB$16 -> 0 | AC99: =AC33*AC$16 -> 0 | AD99: =AD33*AD$16 -> 0 | AE99: =AE33*AE$16 -> 0 | AF99: =AF33*AF$16 -> 0 | AG99: =AG33*AG$16 -> 0 | AH99: =AH33*AH$16 -> 0 | ... BE99: =BE33*BE$16 -> 0 | BG99: =SUMIFS($AA99:$BE99,$AA$2:$BE$2,">="&BG$2,$AA$3:$BE$3,"<="&BG$3) -> 0 | BH99: =SUMIFS($AA99:$BE99,$AA$2:$BE$2,">="&BH$2,$AA$3:$BE$3,"<="&BH$3) -> 0 | BI99: =SUMIFS($AA99:$BE99,$AA$2:$BE$2,">="&BI$2,$AA$3:$BE$3,"<="&BI$3) -> 0 | BJ99: =SUMIFS($AA99:$BE99,$AA$2:$BE$2,">="&BJ$2,$AA$3:$BE$3,"<="&BJ$3) -> 0 | BK99: =SUMIFS($AA99:$BE99,$AA$2:$BE$2,">="&BK$2,$AA$3:$BE$3,"<="&BK$3) -> 0 | BL99: =SUMIFS($AA99:$BE99,$AA$2:$BE$2,">="&BL$2,$AA$3:$BE$3,"<="&BL$3) -> 0 | BM99: =SUMIFS($AA99:$BE99,$AA$2:$BE$2,">="&BM$2,$AA$3:$BE$3,"<="&BM$3) -> 0
F100: Staff Costs | G100: =cstRealUnit -> £ Real | I100: =SUM(AA100:BE100) -> 68791697 | AA100: =AA34*AA$16 -> 0 | AB100: =AB34*AB$16 -> 2124256.4 | AC100: =AC34*AC$16 -> 2140966.4 | AD100: =AD34*AD$16 -> 2153572.6 | AE100: =AE34*AE$16 -> 2166253.1 | AF100: =AF34*AF$16 -> 2176872 | AG100: =AG34*AG$16 -> 2187543 | AH100: =AH34*AH$16 -> 2198266.2 | ... BE100: =BE34*BE$16 -> 2459944.1 | BG100: =SUMIFS($AA100:$BE100,$AA$2:$BE$2,">="&BG$2,$AA$3:$BE$3,"<="&BG$3) -> 0 | BH100: =SUMIFS($AA100:$BE100,$AA$2:$BE$2,">="&BH$2,$AA$3:$BE$3,"<="&BH$3) -> 10761921 | BI100: =SUMIFS($AA100:$BE100,$AA$2:$BE$2,">="&BI$2,$AA$3:$BE$3,"<="&BI$3) -> 11045474 | BJ100: =SUMIFS($AA100:$BE100,$AA$2:$BE$2,">="&BJ$2,$AA$3:$BE$3,"<="&BJ$3) -> 11318864 | BK100: =SUMIFS($AA100:$BE100,$AA$2:$BE$2,">="&BK$2,$AA$3:$BE$3,"<="&BK$3) -> 11599020 | BL100: =SUMIFS($AA100:$BE100,$AA$2:$BE$2,">="&BL$2,$AA$3:$BE$3,"<="&BL$3) -> 11886111 | BM100: =SUMIFS($AA100:$BE100,$AA$2:$BE$2,">="&BM$2,$AA$3:$BE$3,"<="&BM$3) -> 12180307
F101: Software & Hardware Costs | G101: =cstRealUnit -> £ Real | I101: =SUM(AA101:BE101) -> 7327618.8 | AA101: =AA35*AA$16 -> 0 | AB101: =AB35*AB$16 -> 718589.5 | AC101: =AC35*AC$16 -> 160558.5 | AD101: =AD35*AD$16 -> 162291.71 | AE101: =AE35*AE$16 -> 209187.35 | AF101: =AF35*AF$16 -> 165651.9 | AG101: =AG35*AG$16 -> 309430.28 | AH101: =AH35*AH$16 -> 215400.43 | ... BE101: =BE35*BE$16 -> 211408.65 | BG101: =SUMIFS($AA101:$BE101,$AA$2:$BE$2,">="&BG$2,$AA$3:$BE$3,"<="&BG$3) -> 0 | BH101: =SUMIFS($AA101:$BE101,$AA$2:$BE$2,">="&BH$2,$AA$3:$BE$3,"<="&BH$3) -> 1416279 | BI101: =SUMIFS($AA101:$BE101,$AA$2:$BE$2,">="&BI$2,$AA$3:$BE$3,"<="&BI$3) -> 1089444.9 | BJ101: =SUMIFS($AA101:$BE101,$AA$2:$BE$2,">="&BJ$2,$AA$3:$BE$3,"<="&BJ$3) -> 1094127.1 | BK101: =SUMIFS($AA101:$BE101,$AA$2:$BE$2,">="&BK$2,$AA$3:$BE$3,"<="&BK$3) -> 1200080.8 | BL101: =SUMIFS($AA101:$BE101,$AA$2:$BE$2,">="&BL$2,$AA$3:$BE$3,"<="&BL$3) -> 1261133.5 | BM101: =SUMIFS($AA101:$BE101,$AA$2:$BE$2,">="&BM$2,$AA$3:$BE$3,"<="&BM$3) -> 1266553.6
F102: Lease Costs | G102: =cstRealUnit -> £ Real | I102: =SUM(AA102:BE102) -> 1722864.2 | AA102: =AA36*AA$16 -> 0 | AB102: =AB36*AB$16 -> 49443.888 | AC102: =AC36*AC$16 -> 50075.915 | AD102: =AD36*AD$16 -> 50616.479 | AE102: =AE36*AE$16 -> 51162.879 | AF102: =AF36*AF$16 -> 51664.475 | AG102: =AG36*AG$16 -> 52170.99 | AH102: =AH36*AH$16 -> 52682.47 | ... BE102: =BE36*BE$16 -> 65935.355 | BG102: =SUMIFS($AA102:$BE102,$AA$2:$BE$2,">="&BG$2,$AA$3:$BE$3,"<="&BG$3) -> 0 | BH102: =SUMIFS($AA102:$BE102,$AA$2:$BE$2,">="&BH$2,$AA$3:$BE$3,"<="&BH$3) -> 252963.64 | BI102: =SUMIFS($AA102:$BE102,$AA$2:$BE$2,">="&BI$2,$AA$3:$BE$3,"<="&BI$3) -> 266020.14 | BJ102: =SUMIFS($AA102:$BE102,$AA$2:$BE$2,">="&BJ$2,$AA$3:$BE$3,"<="&BJ$3) -> 279318.56 | BK102: =SUMIFS($AA102:$BE102,$AA$2:$BE$2,">="&BK$2,$AA$3:$BE$3,"<="&BK$3) -> 293281.76 | BL102: =SUMIFS($AA102:$BE102,$AA$2:$BE$2,">="&BL$2,$AA$3:$BE$3,"<="&BL$3) -> 307942.99 | BM102: =SUMIFS($AA102:$BE102,$AA$2:$BE$2,">="&BM$2,$AA$3:$BE$3,"<="&BM$3) -> 323337.13
F103: Build & Maintenance Costs | G103: =cstRealUnit -> £ Real | I103: =SUM(AA103:BE103) -> 0 | AA103: =AA37*AA$16 -> 0 | AB103: =AB37*AB$16 -> 0 | AC103: =AC37*AC$16 -> 0 | AD103: =AD37*AD$16 -> 0 | AE103: =AE37*AE$16 -> 0 | AF103: =AF37*AF$16 -> 0 | AG103: =AG37*AG$16 -> 0 | AH103: =AH37*AH$16 -> 0 | ... BE103: =BE37*BE$16 -> 0 | BG103: =SUMIFS($AA103:$BE103,$AA$2:$BE$2,">="&BG$2,$AA$3:$BE$3,"<="&BG$3) -> 0 | BH103: =SUMIFS($AA103:$BE103,$AA$2:$BE$2,">="&BH$2,$AA$3:$BE$3,"<="&BH$3) -> 0 | BI103: =SUMIFS($AA103:$BE103,$AA$2:$BE$2,">="&BI$2,$AA$3:$BE$3,"<="&BI$3) -> 0 | BJ103: =SUMIFS($AA103:$BE103,$AA$2:$BE$2,">="&BJ$2,$AA$3:$BE$3,"<="&BJ$3) -> 0 | BK103: =SUMIFS($AA103:$BE103,$AA$2:$BE$2,">="&BK$2,$AA$3:$BE$3,"<="&BK$3) -> 0 | BL103: =SUMIFS($AA103:$BE103,$AA$2:$BE$2,">="&BL$2,$AA$3:$BE$3,"<="&BL$3) -> 0 | BM103: =SUMIFS($AA103:$BE103,$AA$2:$BE$2,">="&BM$2,$AA$3:$BE$3,"<="&BM$3) -> 0
F105: Outsource | G105: =cstRealUnit -> £ Real | I105: =SUM(AA105:BE105) -> 95659912 | AA105: =SUM(AA106:AA111) -> 0 | AB105: =SUM(AB106:AB111) -> 2745311 | AC105: =SUM(AC106:AC111) -> 2780403.4 | AD105: =SUM(AD106:AD111) -> 2810417.6 | AE105: =SUM(AE106:AE111) -> 2840755.8 | AF105: =SUM(AF106:AF111) -> 2868606.3 | AG105: =SUM(AG106:AG111) -> 2896729.9 | AH105: =SUM(AH106:AH111) -> 2925129.2 | ... BE105: =SUM(BE106:BE111) -> 3660979.3 | BG105: =SUMIFS($AA105:$BE105,$AA$2:$BE$2,">="&BG$2,$AA$3:$BE$3,"<="&BG$3) -> 0 | BH105: =SUMIFS($AA105:$BE105,$AA$2:$BE$2,">="&BH$2,$AA$3:$BE$3,"<="&BH$3) -> 14045494 | BI105: =SUMIFS($AA105:$BE105,$AA$2:$BE$2,">="&BI$2,$AA$3:$BE$3,"<="&BI$3) -> 14770441 | BJ105: =SUMIFS($AA105:$BE105,$AA$2:$BE$2,">="&BJ$2,$AA$3:$BE$3,"<="&BJ$3) -> 15508819 | BK105: =SUMIFS($AA105:$BE105,$AA$2:$BE$2,">="&BK$2,$AA$3:$BE$3,"<="&BK$3) -> 16284108 | BL105: =SUMIFS($AA105:$BE105,$AA$2:$BE$2,">="&BL$2,$AA$3:$BE$3,"<="&BL$3) -> 17098155 | BM105: =SUMIFS($AA105:$BE105,$AA$2:$BE$2,">="&BM$2,$AA$3:$BE$3,"<="&BM$3) -> 17952896
F106: Operating Costs | G106: =cstRealUnit -> £ Real | I106: =SUM(AA106:BE106) -> 95659912 | AA106: =AA40*AA$16 -> 0 | AB106: =AB40*AB$16 -> 2745311 | AC106: =AC40*AC$16 -> 2780403.4 | AD106: =AD40*AD$16 -> 2810417.6 | AE106: =AE40*AE$16 -> 2840755.8 | AF106: =AF40*AF$16 -> 2868606.3 | AG106: =AG40*AG$16 -> 2896729.9 | AH106: =AH40*AH$16 -> 2925129.2 | ... BE106: =BE40*BE$16 -> 3660979.3 | BG106: =SUMIFS($AA106:$BE106,$AA$2:$BE$2,">="&BG$2,$AA$3:$BE$3,"<="&BG$3) -> 0 | BH106: =SUMIFS($AA106:$BE106,$AA$2:$BE$2,">="&BH$2,$AA$3:$BE$3,"<="&BH$3) -> 14045494 | BI106: =SUMIFS($AA106:$BE106,$AA$2:$BE$2,">="&BI$2,$AA$3:$BE$3,"<="&BI$3) -> 14770441 | BJ106: =SUMIFS($AA106:$BE106,$AA$2:$BE$2,">="&BJ$2,$AA$3:$BE$3,"<="&BJ$3) -> 15508819 | BK106: =SUMIFS($AA106:$BE106,$AA$2:$BE$2,">="&BK$2,$AA$3:$BE$3,"<="&BK$3) -> 16284108 | BL106: =SUMIFS($AA106:$BE106,$AA$2:$BE$2,">="&BL$2,$AA$3:$BE$3,"<="&BL$3) -> 17098155 | BM106: =SUMIFS($AA106:$BE106,$AA$2:$BE$2,">="&BM$2,$AA$3:$BE$3,"<="&BM$3) -> 17952896
F107: Staff Costs | G107: =cstRealUnit -> £ Real | I107: =SUM(AA107:BE107) -> 0 | AA107: =AA41*AA$16 -> 0 | AB107: =AB41*AB$16 -> 0 | AC107: =AC41*AC$16 -> 0 | AD107: =AD41*AD$16 -> 0 | AE107: =AE41*AE$16 -> 0 | AF107: =AF41*AF$16 -> 0 | AG107: =AG41*AG$16 -> 0 | AH107: =AH41*AH$16 -> 0 | ... BE107: =BE41*BE$16 -> 0 | BG107: =SUMIFS($AA107:$BE107,$AA$2:$BE$2,">="&BG$2,$AA$3:$BE$3,"<="&BG$3) -> 0 | BH107: =SUMIFS($AA107:$BE107,$AA$2:$BE$2,">="&BH$2,$AA$3:$BE$3,"<="&BH$3) -> 0 | BI107: =SUMIFS($AA107:$BE107,$AA$2:$BE$2,">="&BI$2,$AA$3:$BE$3,"<="&BI$3) -> 0 | BJ107: =SUMIFS($AA107:$BE107,$AA$2:$BE$2,">="&BJ$2,$AA$3:$BE$3,"<="&BJ$3) -> 0 | BK107: =SUMIFS($AA107:$BE107,$AA$2:$BE$2,">="&BK$2,$AA$3:$BE$3,"<="&BK$3) -> 0 | BL107: =SUMIFS($AA107:$BE107,$AA$2:$BE$2,">="&BL$2,$AA$3:$BE$3,"<="&BL$3) -> 0 | BM107: =SUMIFS($AA107:$BE107,$AA$2:$BE$2,">="&BM$2,$AA$3:$BE$3,"<="&BM$3) -> 0
F108: Software & Hardware Costs | G108: =cstRealUnit -> £ Real | I108: =SUM(AA108:BE108) -> 0 | AA108: =AA42*AA$16 -> 0 | AB108: =AB42*AB$16 -> 0 | AC108: =AC42*AC$16 -> 0 | AD108: =AD42*AD$16 -> 0 | AE108: =AE42*AE$16 -> 0 | AF108: =AF42*AF$16 -> 0 | AG108: =AG42*AG$16 -> 0 | AH108: =AH42*AH$16 -> 0 | ... BE108: =BE42*BE$16 -> 0 | BG108: =SUMIFS($AA108:$BE108,$AA$2:$BE$2,">="&BG$2,$AA$3:$BE$3,"<="&BG$3) -> 0 | BH108: =SUMIFS($AA108:$BE108,$AA$2:$BE$2,">="&BH$2,$AA$3:$BE$3,"<="&BH$3) -> 0 | BI108: =SUMIFS($AA108:$BE108,$AA$2:$BE$2,">="&BI$2,$AA$3:$BE$3,"<="&BI$3) -> 0 | BJ108: =SUMIFS($AA108:$BE108,$AA$2:$BE$2,">="&BJ$2,$AA$3:$BE$3,"<="&BJ$3) -> 0 | BK108: =SUMIFS($AA108:$BE108,$AA$2:$BE$2,">="&BK$2,$AA$3:$BE$3,"<="&BK$3) -> 0 | BL108: =SUMIFS($AA108:$BE108,$AA$2:$BE$2,">="&BL$2,$AA$3:$BE$3,"<="&BL$3) -> 0 | BM108: =SUMIFS($AA108:$BE108,$AA$2:$BE$2,">="&BM$2,$AA$3:$BE$3,"<="&BM$3) -> 0
F109: Lease Costs | G109: =cstRealUnit -> £ Real | I109: =SUM(AA109:BE109) -> 0 | AA109: =AA43*AA$16 -> 0 | AB109: =AB43*AB$16 -> 0 | AC109: =AC43*AC$16 -> 0 | AD109: =AD43*AD$16 -> 0 | AE109: =AE43*AE$16 -> 0 | AF109: =AF43*AF$16 -> 0 | AG109: =AG43*AG$16 -> 0 | AH109: =AH43*AH$16 -> 0 | ... BE109: =BE43*BE$16 -> 0 | BG109: =SUMIFS($AA109:$BE109,$AA$2:$BE$2,">="&BG$2,$AA$3:$BE$3,"<="&BG$3) -> 0 | BH109: =SUMIFS($AA109:$BE109,$AA$2:$BE$2,">="&BH$2,$AA$3:$BE$3,"<="&BH$3) -> 0 | BI109: =SUMIFS($AA109:$BE109,$AA$2:$BE$2,">="&BI$2,$AA$3:$BE$3,"<="&BI$3) -> 0 | BJ109: =SUMIFS($AA109:$BE109,$AA$2:$BE$2,">="&BJ$2,$AA$3:$BE$3,"<="&BJ$3) -> 0 | BK109: =SUMIFS($AA109:$BE109,$AA$2:$BE$2,">="&BK$2,$AA$3:$BE$3,"<="&BK$3) -> 0 | BL109: =SUMIFS($AA109:$BE109,$AA$2:$BE$2,">="&BL$2,$AA$3:$BE$3,"<="&BL$3) -> 0 | BM109: =SUMIFS($AA109:$BE109,$AA$2:$BE$2,">="&BM$2,$AA$3:$BE$3,"<="&BM$3) -> 0
F110: Build & Maintenance Costs | G110: =cstRealUnit -> £ Real | I110: =SUM(AA110:BE110) -> 0 | AA110: =AA44*AA$16 -> 0 | AB110: =AB44*AB$16 -> 0 | AC110: =AC44*AC$16 -> 0 | AD110: =AD44*AD$16 -> 0 | AE110: =AE44*AE$16 -> 0 | AF110: =AF44*AF$16 -> 0 | AG110: =AG44*AG$16 -> 0 | AH110: =AH44*AH$16 -> 0 | ... BE110: =BE44*BE$16 -> 0 | BG110: =SUMIFS($AA110:$BE110,$AA$2:$BE$2,">="&BG$2,$AA$3:$BE$3,"<="&BG$3) -> 0 | BH110: =SUMIFS($AA110:$BE110,$AA$2:$BE$2,">="&BH$2,$AA$3:$BE$3,"<="&BH$3) -> 0 | BI110: =SUMIFS($AA110:$BE110,$AA$2:$BE$2,">="&BI$2,$AA$3:$BE$3,"<="&BI$3) -> 0 | BJ110: =SUMIFS($AA110:$BE110,$AA$2:$BE$2,">="&BJ$2,$AA$3:$BE$3,"<="&BJ$3) -> 0 | BK110: =SUMIFS($AA110:$BE110,$AA$2:$BE$2,">="&BK$2,$AA$3:$BE$3,"<="&BK$3) -> 0 | BL110: =SUMIFS($AA110:$BE110,$AA$2:$BE$2,">="&BL$2,$AA$3:$BE$3,"<="&BL$3) -> 0 | BM110: =SUMIFS($AA110:$BE110,$AA$2:$BE$2,">="&BM$2,$AA$3:$BE$3,"<="&BM$3) -> 0
E112: 3.2 | F112: Cumulative Costs
F114: Options
F116: Build & Operate | G116: =cstRealUnit -> £ Real | AA116: =SUM(AA117:AA122) -> 3045073 | AB116: =SUM(AB117:AB122) -> 5918457.8 | AC116: =SUM(AC117:AC122) -> 8250911.8 | AD116: =SUM(AD117:AD122) -> 10598039 | AE116: =SUM(AE117:AE122) -> 13005080 | AF116: =SUM(AF117:AF122) -> 15379515 | AG116: =SUM(AG117:AG122) -> 17908711 | AH116: =SUM(AH117:AH122) -> 20354917 | ... BE116: =SUM(BE117:BE122) -> 80228511 | BG116: =SUMIFS($AA116:$BE116,$AA$3:$BE$3,BG$3) -> 3045073 | BH116: =SUMIFS($AA116:$BE116,$AA$3:$BE$3,BH$3) -> 15379515 | BI116: =SUMIFS($AA116:$BE116,$AA$3:$BE$3,BI$3) -> 27678740 | BJ116: =SUMIFS($AA116:$BE116,$AA$3:$BE$3,BJ$3) -> 40264252 | BK116: =SUMIFS($AA116:$BE116,$AA$3:$BE$3,BK$3) -> 53244497 | BL116: =SUMIFS($AA116:$BE116,$AA$3:$BE$3,BL$3) -> 66581942 | BM116: =SUMIFS($AA116:$BE116,$AA$3:$BE$3,BM$3) -> 80228511
F117: Operating Costs | G117: =cstRealUnit -> £ Real | AA117: =Z117+AA92 -> 0 | AB117: =AA117+AB92 -> 0 | AC117: =AB117+AC92 -> 0 | AD117: =AC117+AD92 -> 0 | AE117: =AD117+AE92 -> 0 | AF117: =AE117+AF92 -> 0 | AG117: =AF117+AG92 -> 0 | AH117: =AG117+AH92 -> 0 | ... BE117: =BD117+BE92 -> 0 | BG117: =SUMIFS($AA117:$BE117,$AA$3:$BE$3,BG$3) -> 0 | BH117: =SUMIFS($AA117:$BE117,$AA$3:$BE$3,BH$3) -> 0 | BI117: =SUMIFS($AA117:$BE117,$AA$3:$BE$3,BI$3) -> 0 | BJ117: =SUMIFS($AA117:$BE117,$AA$3:$BE$3,BJ$3) -> 0 | BK117: =SUMIFS($AA117:$BE117,$AA$3:$BE$3,BK$3) -> 0 | BL117: =SUMIFS($AA117:$BE117,$AA$3:$BE$3,BL$3) -> 0 | BM117: =SUMIFS($AA117:$BE117,$AA$3:$BE$3,BM$3) -> 0
F118: Staff Costs | G118: =cstRealUnit -> £ Real | AA118: =Z118+AA93 -> 0 | AB118: =AA118+AB93 -> 2124256.4 | AC118: =AB118+AC93 -> 4265222.7 | AD118: =AC118+AD93 -> 6418795.4 | AE118: =AD118+AE93 -> 8585048.5 | AF118: =AE118+AF93 -> 10761921 | AG118: =AF118+AG93 -> 12949463 | AH118: =AG118+AH93 -> 15147730 | ... BE118: =BD118+BE93 -> 68791697 | BG118: =SUMIFS($AA118:$BE118,$AA$3:$BE$3,BG$3) -> 0 | BH118: =SUMIFS($AA118:$BE118,$AA$3:$BE$3,BH$3) -> 10761921 | BI118: =SUMIFS($AA118:$BE118,$AA$3:$BE$3,BI$3) -> 21807395 | BJ118: =SUMIFS($AA118:$BE118,$AA$3:$BE$3,BJ$3) -> 33126259 | BK118: =SUMIFS($AA118:$BE118,$AA$3:$BE$3,BK$3) -> 44725279 | BL118: =SUMIFS($AA118:$BE118,$AA$3:$BE$3,BL$3) -> 56611390 | BM118: =SUMIFS($AA118:$BE118,$AA$3:$BE$3,BM$3) -> 68791697
F119: Software & Hardware Costs | G119: =cstRealUnit -> £ Real | AA119: =Z119+AA94 -> 0 | AB119: =AA119+AB94 -> 718589.5 | AC119: =AB119+AC94 -> 879148 | AD119: =AC119+AD94 -> 1041439.7 | AE119: =AD119+AE94 -> 1250627.1 | AF119: =AE119+AF94 -> 1416279 | AG119: =AF119+AG94 -> 1725709.2 | AH119: =AG119+AH94 -> 1941109.7 | ... BE119: =BD119+BE94 -> 7327618.8 | BG119: =SUMIFS($AA119:$BE119,$AA$3:$BE$3,BG$3) -> 0 | BH119: =SUMIFS($AA119:$BE119,$AA$3:$BE$3,BH$3) -> 1416279 | BI119: =SUMIFS($AA119:$BE119,$AA$3:$BE$3,BI$3) -> 2505723.9 | BJ119: =SUMIFS($AA119:$BE119,$AA$3:$BE$3,BJ$3) -> 3599850.9 | BK119: =SUMIFS($AA119:$BE119,$AA$3:$BE$3,BK$3) -> 4799931.8 | BL119: =SUMIFS($AA119:$BE119,$AA$3:$BE$3,BL$3) -> 6061065.3 | BM119: =SUMIFS($AA119:$BE119,$AA$3:$BE$3,BM$3) -> 7327618.8
F120: Lease Costs | G120: =cstRealUnit -> £ Real | AA120: =Z120+AA95 -> 0 | AB120: =AA120+AB95 -> 0 | AC120: =AB120+AC95 -> 0 | AD120: =AC120+AD95 -> 0 | AE120: =AD120+AE95 -> 0 | AF120: =AE120+AF95 -> 0 | AG120: =AF120+AG95 -> 0 | AH120: =AG120+AH95 -> 0 | ... BE120: =BD120+BE95 -> 0 | BG120: =SUMIFS($AA120:$BE120,$AA$3:$BE$3,BG$3) -> 0 | BH120: =SUMIFS($AA120:$BE120,$AA$3:$BE$3,BH$3) -> 0 | BI120: =SUMIFS($AA120:$BE120,$AA$3:$BE$3,BI$3) -> 0 | BJ120: =SUMIFS($AA120:$BE120,$AA$3:$BE$3,BJ$3) -> 0 | BK120: =SUMIFS($AA120:$BE120,$AA$3:$BE$3,BK$3) -> 0 | BL120: =SUMIFS($AA120:$BE120,$AA$3:$BE$3,BL$3) -> 0 | BM120: =SUMIFS($AA120:$BE120,$AA$3:$BE$3,BM$3) -> 0
F121: Build & Maintenance Costs | G121: =cstRealUnit -> £ Real | AA121: =Z121+AA96 -> 3045073 | AB121: =AA121+AB96 -> 3075611.9 | AC121: =AB121+AC96 -> 3106541.1 | AD121: =AC121+AD96 -> 3137804.2 | AE121: =AD121+AE96 -> 3169404.8 | AF121: =AE121+AF96 -> 3201315.2 | AG121: =AF121+AG96 -> 3233538.5 | AH121: =AG121+AH96 -> 3266077.7 | ... BE121: =BD121+BE96 -> 4109195 | BG121: =SUMIFS($AA121:$BE121,$AA$3:$BE$3,BG$3) -> 3045073 | BH121: =SUMIFS($AA121:$BE121,$AA$3:$BE$3,BH$3) -> 3201315.2 | BI121: =SUMIFS($AA121:$BE121,$AA$3:$BE$3,BI$3) -> 3365621.8 | BJ121: =SUMIFS($AA121:$BE121,$AA$3:$BE$3,BJ$3) -> 3538142.1 | BK121: =SUMIFS($AA121:$BE121,$AA$3:$BE$3,BK$3) -> 3719286.7 | BL121: =SUMIFS($AA121:$BE121,$AA$3:$BE$3,BL$3) -> 3909486.8 | BM121: =SUMIFS($AA121:$BE121,$AA$3:$BE$3,BM$3) -> 4109195
F123: Lease & Operate | G123: =cstRealUnit -> £ Real | AA123: =SUM(AA124:AA129) -> 0 | AB123: =SUM(AB124:AB129) -> 2892289.8 | AC123: =SUM(AC124:AC129) -> 5243890.5 | AD123: =SUM(AD124:AD129) -> 7610371.3 | AE123: =SUM(AE124:AE129) -> 10036975 | AF123: =SUM(AF124:AF129) -> 12431163 | AG123: =SUM(AG124:AG129) -> 14980307 | AH123: =SUM(AH124:AH129) -> 17446656 | ... BE123: =SUM(BE124:BE129) -> 77842180 | BG123: =SUMIFS($AA123:$BE123,$AA$3:$BE$3,BG$3) -> 0 | BH123: =SUMIFS($AA123:$BE123,$AA$3:$BE$3,BH$3) -> 12431163 | BI123: =SUMIFS($AA123:$BE123,$AA$3:$BE$3,BI$3) -> 24832102 | BJ123: =SUMIFS($AA123:$BE123,$AA$3:$BE$3,BJ$3) -> 37524412 | BK123: =SUMIFS($AA123:$BE123,$AA$3:$BE$3,BK$3) -> 50616795 | BL123: =SUMIFS($AA123:$BE123,$AA$3:$BE$3,BL$3) -> 64071982 | BM123: =SUMIFS($AA123:$BE123,$AA$3:$BE$3,BM$3) -> 77842180
F124: Operating Costs | G124: =cstRealUnit -> £ Real | AA124: =Z124+AA99 -> 0 | AB124: =AA124+AB99 -> 0 | AC124: =AB124+AC99 -> 0 | AD124: =AC124+AD99 -> 0 | AE124: =AD124+AE99 -> 0 | AF124: =AE124+AF99 -> 0 | AG124: =AF124+AG99 -> 0 | AH124: =AG124+AH99 -> 0 | ... BE124: =BD124+BE99 -> 0 | BG124: =SUMIFS($AA124:$BE124,$AA$3:$BE$3,BG$3) -> 0 | BH124: =SUMIFS($AA124:$BE124,$AA$3:$BE$3,BH$3) -> 0 | BI124: =SUMIFS($AA124:$BE124,$AA$3:$BE$3,BI$3) -> 0 | BJ124: =SUMIFS($AA124:$BE124,$AA$3:$BE$3,BJ$3) -> 0 | BK124: =SUMIFS($AA124:$BE124,$AA$3:$BE$3,BK$3) -> 0 | BL124: =SUMIFS($AA124:$BE124,$AA$3:$BE$3,BL$3) -> 0 | BM124: =SUMIFS($AA124:$BE124,$AA$3:$BE$3,BM$3) -> 0
F125: Staff Costs | G125: =cstRealUnit -> £ Real | AA125: =Z125+AA100 -> 0 | AB125: =AA125+AB100 -> 2124256.4 | AC125: =AB125+AC100 -> 4265222.7 | AD125: =AC125+AD100 -> 6418795.4 | AE125: =AD125+AE100 -> 8585048.5 | AF125: =AE125+AF100 -> 10761921 | AG125: =AF125+AG100 -> 12949463 | AH125: =AG125+AH100 -> 15147730 | ... BE125: =BD125+BE100 -> 68791697 | BG125: =SUMIFS($AA125:$BE125,$AA$3:$BE$3,BG$3) -> 0 | BH125: =SUMIFS($AA125:$BE125,$AA$3:$BE$3,BH$3) -> 10761921 | BI125: =SUMIFS($AA125:$BE125,$AA$3:$BE$3,BI$3) -> 21807395 | BJ125: =SUMIFS($AA125:$BE125,$AA$3:$BE$3,BJ$3) -> 33126259 | BK125: =SUMIFS($AA125:$BE125,$AA$3:$BE$3,BK$3) -> 44725279 | BL125: =SUMIFS($AA125:$BE125,$AA$3:$BE$3,BL$3) -> 56611390 | BM125: =SUMIFS($AA125:$BE125,$AA$3:$BE$3,BM$3) -> 68791697
F126: Software & Hardware Costs | G126: =cstRealUnit -> £ Real | AA126: =Z126+AA101 -> 0 | AB126: =AA126+AB101 -> 718589.5 | AC126: =AB126+AC101 -> 879148 | AD126: =AC126+AD101 -> 1041439.7 | AE126: =AD126+AE101 -> 1250627.1 | AF126: =AE126+AF101 -> 1416279 | AG126: =AF126+AG101 -> 1725709.2 | AH126: =AG126+AH101 -> 1941109.7 | ... BE126: =BD126+BE101 -> 7327618.8 | BG126: =SUMIFS($AA126:$BE126,$AA$3:$BE$3,BG$3) -> 0 | BH126: =SUMIFS($AA126:$BE126,$AA$3:$BE$3,BH$3) -> 1416279 | BI126: =SUMIFS($AA126:$BE126,$AA$3:$BE$3,BI$3) -> 2505723.9 | BJ126: =SUMIFS($AA126:$BE126,$AA$3:$BE$3,BJ$3) -> 3599850.9 | BK126: =SUMIFS($AA126:$BE126,$AA$3:$BE$3,BK$3) -> 4799931.8 | BL126: =SUMIFS($AA126:$BE126,$AA$3:$BE$3,BL$3) -> 6061065.3 | BM126: =SUMIFS($AA126:$BE126,$AA$3:$BE$3,BM$3) -> 7327618.8
F127: Lease Costs | G127: =cstRealUnit -> £ Real | AA127: =Z127+AA102 -> 0 | AB127: =AA127+AB102 -> 49443.888 | AC127: =AB127+AC102 -> 99519.803 | AD127: =AC127+AD102 -> 150136.28 | AE127: =AD127+AE102 -> 201299.16 | AF127: =AE127+AF102 -> 252963.64 | AG127: =AF127+AG102 -> 305134.63 | AH127: =AG127+AH102 -> 357817.1 | ... BE127: =BD127+BE102 -> 1722864.2 | BG127: =SUMIFS($AA127:$BE127,$AA$3:$BE$3,BG$3) -> 0 | BH127: =SUMIFS($AA127:$BE127,$AA$3:$BE$3,BH$3) -> 252963.64 | BI127: =SUMIFS($AA127:$BE127,$AA$3:$BE$3,BI$3) -> 518983.78 | BJ127: =SUMIFS($AA127:$BE127,$AA$3:$BE$3,BJ$3) -> 798302.34 | BK127: =SUMIFS($AA127:$BE127,$AA$3:$BE$3,BK$3) -> 1091584.1 | BL127: =SUMIFS($AA127:$BE127,$AA$3:$BE$3,BL$3) -> 1399527.1 | BM127: =SUMIFS($AA127:$BE127,$AA$3:$BE$3,BM$3) -> 1722864.2
F128: Build & Maintenance Costs | G128: =cstRealUnit -> £ Real | AA128: =Z128+AA103 -> 0 | AB128: =AA128+AB103 -> 0 | AC128: =AB128+AC103 -> 0 | AD128: =AC128+AD103 -> 0 | AE128: =AD128+AE103 -> 0 | AF128: =AE128+AF103 -> 0 | AG128: =AF128+AG103 -> 0 | AH128: =AG128+AH103 -> 0 | ... BE128: =BD128+BE103 -> 0 | BG128: =SUMIFS($AA128:$BE128,$AA$3:$BE$3,BG$3) -> 0 | BH128: =SUMIFS($AA128:$BE128,$AA$3:$BE$3,BH$3) -> 0 | BI128: =SUMIFS($AA128:$BE128,$AA$3:$BE$3,BI$3) -> 0 | BJ128: =SUMIFS($AA128:$BE128,$AA$3:$BE$3,BJ$3) -> 0 | BK128: =SUMIFS($AA128:$BE128,$AA$3:$BE$3,BK$3) -> 0 | BL128: =SUMIFS($AA128:$BE128,$AA$3:$BE$3,BL$3) -> 0 | BM128: =SUMIFS($AA128:$BE128,$AA$3:$BE$3,BM$3) -> 0
F130: Outsource | G130: =cstRealUnit -> £ Real | AA130: =SUM(AA131:AA136) -> 0 | AB130: =SUM(AB131:AB136) -> 2745311 | AC130: =SUM(AC131:AC136) -> 5525714.4 | AD130: =SUM(AD131:AD136) -> 8336132 | AE130: =SUM(AE131:AE136) -> 11176888 | AF130: =SUM(AF131:AF136) -> 14045494 | AG130: =SUM(AG131:AG136) -> 16942224 | AH130: =SUM(AH131:AH136) -> 19867353 | ... BE130: =SUM(BE131:BE136) -> 95659912 | BG130: =SUMIFS($AA130:$BE130,$AA$3:$BE$3,BG$3) -> 0 | BH130: =SUMIFS($AA130:$BE130,$AA$3:$BE$3,BH$3) -> 14045494 | BI130: =SUMIFS($AA130:$BE130,$AA$3:$BE$3,BI$3) -> 28815935 | BJ130: =SUMIFS($AA130:$BE130,$AA$3:$BE$3,BJ$3) -> 44324753 | BK130: =SUMIFS($AA130:$BE130,$AA$3:$BE$3,BK$3) -> 60608861 | BL130: =SUMIFS($AA130:$BE130,$AA$3:$BE$3,BL$3) -> 77707016 | BM130: =SUMIFS($AA130:$BE130,$AA$3:$BE$3,BM$3) -> 95659912
F131: Operating Costs | G131: =cstRealUnit -> £ Real | AA131: =Z131+AA106 -> 0 | AB131: =AA131+AB106 -> 2745311 | AC131: =AB131+AC106 -> 5525714.4 | AD131: =AC131+AD106 -> 8336132 | AE131: =AD131+AE106 -> 11176888 | AF131: =AE131+AF106 -> 14045494 | AG131: =AF131+AG106 -> 16942224 | AH131: =AG131+AH106 -> 19867353 | ... BE131: =BD131+BE106 -> 95659912 | BG131: =SUMIFS($AA131:$BE131,$AA$3:$BE$3,BG$3) -> 0 | BH131: =SUMIFS($AA131:$BE131,$AA$3:$BE$3,BH$3) -> 14045494 | BI131: =SUMIFS($AA131:$BE131,$AA$3:$BE$3,BI$3) -> 28815935 | BJ131: =SUMIFS($AA131:$BE131,$AA$3:$BE$3,BJ$3) -> 44324753 | BK131: =SUMIFS($AA131:$BE131,$AA$3:$BE$3,BK$3) -> 60608861 | BL131: =SUMIFS($AA131:$BE131,$AA$3:$BE$3,BL$3) -> 77707016 | BM131: =SUMIFS($AA131:$BE131,$AA$3:$BE$3,BM$3) -> 95659912
F132: Staff Costs | G132: =cstRealUnit -> £ Real | AA132: =Z132+AA107 -> 0 | AB132: =AA132+AB107 -> 0 | AC132: =AB132+AC107 -> 0 | AD132: =AC132+AD107 -> 0 | AE132: =AD132+AE107 -> 0 | AF132: =AE132+AF107 -> 0 | AG132: =AF132+AG107 -> 0 | AH132: =AG132+AH107 -> 0 | ... BE132: =BD132+BE107 -> 0 | BG132: =SUMIFS($AA132:$BE132,$AA$3:$BE$3,BG$3) -> 0 | BH132: =SUMIFS($AA132:$BE132,$AA$3:$BE$3,BH$3) -> 0 | BI132: =SUMIFS($AA132:$BE132,$AA$3:$BE$3,BI$3) -> 0 | BJ132: =SUMIFS($AA132:$BE132,$AA$3:$BE$3,BJ$3) -> 0 | BK132: =SUMIFS($AA132:$BE132,$AA$3:$BE$3,BK$3) -> 0 | BL132: =SUMIFS($AA132:$BE132,$AA$3:$BE$3,BL$3) -> 0 | BM132: =SUMIFS($AA132:$BE132,$AA$3:$BE$3,BM$3) -> 0
F133: Software & Hardware Costs | G133: =cstRealUnit -> £ Real | AA133: =Z133+AA108 -> 0 | AB133: =AA133+AB108 -> 0 | AC133: =AB133+AC108 -> 0 | AD133: =AC133+AD108 -> 0 | AE133: =AD133+AE108 -> 0 | AF133: =AE133+AF108 -> 0 | AG133: =AF133+AG108 -> 0 | AH133: =AG133+AH108 -> 0 | ... BE133: =BD133+BE108 -> 0 | BG133: =SUMIFS($AA133:$BE133,$AA$3:$BE$3,BG$3) -> 0 | BH133: =SUMIFS($AA133:$BE133,$AA$3:$BE$3,BH$3) -> 0 | BI133: =SUMIFS($AA133:$BE133,$AA$3:$BE$3,BI$3) -> 0 | BJ133: =SUMIFS($AA133:$BE133,$AA$3:$BE$3,BJ$3) -> 0 | BK133: =SUMIFS($AA133:$BE133,$AA$3:$BE$3,BK$3) -> 0 | BL133: =SUMIFS($AA133:$BE133,$AA$3:$BE$3,BL$3) -> 0 | BM133: =SUMIFS($AA133:$BE133,$AA$3:$BE$3,BM$3) -> 0
...

Sheet Output>>

Sheet oFinancials
C1: THIS CASE STUDY MODEL IS FOR ILLUSTRATIVE PURPOSES
C2: =cstProjectName -> Should Cost Modelling Case Study - Illustrative SCM | Z2: =SysTime!Z2 -> Period Start | AA2: =SysTime!AA2 -> 44652 | AB2: =SysTime!AB2 -> 45017 | AC2: =SysTime!AC2 -> 45383 | AD2: =SysTime!AD2 -> 45748 | AE2: =SysTime!AE2 -> 46113 | AF2: =SysTime!AF2 -> 46478 | AG2: =SysTime!AG2 -> 46844 | ... BE2: =SysTime!BE2 -> 55610 | BG2: =SysTime!BG2 -> 44652 | BH2: =SysTime!BH2 -> 45017 | BI2: =SysTime!BI2 -> 46844 | BJ2: =SysTime!BJ2 -> 48670 | BK2: =SysTime!BK2 -> 50496 | BL2: =SysTime!BL2 -> 52322 | BM2: =SysTime!BM2 -> 54149
C3: =MID(CELL("filename",A1),FIND("]",CELL("filename",A1))+1,256)&" Sheet" -> oFinancials Sheet | Z3: =SysTime!Z3 -> Period End | AA3: =SysTime!AA3 -> 45016 | AB3: =SysTime!AB3 -> 45382 | AC3: =SysTime!AC3 -> 45747 | AD3: =SysTime!AD3 -> 46112 | AE3: =SysTime!AE3 -> 46477 | AF3: =SysTime!AF3 -> 46843 | AG3: =SysTime!AG3 -> 47208 | ... BE3: =SysTime!BE3 -> 55974 | BG3: =SysTime!BG3 -> 45016 | BH3: =SysTime!BH3 -> 46843 | BI3: =SysTime!BI3 -> 48669 | BJ3: =SysTime!BJ3 -> 50495 | BK3: =SysTime!BK3 -> 52321 | BL3: =SysTime!BL3 -> 54148 | BM3: =SysTime!BM3 -> 55974
C4: =IF(ISBLANK(cstProtectiveMarking),"",cstProtectiveMarking) -> Not Protectively Marked | Z4: =SysTime!Z4 -> Timeline | AA4: =SysTime!AA4 -> Annual | AB4: =SysTime!AB4 -> Annual | AC4: =SysTime!AC4 -> Annual | AD4: =SysTime!AD4 -> Annual | AE4: =SysTime!AE4 -> Annual | AF4: =SysTime!AF4 -> Annual | AG4: =SysTime!AG4 -> Annual | ... BE4: =SysTime!BE4 -> Annual | BG4: =SysTime!BG4 -> Annual | BH4: =SysTime!BH4 -> 5 Yearly | BI4: =SysTime!BI4 -> 5 Yearly | BJ4: =SysTime!BJ4 -> 5 Yearly | BK4: =SysTime!BK4 -> 5 Yearly | BL4: =SysTime!BL4 -> 5 Yearly | BM4: =SysTime!BM4 -> 5 Yearly
C5: =HYPERLINK("#'Contents'!A1",sysChkWord) -> All Checks OK | Z5: =SysTime!Z5 -> Period index | AA5: =SysTime!AA5 -> 1 | AB5: =SysTime!AB5 -> 2 | AC5: =SysTime!AC5 -> 3 | AD5: =SysTime!AD5 -> 4 | AE5: =SysTime!AE5 -> 5 | AF5: =SysTime!AF5 -> 6 | AG5: =SysTime!AG5 -> 7 | ... BE5: =SysTime!BE5 -> 31 | BG5: =SysTime!BG5 -> 1 | BH5: =SysTime!BH5 -> 2 | BI5: =SysTime!BI5 -> 3 | BJ5: =SysTime!BJ5 -> 4 | BK5: =SysTime!BK5 -> 5 | BL5: =SysTime!BL5 -> 6 | BM5: =SysTime!BM5 -> 7
C6: =HYPERLINK("#'Contents'!A1","Click for Contents") -> Click for Contents | Z6: =SysTime!Z6 -> Year index | AA6: =SysTime!AA6 -> 1 | AB6: =SysTime!AB6 -> 2 | AC6: =SysTime!AC6 -> 3 | AD6: =SysTime!AD6 -> 4 | AE6: =SysTime!AE6 -> 5 | AF6: =SysTime!AF6 -> 6 | AG6: =SysTime!AG6 -> 7 | ... BE6: =SysTime!BE6 -> 31 | BG6: =SysTime!BG6 -> 0 | BH6: =SysTime!BH6 -> 0 | BI6: =SysTime!BI6 -> 0 | BJ6: =SysTime!BJ6 -> 0 | BK6: =SysTime!BK6 -> 0 | BL6: =SysTime!BL6 -> 0 | BM6: =SysTime!BM6 -> 0
Z7: =SysTime!Z7 -> Relative period | AA7: =SysTime!AA7 -> 1 | AB7: =SysTime!AB7 -> 2 | AC7: =SysTime!AC7 -> 3 | AD7: =SysTime!AD7 -> 4 | AE7: =SysTime!AE7 -> 5 | AF7: =SysTime!AF7 -> 6 | AG7: =SysTime!AG7 -> 7 | ... BE7: =SysTime!BE7 -> 31 | BG7: =SysTime!BG7 -> 1 | BH7: =SysTime!BH7 -> 2 | BI7: =SysTime!BI7 -> 3 | BJ7: =SysTime!BJ7 -> 4 | BK7: =SysTime!BK7 -> 5 | BL7: =SysTime!BL7 -> 6 | BM7: =SysTime!BM7 -> 7
A8: =SUM(A9:A178) -> 0 | B8: =SUM(B9:B178) -> 0 | G8: Units
D10: 1 | E10: Active Scenarios
E12: 1.1 | F12: Scenarios
F14: Planned Maximum Call Volumes Scenario
F16: Cost Scenario
D18: 2 | E18: Costs by Option (Nominal)
E20: 2.1 | F20: In year costs
F22: Options | I22: 31 Yr Total
F24: Build & Operate | G24: =cstNominalUnit -> £ Nominal | I24: =cOutputs!I25 -> 1.0891999e+08 | AA24: =cOutputs!AA25 -> 3045073 | AB24: =cOutputs!AB25 -> 2910738.8 | AC24: =cOutputs!AC25 -> 2402943.2 | AD24: =cOutputs!AD25 -> 2464003.1 | AE24: =cOutputs!AE25 -> 2574911.3 | AF24: =cOutputs!AF25 -> 2590831.1 | AG24: =cOutputs!AG25 -> 2814891.6 | AH24: =cOutputs!AH25 -> 2776977 | ... BE24: =cOutputs!BE25 -> 4854956.4 | BG24: =cOutputs!BG25 -> 3045073 | BH24: =cOutputs!BH25 -> 12943427 | BI24: =cOutputs!BI25 -> 14244752 | BJ24: =cOutputs!BJ25 -> 16091951 | BK24: =cOutputs!BK25 -> 18322558 | BL24: =cOutputs!BL25 -> 20789389 | BM24: =cOutputs!BM25 -> 23482839
F25: Operating Costs | G25: =cstNominalUnit -> £ Nominal | I25: =cOutputs!I26 -> 0 | AA25: =cOutputs!AA26 -> 0 | AB25: =cOutputs!AB26 -> 0 | AC25: =cOutputs!AC26 -> 0 | AD25: =cOutputs!AD26 -> 0 | AE25: =cOutputs!AE26 -> 0 | AF25: =cOutputs!AF26 -> 0 | AG25: =cOutputs!AG26 -> 0 | AH25: =cOutputs!AH26 -> 0 | ... BE25: =cOutputs!BE26 -> 0 | BG25: =cOutputs!BG26 -> 0 | BH25: =cOutputs!BH26 -> 0 | BI25: =cOutputs!BI26 -> 0 | BJ25: =cOutputs!BJ26 -> 0 | BK25: =cOutputs!BK26 -> 0 | BL25: =cOutputs!BL26 -> 0 | BM25: =cOutputs!BM26 -> 0
F26: Staff Costs | G26: =cstNominalUnit -> £ Nominal | I26: =cOutputs!I27 -> 94472985 | AA26: =cOutputs!AA27 -> 0 | AB26: =cOutputs!AB27 -> 2151871.7 | AC26: =cOutputs!AC27 -> 2205668.5 | AD26: =cOutputs!AD27 -> 2260810.2 | AE26: =cOutputs!AE27 -> 2317330.5 | AF26: =cOutputs!AF27 -> 2375263.7 | AG26: =cOutputs!AG27 -> 2434645.3 | AH26: =cOutputs!AH27 -> 2495511.5 | ... BE26: =cOutputs!BE27 -> 4403606.2 | BG26: =cOutputs!BG27 -> 0 | BH26: =cOutputs!BH27 -> 11310945 | BI26: =cOutputs!BI27 -> 12797296 | BJ26: =cOutputs!BJ27 -> 14478965 | BK26: =cOutputs!BK27 -> 16381620 | BL26: =cOutputs!BL27 -> 18534300 | BM26: =cOutputs!BM27 -> 20969859
F27: Software & Hardware Costs | G27: =cstNominalUnit -> £ Nominal | I27: =cOutputs!I28 -> 9930144 | AA27: =cOutputs!AA28 -> 0 | AB27: =cOutputs!AB28 -> 727931.17 | AC27: =cOutputs!AC28 -> 165410.73 | AD27: =cOutputs!AD28 -> 170373.06 | AE27: =cOutputs!AE28 -> 223776.35 | AF27: =cOutputs!AF28 -> 180748.78 | AG27: =cOutputs!AG28 -> 344383.17 | AH27: =cOutputs!AH28 -> 244526.46 | ... BE27: =cOutputs!BE28 -> 378447.8 | BG27: =cOutputs!BG28 -> 0 | BH27: =cOutputs!BH28 -> 1468240.1 | BI27: =cOutputs!BI28 -> 1257053.7 | BJ27: =cOutputs!BJ28 -> 1392257.4 | BK27: =cOutputs!BK28 -> 1685052.3 | BL27: =cOutputs!BL28 -> 1958448.7 | BM27: =cOutputs!BM28 -> 2169091.7
F28: Lease Costs | G28: =cstNominalUnit -> £ Nominal | I28: =cOutputs!I29 -> 0 | AA28: =cOutputs!AA29 -> 0 | AB28: =cOutputs!AB29 -> 0 | AC28: =cOutputs!AC29 -> 0 | AD28: =cOutputs!AD29 -> 0 | AE28: =cOutputs!AE29 -> 0 | AF28: =cOutputs!AF29 -> 0 | AG28: =cOutputs!AG29 -> 0 | AH28: =cOutputs!AH29 -> 0 | ... BE28: =cOutputs!BE29 -> 0 | BG28: =cOutputs!BG29 -> 0 | BH28: =cOutputs!BH29 -> 0 | BI28: =cOutputs!BI29 -> 0 | BJ28: =cOutputs!BJ29 -> 0 | BK28: =cOutputs!BK29 -> 0 | BL28: =cOutputs!BL29 -> 0 | BM28: =cOutputs!BM29 -> 0
F29: Build & Maintenance Costs | G29: =cstNominalUnit -> £ Nominal | I29: =cOutputs!I30 -> 4516860.2 | AA29: =cOutputs!AA30 -> 3045073 | AB29: =cOutputs!AB30 -> 30935.878 | AC29: =cOutputs!AC30 -> 31863.954 | AD29: =cOutputs!AD30 -> 32819.873 | AE29: =cOutputs!AE30 -> 33804.469 | AF29: =cOutputs!AF30 -> 34818.603 | AG29: =cOutputs!AG30 -> 35863.161 | AH29: =cOutputs!AH30 -> 36939.056 | ... BE29: =cOutputs!BE30 -> 72902.422 | BG29: =cOutputs!BG30 -> 3045073 | BH29: =cOutputs!BH30 -> 164242.78 | BI29: =cOutputs!BI30 -> 190402.39 | BJ29: =cOutputs!BJ30 -> 220728.56 | BK29: =cOutputs!BK30 -> 255884.89 | BL29: =cOutputs!BL30 -> 296640.72 | BM29: =cOutputs!BM30 -> 343887.9
A31: =SUM(C31:BM31) -> 0 | F31: Error Check | AA31: =IF(ABS(SUM(AA25:AA29)-AA24)<eTol,0,1) -> 0 | AB31: =IF(ABS(SUM(AB25:AB29)-AB24)<eTol,0,1) -> 0 | AC31: =IF(ABS(SUM(AC25:AC29)-AC24)<eTol,0,1) -> 0 | AD31: =IF(ABS(SUM(AD25:AD29)-AD24)<eTol,0,1) -> 0 | AE31: =IF(ABS(SUM(AE25:AE29)-AE24)<eTol,0,1) -> 0 | AF31: =IF(ABS(SUM(AF25:AF29)-AF24)<eTol,0,1) -> 0 | AG31: =IF(ABS(SUM(AG25:AG29)-AG24)<eTol,0,1) -> 0 | AH31: =IF(ABS(SUM(AH25:AH29)-AH24)<eTol,0,1) -> 0 | ... BE31: =IF(ABS(SUM(BE25:BE29)-BE24)<eTol,0,1) -> 0 | BG31: =IF(ABS(SUM(BG25:BG29)-BG24)<eTol,0,1) -> 0 | BH31: =IF(ABS(SUM(BH25:BH29)-BH24)<eTol,0,1) -> 0 | BI31: =IF(ABS(SUM(BI25:BI29)-BI24)<eTol,0,1) -> 0 | BJ31: =IF(ABS(SUM(BJ25:BJ29)-BJ24)<eTol,0,1) -> 0 | BK31: =IF(ABS(SUM(BK25:BK29)-BK24)<eTol,0,1) -> 0 | BL31: =IF(ABS(SUM(BL25:BL29)-BL24)<eTol,0,1) -> 0 | BM31: =IF(ABS(SUM(BM25:BM29)-BM24)<eTol,0,1) -> 0
F33: Lease & Operate | G33: =cstNominalUnit -> £ Nominal | I33: =cOutputs!I32 -> 1.0678602e+08 | AA33: =cOutputs!AA32 -> 0 | AB33: =cOutputs!AB32 -> 2929889.5 | AC33: =cOutputs!AC32 -> 2422668.5 | AD33: =cOutputs!AD32 -> 2484320.2 | AE33: =cOutputs!AE32 -> 2595837.9 | AF33: =cOutputs!AF32 -> 2612385.5 | AG33: =cOutputs!AG32 -> 2837092.7 | AH33: =cOutputs!AH32 -> 2799844 | ... BE33: =cOutputs!BE32 -> 4900086.5 | BG33: =cOutputs!BG32 -> 0 | BH33: =cOutputs!BH32 -> 13045102 | BI33: =cOutputs!BI32 -> 14362620 | BJ33: =cOutputs!BJ32 -> 16228593 | BK33: =cOutputs!BK32 -> 18480962 | BL33: =cOutputs!BL32 -> 20973024 | BM33: =cOutputs!BM32 -> 23695722
F34: Operating Costs | G34: =cstNominalUnit -> £ Nominal | I34: =cOutputs!I33 -> 0 | AA34: =cOutputs!AA33 -> 0 | AB34: =cOutputs!AB33 -> 0 | AC34: =cOutputs!AC33 -> 0 | AD34: =cOutputs!AD33 -> 0 | AE34: =cOutputs!AE33 -> 0 | AF34: =cOutputs!AF33 -> 0 | AG34: =cOutputs!AG33 -> 0 | AH34: =cOutputs!AH33 -> 0 | ... BE34: =cOutputs!BE33 -> 0 | BG34: =cOutputs!BG33 -> 0 | BH34: =cOutputs!BH33 -> 0 | BI34: =cOutputs!BI33 -> 0 | BJ34: =cOutputs!BJ33 -> 0 | BK34: =cOutputs!BK33 -> 0 | BL34: =cOutputs!BL33 -> 0 | BM34: =cOutputs!BM33 -> 0
F35: Staff Costs | G35: =cstNominalUnit -> £ Nominal | I35: =cOutputs!I34 -> 94472985 | AA35: =cOutputs!AA34 -> 0 | AB35: =cOutputs!AB34 -> 2151871.7 | AC35: =cOutputs!AC34 -> 2205668.5 | AD35: =cOutputs!AD34 -> 2260810.2 | AE35: =cOutputs!AE34 -> 2317330.5 | AF35: =cOutputs!AF34 -> 2375263.7 | AG35: =cOutputs!AG34 -> 2434645.3 | AH35: =cOutputs!AH34 -> 2495511.5 | ... BE35: =cOutputs!BE34 -> 4403606.2 | BG35: =cOutputs!BG34 -> 0 | BH35: =cOutputs!BH34 -> 11310945 | BI35: =cOutputs!BI34 -> 12797296 | BJ35: =cOutputs!BJ34 -> 14478965 | BK35: =cOutputs!BK34 -> 16381620 | BL35: =cOutputs!BL34 -> 18534300 | BM35: =cOutputs!BM34 -> 20969859
F36: Software & Hardware Costs | G36: =cstNominalUnit -> £ Nominal | I36: =cOutputs!I35 -> 9930144 | AA36: =cOutputs!AA35 -> 0 | AB36: =cOutputs!AB35 -> 727931.17 | AC36: =cOutputs!AC35 -> 165410.73 | AD36: =cOutputs!AD35 -> 170373.06 | AE36: =cOutputs!AE35 -> 223776.35 | AF36: =cOutputs!AF35 -> 180748.78 | AG36: =cOutputs!AG35 -> 344383.17 | AH36: =cOutputs!AH35 -> 244526.46 | ... BE36: =cOutputs!BE35 -> 378447.8 | BG36: =cOutputs!BG35 -> 0 | BH36: =cOutputs!BH35 -> 1468240.1 | BI36: =cOutputs!BI35 -> 1257053.7 | BJ36: =cOutputs!BJ35 -> 1392257.4 | BK36: =cOutputs!BK35 -> 1685052.3 | BL36: =cOutputs!BL35 -> 1958448.7 | BM36: =cOutputs!BM35 -> 2169091.7
F37: Lease Costs | G37: =cstNominalUnit -> £ Nominal | I37: =cOutputs!I36 -> 2382893.6 | AA37: =cOutputs!AA36 -> 0 | AB37: =cOutputs!AB36 -> 50086.659 | AC37: =cOutputs!AC36 -> 51589.259 | AD37: =cOutputs!AD36 -> 53136.937 | AE37: =cOutputs!AE36 -> 54731.045 | AF37: =cOutputs!AF36 -> 56372.976 | AG37: =cOutputs!AG36 -> 58064.165 | AH37: =cOutputs!AH36 -> 59806.09 | ... BE37: =cOutputs!BE36 -> 118032.49 | BG37: =cOutputs!BG36 -> 0 | BH37: =cOutputs!BH36 -> 265916.87 | BI37: =cOutputs!BI36 -> 308270.54 | BJ37: =cOutputs!BJ36 -> 357370.04 | BK37: =cOutputs!BK36 -> 414289.83 | BL37: =cOutputs!BL36 -> 480275.46 | BM37: =cOutputs!BM36 -> 556770.88
F38: Build & Maintenance Costs | G38: =cstNominalUnit -> £ Nominal | I38: =cOutputs!I37 -> 0 | AA38: =cOutputs!AA37 -> 0 | AB38: =cOutputs!AB37 -> 0 | AC38: =cOutputs!AC37 -> 0 | AD38: =cOutputs!AD37 -> 0 | AE38: =cOutputs!AE37 -> 0 | AF38: =cOutputs!AF37 -> 0 | AG38: =cOutputs!AG37 -> 0 | AH38: =cOutputs!AH37 -> 0 | ... BE38: =cOutputs!BE37 -> 0 | BG38: =cOutputs!BG37 -> 0 | BH38: =cOutputs!BH37 -> 0 | BI38: =cOutputs!BI37 -> 0 | BJ38: =cOutputs!BJ37 -> 0 | BK38: =cOutputs!BK37 -> 0 | BL38: =cOutputs!BL37 -> 0 | BM38: =cOutputs!BM37 -> 0
A40: =SUM(C40:BM40) -> 0 | F40: Error Check | AA40: =IF(ABS(SUM(AA34:AA38)-AA33)<eTol,0,1) -> 0 | AB40: =IF(ABS(SUM(AB34:AB38)-AB33)<eTol,0,1) -> 0 | AC40: =IF(ABS(SUM(AC34:AC38)-AC33)<eTol,0,1) -> 0 | AD40: =IF(ABS(SUM(AD34:AD38)-AD33)<eTol,0,1) -> 0 | AE40: =IF(ABS(SUM(AE34:AE38)-AE33)<eTol,0,1) -> 0 | AF40: =IF(ABS(SUM(AF34:AF38)-AF33)<eTol,0,1) -> 0 | AG40: =IF(ABS(SUM(AG34:AG38)-AG33)<eTol,0,1) -> 0 | AH40: =IF(ABS(SUM(AH34:AH38)-AH33)<eTol,0,1) -> 0 | ... BE40: =IF(ABS(SUM(BE34:BE38)-BE33)<eTol,0,1) -> 0 | BG40: =IF(ABS(SUM(BG34:BG38)-BG33)<eTol,0,1) -> 0 | BH40: =IF(ABS(SUM(BH34:BH38)-BH33)<eTol,0,1) -> 0 | BI40: =IF(ABS(SUM(BI34:BI38)-BI33)<eTol,0,1) -> 0 | BJ40: =IF(ABS(SUM(BJ34:BJ38)-BJ33)<eTol,0,1) -> 0 | BK40: =IF(ABS(SUM(BK34:BK38)-BK33)<eTol,0,1) -> 0 | BL40: =IF(ABS(SUM(BL34:BL38)-BL33)<eTol,0,1) -> 0 | BM40: =IF(ABS(SUM(BM34:BM38)-BM33)<eTol,0,1) -> 0
F42: Outsource | G42: =cstNominalUnit -> £ Nominal | I42: =cOutputs!I39 -> 1.3230723e+08 | AA42: =cOutputs!AA39 -> 0 | AB42: =cOutputs!AB39 -> 2781000 | AC42: =cOutputs!AC39 -> 2864430 | AD42: =cOutputs!AD39 -> 2950362.9 | AE42: =cOutputs!AE39 -> 3038873.8 | AF42: =cOutputs!AF39 -> 3130040 | AG42: =cOutputs!AG39 -> 3223941.2 | AH42: =cOutputs!AH39 -> 3320659.4 | ... BE42: =cOutputs!BE39 -> 6553608.7 | BG42: =cOutputs!BG39 -> 0 | BH42: =cOutputs!BH39 -> 14764707 | BI42: =cOutputs!BI39 -> 17116342 | BJ42: =cOutputs!BJ39 -> 19842531 | BK42: =cOutputs!BK39 -> 23002932 | BL42: =cOutputs!BL39 -> 26666703 | BM42: =cOutputs!BM39 -> 30914017
F43: Operating Costs | G43: =cstNominalUnit -> £ Nominal | I43: =cOutputs!I40 -> 1.3230723e+08 | AA43: =cOutputs!AA40 -> 0 | AB43: =cOutputs!AB40 -> 2781000 | AC43: =cOutputs!AC40 -> 2864430 | AD43: =cOutputs!AD40 -> 2950362.9 | AE43: =cOutputs!AE40 -> 3038873.8 | AF43: =cOutputs!AF40 -> 3130040 | AG43: =cOutputs!AG40 -> 3223941.2 | AH43: =cOutputs!AH40 -> 3320659.4 | ... BE43: =cOutputs!BE40 -> 6553608.7 | BG43: =cOutputs!BG40 -> 0 | BH43: =cOutputs!BH40 -> 14764707 | BI43: =cOutputs!BI40 -> 17116342 | BJ43: =cOutputs!BJ40 -> 19842531 | BK43: =cOutputs!BK40 -> 23002932 | BL43: =cOutputs!BL40 -> 26666703 | BM43: =cOutputs!BM40 -> 30914017
F44: Staff Costs | G44: =cstNominalUnit -> £ Nominal | I44: =cOutputs!I41 -> 0 | AA44: =cOutputs!AA41 -> 0 | AB44: =cOutputs!AB41 -> 0 | AC44: =cOutputs!AC41 -> 0 | AD44: =cOutputs!AD41 -> 0 | AE44: =cOutputs!AE41 -> 0 | AF44: =cOutputs!AF41 -> 0 | AG44: =cOutputs!AG41 -> 0 | AH44: =cOutputs!AH41 -> 0 | ... BE44: =cOutputs!BE41 -> 0 | BG44: =cOutputs!BG41 -> 0 | BH44: =cOutputs!BH41 -> 0 | BI44: =cOutputs!BI41 -> 0 | BJ44: =cOutputs!BJ41 -> 0 | BK44: =cOutputs!BK41 -> 0 | BL44: =cOutputs!BL41 -> 0 | BM44: =cOutputs!BM41 -> 0
F45: Software & Hardware Costs | G45: =cstNominalUnit -> £ Nominal | I45: =cOutputs!I42 -> 0 | AA45: =cOutputs!AA42 -> 0 | AB45: =cOutputs!AB42 -> 0 | AC45: =cOutputs!AC42 -> 0 | AD45: =cOutputs!AD42 -> 0 | AE45: =cOutputs!AE42 -> 0 | AF45: =cOutputs!AF42 -> 0 | AG45: =cOutputs!AG42 -> 0 | AH45: =cOutputs!AH42 -> 0 | ... BE45: =cOutputs!BE42 -> 0 | BG45: =cOutputs!BG42 -> 0 | BH45: =cOutputs!BH42 -> 0 | BI45: =cOutputs!BI42 -> 0 | BJ45: =cOutputs!BJ42 -> 0 | BK45: =cOutputs!BK42 -> 0 | BL45: =cOutputs!BL42 -> 0 | BM45: =cOutputs!BM42 -> 0
F46: Lease Costs | G46: =cstNominalUnit -> £ Nominal | I46: =cOutputs!I43 -> 0 | AA46: =cOutputs!AA43 -> 0 | AB46: =cOutputs!AB43 -> 0 | AC46: =cOutputs!AC43 -> 0 | AD46: =cOutputs!AD43 -> 0 | AE46: =cOutputs!AE43 -> 0 | AF46: =cOutputs!AF43 -> 0 | AG46: =cOutputs!AG43 -> 0 | AH46: =cOutputs!AH43 -> 0 | ... BE46: =cOutputs!BE43 -> 0 | BG46: =cOutputs!BG43 -> 0 | BH46: =cOutputs!BH43 -> 0 | BI46: =cOutputs!BI43 -> 0 | BJ46: =cOutputs!BJ43 -> 0 | BK46: =cOutputs!BK43 -> 0 | BL46: =cOutputs!BL43 -> 0 | BM46: =cOutputs!BM43 -> 0
F47: Build & Maintenance Costs | G47: =cstNominalUnit -> £ Nominal | I47: =cOutputs!I44 -> 0 | AA47: =cOutputs!AA44 -> 0 | AB47: =cOutputs!AB44 -> 0 | AC47: =cOutputs!AC44 -> 0 | AD47: =cOutputs!AD44 -> 0 | AE47: =cOutputs!AE44 -> 0 | AF47: =cOutputs!AF44 -> 0 | AG47: =cOutputs!AG44 -> 0 | AH47: =cOutputs!AH44 -> 0 | ... BE47: =cOutputs!BE44 -> 0 | BG47: =cOutputs!BG44 -> 0 | BH47: =cOutputs!BH44 -> 0 | BI47: =cOutputs!BI44 -> 0 | BJ47: =cOutputs!BJ44 -> 0 | BK47: =cOutputs!BK44 -> 0 | BL47: =cOutputs!BL44 -> 0 | BM47: =cOutputs!BM44 -> 0
A49: =SUM(C49:BM49) -> 0 | F49: Error Check | AA49: =IF(ABS(SUM(AA43:AA47)-AA42)<eTol,0,1) -> 0 | AB49: =IF(ABS(SUM(AB43:AB47)-AB42)<eTol,0,1) -> 0 | AC49: =IF(ABS(SUM(AC43:AC47)-AC42)<eTol,0,1) -> 0 | AD49: =IF(ABS(SUM(AD43:AD47)-AD42)<eTol,0,1) -> 0 | AE49: =IF(ABS(SUM(AE43:AE47)-AE42)<eTol,0,1) -> 0 | AF49: =IF(ABS(SUM(AF43:AF47)-AF42)<eTol,0,1) -> 0 | AG49: =IF(ABS(SUM(AG43:AG47)-AG42)<eTol,0,1) -> 0 | AH49: =IF(ABS(SUM(AH43:AH47)-AH42)<eTol,0,1) -> 0 | ... BE49: =IF(ABS(SUM(BE43:BE47)-BE42)<eTol,0,1) -> 0 | BG49: =IF(ABS(SUM(BG43:BG47)-BG42)<eTol,0,1) -> 0 | BH49: =IF(ABS(SUM(BH43:BH47)-BH42)<eTol,0,1) -> 0 | BI49: =IF(ABS(SUM(BI43:BI47)-BI42)<eTol,0,1) -> 0 | BJ49: =IF(ABS(SUM(BJ43:BJ47)-BJ42)<eTol,0,1) -> 0 | BK49: =IF(ABS(SUM(BK43:BK47)-BK42)<eTol,0,1) -> 0 | BL49: =IF(ABS(SUM(BL43:BL47)-BL42)<eTol,0,1) -> 0 | BM49: =IF(ABS(SUM(BM43:BM47)-BM42)<eTol,0,1) -> 0
E51: 2.2 | F51: Cumulative Costs
F53: Options
F55: Build & Operate | G55: =cstNominalUnit -> £ Nominal | AA55: =cOutputs!AA50 -> 3045073 | AB55: =cOutputs!AB50 -> 5955811.8 | AC55: =cOutputs!AC50 -> 8358754.9 | AD55: =cOutputs!AD50 -> 10822758 | AE55: =cOutputs!AE50 -> 13397669 | AF55: =cOutputs!AF50 -> 15988500 | AG55: =cOutputs!AG50 -> 18803392 | AH55: =cOutputs!AH50 -> 21580369 | ... BE55: =cOutputs!BE50 -> 1.0891999e+08 | BG55: =cOutputs!BG50 -> 3045073 | BH55: =cOutputs!BH50 -> 15988500 | BI55: =cOutputs!BI50 -> 30233252 | BJ55: =cOutputs!BJ50 -> 46325204 | BK55: =cOutputs!BK50 -> 64647761 | BL55: =cOutputs!BL50 -> 85437150 | BM55: =cOutputs!BM50 -> 1.0891999e+08
F56: Operating Costs | G56: =cstNominalUnit -> £ Nominal | AA56: =cOutputs!AA51 -> 0 | AB56: =cOutputs!AB51 -> 0 | AC56: =cOutputs!AC51 -> 0 | AD56: =cOutputs!AD51 -> 0 | AE56: =cOutputs!AE51 -> 0 | AF56: =cOutputs!AF51 -> 0 | AG56: =cOutputs!AG51 -> 0 | AH56: =cOutputs!AH51 -> 0 | ... BE56: =cOutputs!BE51 -> 0 | BG56: =cOutputs!BG51 -> 0 | BH56: =cOutputs!BH51 -> 0 | BI56: =cOutputs!BI51 -> 0 | BJ56: =cOutputs!BJ51 -> 0 | BK56: =cOutputs!BK51 -> 0 | BL56: =cOutputs!BL51 -> 0 | BM56: =cOutputs!BM51 -> 0
F57: Staff Costs | G57: =cstNominalUnit -> £ Nominal | AA57: =cOutputs!AA52 -> 0 | AB57: =cOutputs!AB52 -> 2151871.7 | AC57: =cOutputs!AC52 -> 4357540.2 | AD57: =cOutputs!AD52 -> 6618350.4 | AE57: =cOutputs!AE52 -> 8935680.9 | AF57: =cOutputs!AF52 -> 11310945 | AG57: =cOutputs!AG52 -> 13745590 | AH57: =cOutputs!AH52 -> 16241101 | ... BE57: =cOutputs!BE52 -> 94472985 | BG57: =cOutputs!BG52 -> 0 | BH57: =cOutputs!BH52 -> 11310945 | BI57: =cOutputs!BI52 -> 24108240 | BJ57: =cOutputs!BJ52 -> 38587206 | BK57: =cOutputs!BK52 -> 54968826 | BL57: =cOutputs!BL52 -> 73503126 | BM57: =cOutputs!BM52 -> 94472985
F58: Software & Hardware Costs | G58: =cstNominalUnit -> £ Nominal | AA58: =cOutputs!AA53 -> 0 | AB58: =cOutputs!AB53 -> 727931.17 | AC58: =cOutputs!AC53 -> 893341.9 | AD58: =cOutputs!AD53 -> 1063715 | AE58: =cOutputs!AE53 -> 1287491.3 | AF58: =cOutputs!AF53 -> 1468240.1 | AG58: =cOutputs!AG53 -> 1812623.2 | AH58: =cOutputs!AH53 -> 2057149.7 | ... BE58: =cOutputs!BE53 -> 9930144 | BG58: =cOutputs!BG53 -> 0 | BH58: =cOutputs!BH53 -> 1468240.1 | BI58: =cOutputs!BI53 -> 2725293.8 | BJ58: =cOutputs!BJ53 -> 4117551.2 | BK58: =cOutputs!BK53 -> 5802603.5 | BL58: =cOutputs!BL53 -> 7761052.2 | BM58: =cOutputs!BM53 -> 9930144
F59: Lease Costs | G59: =cstNominalUnit -> £ Nominal | AA59: =cOutputs!AA54 -> 0 | AB59: =cOutputs!AB54 -> 0 | AC59: =cOutputs!AC54 -> 0 | AD59: =cOutputs!AD54 -> 0 | AE59: =cOutputs!AE54 -> 0 | AF59: =cOutputs!AF54 -> 0 | AG59: =cOutputs!AG54 -> 0 | AH59: =cOutputs!AH54 -> 0 | ... BE59: =cOutputs!BE54 -> 0 | BG59: =cOutputs!BG54 -> 0 | BH59: =cOutputs!BH54 -> 0 | BI59: =cOutputs!BI54 -> 0 | BJ59: =cOutputs!BJ54 -> 0 | BK59: =cOutputs!BK54 -> 0 | BL59: =cOutputs!BL54 -> 0 | BM59: =cOutputs!BM54 -> 0
F60: Build & Maintenance Costs | G60: =cstNominalUnit -> £ Nominal | AA60: =cOutputs!AA55 -> 3045073 | AB60: =cOutputs!AB55 -> 3076008.9 | AC60: =cOutputs!AC55 -> 3107872.8 | AD60: =cOutputs!AD55 -> 3140692.7 | AE60: =cOutputs!AE55 -> 3174497.2 | AF60: =cOutputs!AF55 -> 3209315.8 | AG60: =cOutputs!AG55 -> 3245178.9 | AH60: =cOutputs!AH55 -> 3282118 | ... BE60: =cOutputs!BE55 -> 4516860.2 | BG60: =cOutputs!BG55 -> 3045073 | BH60: =cOutputs!BH55 -> 3209315.8 | BI60: =cOutputs!BI55 -> 3399718.2 | BJ60: =cOutputs!BJ55 -> 3620446.7 | BK60: =cOutputs!BK55 -> 3876331.6 | BL60: =cOutputs!BL55 -> 4172972.3 | BM60: =cOutputs!BM55 -> 4516860.2
A62: =SUM(C62:BM62) -> 0 | F62: Error Check | AA62: =IF(ABS(SUM(AA56:AA60)-AA55)<eTol,0,1) -> 0 | AB62: =IF(ABS(SUM(AB56:AB60)-AB55)<eTol,0,1) -> 0 | AC62: =IF(ABS(SUM(AC56:AC60)-AC55)<eTol,0,1) -> 0 | AD62: =IF(ABS(SUM(AD56:AD60)-AD55)<eTol,0,1) -> 0 | AE62: =IF(ABS(SUM(AE56:AE60)-AE55)<eTol,0,1) -> 0 | AF62: =IF(ABS(SUM(AF56:AF60)-AF55)<eTol,0,1) -> 0 | AG62: =IF(ABS(SUM(AG56:AG60)-AG55)<eTol,0,1) -> 0 | AH62: =IF(ABS(SUM(AH56:AH60)-AH55)<eTol,0,1) -> 0 | ... BE62: =IF(ABS(SUM(BE56:BE60)-BE55)<eTol,0,1) -> 0 | BG62: =IF(ABS(SUM(BG56:BG60)-BG55)<eTol,0,1) -> 0 | BH62: =IF(ABS(SUM(BH56:BH60)-BH55)<eTol,0,1) -> 0 | BI62: =IF(ABS(SUM(BI56:BI60)-BI55)<eTol,0,1) -> 0 | BJ62: =IF(ABS(SUM(BJ56:BJ60)-BJ55)<eTol,0,1) -> 0 | BK62: =IF(ABS(SUM(BK56:BK60)-BK55)<eTol,0,1) -> 0 | BL62: =IF(ABS(SUM(BL56:BL60)-BL55)<eTol,0,1) -> 0 | BM62: =IF(ABS(SUM(BM56:BM60)-BM55)<eTol,0,1) -> 0
F64: Lease & Operate | G64: =cstNominalUnit -> £ Nominal | AA64: =cOutputs!AA57 -> 0 | AB64: =cOutputs!AB57 -> 2929889.5 | AC64: =cOutputs!AC57 -> 5352558 | AD64: =cOutputs!AD57 -> 7836878.2 | AE64: =cOutputs!AE57 -> 10432716 | AF64: =cOutputs!AF57 -> 13045102 | AG64: =cOutputs!AG57 -> 15882194 | AH64: =cOutputs!AH57 -> 18682038 | ... BE64: =cOutputs!BE57 -> 1.0678602e+08 | BG64: =cOutputs!BG57 -> 0 | BH64: =cOutputs!BH57 -> 13045102 | BI64: =cOutputs!BI57 -> 27407721 | BJ64: =cOutputs!BJ57 -> 43636314 | BK64: =cOutputs!BK57 -> 62117277 | BL64: =cOutputs!BL57 -> 83090301 | BM64: =cOutputs!BM57 -> 1.0678602e+08
F65: Operating Costs | G65: =cstNominalUnit -> £ Nominal | AA65: =cOutputs!AA58 -> 0 | AB65: =cOutputs!AB58 -> 0 | AC65: =cOutputs!AC58 -> 0 | AD65: =cOutputs!AD58 -> 0 | AE65: =cOutputs!AE58 -> 0 | AF65: =cOutputs!AF58 -> 0 | AG65: =cOutputs!AG58 -> 0 | AH65: =cOutputs!AH58 -> 0 | ... BE65: =cOutputs!BE58 -> 0 | BG65: =cOutputs!BG58 -> 0 | BH65: =cOutputs!BH58 -> 0 | BI65: =cOutputs!BI58 -> 0 | BJ65: =cOutputs!BJ58 -> 0 | BK65: =cOutputs!BK58 -> 0 | BL65: =cOutputs!BL58 -> 0 | BM65: =cOutputs!BM58 -> 0
F66: Staff Costs | G66: =cstNominalUnit -> £ Nominal | AA66: =cOutputs!AA59 -> 0 | AB66: =cOutputs!AB59 -> 2151871.7 | AC66: =cOutputs!AC59 -> 4357540.2 | AD66: =cOutputs!AD59 -> 6618350.4 | AE66: =cOutputs!AE59 -> 8935680.9 | AF66: =cOutputs!AF59 -> 11310945 | AG66: =cOutputs!AG59 -> 13745590 | AH66: =cOutputs!AH59 -> 16241101 | ... BE66: =cOutputs!BE59 -> 94472985 | BG66: =cOutputs!BG59 -> 0 | BH66: =cOutputs!BH59 -> 11310945 | BI66: =cOutputs!BI59 -> 24108240 | BJ66: =cOutputs!BJ59 -> 38587206 | BK66: =cOutputs!BK59 -> 54968826 | BL66: =cOutputs!BL59 -> 73503126 | BM66: =cOutputs!BM59 -> 94472985
F67: Software & Hardware Costs | G67: =cstNominalUnit -> £ Nominal | AA67: =cOutputs!AA60 -> 0 | AB67: =cOutputs!AB60 -> 727931.17 | AC67: =cOutputs!AC60 -> 893341.9 | AD67: =cOutputs!AD60 -> 1063715 | AE67: =cOutputs!AE60 -> 1287491.3 | AF67: =cOutputs!AF60 -> 1468240.1 | AG67: =cOutputs!AG60 -> 1812623.2 | AH67: =cOutputs!AH60 -> 2057149.7 | ... BE67: =cOutputs!BE60 -> 9930144 | BG67: =cOutputs!BG60 -> 0 | BH67: =cOutputs!BH60 -> 1468240.1 | BI67: =cOutputs!BI60 -> 2725293.8 | BJ67: =cOutputs!BJ60 -> 4117551.2 | BK67: =cOutputs!BK60 -> 5802603.5 | BL67: =cOutputs!BL60 -> 7761052.2 | BM67: =cOutputs!BM60 -> 9930144
F68: Lease Costs | G68: =cstNominalUnit -> £ Nominal | AA68: =cOutputs!AA61 -> 0 | AB68: =cOutputs!AB61 -> 50086.659 | AC68: =cOutputs!AC61 -> 101675.92 | AD68: =cOutputs!AD61 -> 154812.85 | AE68: =cOutputs!AE61 -> 209543.9 | AF68: =cOutputs!AF61 -> 265916.87 | AG68: =cOutputs!AG61 -> 323981.04 | AH68: =cOutputs!AH61 -> 383787.13 | ... BE68: =cOutputs!BE61 -> 2382893.6 | BG68: =cOutputs!BG61 -> 0 | BH68: =cOutputs!BH61 -> 265916.87 | BI68: =cOutputs!BI61 -> 574187.41 | BJ68: =cOutputs!BJ61 -> 931557.46 | BK68: =cOutputs!BK61 -> 1345847.3 | BL68: =cOutputs!BL61 -> 1826122.7 | BM68: =cOutputs!BM61 -> 2382893.6
F69: Build & Maintenance Costs | G69: =cstNominalUnit -> £ Nominal | AA69: =cOutputs!AA62 -> 0 | AB69: =cOutputs!AB62 -> 0 | AC69: =cOutputs!AC62 -> 0 | AD69: =cOutputs!AD62 -> 0 | AE69: =cOutputs!AE62 -> 0 | AF69: =cOutputs!AF62 -> 0 | AG69: =cOutputs!AG62 -> 0 | AH69: =cOutputs!AH62 -> 0 | ... BE69: =cOutputs!BE62 -> 0 | BG69: =cOutputs!BG62 -> 0 | BH69: =cOutputs!BH62 -> 0 | BI69: =cOutputs!BI62 -> 0 | BJ69: =cOutputs!BJ62 -> 0 | BK69: =cOutputs!BK62 -> 0 | BL69: =cOutputs!BL62 -> 0 | BM69: =cOutputs!BM62 -> 0
A71: =SUM(C71:BM71) -> 0 | F71: Error Check | AA71: =IF(ABS(SUM(AA65:AA69)-AA64)<eTol,0,1) -> 0 | AB71: =IF(ABS(SUM(AB65:AB69)-AB64)<eTol,0,1) -> 0 | AC71: =IF(ABS(SUM(AC65:AC69)-AC64)<eTol,0,1) -> 0 | AD71: =IF(ABS(SUM(AD65:AD69)-AD64)<eTol,0,1) -> 0 | AE71: =IF(ABS(SUM(AE65:AE69)-AE64)<eTol,0,1) -> 0 | AF71: =IF(ABS(SUM(AF65:AF69)-AF64)<eTol,0,1) -> 0 | AG71: =IF(ABS(SUM(AG65:AG69)-AG64)<eTol,0,1) -> 0 | AH71: =IF(ABS(SUM(AH65:AH69)-AH64)<eTol,0,1) -> 0 | ... BE71: =IF(ABS(SUM(BE65:BE69)-BE64)<eTol,0,1) -> 0 | BG71: =IF(ABS(SUM(BG65:BG69)-BG64)<eTol,0,1) -> 0 | BH71: =IF(ABS(SUM(BH65:BH69)-BH64)<eTol,0,1) -> 0 | BI71: =IF(ABS(SUM(BI65:BI69)-BI64)<eTol,0,1) -> 0 | BJ71: =IF(ABS(SUM(BJ65:BJ69)-BJ64)<eTol,0,1) -> 0 | BK71: =IF(ABS(SUM(BK65:BK69)-BK64)<eTol,0,1) -> 0 | BL71: =IF(ABS(SUM(BL65:BL69)-BL64)<eTol,0,1) -> 0 | BM71: =IF(ABS(SUM(BM65:BM69)-BM64)<eTol,0,1) -> 0
F73: Outsource | G73: =cstNominalUnit -> £ Nominal | AA73: =cOutputs!AA64 -> 0 | AB73: =cOutputs!AB64 -> 2781000 | AC73: =cOutputs!AC64 -> 5645430 | AD73: =cOutputs!AD64 -> 8595792.9 | AE73: =cOutputs!AE64 -> 11634667 | AF73: =cOutputs!AF64 -> 14764707 | AG73: =cOutputs!AG64 -> 17988648 | AH73: =cOutputs!AH64 -> 21309307 | ... BE73: =cOutputs!BE64 -> 1.3230723e+08 | BG73: =cOutputs!BG64 -> 0 | BH73: =cOutputs!BH64 -> 14764707 | BI73: =cOutputs!BI64 -> 31881048 | BJ73: =cOutputs!BJ64 -> 51723580 | BK73: =cOutputs!BK64 -> 74726511 | BL73: =cOutputs!BL64 -> 1.0139321e+08 | BM73: =cOutputs!BM64 -> 1.3230723e+08
F74: Operating Costs | G74: =cstNominalUnit -> £ Nominal | AA74: =cOutputs!AA65 -> 0 | AB74: =cOutputs!AB65 -> 2781000 | AC74: =cOutputs!AC65 -> 5645430 | AD74: =cOutputs!AD65 -> 8595792.9 | AE74: =cOutputs!AE65 -> 11634667 | AF74: =cOutputs!AF65 -> 14764707 | AG74: =cOutputs!AG65 -> 17988648 | AH74: =cOutputs!AH65 -> 21309307 | ... BE74: =cOutputs!BE65 -> 1.3230723e+08 | BG74: =cOutputs!BG65 -> 0 | BH74: =cOutputs!BH65 -> 14764707 | BI74: =cOutputs!BI65 -> 31881048 | BJ74: =cOutputs!BJ65 -> 51723580 | BK74: =cOutputs!BK65 -> 74726511 | BL74: =cOutputs!BL65 -> 1.0139321e+08 | BM74: =cOutputs!BM65 -> 1.3230723e+08
F75: Staff Costs | G75: =cstNominalUnit -> £ Nominal | AA75: =cOutputs!AA66 -> 0 | AB75: =cOutputs!AB66 -> 0 | AC75: =cOutputs!AC66 -> 0 | AD75: =cOutputs!AD66 -> 0 | AE75: =cOutputs!AE66 -> 0 | AF75: =cOutputs!AF66 -> 0 | AG75: =cOutputs!AG66 -> 0 | AH75: =cOutputs!AH66 -> 0 | ... BE75: =cOutputs!BE66 -> 0 | BG75: =cOutputs!BG66 -> 0 | BH75: =cOutputs!BH66 -> 0 | BI75: =cOutputs!BI66 -> 0 | BJ75: =cOutputs!BJ66 -> 0 | BK75: =cOutputs!BK66 -> 0 | BL75: =cOutputs!BL66 -> 0 | BM75: =cOutputs!BM66 -> 0
F76: Software & Hardware Costs | G76: =cstNominalUnit -> £ Nominal | AA76: =cOutputs!AA67 -> 0 | AB76: =cOutputs!AB67 -> 0 | AC76: =cOutputs!AC67 -> 0 | AD76: =cOutputs!AD67 -> 0 | AE76: =cOutputs!AE67 -> 0 | AF76: =cOutputs!AF67 -> 0 | AG76: =cOutputs!AG67 -> 0 | AH76: =cOutputs!AH67 -> 0 | ... BE76: =cOutputs!BE67 -> 0 | BG76: =cOutputs!BG67 -> 0 | BH76: =cOutputs!BH67 -> 0 | BI76: =cOutputs!BI67 -> 0 | BJ76: =cOutputs!BJ67 -> 0 | BK76: =cOutputs!BK67 -> 0 | BL76: =cOutputs!BL67 -> 0 | BM76: =cOutputs!BM67 -> 0
F77: Lease Costs | G77: =cstNominalUnit -> £ Nominal | AA77: =cOutputs!AA68 -> 0 | AB77: =cOutputs!AB68 -> 0 | AC77: =cOutputs!AC68 -> 0 | AD77: =cOutputs!AD68 -> 0 | AE77: =cOutputs!AE68 -> 0 | AF77: =cOutputs!AF68 -> 0 | AG77: =cOutputs!AG68 -> 0 | AH77: =cOutputs!AH68 -> 0 | ... BE77: =cOutputs!BE68 -> 0 | BG77: =cOutputs!BG68 -> 0 | BH77: =cOutputs!BH68 -> 0 | BI77: =cOutputs!BI68 -> 0 | BJ77: =cOutputs!BJ68 -> 0 | BK77: =cOutputs!BK68 -> 0 | BL77: =cOutputs!BL68 -> 0 | BM77: =cOutputs!BM68 -> 0
F78: Build & Maintenance Costs | G78: =cstNominalUnit -> £ Nominal | AA78: =cOutputs!AA69 -> 0 | AB78: =cOutputs!AB69 -> 0 | AC78: =cOutputs!AC69 -> 0 | AD78: =cOutputs!AD69 -> 0 | AE78: =cOutputs!AE69 -> 0 | AF78: =cOutputs!AF69 -> 0 | AG78: =cOutputs!AG69 -> 0 | AH78: =cOutputs!AH69 -> 0 | ... BE78: =cOutputs!BE69 -> 0 | BG78: =cOutputs!BG69 -> 0 | BH78: =cOutputs!BH69 -> 0 | BI78: =cOutputs!BI69 -> 0 | BJ78: =cOutputs!BJ69 -> 0 | BK78: =cOutputs!BK69 -> 0 | BL78: =cOutputs!BL69 -> 0 | BM78: =cOutputs!BM69 -> 0
A80: =SUM(C80:BM80) -> 0 | F80: Error Check | AA80: =IF(ABS(SUM(AA74:AA78)-AA73)<eTol,0,1) -> 0 | AB80: =IF(ABS(SUM(AB74:AB78)-AB73)<eTol,0,1) -> 0 | AC80: =IF(ABS(SUM(AC74:AC78)-AC73)<eTol,0,1) -> 0 | AD80: =IF(ABS(SUM(AD74:AD78)-AD73)<eTol,0,1) -> 0 | AE80: =IF(ABS(SUM(AE74:AE78)-AE73)<eTol,0,1) -> 0 | AF80: =IF(ABS(SUM(AF74:AF78)-AF73)<eTol,0,1) -> 0 | AG80: =IF(ABS(SUM(AG74:AG78)-AG73)<eTol,0,1) -> 0 | AH80: =IF(ABS(SUM(AH74:AH78)-AH73)<eTol,0,1) -> 0 | ... BE80: =IF(ABS(SUM(BE74:BE78)-BE73)<eTol,0,1) -> 0 | BG80: =IF(ABS(SUM(BG74:BG78)-BG73)<eTol,0,1) -> 0 | BH80: =IF(ABS(SUM(BH74:BH78)-BH73)<eTol,0,1) -> 0 | BI80: =IF(ABS(SUM(BI74:BI78)-BI73)<eTol,0,1) -> 0 | BJ80: =IF(ABS(SUM(BJ74:BJ78)-BJ73)<eTol,0,1) -> 0 | BK80: =IF(ABS(SUM(BK74:BK78)-BK73)<eTol,0,1) -> 0 | BL80: =IF(ABS(SUM(BL74:BL78)-BL73)<eTol,0,1) -> 0 | BM80: =IF(ABS(SUM(BM74:BM78)-BM73)<eTol,0,1) -> 0
E82: 2.3 | F82: Average Cost per Call Hour
F84: Options
F86: Build & Operate | G86: =cstNominalUnit -> £ Nominal | I86: =cOutputs!I79 -> 40.340737
F88: Lease & Operate | G88: =cstNominalUnit -> £ Nominal | I88: =cOutputs!I81 -> 39.550379
F90: Outsource | G90: =cstNominalUnit -> £ Nominal | I90: =cOutputs!I83 -> 49.002678
D92: 3 | E92: Costs by Option (Real)
E94: 3.1 | F94: In year costs
F96: Options | I96: 31 Yr Total
F98: Build & Operate | G98: =cstRealUnit -> £ Real | I98: =cOutputs!I91 -> 80228511 | AA98: =cOutputs!AA91 -> 3045073 | AB98: =cOutputs!AB91 -> 2873384.7 | AC98: =cOutputs!AC91 -> 2332454.1 | AD98: =cOutputs!AD91 -> 2347127.5 | AE98: =cOutputs!AE91 -> 2407041.1 | AF98: =cOutputs!AF91 -> 2374434.3 | AG98: =cOutputs!AG91 -> 2529196.5 | AH98: =cOutputs!AH91 -> 2446205.8 | ... BE98: =cOutputs!BE91 -> 2712077.5 | BG98: =cOutputs!BG91 -> 3045073 | BH98: =cOutputs!BH91 -> 12334442 | BI98: =cOutputs!BI91 -> 12299226 | BJ98: =cOutputs!BJ91 -> 12585511 | BK98: =cOutputs!BK91 -> 12980246 | BL98: =cOutputs!BL91 -> 13337444 | BM98: =cOutputs!BM91 -> 13646569
F99: Operating Costs | G99: =cstRealUnit -> £ Real | I99: =cOutputs!I92 -> 0 | AA99: =cOutputs!AA92 -> 0 | AB99: =cOutputs!AB92 -> 0 | AC99: =cOutputs!AC92 -> 0 | AD99: =cOutputs!AD92 -> 0 | AE99: =cOutputs!AE92 -> 0 | AF99: =cOutputs!AF92 -> 0 | AG99: =cOutputs!AG92 -> 0 | AH99: =cOutputs!AH92 -> 0 | ... BE99: =cOutputs!BE92 -> 0 | BG99: =cOutputs!BG92 -> 0 | BH99: =cOutputs!BH92 -> 0 | BI99: =cOutputs!BI92 -> 0 | BJ99: =cOutputs!BJ92 -> 0 | BK99: =cOutputs!BK92 -> 0 | BL99: =cOutputs!BL92 -> 0 | BM99: =cOutputs!BM92 -> 0
F100: Staff Costs | G100: =cstRealUnit -> £ Real | I100: =cOutputs!I93 -> 68791697 | AA100: =cOutputs!AA93 -> 0 | AB100: =cOutputs!AB93 -> 2124256.4 | AC100: =cOutputs!AC93 -> 2140966.4 | AD100: =cOutputs!AD93 -> 2153572.6 | AE100: =cOutputs!AE93 -> 2166253.1 | AF100: =cOutputs!AF93 -> 2176872 | AG100: =cOutputs!AG93 -> 2187543 | AH100: =cOutputs!AH93 -> 2198266.2 | ... BE100: =cOutputs!BE93 -> 2459944.1 | BG100: =cOutputs!BG93 -> 0 | BH100: =cOutputs!BH93 -> 10761921 | BI100: =cOutputs!BI93 -> 11045474 | BJ100: =cOutputs!BJ93 -> 11318864 | BK100: =cOutputs!BK93 -> 11599020 | BL100: =cOutputs!BL93 -> 11886111 | BM100: =cOutputs!BM93 -> 12180307
F101: Software & Hardware Costs | G101: =cstRealUnit -> £ Real | I101: =cOutputs!I94 -> 7327618.8 | AA101: =cOutputs!AA94 -> 0 | AB101: =cOutputs!AB94 -> 718589.5 | AC101: =cOutputs!AC94 -> 160558.5 | AD101: =cOutputs!AD94 -> 162291.71 | AE101: =cOutputs!AE94 -> 209187.35 | AF101: =cOutputs!AF94 -> 165651.9 | AG101: =cOutputs!AG94 -> 309430.28 | AH101: =cOutputs!AH94 -> 215400.43 | ... BE101: =cOutputs!BE94 -> 211408.65 | BG101: =cOutputs!BG94 -> 0 | BH101: =cOutputs!BH94 -> 1416279 | BI101: =cOutputs!BI94 -> 1089444.9 | BJ101: =cOutputs!BJ94 -> 1094127.1 | BK101: =cOutputs!BK94 -> 1200080.8 | BL101: =cOutputs!BL94 -> 1261133.5 | BM101: =cOutputs!BM94 -> 1266553.6
F102: Lease Costs | G102: =cstRealUnit -> £ Real | I102: =cOutputs!I95 -> 0 | AA102: =cOutputs!AA95 -> 0 | AB102: =cOutputs!AB95 -> 0 | AC102: =cOutputs!AC95 -> 0 | AD102: =cOutputs!AD95 -> 0 | AE102: =cOutputs!AE95 -> 0 | AF102: =cOutputs!AF95 -> 0 | AG102: =cOutputs!AG95 -> 0 | AH102: =cOutputs!AH95 -> 0 | ... BE102: =cOutputs!BE95 -> 0 | BG102: =cOutputs!BG95 -> 0 | BH102: =cOutputs!BH95 -> 0 | BI102: =cOutputs!BI95 -> 0 | BJ102: =cOutputs!BJ95 -> 0 | BK102: =cOutputs!BK95 -> 0 | BL102: =cOutputs!BL95 -> 0 | BM102: =cOutputs!BM95 -> 0
F103: Build & Maintenance Costs | G103: =cstRealUnit -> £ Real | I103: =cOutputs!I96 -> 4109195 | AA103: =cOutputs!AA96 -> 3045073 | AB103: =cOutputs!AB96 -> 30538.872 | AC103: =cOutputs!AC96 -> 30929.241 | AD103: =cOutputs!AD96 -> 31263.119 | AE103: =cOutputs!AE96 -> 31600.601 | AF103: =cOutputs!AF96 -> 31910.411 | AG103: =cOutputs!AG96 -> 32223.258 | AH103: =cOutputs!AH96 -> 32539.173 | ... BE103: =cOutputs!BE96 -> 40724.778 | BG103: =cOutputs!BG96 -> 3045073 | BH103: =cOutputs!BH96 -> 156242.25 | BI103: =cOutputs!BI96 -> 164306.56 | BJ103: =cOutputs!BJ96 -> 172520.28 | BK103: =cOutputs!BK96 -> 181144.62 | BL103: =cOutputs!BL96 -> 190200.08 | BM103: =cOutputs!BM96 -> 199708.23
A105: =SUM(C105:BM105) -> 0 | F105: Error Check | AA105: =IF(ABS(SUM(AA99:AA103)-AA98)<eTol,0,1) -> 0 | AB105: =IF(ABS(SUM(AB99:AB103)-AB98)<eTol,0,1) -> 0 | AC105: =IF(ABS(SUM(AC99:AC103)-AC98)<eTol,0,1) -> 0 | AD105: =IF(ABS(SUM(AD99:AD103)-AD98)<eTol,0,1) -> 0 | AE105: =IF(ABS(SUM(AE99:AE103)-AE98)<eTol,0,1) -> 0 | AF105: =IF(ABS(SUM(AF99:AF103)-AF98)<eTol,0,1) -> 0 | AG105: =IF(ABS(SUM(AG99:AG103)-AG98)<eTol,0,1) -> 0 | AH105: =IF(ABS(SUM(AH99:AH103)-AH98)<eTol,0,1) -> 0 | ... BE105: =IF(ABS(SUM(BE99:BE103)-BE98)<eTol,0,1) -> 0 | BG105: =IF(ABS(SUM(BG99:BG103)-BG98)<eTol,0,1) -> 0 | BH105: =IF(ABS(SUM(BH99:BH103)-BH98)<eTol,0,1) -> 0 | BI105: =IF(ABS(SUM(BI99:BI103)-BI98)<eTol,0,1) -> 0 | BJ105: =IF(ABS(SUM(BJ99:BJ103)-BJ98)<eTol,0,1) -> 0 | BK105: =IF(ABS(SUM(BK99:BK103)-BK98)<eTol,0,1) -> 0 | BL105: =IF(ABS(SUM(BL99:BL103)-BL98)<eTol,0,1) -> 0 | BM105: =IF(ABS(SUM(BM99:BM103)-BM98)<eTol,0,1) -> 0
F107: Lease & Operate | G107: =cstRealUnit -> £ Real | I107: =cOutputs!I98 -> 77842180 | AA107: =cOutputs!AA98 -> 0 | AB107: =cOutputs!AB98 -> 2892289.8 | AC107: =cOutputs!AC98 -> 2351600.8 | AD107: =cOutputs!AD98 -> 2366480.8 | AE107: =cOutputs!AE98 -> 2426603.4 | AF107: =cOutputs!AF98 -> 2394188.4 | AG107: =cOutputs!AG98 -> 2549144.2 | AH107: =cOutputs!AH98 -> 2466349.1 | ... BE107: =cOutputs!BE98 -> 2737288.1 | BG107: =cOutputs!BG98 -> 0 | BH107: =cOutputs!BH98 -> 12431163 | BI107: =cOutputs!BI98 -> 12400939 | BJ107: =cOutputs!BJ98 -> 12692310 | BK107: =cOutputs!BK98 -> 13092383 | BL107: =cOutputs!BL98 -> 13455187 | BM107: =cOutputs!BM98 -> 13770198
F108: Operating Costs | G108: =cstRealUnit -> £ Real | I108: =cOutputs!I99 -> 0 | AA108: =cOutputs!AA99 -> 0 | AB108: =cOutputs!AB99 -> 0 | AC108: =cOutputs!AC99 -> 0 | AD108: =cOutputs!AD99 -> 0 | AE108: =cOutputs!AE99 -> 0 | AF108: =cOutputs!AF99 -> 0 | AG108: =cOutputs!AG99 -> 0 | AH108: =cOutputs!AH99 -> 0 | ... BE108: =cOutputs!BE99 -> 0 | BG108: =cOutputs!BG99 -> 0 | BH108: =cOutputs!BH99 -> 0 | BI108: =cOutputs!BI99 -> 0 | BJ108: =cOutputs!BJ99 -> 0 | BK108: =cOutputs!BK99 -> 0 | BL108: =cOutputs!BL99 -> 0 | BM108: =cOutputs!BM99 -> 0
F109: Staff Costs | G109: =cstRealUnit -> £ Real | I109: =cOutputs!I100 -> 68791697 | AA109: =cOutputs!AA100 -> 0 | AB109: =cOutputs!AB100 -> 2124256.4 | AC109: =cOutputs!AC100 -> 2140966.4 | AD109: =cOutputs!AD100 -> 2153572.6 | AE109: =cOutputs!AE100 -> 2166253.1 | AF109: =cOutputs!AF100 -> 2176872 | AG109: =cOutputs!AG100 -> 2187543 | AH109: =cOutputs!AH100 -> 2198266.2 | ... BE109: =cOutputs!BE100 -> 2459944.1 | BG109: =cOutputs!BG100 -> 0 | BH109: =cOutputs!BH100 -> 10761921 | BI109: =cOutputs!BI100 -> 11045474 | BJ109: =cOutputs!BJ100 -> 11318864 | BK109: =cOutputs!BK100 -> 11599020 | BL109: =cOutputs!BL100 -> 11886111 | BM109: =cOutputs!BM100 -> 12180307
F110: Software & Hardware Costs | G110: =cstRealUnit -> £ Real | I110: =cOutputs!I101 -> 7327618.8 | AA110: =cOutputs!AA101 -> 0 | AB110: =cOutputs!AB101 -> 718589.5 | AC110: =cOutputs!AC101 -> 160558.5 | AD110: =cOutputs!AD101 -> 162291.71 | AE110: =cOutputs!AE101 -> 209187.35 | AF110: =cOutputs!AF101 -> 165651.9 | AG110: =cOutputs!AG101 -> 309430.28 | AH110: =cOutputs!AH101 -> 215400.43 | ... BE110: =cOutputs!BE101 -> 211408.65 | BG110: =cOutputs!BG101 -> 0 | BH110: =cOutputs!BH101 -> 1416279 | BI110: =cOutputs!BI101 -> 1089444.9 | BJ110: =cOutputs!BJ101 -> 1094127.1 | BK110: =cOutputs!BK101 -> 1200080.8 | BL110: =cOutputs!BL101 -> 1261133.5 | BM110: =cOutputs!BM101 -> 1266553.6
F111: Lease Costs | G111: =cstRealUnit -> £ Real | I111: =cOutputs!I102 -> 1722864.2 | AA111: =cOutputs!AA102 -> 0 | AB111: =cOutputs!AB102 -> 49443.888 | AC111: =cOutputs!AC102 -> 50075.915 | AD111: =cOutputs!AD102 -> 50616.479 | AE111: =cOutputs!AE102 -> 51162.879 | AF111: =cOutputs!AF102 -> 51664.475 | AG111: =cOutputs!AG102 -> 52170.99 | AH111: =cOutputs!AH102 -> 52682.47 | ... BE111: =cOutputs!BE102 -> 65935.355 | BG111: =cOutputs!BG102 -> 0 | BH111: =cOutputs!BH102 -> 252963.64 | BI111: =cOutputs!BI102 -> 266020.14 | BJ111: =cOutputs!BJ102 -> 279318.56 | BK111: =cOutputs!BK102 -> 293281.76 | BL111: =cOutputs!BL102 -> 307942.99 | BM111: =cOutputs!BM102 -> 323337.13
F112: Build & Maintenance Costs | G112: =cstRealUnit -> £ Real | I112: =cOutputs!I103 -> 0 | AA112: =cOutputs!AA103 -> 0 | AB112: =cOutputs!AB103 -> 0 | AC112: =cOutputs!AC103 -> 0 | AD112: =cOutputs!AD103 -> 0 | AE112: =cOutputs!AE103 -> 0 | AF112: =cOutputs!AF103 -> 0 | AG112: =cOutputs!AG103 -> 0 | AH112: =cOutputs!AH103 -> 0 | ... BE112: =cOutputs!BE103 -> 0 | BG112: =cOutputs!BG103 -> 0 | BH112: =cOutputs!BH103 -> 0 | BI112: =cOutputs!BI103 -> 0 | BJ112: =cOutputs!BJ103 -> 0 | BK112: =cOutputs!BK103 -> 0 | BL112: =cOutputs!BL103 -> 0 | BM112: =cOutputs!BM103 -> 0
A114: =SUM(C114:BM114) -> 0 | F114: Error Check | AA114: =IF(ABS(SUM(AA108:AA112)-AA107)<eTol,0,1) -> 0 | AB114: =IF(ABS(SUM(AB108:AB112)-AB107)<eTol,0,1) -> 0 | AC114: =IF(ABS(SUM(AC108:AC112)-AC107)<eTol,0,1) -> 0 | AD114: =IF(ABS(SUM(AD108:AD112)-AD107)<eTol,0,1) -> 0 | AE114: =IF(ABS(SUM(AE108:AE112)-AE107)<eTol,0,1) -> 0 | AF114: =IF(ABS(SUM(AF108:AF112)-AF107)<eTol,0,1) -> 0 | AG114: =IF(ABS(SUM(AG108:AG112)-AG107)<eTol,0,1) -> 0 | AH114: =IF(ABS(SUM(AH108:AH112)-AH107)<eTol,0,1) -> 0 | ... BE114: =IF(ABS(SUM(BE108:BE112)-BE107)<eTol,0,1) -> 0 | BG114: =IF(ABS(SUM(BG108:BG112)-BG107)<eTol,0,1) -> 0 | BH114: =IF(ABS(SUM(BH108:BH112)-BH107)<eTol,0,1) -> 0 | BI114: =IF(ABS(SUM(BI108:BI112)-BI107)<eTol,0,1) -> 0 | BJ114: =IF(ABS(SUM(BJ108:BJ112)-BJ107)<eTol,0,1) -> 0 | BK114: =IF(ABS(SUM(BK108:BK112)-BK107)<eTol,0,1) -> 0 | BL114: =IF(ABS(SUM(BL108:BL112)-BL107)<eTol,0,1) -> 0 | BM114: =IF(ABS(SUM(BM108:BM112)-BM107)<eTol,0,1) -> 0
F116: Outsource | G116: =cstRealUnit -> £ Real | I116: =cOutputs!I105 -> 95659912 | AA116: =cOutputs!AA105 -> 0 | AB116: =cOutputs!AB105 -> 2745311 | AC116: =cOutputs!AC105 -> 2780403.4 | AD116: =cOutputs!AD105 -> 2810417.6 | AE116: =cOutputs!AE105 -> 2840755.8 | AF116: =cOutputs!AF105 -> 2868606.3 | AG116: =cOutputs!AG105 -> 2896729.9 | AH116: =cOutputs!AH105 -> 2925129.2 | ... BE116: =cOutputs!BE105 -> 3660979.3 | BG116: =cOutputs!BG105 -> 0 | BH116: =cOutputs!BH105 -> 14045494 | BI116: =cOutputs!BI105 -> 14770441 | BJ116: =cOutputs!BJ105 -> 15508819 | BK116: =cOutputs!BK105 -> 16284108 | BL116: =cOutputs!BL105 -> 17098155 | BM116: =cOutputs!BM105 -> 17952896
F117: Operating Costs | G117: =cstRealUnit -> £ Real | I117: =cOutputs!I106 -> 95659912 | AA117: =cOutputs!AA106 -> 0 | AB117: =cOutputs!AB106 -> 2745311 | AC117: =cOutputs!AC106 -> 2780403.4 | AD117: =cOutputs!AD106 -> 2810417.6 | AE117: =cOutputs!AE106 -> 2840755.8 | AF117: =cOutputs!AF106 -> 2868606.3 | AG117: =cOutputs!AG106 -> 2896729.9 | AH117: =cOutputs!AH106 -> 2925129.2 | ... BE117: =cOutputs!BE106 -> 3660979.3 | BG117: =cOutputs!BG106 -> 0 | BH117: =cOutputs!BH106 -> 14045494 | BI117: =cOutputs!BI106 -> 14770441 | BJ117: =cOutputs!BJ106 -> 15508819 | BK117: =cOutputs!BK106 -> 16284108 | BL117: =cOutputs!BL106 -> 17098155 | BM117: =cOutputs!BM106 -> 17952896
F118: Staff Costs | G118: =cstRealUnit -> £ Real | I118: =cOutputs!I107 -> 0 | AA118: =cOutputs!AA107 -> 0 | AB118: =cOutputs!AB107 -> 0 | AC118: =cOutputs!AC107 -> 0 | AD118: =cOutputs!AD107 -> 0 | AE118: =cOutputs!AE107 -> 0 | AF118: =cOutputs!AF107 -> 0 | AG118: =cOutputs!AG107 -> 0 | AH118: =cOutputs!AH107 -> 0 | ... BE118: =cOutputs!BE107 -> 0 | BG118: =cOutputs!BG107 -> 0 | BH118: =cOutputs!BH107 -> 0 | BI118: =cOutputs!BI107 -> 0 | BJ118: =cOutputs!BJ107 -> 0 | BK118: =cOutputs!BK107 -> 0 | BL118: =cOutputs!BL107 -> 0 | BM118: =cOutputs!BM107 -> 0
F119: Software & Hardware Costs | G119: =cstRealUnit -> £ Real | I119: =cOutputs!I108 -> 0 | AA119: =cOutputs!AA108 -> 0 | AB119: =cOutputs!AB108 -> 0 | AC119: =cOutputs!AC108 -> 0 | AD119: =cOutputs!AD108 -> 0 | AE119: =cOutputs!AE108 -> 0 | AF119: =cOutputs!AF108 -> 0 | AG119: =cOutputs!AG108 -> 0 | AH119: =cOutputs!AH108 -> 0 | ... BE119: =cOutputs!BE108 -> 0 | BG119: =cOutputs!BG108 -> 0 | BH119: =cOutputs!BH108 -> 0 | BI119: =cOutputs!BI108 -> 0 | BJ119: =cOutputs!BJ108 -> 0 | BK119: =cOutputs!BK108 -> 0 | BL119: =cOutputs!BL108 -> 0 | BM119: =cOutputs!BM108 -> 0
F120: Lease Costs | G120: =cstRealUnit -> £ Real | I120: =cOutputs!I109 -> 0 | AA120: =cOutputs!AA109 -> 0 | AB120: =cOutputs!AB109 -> 0 | AC120: =cOutputs!AC109 -> 0 | AD120: =cOutputs!AD109 -> 0 | AE120: =cOutputs!AE109 -> 0 | AF120: =cOutputs!AF109 -> 0 | AG120: =cOutputs!AG109 -> 0 | AH120: =cOutputs!AH109 -> 0 | ... BE120: =cOutputs!BE109 -> 0 | BG120: =cOutputs!BG109 -> 0 | BH120: =cOutputs!BH109 -> 0 | BI120: =cOutputs!BI109 -> 0 | BJ120: =cOutputs!BJ109 -> 0 | BK120: =cOutputs!BK109 -> 0 | BL120: =cOutputs!BL109 -> 0 | BM120: =cOutputs!BM109 -> 0
F121: Build & Maintenance Costs | G121: =cstRealUnit -> £ Real | I121: =cOutputs!I110 -> 0 | AA121: =cOutputs!AA110 -> 0 | AB121: =cOutputs!AB110 -> 0 | AC121: =cOutputs!AC110 -> 0 | AD121: =cOutputs!AD110 -> 0 | AE121: =cOutputs!AE110 -> 0 | AF121: =cOutputs!AF110 -> 0 | AG121: =cOutputs!AG110 -> 0 | AH121: =cOutputs!AH110 -> 0 | ... BE121: =cOutputs!BE110 -> 0 | BG121: =cOutputs!BG110 -> 0 | BH121: =cOutputs!BH110 -> 0 | BI121: =cOutputs!BI110 -> 0 | BJ121: =cOutputs!BJ110 -> 0 | BK121: =cOutputs!BK110 -> 0 | BL121: =cOutputs!BL110 -> 0 | BM121: =cOutputs!BM110 -> 0
A123: =SUM(C123:BM123) -> 0 | F123: Error Check | AA123: =IF(ABS(SUM(AA117:AA121)-AA116)<eTol,0,1) -> 0 | AB123: =IF(ABS(SUM(AB117:AB121)-AB116)<eTol,0,1) -> 0 | AC123: =IF(ABS(SUM(AC117:AC121)-AC116)<eTol,0,1) -> 0 | AD123: =IF(ABS(SUM(AD117:AD121)-AD116)<eTol,0,1) -> 0 | AE123: =IF(ABS(SUM(AE117:AE121)-AE116)<eTol,0,1) -> 0 | AF123: =IF(ABS(SUM(AF117:AF121)-AF116)<eTol,0,1) -> 0 | AG123: =IF(ABS(SUM(AG117:AG121)-AG116)<eTol,0,1) -> 0 | AH123: =IF(ABS(SUM(AH117:AH121)-AH116)<eTol,0,1) -> 0 | ... BE123: =IF(ABS(SUM(BE117:BE121)-BE116)<eTol,0,1) -> 0 | BG123: =IF(ABS(SUM(BG117:BG121)-BG116)<eTol,0,1) -> 0 | BH123: =IF(ABS(SUM(BH117:BH121)-BH116)<eTol,0,1) -> 0 | BI123: =IF(ABS(SUM(BI117:BI121)-BI116)<eTol,0,1) -> 0 | BJ123: =IF(ABS(SUM(BJ117:BJ121)-BJ116)<eTol,0,1) -> 0 | BK123: =IF(ABS(SUM(BK117:BK121)-BK116)<eTol,0,1) -> 0 | BL123: =IF(ABS(SUM(BL117:BL121)-BL116)<eTol,0,1) -> 0 | BM123: =IF(ABS(SUM(BM117:BM121)-BM116)<eTol,0,1) -> 0
E125: 3.2 | F125: Cumulative Costs
F127: Options
F129: Build & Operate | G129: =cstRealUnit -> £ Real | AA129: =cOutputs!AA116 -> 3045073 | AB129: =cOutputs!AB116 -> 5918457.8 | AC129: =cOutputs!AC116 -> 8250911.8 | AD129: =cOutputs!AD116 -> 10598039 | AE129: =cOutputs!AE116 -> 13005080 | AF129: =cOutputs!AF116 -> 15379515 | AG129: =cOutputs!AG116 -> 17908711 | AH129: =cOutputs!AH116 -> 20354917 | ... BE129: =cOutputs!BE116 -> 80228511 | BG129: =cOutputs!BG116 -> 3045073 | BH129: =cOutputs!BH116 -> 15379515 | BI129: =cOutputs!BI116 -> 27678740 | BJ129: =cOutputs!BJ116 -> 40264252 | BK129: =cOutputs!BK116 -> 53244497 | BL129: =cOutputs!BL116 -> 66581942 | BM129: =cOutputs!BM116 -> 80228511
F130: Operating Costs | G130: =cstRealUnit -> £ Real | AA130: =cOutputs!AA117 -> 0 | AB130: =cOutputs!AB117 -> 0 | AC130: =cOutputs!AC117 -> 0 | AD130: =cOutputs!AD117 -> 0 | AE130: =cOutputs!AE117 -> 0 | AF130: =cOutputs!AF117 -> 0 | AG130: =cOutputs!AG117 -> 0 | AH130: =cOutputs!AH117 -> 0 | ... BE130: =cOutputs!BE117 -> 0 | BG130: =cOutputs!BG117 -> 0 | BH130: =cOutputs!BH117 -> 0 | BI130: =cOutputs!BI117 -> 0 | BJ130: =cOutputs!BJ117 -> 0 | BK130: =cOutputs!BK117 -> 0 | BL130: =cOutputs!BL117 -> 0 | BM130: =cOutputs!BM117 -> 0
F131: Staff Costs | G131: =cstRealUnit -> £ Real | AA131: =cOutputs!AA118 -> 0 | AB131: =cOutputs!AB118 -> 2124256.4 | AC131: =cOutputs!AC118 -> 4265222.7 | AD131: =cOutputs!AD118 -> 6418795.4 | AE131: =cOutputs!AE118 -> 8585048.5 | AF131: =cOutputs!AF118 -> 10761921 | AG131: =cOutputs!AG118 -> 12949463 | AH131: =cOutputs!AH118 -> 15147730 | ... BE131: =cOutputs!BE118 -> 68791697 | BG131: =cOutputs!BG118 -> 0 | BH131: =cOutputs!BH118 -> 10761921 | BI131: =cOutputs!BI118 -> 21807395 | BJ131: =cOutputs!BJ118 -> 33126259 | BK131: =cOutputs!BK118 -> 44725279 | BL131: =cOutputs!BL118 -> 56611390 | BM131: =cOutputs!BM118 -> 68791697
F132: Software & Hardware Costs | G132: =cstRealUnit -> £ Real | AA132: =cOutputs!AA119 -> 0 | AB132: =cOutputs!AB119 -> 718589.5 | AC132: =cOutputs!AC119 -> 879148 | AD132: =cOutputs!AD119 -> 1041439.7 | AE132: =cOutputs!AE119 -> 1250627.1 | AF132: =cOutputs!AF119 -> 1416279 | AG132: =cOutputs!AG119 -> 1725709.2 | AH132: =cOutputs!AH119 -> 1941109.7 | ... BE132: =cOutputs!BE119 -> 7327618.8 | BG132: =cOutputs!BG119 -> 0 | BH132: =cOutputs!BH119 -> 1416279 | BI132: =cOutputs!BI119 -> 2505723.9 | BJ132: =cOutputs!BJ119 -> 3599850.9 | BK132: =cOutputs!BK119 -> 4799931.8 | BL132: =cOutputs!BL119 -> 6061065.3 | BM132: =cOutputs!BM119 -> 7327618.8
F133: Lease Costs | G133: =cstRealUnit -> £ Real | AA133: =cOutputs!AA120 -> 0 | AB133: =cOutputs!AB120 -> 0 | AC133: =cOutputs!AC120 -> 0 | AD133: =cOutputs!AD120 -> 0 | AE133: =cOutputs!AE120 -> 0 | AF133: =cOutputs!AF120 -> 0 | AG133: =cOutputs!AG120 -> 0 | AH133: =cOutputs!AH120 -> 0 | ... BE133: =cOutputs!BE120 -> 0 | BG133: =cOutputs!BG120 -> 0 | BH133: =cOutputs!BH120 -> 0 | BI133: =cOutputs!BI120 -> 0 | BJ133: =cOutputs!BJ120 -> 0 | BK133: =cOutputs!BK120 -> 0 | BL133: =cOutputs!BL120 -> 0 | BM133: =cOutputs!BM120 -> 0
F134: Build & Maintenance Costs | G134: =cstRealUnit -> £ Real | AA134: =cOutputs!AA121 -> 3045073 | AB134: =cOutputs!AB121 -> 3075611.9 | AC134: =cOutputs!AC121 -> 3106541.1 | AD134: =cOutputs!AD121 -> 3137804.2 | AE134: =cOutputs!AE121 -> 3169404.8 | AF134: =cOutputs!AF121 -> 3201315.2 | AG134: =cOutputs!AG121 -> 3233538.5 | AH134: =cOutputs!AH121 -> 3266077.7 | ... BE134: =cOutputs!BE121 -> 4109195 | BG134: =cOutputs!BG121 -> 3045073 | BH134: =cOutputs!BH121 -> 3201315.2 | BI134: =cOutputs!BI121 -> 3365621.8 | BJ134: =cOutputs!BJ121 -> 3538142.1 | BK134: =cOutputs!BK121 -> 3719286.7 | BL134: =cOutputs!BL121 -> 3909486.8 | BM134: =cOutputs!BM121 -> 4109195
A136: =SUM(C136:BM136) -> 0 | F136: Error Check | AA136: =IF(ABS(SUM(AA130:AA134)-AA129)<eTol,0,1) -> 0 | AB136: =IF(ABS(SUM(AB130:AB134)-AB129)<eTol,0,1) -> 0 | AC136: =IF(ABS(SUM(AC130:AC134)-AC129)<eTol,0,1) -> 0 | AD136: =IF(ABS(SUM(AD130:AD134)-AD129)<eTol,0,1) -> 0 | AE136: =IF(ABS(SUM(AE130:AE134)-AE129)<eTol,0,1) -> 0 | AF136: =IF(ABS(SUM(AF130:AF134)-AF129)<eTol,0,1) -> 0 | AG136: =IF(ABS(SUM(AG130:AG134)-AG129)<eTol,0,1) -> 0 | AH136: =IF(ABS(SUM(AH130:AH134)-AH129)<eTol,0,1) -> 0 | ... BE136: =IF(ABS(SUM(BE130:BE134)-BE129)<eTol,0,1) -> 0 | BG136: =IF(ABS(SUM(BG130:BG134)-BG129)<eTol,0,1) -> 0 | BH136: =IF(ABS(SUM(BH130:BH134)-BH129)<eTol,0,1) -> 0 | BI136: =IF(ABS(SUM(BI130:BI134)-BI129)<eTol,0,1) -> 0 | BJ136: =IF(ABS(SUM(BJ130:BJ134)-BJ129)<eTol,0,1) -> 0 | BK136: =IF(ABS(SUM(BK130:BK134)-BK129)<eTol,0,1) -> 0 | BL136: =IF(ABS(SUM(BL130:BL134)-BL129)<eTol,0,1) -> 0 | BM136: =IF(ABS(SUM(BM130:BM134)-BM129)<eTol,0,1) -> 0
F138: Lease & Operate | G138: =cstRealUnit -> £ Real | AA138: =cOutputs!AA123 -> 0 | AB138: =cOutputs!AB123 -> 2892289.8 | AC138: =cOutputs!AC123 -> 5243890.5 | AD138: =cOutputs!AD123 -> 7610371.3 | AE138: =cOutputs!AE123 -> 10036975 | AF138: =cOutputs!AF123 -> 12431163 | AG138: =cOutputs!AG123 -> 14980307 | AH138: =cOutputs!AH123 -> 17446656 | ... BE138: =cOutputs!BE123 -> 77842180 | BG138: =cOutputs!BG123 -> 0 | BH138: =cOutputs!BH123 -> 12431163 | BI138: =cOutputs!BI123 -> 24832102 | BJ138: =cOutputs!BJ123 -> 37524412 | BK138: =cOutputs!BK123 -> 50616795 | BL138: =cOutputs!BL123 -> 64071982 | BM138: =cOutputs!BM123 -> 77842180
F139: Operating Costs | G139: =cstRealUnit -> £ Real | AA139: =cOutputs!AA124 -> 0 | AB139: =cOutputs!AB124 -> 0 | AC139: =cOutputs!AC124 -> 0 | AD139: =cOutputs!AD124 -> 0 | AE139: =cOutputs!AE124 -> 0 | AF139: =cOutputs!AF124 -> 0 | AG139: =cOutputs!AG124 -> 0 | AH139: =cOutputs!AH124 -> 0 | ... BE139: =cOutputs!BE124 -> 0 | BG139: =cOutputs!BG124 -> 0 | BH139: =cOutputs!BH124 -> 0 | BI139: =cOutputs!BI124 -> 0 | BJ139: =cOutputs!BJ124 -> 0 | BK139: =cOutputs!BK124 -> 0 | BL139: =cOutputs!BL124 -> 0 | BM139: =cOutputs!BM124 -> 0
F140: Staff Costs | G140: =cstRealUnit -> £ Real | AA140: =cOutputs!AA125 -> 0 | AB140: =cOutputs!AB125 -> 2124256.4 | AC140: =cOutputs!AC125 -> 4265222.7 | AD140: =cOutputs!AD125 -> 6418795.4 | AE140: =cOutputs!AE125 -> 8585048.5 | AF140: =cOutputs!AF125 -> 10761921 | AG140: =cOutputs!AG125 -> 12949463 | AH140: =cOutputs!AH125 -> 15147730 | ... BE140: =cOutputs!BE125 -> 68791697 | BG140: =cOutputs!BG125 -> 0 | BH140: =cOutputs!BH125 -> 10761921 | BI140: =cOutputs!BI125 -> 21807395 | BJ140: =cOutputs!BJ125 -> 33126259 | BK140: =cOutputs!BK125 -> 44725279 | BL140: =cOutputs!BL125 -> 56611390 | BM140: =cOutputs!BM125 -> 68791697
...

Sheet oDashboard
C1: THIS CASE STUDY MODEL IS FOR ILLUSTRATIVE PURPOSES
C2: =cstProjectName -> Should Cost Modelling Case Study - Illustrative SCM
C3: =MID(CELL("filename",A1),FIND("]",CELL("filename",A1))+1,256)&" Sheet" -> oDashboard Sheet
C4: =IF(ISBLANK(cstProtectiveMarking),"",cstProtectiveMarking) -> Not Protectively Marked
C5: =HYPERLINK("#'Contents'!A1",sysChkWord) -> All Checks OK
C6: =HYPERLINK("#'Contents'!A1","Click for Contents") -> Click for Contents
A8: =SUM(A9:A38) -> 0 | B8: =SUM(B9:B38) -> 0
D10: 1 | E10: Active Scenarios
E12: 1.1 | F12: Scenarios
F14: Planned Maximum Call Volumes Scenario
F16: Cost Scenario
D18: 2 | E18: Dashboard
D20: ="NPV by Option (£m) - "&cOutputs!I195 -> NPV by Option (£m) - Scenario A - Base Case | J20: ="Total Nominal Cost by Option (£m) - "&cOutputs!I195 -> Total Nominal Cost by Option (£m) - Scenario A - Base Case | Q20: ="Nominal Costs by Option over time (£m) - "&cOutputs!I195 -> Nominal Costs by Option over time (£m) - Scenario A - Base Case
D38: END OF WORKSHEET - INSERT ROWS ABOVE

Sheet Admin>>

Sheet SysConfig
C1: THIS CASE STUDY MODEL IS FOR ILLUSTRATIVE PURPOSES
C2: =cstProjectName -> Should Cost Modelling Case Study - Illustrative SCM
C3: =MID(CELL("filename",A1),FIND("]",CELL("filename",A1))+1,256)&" Sheet" -> SysConfig Sheet
C4: =IF(ISBLANK(cstProtectiveMarking),"",cstProtectiveMarking) -> Not Protectively Marked
C5: =HYPERLINK("#'Contents'!A1",sysChkWord) -> All Checks OK
C6: =HYPERLINK("#'Contents'!A1","Click for Contents") -> Click for Contents
A8: =SUM(A9:A105) -> 0 | B8: =SUM(B9:B105) -> 0
D10: 1 | E10: General Details
F12: Project Name | G12: Should Cost Modelling Case Study - Illustrative SCM
F13: Contracting Authority | G13: CASE
F14: IMA Score | G14: Medium
F15: Model Developer | G15: Sydney Jones
F16: Contact Details | G16: sourcing.programme@cabinetoffice.gov.uk
F17: Model Owner | G17: Joe Snow
F18: Protective Marking | G18: Not Protectively Marked
D20: 2 | E20: Setup
F22: Model Start Date (dd/mm/yy) | G22: 44652
F23: Years per Summary Period | G23: 5
F24: Operation Commencement Date | G24: 45017
D26: 3 | E26: Named Constants
F28: cstThou | G28: 1000
F29: cstMil | G29: 1000000
F30: cstDaysInWk | G30: 7
F31: cstWeeksInYr | G31: 52
F32: cstMonthsInQtr | G32: 3
F33: cstMonthsInYr | G33: 12
D35: 4 | E35: Units
F37: cstConstantUnit | G37: £ 2022/23
F38: cstNominalUnit | G38: £ Nominal
F39: cstRealUnit | G39: £ Real
F40: cstArea | G40: m2
F41: cstFTE | G41: FTE
F42: cstNum | G42: #
F43: cstPercent | G43: %
F44: cstYears | G44: Yrs
F45: cstHours | G45: Hrs
F46: cstFlag | G46: Flag
D48: 5 | E48: Error Check Settings
B50: =IF(eTol="",1,0) -> 0 | F50: Error Tolerance | G50: 0.0001
F52: Error Check Wording | G52: =IF(AND(sysChk=0,sysWarn=0),"All Checks OK",IF(sysChk<>0,sysChk&" Error"&IF(sysChk=1," ","s "),"")&IF(sysWarn<>0,sysWarn&" Warning"&IF(sysWarn=1,"","s"),"")) -> All Checks OK
D54: 6 | E54: Named Ranges List
F56: Name | G56: Address | H56: Purpose
F57: ActiveCallVolumeScenarioIndex | G57: iControl!$I$14 | H57: Scenario selection
F58: ActiveCostScenarioIndex | G58: iControl!$I$24 | H58: Scenario selection
F59: cstArea | G59: SysConfig!$G$40 | H59: Units Constant
F60: cstConstantUnit | G60: SysConfig!$G$37 | H60: Units Constant
F61: cstDaysInWk | G61: SysConfig!$G$30 | H61: Number of Days in a week constant
F62: cstFlag | G62: SysConfig!$G$46 | H62: Units Constant
F63: cstFTE | G63: SysConfig!$G$41 | H63: Units Constant
F64: cstHours | G64: SysConfig!$G$45 | H64: Units Constant
F65: cstMil | G65: SysConfig!$G$29 | H65: Million constant
F66: cstMonthsInQtr | G66: SysConfig!$G$32 | H66: Number of months in quarter constant
F67: cstMonthsInYr | G67: SysConfig!$G$33 | H67: Number of months in year constant
... F88: sysWarn | G88: Contents!$I$27 | H88: Number of Warnings in model
F89: INSERT NEW ROWS ABOVE THIS ROW
D91: 7 | E91: Lists
E93: 7.1 | F93: Planned Maximum Call Volume Scenarios
F95: Scenario A
F96: Scenario B
F97: Scenario C
E99: 7.2 | F99: Cost Scenarios
F101: Low Case
F102: Base Case
F103: High Case
D105: END OF WORKSHEET - INSERT ROWS ABOVE

Sheet SysTime
C1: THIS CASE STUDY MODEL IS FOR ILLUSTRATIVE PURPOSES
